{
  "type": "Feature",
  "properties": {
    "gn:admin1_code":"7.0",
    "gn:asciiname":"Munyema",
    "gn:country_code":"ZM",
    "gn:dem":996,
    "gn:feature_class":"P",
    "gn:feature_code":"PPL",
    "gn:name":"Munyema",
    "gn:population":0,
    "gn:timezone":"Africa/Lusaka",
    "iso:country":"ZM",
    "wof:name":"Munyema",
    "wof:placetype":"locality"
},
  "geometry": {"coordinates":[26.81153,-15.44618],"type":"Point"}
}