{
  "type": "Feature",
  "properties": {
    "gn:admin1_code":"3.0",
    "gn:asciiname":"Manyara",
    "gn:country_code":"ZM",
    "gn:dem":1151,
    "gn:feature_class":"P",
    "gn:feature_code":"PPL",
    "gn:name":"Manyara",
    "gn:population":0,
    "gn:timezone":"Africa/Lusaka",
    "iso:country":"ZM",
    "name:hun_x_preferred":[
        "Manyara"
    ],
    "wof:name":"Manyara",
    "wof:placetype":"locality"
},
  "geometry": {"coordinates":[33.16667,-11.93333],"type":"Point"}
}