{
  "type": "Feature",
  "properties": {
    "gn:admin1_code":"10.0",
    "gn:asciiname":"Mulengwe",
    "gn:country_code":"ZM",
    "gn:dem":550,
    "gn:feature_class":"P",
    "gn:feature_code":"PPL",
    "gn:name":"Mulengwe",
    "gn:population":0,
    "gn:timezone":"Africa/Lusaka",
    "iso:country":"ZM",
    "wof:name":"Mulengwe",
    "wof:placetype":"locality"
},
  "geometry": {"coordinates":[32.08333,-12.66667],"type":"Point"}
}