{
  "type": "Feature",
  "properties": {
    "gn:admin1_code":"3.0",
    "gn:asciiname":"Enosi",
    "gn:country_code":"ZM",
    "gn:dem":1064,
    "gn:feature_class":"P",
    "gn:feature_code":"PPL",
    "gn:name":"Enosi",
    "gn:population":0,
    "gn:timezone":"Africa/Lusaka",
    "iso:country":"ZM",
    "name:und_x_variant":[
        "Enos",
        "Enosi"
    ],
    "wof:name":"Enosi",
    "wof:placetype":"locality"
},
  "geometry": {"coordinates":[31.85975,-14.06278],"type":"Point"}
}