{
  "type": "Feature",
  "properties": {
    "gn:admin1_code":"3.0",
    "gn:asciiname":"Amos",
    "gn:country_code":"ZM",
    "gn:dem":966,
    "gn:feature_class":"P",
    "gn:feature_code":"PPL",
    "gn:name":"Amos",
    "gn:population":0,
    "gn:timezone":"Africa/Lusaka",
    "iso:country":"ZM",
    "name:cat_x_preferred":[
        "Amos"
    ],
    "name:ceb_x_preferred":[
        "Amos"
    ],
    "name:deu_x_preferred":[
        "Amos"
    ],
    "name:epo_x_preferred":[
        "Amos"
    ],
    "name:fin_x_preferred":[
        "Amos"
    ],
    "name:fra_x_preferred":[
        "Amos"
    ],
    "name:fry_x_preferred":[
        "Amos"
    ],
    "name:heb_x_preferred":[
        "\u05e2\u05de\u05d5\u05e1"
    ],
    "name:hrv_x_preferred":[
        "AMOS"
    ],
    "name:ind_x_preferred":[
        "Amos"
    ],
    "name:ita_x_preferred":[
        "Amos"
    ],
    "name:jpn_x_preferred":[
        "\u30a2\u30e2\u30b9"
    ],
    "name:kor_x_preferred":[
        "\uc544\ubaa8\uc2a4"
    ],
    "name:nld_x_preferred":[
        "Amos"
    ],
    "name:nor_x_preferred":[
        "Amos"
    ],
    "name:por_x_preferred":[
        "Amos"
    ],
    "name:slk_x_preferred":[
        "Amos"
    ],
    "name:slv_x_preferred":[
        "Amos"
    ],
    "name:spa_x_preferred":[
        "Am\u00f3s"
    ],
    "name:swe_x_preferred":[
        "Amos"
    ],
    "wof:name":"Amos",
    "wof:placetype":"locality"
},
  "geometry": {"coordinates":[31.33333,-14.43333],"type":"Point"}
}