{
  "type": "Feature",
  "properties": {
    "gn:admin1_code":"5.0",
    "gn:asciiname":"Shimulamba",
    "gn:country_code":"ZM",
    "gn:dem":1276,
    "gn:feature_class":"P",
    "gn:feature_code":"PPL",
    "gn:name":"Shimulamba",
    "gn:population":0,
    "gn:timezone":"Africa/Lusaka",
    "iso:country":"ZM",
    "name:und_x_variant":[
        "Simulambo",
        "Shimulamba"
    ],
    "wof:name":"Shimulamba",
    "wof:placetype":"locality"
},
  "geometry": {"coordinates":[31.2908,-10.28172],"type":"Point"}
}