{
  "type": "Feature",
  "properties": {
    "gn:admin1_code":"2.0",
    "gn:asciiname":"Shipokola",
    "gn:country_code":"ZM",
    "gn:dem":1141,
    "gn:feature_class":"P",
    "gn:feature_code":"PPL",
    "gn:name":"Shipokola",
    "gn:population":0,
    "gn:timezone":"Africa/Lusaka",
    "iso:country":"ZM",
    "wof:name":"Shipokola",
    "wof:placetype":"locality"
},
  "geometry": {"coordinates":[27.61667000000001,-14.25],"type":"Point"}
}