{
  "type": "Feature",
  "properties": {
    "gn:admin1_code":"5.0",
    "gn:asciiname":"Kundimambwe",
    "gn:country_code":"ZM",
    "gn:dem":1297,
    "gn:feature_class":"P",
    "gn:feature_code":"PPL",
    "gn:name":"Kundimambwe",
    "gn:population":0,
    "gn:timezone":"Africa/Lusaka",
    "iso:country":"ZM",
    "wof:name":"Kundimambwe",
    "wof:placetype":"locality"
},
  "geometry": {"coordinates":[32.13333,-9.23333],"type":"Point"}
}