{
  "type": "Feature",
  "properties": {
    "gn:admin1_code":"3.0",
    "gn:asciiname":"Mwanya",
    "gn:country_code":"ZM",
    "gn:dem":593,
    "gn:feature_class":"P",
    "gn:feature_code":"PPL",
    "gn:name":"Mwanya",
    "gn:population":0,
    "gn:timezone":"Africa/Lusaka",
    "iso:country":"ZM",
    "wof:name":"Mwanya",
    "wof:placetype":"locality"
},
  "geometry": {"coordinates":[32.25103,-12.7269],"type":"Point"}
}