{
  "type": "Feature",
  "properties": {
    "gn:admin1_code":"1.0",
    "gn:asciiname":"Kabanje",
    "gn:country_code":"ZM",
    "gn:dem":1129,
    "gn:feature_class":"P",
    "gn:feature_code":"PPL",
    "gn:name":"Kabanje",
    "gn:population":0,
    "gn:timezone":"Africa/Lusaka",
    "iso:country":"ZM",
    "wof:name":"Kabanje",
    "wof:placetype":"locality"
},
  "geometry": {"coordinates":[24.26667,-14.91667],"type":"Point"}
}