{
  "type": "Feature",
  "properties": {
    "gn:admin1_code":"1.0",
    "gn:asciiname":"Liezi",
    "gn:country_code":"ZM",
    "gn:dem":1145,
    "gn:feature_class":"P",
    "gn:feature_code":"PPL",
    "gn:name":"Liezi",
    "gn:population":0,
    "gn:timezone":"Africa/Lusaka",
    "iso:country":"ZM",
    "name:cat_x_preferred":[
        "Lie Zi"
    ],
    "name:fra_x_preferred":[
        "Lie Zi"
    ],
    "name:glg_x_preferred":[
        "Lie Zi"
    ],
    "name:hun_x_preferred":[
        "Lie-ce"
    ],
    "name:mwl_x_preferred":[
        "Liezi"
    ],
    "name:nld_x_preferred":[
        "Liezi"
    ],
    "name:nor_x_preferred":[
        "Liezi"
    ],
    "name:pol_x_preferred":[
        "Liezi"
    ],
    "name:por_x_preferred":[
        "Liezi"
    ],
    "name:rus_x_preferred":[
        "\u041b\u0435-\u0446\u0437\u044b"
    ],
    "name:spa_x_preferred":[
        "Lie Zi"
    ],
    "name:swe_x_preferred":[
        "Liezi"
    ],
    "name:ukr_x_preferred":[
        "\u041b\u0435-\u0446\u0437\u0438"
    ],
    "name:vie_x_preferred":[
        "Li\u1ec7t t\u1eed"
    ],
    "wof:name":"Liezi",
    "wof:placetype":"locality"
},
  "geometry": {"coordinates":[24.88333,-14.73333],"type":"Point"}
}