{
  "type": "Feature",
  "properties": {
    "gn:admin1_code":"7.0",
    "gn:asciiname":"Lazao",
    "gn:country_code":"ZM",
    "gn:dem":510,
    "gn:feature_class":"P",
    "gn:feature_code":"PPL",
    "gn:name":"Lazao",
    "gn:population":0,
    "gn:timezone":"Africa/Lusaka",
    "iso:country":"ZM",
    "wof:name":"Lazao",
    "wof:placetype":"locality"
},
  "geometry": {"coordinates":[28.06667,-16.66667],"type":"Point"}
}