{
  "type": "Feature",
  "properties": {
    "gn:admin1_code":"7.0",
    "gn:asciiname":"Changa",
    "gn:country_code":"ZM",
    "gn:dem":564,
    "gn:feature_class":"P",
    "gn:feature_code":"PPL",
    "gn:name":"Changa",
    "gn:population":0,
    "gn:timezone":"Africa/Lusaka",
    "iso:country":"ZM",
    "name:ceb_x_preferred":[
        "Changa"
    ],
    "name:swe_x_preferred":[
        "Changa"
    ],
    "wof:name":"Changa",
    "wof:placetype":"locality"
},
  "geometry": {"coordinates":[28.4021,-16.28436],"type":"Point"}
}