{
  "type": "Feature",
  "properties": {
    "gn:admin1_code":"8.0",
    "gn:asciiname":"Katola",
    "gn:country_code":"ZM",
    "gn:dem":1190,
    "gn:feature_class":"P",
    "gn:feature_code":"PPL",
    "gn:name":"Katola",
    "gn:population":0,
    "gn:timezone":"Africa/Lusaka",
    "iso:country":"ZM",
    "wof:name":"Katola",
    "wof:placetype":"locality"
},
  "geometry": {"coordinates":[27.76667,-13.13333],"type":"Point"}
}