{
  "type": "Feature",
  "properties": {
    "gn:admin1_code":"9.0",
    "gn:asciiname":"Chalimbana",
    "gn:country_code":"ZM",
    "gn:dem":1176,
    "gn:feature_class":"P",
    "gn:feature_code":"PPL",
    "gn:name":"Chalimbana",
    "gn:population":0,
    "gn:timezone":"Africa/Lusaka",
    "iso:country":"ZM",
    "wof:name":"Chalimbana",
    "wof:placetype":"locality"
},
  "geometry": {"coordinates":[28.43333,-15.36667],"type":"Point"}
}