{
  "type": "Feature",
  "properties": {
    "gn:admin1_code":"6.0",
    "gn:asciiname":"Mutwewakai",
    "gn:country_code":"ZM",
    "gn:dem":1072,
    "gn:feature_class":"P",
    "gn:feature_code":"PPL",
    "gn:name":"Mutwewakai",
    "gn:population":0,
    "gn:timezone":"Africa/Lusaka",
    "iso:country":"ZM",
    "name:und_x_variant":[
        "Mutuwankai",
        "Mutwewakai"
    ],
    "wof:name":"Mutwewakai",
    "wof:placetype":"locality"
},
  "geometry": {"coordinates":[22.75891,-13.20317],"type":"Point"}
}