{
  "type": "Feature",
  "properties": {
    "gn:admin1_code":"1.0",
    "gn:asciiname":"Chingwali",
    "gn:country_code":"ZM",
    "gn:dem":1051,
    "gn:feature_class":"P",
    "gn:feature_code":"PPL",
    "gn:name":"Chingwali",
    "gn:population":0,
    "gn:timezone":"Africa/Lusaka",
    "iso:country":"ZM",
    "wof:name":"Chingwali",
    "wof:placetype":"locality"
},
  "geometry": {"coordinates":[22.81667,-13.95],"type":"Point"}
}