{
  "type": "Feature",
  "properties": {
    "gn:admin1_code":"3.0",
    "gn:asciiname":"Matiti",
    "gn:country_code":"ZM",
    "gn:dem":912,
    "gn:feature_class":"P",
    "gn:feature_code":"PPL",
    "gn:name":"Matiti",
    "gn:population":0,
    "gn:timezone":"Africa/Lusaka",
    "iso:country":"ZM",
    "wof:name":"Matiti",
    "wof:placetype":"locality"
},
  "geometry": {"coordinates":[30.9992,-14.4104],"type":"Point"}
}