{
  "type": "Feature",
  "properties": {
    "gn:admin1_code":"3.0",
    "gn:asciiname":"Samuneko",
    "gn:country_code":"ZM",
    "gn:dem":1055,
    "gn:feature_class":"P",
    "gn:feature_code":"PPL",
    "gn:name":"Samuneko",
    "gn:population":0,
    "gn:timezone":"Africa/Lusaka",
    "iso:country":"ZM",
    "wof:name":"Samuneko",
    "wof:placetype":"locality"
},
  "geometry": {"coordinates":[22.96667,-13.96667],"type":"Point"}
}