{
  "type": "Feature",
  "properties": {
    "gn:admin1_code":"7.0",
    "gn:asciiname":"Chiyumpe",
    "gn:country_code":"ZM",
    "gn:dem":1301,
    "gn:feature_class":"P",
    "gn:feature_code":"PPL",
    "gn:name":"Chiyumpe",
    "gn:population":0,
    "gn:timezone":"Africa/Lusaka",
    "iso:country":"ZM",
    "name:und_x_variant":[
        "Chiumbe",
        "Chiumpe",
        "Chiyumpe"
    ],
    "wof:name":"Chiyumpe",
    "wof:placetype":"locality"
},
  "geometry": {"coordinates":[26.55,-16.91667],"type":"Point"}
}