{
  "type": "Feature",
  "properties": {
    "gn:admin1_code":"10.0",
    "gn:asciiname":"Mwisi",
    "gn:country_code":"ZM",
    "gn:dem":1181,
    "gn:feature_class":"P",
    "gn:feature_code":"PPL",
    "gn:name":"Mwisi",
    "gn:population":0,
    "gn:timezone":"Africa/Lusaka",
    "iso:country":"ZM",
    "name:und_x_variant":[
        "Wisi",
        "Mwisi"
    ],
    "wof:name":"Mwisi",
    "wof:placetype":"locality"
},
  "geometry": {"coordinates":[32.81667,-9.95],"type":"Point"}
}