{
  "type": "Feature",
  "properties": {
    "gn:admin1_code":"5.0",
    "gn:asciiname":"Shachele",
    "gn:cc2":"ZM",
    "gn:country_code":"ZM",
    "gn:dem":978,
    "gn:feature_class":"P",
    "gn:feature_code":"PPL",
    "gn:name":"Shachele",
    "gn:population":0,
    "gn:timezone":"Africa/Lusaka",
    "iso:country":"ZM",
    "name:und_x_variant":[
        "Sichele",
        "Shachele"
    ],
    "wof:name":"Shachele",
    "wof:placetype":"locality"
},
  "geometry": {"coordinates":[27.56667,-15.46667],"type":"Point"}
}