{
  "type": "Feature",
  "properties": {
    "gn:admin1_code":"7.0",
    "gn:asciiname":"Haddo",
    "gn:country_code":"ZM",
    "gn:dem":1272,
    "gn:feature_class":"P",
    "gn:feature_code":"PPL",
    "gn:name":"Haddo",
    "gn:population":0,
    "gn:timezone":"Africa/Lusaka",
    "iso:country":"ZM",
    "wof:name":"Haddo",
    "wof:placetype":"locality"
},
  "geometry": {"coordinates":[26.23636,-17.31603],"type":"Point"}
}