{
  "type": "Feature",
  "properties": {
    "gn:admin1_code":"3.0",
    "gn:asciiname":"Chiparamba",
    "gn:country_code":"ZM",
    "gn:dem":992,
    "gn:feature_class":"P",
    "gn:feature_code":"PPL",
    "gn:name":"Chiparamba",
    "gn:population":0,
    "gn:timezone":"Africa/Lusaka",
    "iso:country":"ZM",
    "name:und_x_variant":[
        "Chewa",
        "Chiparamba"
    ],
    "wof:name":"Chiparamba",
    "wof:placetype":"locality"
},
  "geometry": {"coordinates":[32.48333,-13.56667],"type":"Point"}
}