{
  "type": "Feature",
  "properties": {
    "gn:admin1_code":"10.0",
    "gn:asciiname":"Chilanga",
    "gn:country_code":"ZM",
    "gn:dem":1346,
    "gn:feature_class":"P",
    "gn:feature_code":"PPL",
    "gn:name":"Chilanga",
    "gn:population":0,
    "gn:timezone":"Africa/Lusaka",
    "iso:country":"ZM",
    "name:und_x_variant":[
        "Chiranga",
        "Chilanga"
    ],
    "wof:name":"Chilanga",
    "wof:placetype":"locality"
},
  "geometry": {"coordinates":[32.45,-9.23333],"type":"Point"}
}