{
  "type": "Feature",
  "properties": {
    "gn:admin1_code":"2.0",
    "gn:asciiname":"Musopelo",
    "gn:country_code":"ZM",
    "gn:dem":1188,
    "gn:feature_class":"P",
    "gn:feature_code":"PPL",
    "gn:name":"Musopelo",
    "gn:population":0,
    "gn:timezone":"Africa/Lusaka",
    "iso:country":"ZM",
    "wof:name":"Musopelo",
    "wof:placetype":"locality"
},
  "geometry": {"coordinates":[27.98738,-14.86107],"type":"Point"}
}