{
  "type": "Feature",
  "properties": {
    "gn:admin1_code":"2.0",
    "gn:asciiname":"Sande Manyolwa",
    "gn:country_code":"ZM",
    "gn:dem":1294,
    "gn:feature_class":"P",
    "gn:feature_code":"PPL",
    "gn:name":"Sande Manyolwa",
    "gn:population":0,
    "gn:timezone":"Africa/Lusaka",
    "iso:country":"ZM",
    "wof:name":"Sande Manyolwa",
    "wof:placetype":"locality"
},
  "geometry": {"coordinates":[30.33473,-12.80191],"type":"Point"}
}