{
  "type": "Feature",
  "properties": {
    "gn:admin1_code":"3.0",
    "gn:asciiname":"Mtavu",
    "gn:country_code":"ZM",
    "gn:dem":1424,
    "gn:feature_class":"P",
    "gn:feature_code":"PPL",
    "gn:name":"Mtavu",
    "gn:population":0,
    "gn:timezone":"Africa/Lusaka",
    "iso:country":"ZM",
    "wof:name":"Mtavu",
    "wof:placetype":"locality"
},
  "geometry": {"coordinates":[33.45,-12.41667],"type":"Point"}
}