{
  "type": "Feature",
  "properties": {
    "gn:admin1_code":"2.0",
    "gn:asciiname":"Taki Kunda",
    "gn:country_code":"ZM",
    "gn:dem":1299,
    "gn:feature_class":"P",
    "gn:feature_code":"PPL",
    "gn:name":"Taki Kunda",
    "gn:population":0,
    "gn:timezone":"Africa/Lusaka",
    "iso:country":"ZM",
    "wof:name":"Taki Kunda",
    "wof:placetype":"locality"
},
  "geometry": {"coordinates":[30.33515,-12.79596],"type":"Point"}
}