{
  "type": "Feature",
  "properties": {
    "gn:admin1_code":"1.0",
    "gn:asciiname":"Shangombo",
    "gn:country_code":"ZM",
    "gn:dem":1026,
    "gn:feature_class":"P",
    "gn:feature_code":"PPL",
    "gn:name":"Shangombo",
    "gn:population":0,
    "gn:timezone":"Africa/Lusaka",
    "iso:country":"ZM",
    "name:deu_x_preferred":[
        "Shangombo"
    ],
    "name:mrj_x_preferred":[
        "\u0428\u0430\u043d\u0433\u043e\u043c\u0431\u043e"
    ],
    "name:pol_x_preferred":[
        "Shangombo"
    ],
    "name:por_x_preferred":[
        "Shangombo"
    ],
    "name:ron_x_preferred":[
        "Shangombo"
    ],
    "name:zho_x_preferred":[
        "\u5c1a\u8ca2\u535a"
    ],
    "wof:name":"Shangombo",
    "wof:placetype":"locality"
},
  "geometry": {"coordinates":[22.08722,-16.32013],"type":"Point"}
}