{
  "type": "Feature",
  "properties": {
    "gn:admin1_code":"3.0",
    "gn:asciiname":"Chondi",
    "gn:country_code":"ZM",
    "gn:dem":725,
    "gn:feature_class":"P",
    "gn:feature_code":"PPL",
    "gn:name":"Chondi",
    "gn:population":0,
    "gn:timezone":"Africa/Lusaka",
    "iso:country":"ZM",
    "wof:name":"Chondi",
    "wof:placetype":"locality"
},
  "geometry": {"coordinates":[31.56667,-13.78333],"type":"Point"}
}