{
  "type": "Feature",
  "properties": {
    "gn:admin1_code":"2.0",
    "gn:asciiname":"Kapini",
    "gn:country_code":"ZM",
    "gn:dem":1125,
    "gn:feature_class":"P",
    "gn:feature_code":"PPL",
    "gn:name":"Kapini",
    "gn:population":0,
    "gn:timezone":"Africa/Lusaka",
    "iso:country":"ZM",
    "wof:name":"Kapini",
    "wof:placetype":"locality"
},
  "geometry": {"coordinates":[27.80524,-14.7455],"type":"Point"}
}