{
  "type": "Feature",
  "properties": {
    "gn:admin1_code":"7.0",
    "gn:asciiname":"Ngabo",
    "gn:country_code":"ZM",
    "gn:dem":1017,
    "gn:feature_class":"P",
    "gn:feature_code":"PPL",
    "gn:name":"Ngabo",
    "gn:population":0,
    "gn:timezone":"Africa/Lusaka",
    "iso:country":"ZM",
    "wof:name":"Ngabo",
    "wof:placetype":"locality"
},
  "geometry": {"coordinates":[26.58431,-15.93375],"type":"Point"}
}