{
  "type": "Feature",
  "properties": {
    "gn:admin1_code":"9.0",
    "gn:asciiname":"Sabola",
    "gn:country_code":"ZM",
    "gn:dem":891,
    "gn:feature_class":"P",
    "gn:feature_code":"PPL",
    "gn:name":"Sabola",
    "gn:population":0,
    "gn:timezone":"Africa/Lusaka",
    "iso:country":"ZM",
    "wof:name":"Sabola",
    "wof:placetype":"locality"
},
  "geometry": {"coordinates":[29.55,-15.21667],"type":"Point"}
}