{
  "type": "Feature",
  "properties": {
    "gn:admin1_code":"2.0",
    "gn:asciiname":"Dauti Mumba",
    "gn:country_code":"ZM",
    "gn:dem":1496,
    "gn:feature_class":"P",
    "gn:feature_code":"PPL",
    "gn:name":"Dauti Mumba",
    "gn:population":0,
    "gn:timezone":"Africa/Lusaka",
    "iso:country":"ZM",
    "wof:name":"Dauti Mumba",
    "wof:placetype":"locality"
},
  "geometry": {"coordinates":[30.43293,-12.99127],"type":"Point"}
}