{
  "type": "Feature",
  "properties": {
    "gn:admin1_code":"1.0",
    "gn:asciiname":"Tungulu",
    "gn:country_code":"ZM",
    "gn:dem":971,
    "gn:feature_class":"P",
    "gn:feature_code":"PPL",
    "gn:name":"Tungulu",
    "gn:population":0,
    "gn:timezone":"Africa/Lusaka",
    "iso:country":"ZM",
    "wof:name":"Tungulu",
    "wof:placetype":"locality"
},
  "geometry": {"coordinates":[24.73333,-17.28333],"type":"Point"}
}