{
  "type": "Feature",
  "properties": {
    "gn:admin1_code":"6.0",
    "gn:asciiname":"Kajila",
    "gn:country_code":"ZM",
    "gn:dem":1073,
    "gn:feature_class":"P",
    "gn:feature_code":"PPL",
    "gn:name":"Kajila",
    "gn:population":0,
    "gn:timezone":"Africa/Lusaka",
    "iso:country":"ZM",
    "name:und_x_variant":[
        "Kazila",
        "Kajila"
    ],
    "wof:name":"Kajila",
    "wof:placetype":"locality"
},
  "geometry": {"coordinates":[22.45,-13.46667],"type":"Point"}
}