{
  "type": "Feature",
  "properties": {
    "gn:admin1_code":"7.0",
    "gn:asciiname":"Siantumba",
    "gn:country_code":"ZM",
    "gn:dem":1043,
    "gn:feature_class":"P",
    "gn:feature_code":"PPL",
    "gn:name":"Siantumba",
    "gn:population":0,
    "gn:timezone":"Africa/Lusaka",
    "iso:country":"ZM",
    "wof:name":"Siantumba",
    "wof:placetype":"locality"
},
  "geometry": {"coordinates":[27.66667,-16.03333],"type":"Point"}
}