{
  "type": "Feature",
  "properties": {
    "gn:admin1_code":"10.0",
    "gn:asciiname":"Andrew Sinkala",
    "gn:country_code":"ZM",
    "gn:dem":1309,
    "gn:feature_class":"P",
    "gn:feature_code":"PPL",
    "gn:name":"Andrew Sinkala",
    "gn:population":0,
    "gn:timezone":"Africa/Lusaka",
    "iso:country":"ZM",
    "name:ara_x_preferred":[
        "\u0623\u0646\u062f\u0631\u064a\u0647 \u0645\u0648\u062a\u0627\u0645\u0628\u0648 \u0633\u064a\u0646\u0643\u0627\u0644\u0627"
    ],
    "name:deu_x_preferred":[
        "Andrew Sinkala"
    ],
    "name:fra_x_preferred":[
        "Andrew Sinkala"
    ],
    "name:ita_x_preferred":[
        "Andrew Sinkala"
    ],
    "name:jpn_x_preferred":[
        "\u30a2\u30f3\u30c9\u30ea\u30e5\u30fc\u30fb\u30b7\u30f3\u30ab\u30e9"
    ],
    "name:pol_x_preferred":[
        "Andrew Sinkala"
    ],
    "name:spa_x_preferred":[
        "Andrew Sinkala"
    ],
    "wof:name":"Andrew Sinkala",
    "wof:placetype":"locality"
},
  "geometry": {"coordinates":[32.61667,-9.56667],"type":"Point"}
}