{
  "type": "Feature",
  "properties": {
    "gn:admin1_code":"3.0",
    "gn:asciiname":"Chiwale",
    "gn:country_code":"ZM",
    "gn:dem":1044,
    "gn:feature_class":"P",
    "gn:feature_code":"PPL",
    "gn:name":"Chiwale",
    "gn:population":0,
    "gn:timezone":"Africa/Lusaka",
    "iso:country":"ZM",
    "name:und_x_variant":[
        "Chawale",
        "Chiwela",
        "Chiwale"
    ],
    "wof:name":"Chiwale",
    "wof:placetype":"locality"
},
  "geometry": {"coordinates":[31.71667,-14.46667],"type":"Point"}
}