{
  "type": "Feature",
  "properties": {
    "gn:admin1_code":"5.0",
    "gn:asciiname":"Kenneth",
    "gn:country_code":"ZM",
    "gn:dem":828,
    "gn:feature_class":"P",
    "gn:feature_code":"PPL",
    "gn:name":"Kenneth",
    "gn:population":0,
    "gn:timezone":"Africa/Lusaka",
    "iso:country":"ZM",
    "name:deu_x_preferred":[
        "Kenneth"
    ],
    "name:epo_x_preferred":[
        "Kenneth"
    ],
    "name:fin_x_preferred":[
        "Kenneth"
    ],
    "name:gla_x_preferred":[
        "Coinneach"
    ],
    "name:glg_x_preferred":[
        "Kenneth"
    ],
    "name:heb_x_preferred":[
        "\u05e7\u05e0\u05ea"
    ],
    "name:ita_x_preferred":[
        "Kenneth"
    ],
    "name:jpn_x_preferred":[
        "\u30b1\u30cd\u30b9"
    ],
    "name:kor_x_preferred":[
        "\ucf00\ub124\uc2a4"
    ],
    "name:lat_x_preferred":[
        "Canicus"
    ],
    "name:nor_x_preferred":[
        "Kenneth"
    ],
    "name:spa_x_preferred":[
        "Kenneth"
    ],
    "name:swe_x_preferred":[
        "Kennet"
    ],
    "name:und_x_variant":[
        "Keneth"
    ],
    "wof:name":"Kenneth",
    "wof:placetype":"locality"
},
  "geometry": {"coordinates":[30.73333,-8.65],"type":"Point"}
}