{
  "type": "Feature",
  "properties": {
    "gn:admin1_code":"6.0",
    "gn:asciiname":"Kalengozola",
    "gn:country_code":"ZM",
    "gn:dem":1087,
    "gn:feature_class":"P",
    "gn:feature_code":"PPL",
    "gn:name":"Kalengozola",
    "gn:population":0,
    "gn:timezone":"Africa/Lusaka",
    "iso:country":"ZM",
    "wof:name":"Kalengozola",
    "wof:placetype":"locality"
},
  "geometry": {"coordinates":[23.15,-13.48333],"type":"Point"}
}