{
  "type": "Feature",
  "properties": {
    "gn:admin1_code":"3.0",
    "gn:asciiname":"Mpomwa",
    "gn:country_code":"ZM",
    "gn:dem":859,
    "gn:feature_class":"P",
    "gn:feature_code":"PPL",
    "gn:name":"Mpomwa",
    "gn:population":0,
    "gn:timezone":"Africa/Lusaka",
    "iso:country":"ZM",
    "wof:name":"Mpomwa",
    "wof:placetype":"locality"
},
  "geometry": {"coordinates":[32.33333,-13.43333],"type":"Point"}
}