{
  "type": "Feature",
  "properties": {
    "gn:admin1_code":"3.0",
    "gn:asciiname":"Nderimani",
    "gn:country_code":"ZM",
    "gn:dem":641,
    "gn:feature_class":"P",
    "gn:feature_code":"PPL",
    "gn:name":"Nderimani",
    "gn:population":0,
    "gn:timezone":"Africa/Lusaka",
    "iso:country":"ZM",
    "wof:name":"Nderimani",
    "wof:placetype":"locality"
},
  "geometry": {"coordinates":[31.88237,-13.59216],"type":"Point"}
}