{
  "type": "Feature",
  "properties": {
    "gn:admin1_code":"9.0",
    "gn:asciiname":"Kampulu",
    "gn:country_code":"ZM",
    "gn:dem":1165,
    "gn:feature_class":"P",
    "gn:feature_code":"PPL",
    "gn:name":"Kampulu",
    "gn:population":0,
    "gn:timezone":"Africa/Lusaka",
    "iso:country":"ZM",
    "wof:name":"Kampulu",
    "wof:placetype":"locality"
},
  "geometry": {"coordinates":[28.58873,-15.44148],"type":"Point"}
}