{
  "type": "Feature",
  "properties": {
    "gn:admin1_code":"3.0",
    "gn:asciiname":"Kachubwa",
    "gn:country_code":"ZM",
    "gn:dem":1063,
    "gn:feature_class":"P",
    "gn:feature_code":"PPL",
    "gn:name":"Kachubwa",
    "gn:population":0,
    "gn:timezone":"Africa/Lusaka",
    "iso:country":"ZM",
    "wof:name":"Kachubwa",
    "wof:placetype":"locality"
},
  "geometry": {"coordinates":[32.21667,-14.01667],"type":"Point"}
}