{
  "type": "Feature",
  "properties": {
    "gn:admin1_code":"10.0",
    "gn:asciiname":"Takombo",
    "gn:country_code":"ZM",
    "gn:dem":1485,
    "gn:feature_class":"P",
    "gn:feature_code":"PPL",
    "gn:name":"Takombo",
    "gn:population":0,
    "gn:timezone":"Africa/Lusaka",
    "iso:country":"ZM",
    "wof:name":"Takombo",
    "wof:placetype":"locality"
},
  "geometry": {"coordinates":[31.76667,-11.23333],"type":"Point"}
}