{
  "type": "Feature",
  "properties": {
    "gn:admin1_code":"1.0",
    "gn:asciiname":"Ngubulu",
    "gn:country_code":"ZM",
    "gn:dem":1184,
    "gn:feature_class":"P",
    "gn:feature_code":"PPL",
    "gn:name":"Ngubulu",
    "gn:population":0,
    "gn:timezone":"Africa/Lusaka",
    "iso:country":"ZM",
    "wof:name":"Ngubulu",
    "wof:placetype":"locality"
},
  "geometry": {"coordinates":[24.88415,-14.59585],"type":"Point"}
}