{
  "type": "Feature",
  "properties": {
    "gn:admin1_code":"4.0",
    "gn:asciiname":"Chimpembe",
    "gn:country_code":"ZM",
    "gn:dem":1220,
    "gn:feature_class":"P",
    "gn:feature_code":"PPL",
    "gn:name":"Chimpembe",
    "gn:population":0,
    "gn:timezone":"Africa/Lusaka",
    "iso:country":"ZM",
    "wof:name":"Chimpembe",
    "wof:placetype":"locality"
},
  "geometry": {"coordinates":[29.43461,-9.54713],"type":"Point"}
}