{
  "type": "Feature",
  "properties": {
    "gn:admin1_code":"7.0",
    "gn:asciiname":"Mbila",
    "gn:country_code":"ZM",
    "gn:dem":1052,
    "gn:feature_class":"P",
    "gn:feature_code":"PPL",
    "gn:name":"Mbila",
    "gn:population":0,
    "gn:timezone":"Africa/Lusaka",
    "iso:country":"ZM",
    "name:und_x_variant":[
        "Mulilabanyama",
        "Mbila"
    ],
    "wof:name":"Mbila",
    "wof:placetype":"locality"
},
  "geometry": {"coordinates":[26.31667,-16.15],"type":"Point"}
}