{
  "type": "Feature",
  "properties": {
    "gn:admin1_code":"3.0",
    "gn:asciiname":"Suwinda",
    "gn:country_code":"ZM",
    "gn:dem":878,
    "gn:feature_class":"P",
    "gn:feature_code":"PPL",
    "gn:name":"Suwinda",
    "gn:population":0,
    "gn:timezone":"Africa/Lusaka",
    "iso:country":"ZM",
    "wof:name":"Suwinda",
    "wof:placetype":"locality"
},
  "geometry": {"coordinates":[32.57573,-14.08895],"type":"Point"}
}