{
  "type": "Feature",
  "properties": {
    "gn:admin1_code":"2.0",
    "gn:asciiname":"Lulamba",
    "gn:country_code":"ZM",
    "gn:dem":1578,
    "gn:feature_class":"P",
    "gn:feature_code":"PPL",
    "gn:name":"Lulamba",
    "gn:population":0,
    "gn:timezone":"Africa/Lusaka",
    "iso:country":"ZM",
    "wof:name":"Lulamba",
    "wof:placetype":"locality"
},
  "geometry": {"coordinates":[30.69983,-12.94203],"type":"Point"}
}