{
  "type": "Feature",
  "properties": {
    "gn:admin1_code":"5.0",
    "gn:asciiname":"Zombe",
    "gn:country_code":"ZM",
    "gn:dem":1639,
    "gn:feature_class":"P",
    "gn:feature_code":"PPL",
    "gn:name":"Zombe",
    "gn:population":0,
    "gn:timezone":"Africa/Lusaka",
    "iso:country":"ZM",
    "wof:name":"Zombe",
    "wof:placetype":"locality"
},
  "geometry": {"coordinates":[31.43333,-8.73333],"type":"Point"}
}