{
  "type": "Feature",
  "properties": {
    "gn:admin1_code":"10.0",
    "gn:asciiname":"Sitima",
    "gn:country_code":"ZM",
    "gn:dem":1263,
    "gn:feature_class":"P",
    "gn:feature_code":"PPL",
    "gn:name":"Sitima",
    "gn:population":0,
    "gn:timezone":"Africa/Lusaka",
    "iso:country":"ZM",
    "wof:name":"Sitima",
    "wof:placetype":"locality"
},
  "geometry": {"coordinates":[32.61667,-10.08333],"type":"Point"}
}