{
  "type": "Feature",
  "properties": {
    "gn:admin1_code":"7.0",
    "gn:asciiname":"Shakulya",
    "gn:country_code":"ZM",
    "gn:dem":1246,
    "gn:feature_class":"P",
    "gn:feature_code":"PPL",
    "gn:name":"Shakulya",
    "gn:population":0,
    "gn:timezone":"Africa/Lusaka",
    "iso:country":"ZM",
    "name:und_x_variant":[
        "Shakadya",
        "Shakudya",
        "Shakulya"
    ],
    "wof:name":"Shakulya",
    "wof:placetype":"locality"
},
  "geometry": {"coordinates":[28.28645,-15.79171],"type":"Point"}
}