{
  "type": "Feature",
  "properties": {
    "gn:admin1_code":"3.0",
    "gn:asciiname":"Tenje",
    "gn:country_code":"ZM",
    "gn:dem":892,
    "gn:feature_class":"P",
    "gn:feature_code":"PPL",
    "gn:name":"Tenje",
    "gn:population":0,
    "gn:timezone":"Africa/Lusaka",
    "iso:country":"ZM",
    "wof:name":"Tenje",
    "wof:placetype":"locality"
},
  "geometry": {"coordinates":[32.89792,-14.05114],"type":"Point"}
}