{
  "type": "Feature",
  "properties": {
    "gn:admin1_code":"2.0",
    "gn:asciiname":"Mulungushi",
    "gn:country_code":"ZM",
    "gn:dem":1173,
    "gn:feature_class":"P",
    "gn:feature_code":"PPL",
    "gn:name":"Mulungushi",
    "gn:population":0,
    "gn:timezone":"Africa/Lusaka",
    "iso:country":"ZM",
    "wof:name":"Mulungushi",
    "wof:placetype":"locality"
},
  "geometry": {"coordinates":[27.14161,-14.49538],"type":"Point"}
}