{
  "type": "Feature",
  "properties": {
    "gn:admin1_code":"3.0",
    "gn:asciiname":"Chuni",
    "gn:country_code":"ZM",
    "gn:dem":577,
    "gn:feature_class":"P",
    "gn:feature_code":"PPL",
    "gn:name":"Chuni",
    "gn:population":0,
    "gn:timezone":"Africa/Lusaka",
    "iso:country":"ZM",
    "name:ceb_x_preferred":[
        "Chuni"
    ],
    "wof:name":"Chuni",
    "wof:placetype":"locality"
},
  "geometry": {"coordinates":[32.15,-12.73333],"type":"Point"}
}