{
  "type": "Feature",
  "properties": {
    "gn:admin1_code":"1.0",
    "gn:asciiname":"Kalema",
    "gn:country_code":"ZM",
    "gn:dem":1199,
    "gn:feature_class":"P",
    "gn:feature_code":"PPL",
    "gn:name":"Kalema",
    "gn:population":0,
    "gn:timezone":"Africa/Lusaka",
    "iso:country":"ZM",
    "name:azb_x_preferred":[
        "\u06a9\u0627\u0644\u0645\u0627"
    ],
    "name:fas_x_preferred":[
        "\u06a9\u0627\u0644\u0645\u0627"
    ],
    "wof:name":"Kalema",
    "wof:placetype":"locality"
},
  "geometry": {"coordinates":[24.91667,-14.56667],"type":"Point"}
}