{
  "type": "Feature",
  "properties": {
    "gn:admin1_code":"1.0",
    "gn:asciiname":"Ndundu",
    "gn:country_code":"ZM",
    "gn:dem":1046,
    "gn:feature_class":"P",
    "gn:feature_code":"PPL",
    "gn:name":"Ndundu",
    "gn:population":0,
    "gn:timezone":"Africa/Lusaka",
    "iso:country":"ZM",
    "wof:name":"Ndundu",
    "wof:placetype":"locality"
},
  "geometry": {"coordinates":[23.08333,-14.18333],"type":"Point"}
}