{
  "type": "Feature",
  "properties": {
    "gn:admin1_code":"5.0",
    "gn:asciiname":"Matandiko",
    "gn:country_code":"ZM",
    "gn:dem":1530,
    "gn:feature_class":"P",
    "gn:feature_code":"PPL",
    "gn:name":"Matandiko",
    "gn:population":0,
    "gn:timezone":"Africa/Lusaka",
    "iso:country":"ZM",
    "wof:name":"Matandiko",
    "wof:placetype":"locality"
},
  "geometry": {"coordinates":[31.68333,-9.25],"type":"Point"}
}