{
  "type": "Feature",
  "properties": {
    "gn:admin1_code":"2.0",
    "gn:asciiname":"Mwape Mapulanga",
    "gn:country_code":"ZM",
    "gn:dem":1257,
    "gn:feature_class":"P",
    "gn:feature_code":"PPL",
    "gn:name":"Mwape Mapulanga",
    "gn:population":0,
    "gn:timezone":"Africa/Lusaka",
    "iso:country":"ZM",
    "wof:name":"Mwape Mapulanga",
    "wof:placetype":"locality"
},
  "geometry": {"coordinates":[30.27537,-12.84657],"type":"Point"}
}