{
  "type": "Feature",
  "properties": {
    "gn:admin1_code":"1.0",
    "gn:asciiname":"Likupe",
    "gn:country_code":"ZM",
    "gn:dem":1070,
    "gn:feature_class":"P",
    "gn:feature_code":"PPL",
    "gn:name":"Likupe",
    "gn:population":0,
    "gn:timezone":"Africa/Lusaka",
    "iso:country":"ZM",
    "wof:name":"Likupe",
    "wof:placetype":"locality"
},
  "geometry": {"coordinates":[22.56667,-15.15],"type":"Point"}
}