{
  "type": "Feature",
  "properties": {
    "gn:admin1_code":"6.0",
    "gn:asciiname":"Mulumbakanyi",
    "gn:country_code":"ZM",
    "gn:dem":1077,
    "gn:feature_class":"P",
    "gn:feature_code":"PPL",
    "gn:name":"Mulumbakanyi",
    "gn:population":0,
    "gn:timezone":"Africa/Lusaka",
    "iso:country":"ZM",
    "name:und_x_variant":[
        "Mulumbakani",
        "Mulumbakanyi"
    ],
    "wof:name":"Mulumbakanyi",
    "wof:placetype":"locality"
},
  "geometry": {"coordinates":[23.45185,-13.72972],"type":"Point"}
}