{
  "type": "Feature",
  "properties": {
    "gn:admin1_code":"6.0",
    "gn:asciiname":"Mukenda",
    "gn:country_code":"ZM",
    "gn:dem":1084,
    "gn:feature_class":"P",
    "gn:feature_code":"PPL",
    "gn:name":"Mukenda",
    "gn:population":0,
    "gn:timezone":"Africa/Lusaka",
    "iso:country":"ZM",
    "wof:name":"Mukenda",
    "wof:placetype":"locality"
},
  "geometry": {"coordinates":[23.07553,-13.44649],"type":"Point"}
}