{
  "type": "Feature",
  "properties": {
    "gn:admin1_code":"1.0",
    "gn:asciiname":"Siamizinga",
    "gn:country_code":"ZM",
    "gn:dem":1108,
    "gn:feature_class":"P",
    "gn:feature_code":"PPL",
    "gn:name":"Siamizinga",
    "gn:population":0,
    "gn:timezone":"Africa/Lusaka",
    "iso:country":"ZM",
    "wof:name":"Siamizinga",
    "wof:placetype":"locality"
},
  "geometry": {"coordinates":[24.96634,-16.50796],"type":"Point"}
}