{
  "type": "Feature",
  "properties": {
    "gn:admin1_code":"1.0",
    "gn:asciiname":"Bwina",
    "gn:country_code":"ZM",
    "gn:dem":1103,
    "gn:feature_class":"P",
    "gn:feature_code":"PPL",
    "gn:name":"Bwina",
    "gn:population":0,
    "gn:timezone":"Africa/Lusaka",
    "iso:country":"ZM",
    "wof:name":"Bwina",
    "wof:placetype":"locality"
},
  "geometry": {"coordinates":[24.95461,-16.43941],"type":"Point"}
}