{
  "type": "Feature",
  "properties": {
    "gn:admin1_code":"3.0",
    "gn:asciiname":"Mkubwa",
    "gn:country_code":"ZM",
    "gn:dem":647,
    "gn:feature_class":"P",
    "gn:feature_code":"PPL",
    "gn:name":"Mkubwa",
    "gn:population":0,
    "gn:timezone":"Africa/Lusaka",
    "iso:country":"ZM",
    "wof:name":"Mkubwa",
    "wof:placetype":"locality"
},
  "geometry": {"coordinates":[32.11115,-13.42606],"type":"Point"}
}