{
  "type": "Feature",
  "properties": {
    "gn:admin1_code":"6.0",
    "gn:asciiname":"Mwepu",
    "gn:country_code":"ZM",
    "gn:dem":1323,
    "gn:feature_class":"P",
    "gn:feature_code":"PPL",
    "gn:name":"Mwepu",
    "gn:population":0,
    "gn:timezone":"Africa/Lusaka",
    "iso:country":"ZM",
    "name:und_x_variant":[
        "Mwepa",
        "Mwepu"
    ],
    "wof:name":"Mwepu",
    "wof:placetype":"locality"
},
  "geometry": {"coordinates":[26.48333,-12.41667],"type":"Point"}
}