{
  "type": "Feature",
  "properties": {
    "gn:admin1_code":"2.0",
    "gn:asciiname":"Kawinga",
    "gn:country_code":"ZM",
    "gn:dem":1172,
    "gn:feature_class":"P",
    "gn:feature_code":"PPL",
    "gn:name":"Kawinga",
    "gn:population":0,
    "gn:timezone":"Africa/Lusaka",
    "iso:country":"ZM",
    "wof:name":"Kawinga",
    "wof:placetype":"locality"
},
  "geometry": {"coordinates":[29.89975,-12.38986],"type":"Point"}
}