{
  "type": "Feature",
  "properties": {
    "gn:admin1_code":"10.0",
    "gn:asciiname":"Kasembe",
    "gn:country_code":"ZM",
    "gn:dem":754,
    "gn:feature_class":"P",
    "gn:feature_code":"PPL",
    "gn:name":"Kasembe",
    "gn:population":0,
    "gn:timezone":"Africa/Lusaka",
    "iso:country":"ZM",
    "wof:name":"Kasembe",
    "wof:placetype":"locality"
},
  "geometry": {"coordinates":[33.11596,-11.11085],"type":"Point"}
}