{
  "type": "Feature",
  "properties": {
    "gn:admin1_code":"3.0",
    "gn:asciiname":"Philipo",
    "gn:country_code":"ZM",
    "gn:dem":643,
    "gn:feature_class":"P",
    "gn:feature_code":"PPL",
    "gn:name":"Philipo",
    "gn:population":0,
    "gn:timezone":"Africa/Lusaka",
    "iso:country":"ZM",
    "name:und_x_variant":[
        "Phillipo",
        "Philipo"
    ],
    "wof:name":"Philipo",
    "wof:placetype":"locality"
},
  "geometry": {"coordinates":[31.60012,-13.71919],"type":"Point"}
}