{
  "type": "Feature",
  "properties": {
    "gn:admin1_code":"5.0",
    "gn:asciiname":"Machemba",
    "gn:country_code":"ZM",
    "gn:dem":1358,
    "gn:feature_class":"P",
    "gn:feature_code":"PPL",
    "gn:name":"Machemba",
    "gn:population":0,
    "gn:timezone":"Africa/Lusaka",
    "iso:country":"ZM",
    "wof:name":"Machemba",
    "wof:placetype":"locality"
},
  "geometry": {"coordinates":[31.41603,-10.12318],"type":"Point"}
}