{
  "type": "Feature",
  "properties": {
    "gn:admin1_code":"5.0",
    "gn:asciiname":"Nsombo",
    "gn:country_code":"ZM",
    "gn:dem":1186,
    "gn:feature_class":"P",
    "gn:feature_code":"PPL",
    "gn:name":"Nsombo",
    "gn:population":0,
    "gn:timezone":"Africa/Lusaka",
    "iso:country":"ZM",
    "wof:name":"Nsombo",
    "wof:placetype":"locality"
},
  "geometry": {"coordinates":[29.95,-10.81667],"type":"Point"}
}