{
  "type": "Feature",
  "properties": {
    "gn:admin1_code":"6.0",
    "gn:asciiname":"Sambaza",
    "gn:country_code":"ZM",
    "gn:dem":1054,
    "gn:feature_class":"P",
    "gn:feature_code":"PPL",
    "gn:name":"Sambaza",
    "gn:population":0,
    "gn:timezone":"Africa/Lusaka",
    "iso:country":"ZM",
    "wof:name":"Sambaza",
    "wof:placetype":"locality"
},
  "geometry": {"coordinates":[22.88333,-13.16667],"type":"Point"}
}