{
  "type": "Feature",
  "properties": {
    "gn:admin1_code":"1.0",
    "gn:asciiname":"Ntesa",
    "gn:country_code":"ZM",
    "gn:dem":1009,
    "gn:feature_class":"P",
    "gn:feature_code":"PPL",
    "gn:name":"Ntesa",
    "gn:population":0,
    "gn:timezone":"Africa/Lusaka",
    "iso:country":"ZM",
    "wof:name":"Ntesa",
    "wof:placetype":"locality"
},
  "geometry": {"coordinates":[24.50491,-17.15098],"type":"Point"}
}