{
  "type": "Feature",
  "properties": {
    "iso:country":"ZM",
    "qs:gn_country":"ZM",
    "qs:gn_fcode":"PPLX",
    "qs:gn_pop":0,
    "qs:name":"Libuyu",
    "qs:name_adm0":"Zambia",
    "qs:name_adm1":"Southern",
    "qs:photos":32,
    "qs:photos_1k":6,
    "qs:photos_9k":1,
    "qs:photos_9r":2,
    "qs:photos_all":32,
    "qs:photos_sr":2,
    "qs:placetype":"Town",
    "qs:pop_sr":"0",
    "qs:woe_adm0":23425003,
    "wof:name":"Libuyu",
    "wof:placetype":"locality"
},
  "geometry": {"coordinates":[25.88333,-17.85],"type":"Point"}
}