{
  "type": "Feature",
  "properties": {
    "gn:admin1_code":"7.0",
    "gn:asciiname":"Nzovu",
    "gn:country_code":"ZM",
    "gn:dem":1007,
    "gn:feature_class":"P",
    "gn:feature_code":"PPL",
    "gn:name":"Nzovu",
    "gn:population":0,
    "gn:timezone":"Africa/Lusaka",
    "iso:country":"ZM",
    "name:und_x_variant":[
        "Nzofu",
        "Nzovu"
    ],
    "wof:name":"Nzovu",
    "wof:placetype":"locality"
},
  "geometry": {"coordinates":[26.77318,-15.4132],"type":"Point"}
}