{
  "type": "Feature",
  "properties": {
    "gn:admin1_code":"2.0",
    "gn:asciiname":"Takasia",
    "gn:country_code":"ZM",
    "gn:dem":1282,
    "gn:feature_class":"P",
    "gn:feature_code":"PPL",
    "gn:name":"Takasia",
    "gn:population":0,
    "gn:timezone":"Africa/Lusaka",
    "iso:country":"ZM",
    "wof:name":"Takasia",
    "wof:placetype":"locality"
},
  "geometry": {"coordinates":[29.86667000000001,-12.86667],"type":"Point"}
}