{
  "type": "Feature",
  "properties": {
    "gn:admin1_code":"10.0",
    "gn:asciiname":"Mitonda",
    "gn:country_code":"ZM",
    "gn:dem":1345,
    "gn:feature_class":"P",
    "gn:feature_code":"PPL",
    "gn:name":"Mitonda",
    "gn:population":0,
    "gn:timezone":"Africa/Lusaka",
    "iso:country":"ZM",
    "wof:name":"Mitonda",
    "wof:placetype":"locality"
},
  "geometry": {"coordinates":[31.51114,-11.01211],"type":"Point"}
}