{
  "type": "Feature",
  "properties": {
    "gn:admin1_code":"1.0",
    "gn:asciiname":"Yusikwakuonga",
    "gn:country_code":"ZM",
    "gn:dem":1076,
    "gn:feature_class":"P",
    "gn:feature_code":"PPL",
    "gn:name":"Yusikwakuonga",
    "gn:population":0,
    "gn:timezone":"Africa/Lusaka",
    "iso:country":"ZM",
    "wof:name":"Yusikwakuonga",
    "wof:placetype":"locality"
},
  "geometry": {"coordinates":[23.56667,-15.38333],"type":"Point"}
}