{
  "type": "Feature",
  "properties": {
    "gn:admin1_code":"7.0",
    "gn:asciiname":"Sianambwe",
    "gn:country_code":"ZM",
    "gn:dem":656,
    "gn:feature_class":"P",
    "gn:feature_code":"PPL",
    "gn:name":"Sianambwe",
    "gn:population":0,
    "gn:timezone":"Africa/Lusaka",
    "iso:country":"ZM",
    "name:und_x_variant":[
        "Siananbwe",
        "Sianambwe"
    ],
    "wof:name":"Sianambwe",
    "wof:placetype":"locality"
},
  "geometry": {"coordinates":[28.05,-16.56667],"type":"Point"}
}