{
  "type": "Feature",
  "properties": {
    "gn:admin1_code":"1.0",
    "gn:asciiname":"Kakinda",
    "gn:country_code":"ZM",
    "gn:dem":1174,
    "gn:feature_class":"P",
    "gn:feature_code":"PPL",
    "gn:name":"Kakinda",
    "gn:population":0,
    "gn:timezone":"Africa/Lusaka",
    "iso:country":"ZM",
    "wof:name":"Kakinda",
    "wof:placetype":"locality"
},
  "geometry": {"coordinates":[24.85,-15.06667],"type":"Point"}
}