{
  "type": "Feature",
  "properties": {
    "gn:admin1_code":"6.0",
    "gn:asciiname":"Jobolola",
    "gn:country_code":"ZM",
    "gn:dem":1170,
    "gn:feature_class":"P",
    "gn:feature_code":"PPL",
    "gn:name":"Jobolola",
    "gn:population":0,
    "gn:timezone":"Africa/Lusaka",
    "iso:country":"ZM",
    "wof:name":"Jobolola",
    "wof:placetype":"locality"
},
  "geometry": {"coordinates":[25.56667,-12.73333],"type":"Point"}
}