{
  "type": "Feature",
  "properties": {
    "gn:admin1_code":"10.0",
    "gn:asciiname":"Mbokozi",
    "gn:country_code":"ZM",
    "gn:dem":1502,
    "gn:feature_class":"P",
    "gn:feature_code":"PPL",
    "gn:name":"Mbokozi",
    "gn:population":0,
    "gn:timezone":"Africa/Lusaka",
    "iso:country":"ZM",
    "name:und_x_variant":[
        "Mbukozi",
        "Mbokozi"
    ],
    "wof:name":"Mbokozi",
    "wof:placetype":"locality"
},
  "geometry": {"coordinates":[32.89763,-9.43608],"type":"Point"}
}