{
  "type": "Feature",
  "properties": {
    "gn:admin1_code":"2.0",
    "gn:asciiname":"Balumika",
    "gn:country_code":"ZM",
    "gn:dem":1207,
    "gn:feature_class":"P",
    "gn:feature_code":"PPL",
    "gn:name":"Balumika",
    "gn:population":0,
    "gn:timezone":"Africa/Lusaka",
    "iso:country":"ZM",
    "wof:name":"Balumika",
    "wof:placetype":"locality"
},
  "geometry": {"coordinates":[29.41667,-14.46667],"type":"Point"}
}