{
  "type": "Feature",
  "properties": {
    "gn:admin1_code":"2.0",
    "gn:asciiname":"Miselo Funga",
    "gn:country_code":"ZM",
    "gn:dem":1416,
    "gn:feature_class":"P",
    "gn:feature_code":"PPL",
    "gn:name":"Miselo Funga",
    "gn:population":0,
    "gn:timezone":"Africa/Lusaka",
    "iso:country":"ZM",
    "wof:name":"Miselo Funga",
    "wof:placetype":"locality"
},
  "geometry": {"coordinates":[30.40684000000001,-12.93933],"type":"Point"}
}