{
  "type": "Feature",
  "properties": {
    "gn:admin1_code":"2.0",
    "gn:asciiname":"Sitanko",
    "gn:country_code":"ZM",
    "gn:dem":502,
    "gn:feature_class":"P",
    "gn:feature_code":"PPL",
    "gn:name":"Sitanko",
    "gn:population":0,
    "gn:timezone":"Africa/Lusaka",
    "iso:country":"ZM",
    "wof:name":"Sitanko",
    "wof:placetype":"locality"
},
  "geometry": {"coordinates":[29.14788,-14.82444],"type":"Point"}
}