{
  "type": "Feature",
  "properties": {
    "gn:admin1_code":"1.0",
    "gn:asciiname":"Nguni",
    "gn:country_code":"ZM",
    "gn:dem":1064,
    "gn:feature_class":"P",
    "gn:feature_code":"PPL",
    "gn:name":"Nguni",
    "gn:population":0,
    "gn:timezone":"Africa/Lusaka",
    "iso:country":"ZM",
    "name:afr_x_preferred":[
        "Nguni"
    ],
    "name:ceb_x_preferred":[
        "Nguni"
    ],
    "name:fra_x_preferred":[
        "Nguni"
    ],
    "name:rus_x_preferred":[
        "\u041d\u0433\u0443\u043d\u0438"
    ],
    "name:swe_x_preferred":[
        "Nguni"
    ],
    "wof:name":"Nguni",
    "wof:placetype":"locality"
},
  "geometry": {"coordinates":[22.53333,-15.21667],"type":"Point"}
}