{
  "type": "Feature",
  "properties": {
    "gn:admin1_code":"1.0",
    "gn:asciiname":"Nguni",
    "gn:country_code":"ZM",
    "gn:dem":1064,
    "gn:feature_class":"P",
    "gn:feature_code":"PPL",
    "gn:name":"Nguni",
    "gn:population":0,
    "gn:timezone":"Africa/Lusaka",
    "iso:country":"ZM",
    "wof:name":"Nguni",
    "wof:placetype":"locality"
},
  "geometry": {"coordinates":[22.53333,-15.21667],"type":"Point"}
}