{
  "type": "Feature",
  "properties": {
    "gn:admin1_code":"7.0",
    "gn:asciiname":"Namashova",
    "gn:country_code":"ZM",
    "gn:dem":1295,
    "gn:feature_class":"P",
    "gn:feature_code":"PPL",
    "gn:name":"Namashova",
    "gn:population":0,
    "gn:timezone":"Africa/Lusaka",
    "iso:country":"ZM",
    "wof:name":"Namashova",
    "wof:placetype":"locality"
},
  "geometry": {"coordinates":[27.03333,-16.85],"type":"Point"}
}