{
  "type": "Feature",
  "properties": {
    "gn:admin1_code":"10.0",
    "gn:asciiname":"Chitembo",
    "gn:country_code":"ZM",
    "gn:dem":1536,
    "gn:feature_class":"P",
    "gn:feature_code":"PPL",
    "gn:name":"Chitembo",
    "gn:population":0,
    "gn:timezone":"Africa/Lusaka",
    "iso:country":"ZM",
    "wof:name":"Chitembo",
    "wof:placetype":"locality"
},
  "geometry": {"coordinates":[31.72723,-11.44748],"type":"Point"}
}