{
  "type": "Feature",
  "properties": {
    "gn:admin1_code":"1.0",
    "gn:asciiname":"Mulauli",
    "gn:country_code":"ZM",
    "gn:dem":972,
    "gn:feature_class":"P",
    "gn:feature_code":"PPL",
    "gn:name":"Mulauli",
    "gn:population":0,
    "gn:timezone":"Africa/Lusaka",
    "iso:country":"ZM",
    "name:und_x_variant":[
        "Maulauli",
        "Muliuli",
        "Mulauli"
    ],
    "wof:name":"Mulauli",
    "wof:placetype":"locality"
},
  "geometry": {"coordinates":[25.13932,-16.92441],"type":"Point"}
}