{
  "type": "Feature",
  "properties": {
    "gn:admin1_code":"5.0",
    "gn:asciiname":"Chisinga",
    "gn:country_code":"ZM",
    "gn:dem":1197,
    "gn:feature_class":"P",
    "gn:feature_code":"PPL",
    "gn:name":"Chisinga",
    "gn:population":0,
    "gn:timezone":"Africa/Lusaka",
    "iso:country":"ZM",
    "wof:name":"Chisinga",
    "wof:placetype":"locality"
},
  "geometry": {"coordinates":[29.48333,-10.71667],"type":"Point"}
}