{
  "type": "Feature",
  "properties": {
    "gn:admin1_code":"2.0",
    "gn:asciiname":"Musela",
    "gn:country_code":"ZM",
    "gn:dem":1183,
    "gn:feature_class":"P",
    "gn:feature_code":"PPL",
    "gn:name":"Musela",
    "gn:population":0,
    "gn:timezone":"Africa/Lusaka",
    "iso:country":"ZM",
    "name:und_x_variant":[
        "Musera",
        "Musela"
    ],
    "wof:name":"Musela",
    "wof:placetype":"locality"
},
  "geometry": {"coordinates":[30.06667,-12.58333],"type":"Point"}
}