{
  "type": "Feature",
  "properties": {
    "gn:admin1_code":"9.0",
    "gn:asciiname":"Buckleys",
    "gn:cc2":"ZM",
    "gn:country_code":"ZM",
    "gn:dem":1251,
    "gn:feature_class":"P",
    "gn:feature_code":"PPL",
    "gn:name":"Buckleys",
    "gn:population":0,
    "gn:timezone":"Africa/Lusaka",
    "iso:country":"ZM",
    "name:und_x_variant":[
        "Buckleys Township",
        "Buckleys"
    ],
    "wof:name":"Buckleys",
    "wof:placetype":"locality"
},
  "geometry": {"coordinates":[28.23333,-15.51667],"type":"Point"}
}