{
  "type": "Feature",
  "properties": {
    "gn:admin1_code":"7.0",
    "gn:asciiname":"Mwanachisalu",
    "gn:country_code":"ZM",
    "gn:dem":1039,
    "gn:feature_class":"P",
    "gn:feature_code":"PPL",
    "gn:name":"Mwanachisalu",
    "gn:population":0,
    "gn:timezone":"Africa/Lusaka",
    "iso:country":"ZM",
    "wof:name":"Mwanachisalu",
    "wof:placetype":"locality"
},
  "geometry": {"coordinates":[26.05,-16.01667],"type":"Point"}
}