{
  "type": "Feature",
  "properties": {
    "gn:admin1_code":"10.0",
    "gn:asciiname":"Longwe",
    "gn:country_code":"ZM",
    "gn:dem":760,
    "gn:feature_class":"P",
    "gn:feature_code":"PPL",
    "gn:name":"Longwe",
    "gn:population":0,
    "gn:timezone":"Africa/Lusaka",
    "iso:country":"ZM",
    "wof:name":"Longwe",
    "wof:placetype":"locality"
},
  "geometry": {"coordinates":[33.18333,-10.85],"type":"Point"}
}