{
  "type": "Feature",
  "properties": {
    "gn:admin1_code":"2.0",
    "gn:asciiname":"Ezekiya Nkamfwa",
    "gn:country_code":"ZM",
    "gn:dem":1497,
    "gn:feature_class":"P",
    "gn:feature_code":"PPL",
    "gn:name":"Ezekiya Nkamfwa",
    "gn:population":0,
    "gn:timezone":"Africa/Lusaka",
    "iso:country":"ZM",
    "wof:name":"Ezekiya Nkamfwa",
    "wof:placetype":"locality"
},
  "geometry": {"coordinates":[30.69891,-12.8774],"type":"Point"}
}