{
  "type": "Feature",
  "properties": {
    "gn:admin1_code":"8.0",
    "gn:asciiname":"Munkumpu",
    "gn:country_code":"ZM",
    "gn:dem":1201,
    "gn:feature_class":"P",
    "gn:feature_code":"PPL",
    "gn:name":"Munkumpu",
    "gn:population":0,
    "gn:timezone":"Africa/Lusaka",
    "iso:country":"ZM",
    "wof:name":"Munkumpu",
    "wof:placetype":"locality"
},
  "geometry": {"coordinates":[27.81304,-13.5899],"type":"Point"}
}