{
  "type": "Feature",
  "properties": {
    "gn:admin1_code":"10.0",
    "gn:asciiname":"Lazarus",
    "gn:country_code":"ZM",
    "gn:dem":1498,
    "gn:feature_class":"P",
    "gn:feature_code":"PPL",
    "gn:name":"Lazarus",
    "gn:population":0,
    "gn:timezone":"Africa/Lusaka",
    "iso:country":"ZM",
    "name:ara_x_preferred":[
        "\u0644\u0627\u0632\u0627\u0631\u0648\u0633"
    ],
    "name:deu_x_preferred":[
        "Lazarus"
    ],
    "name:est_x_preferred":[
        "Laatsarus"
    ],
    "name:fin_x_preferred":[
        "Lazarus"
    ],
    "name:fra_x_preferred":[
        "Lazarus"
    ],
    "name:heb_x_preferred":[
        "\u05dc\u05d6\u05e8\u05d5\u05e1"
    ],
    "name:hun_x_preferred":[
        "Lazarus"
    ],
    "name:ind_x_preferred":[
        "Lazarus"
    ],
    "name:ita_x_preferred":[
        "Lazarus"
    ],
    "name:jpn_x_preferred":[
        "\u30e9\u30b6\u30ed"
    ],
    "name:kor_x_preferred":[
        "\ub77c\uc790\ub8e8\uc2a4"
    ],
    "name:nld_x_preferred":[
        "Lazarus"
    ],
    "name:pol_x_preferred":[
        "Lazarus"
    ],
    "name:por_x_preferred":[
        "Lazarus"
    ],
    "name:rus_x_preferred":[
        "\u041b\u0430\u0437\u0430\u0440\u0443\u0441"
    ],
    "name:spa_x_preferred":[
        "Lazarus"
    ],
    "name:srp_x_preferred":[
        "\u041b\u0430\u0437\u0430\u0440\u0443\u0441"
    ],
    "name:swe_x_preferred":[
        "Lasarus"
    ],
    "name:tur_x_preferred":[
        "Lazarus"
    ],
    "name:zho_x_preferred":[
        "\u62c9\u6492\u8def"
    ],
    "wof:name":"Lazarus",
    "wof:placetype":"locality"
},
  "geometry": {"coordinates":[33.26667,-10.25],"type":"Point"}
}