{
  "type": "Feature",
  "properties": {
    "gn:admin1_code":"10.0",
    "gn:asciiname":"Lazarus",
    "gn:country_code":"ZM",
    "gn:dem":1498,
    "gn:feature_class":"P",
    "gn:feature_code":"PPL",
    "gn:name":"Lazarus",
    "gn:population":0,
    "gn:timezone":"Africa/Lusaka",
    "iso:country":"ZM",
    "wof:name":"Lazarus",
    "wof:placetype":"locality"
},
  "geometry": {"coordinates":[33.26667,-10.25],"type":"Point"}
}