{
  "type": "Feature",
  "properties": {
    "gn:admin1_code":"7.0",
    "gn:asciiname":"Siabunkululu",
    "gn:country_code":"ZM",
    "gn:dem":1188,
    "gn:feature_class":"P",
    "gn:feature_code":"PPL",
    "gn:name":"Siabunkululu",
    "gn:population":0,
    "gn:timezone":"Africa/Lusaka",
    "iso:country":"ZM",
    "name:und_x_variant":[
        "Siavunkururu",
        "Siabunkululu"
    ],
    "wof:name":"Siabunkululu",
    "wof:placetype":"locality"
},
  "geometry": {"coordinates":[26.66928,-16.47538],"type":"Point"}
}