{
  "type": "Feature",
  "properties": {
    "gn:admin1_code":"1.0",
    "gn:asciiname":"Sampande",
    "gn:country_code":"ZM",
    "gn:dem":1096,
    "gn:feature_class":"P",
    "gn:feature_code":"PPL",
    "gn:name":"Sampande",
    "gn:population":0,
    "gn:timezone":"Africa/Lusaka",
    "iso:country":"ZM",
    "wof:name":"Sampande",
    "wof:placetype":"locality"
},
  "geometry": {"coordinates":[24.77685,-16.55936],"type":"Point"}
}