{
  "type": "Feature",
  "properties": {
    "gn:admin1_code":"1.0",
    "gn:asciiname":"Sitwala",
    "gn:country_code":"ZM",
    "gn:dem":1040,
    "gn:feature_class":"P",
    "gn:feature_code":"PPL",
    "gn:name":"Sitwala",
    "gn:population":0,
    "gn:timezone":"Africa/Lusaka",
    "iso:country":"ZM",
    "wof:name":"Sitwala",
    "wof:placetype":"locality"
},
  "geometry": {"coordinates":[23.03333,-16.15],"type":"Point"}
}