{
  "type": "Feature",
  "properties": {
    "gn:admin1_code":"1.0",
    "gn:asciiname":"Namushakende",
    "gn:country_code":"ZM",
    "gn:dem":1013,
    "gn:feature_class":"P",
    "gn:feature_code":"PPL",
    "gn:name":"Namushakende",
    "gn:population":0,
    "gn:timezone":"Africa/Lusaka",
    "iso:country":"ZM",
    "wof:name":"Namushakende",
    "wof:placetype":"locality"
},
  "geometry": {"coordinates":[23.1986,-15.42897],"type":"Point"}
}