{
  "type": "Feature",
  "properties": {
    "gn:admin1_code":"10.0",
    "gn:asciiname":"Kasera",
    "gn:country_code":"ZM",
    "gn:dem":784,
    "gn:feature_class":"P",
    "gn:feature_code":"PPL",
    "gn:name":"Kasera",
    "gn:population":0,
    "gn:timezone":"Africa/Lusaka",
    "iso:country":"ZM",
    "wof:name":"Kasera",
    "wof:placetype":"locality"
},
  "geometry": {"coordinates":[32.68333,-12.05],"type":"Point"}
}