{
  "type": "Feature",
  "properties": {
    "gn:admin1_code":"5.0",
    "gn:asciiname":"Kaniki",
    "gn:country_code":"ZM",
    "gn:dem":1368,
    "gn:feature_class":"P",
    "gn:feature_code":"PPL",
    "gn:name":"Kaniki",
    "gn:population":0,
    "gn:timezone":"Africa/Lusaka",
    "iso:country":"ZM",
    "wof:name":"Kaniki",
    "wof:placetype":"locality"
},
  "geometry": {"coordinates":[30.63504,-8.88041],"type":"Point"}
}