{
  "type": "Feature",
  "properties": {
    "gn:admin1_code":"1.0",
    "gn:asciiname":"Mampiana",
    "gn:country_code":"ZM",
    "gn:dem":1017,
    "gn:feature_class":"P",
    "gn:feature_code":"PPL",
    "gn:name":"Mampiana",
    "gn:population":0,
    "gn:timezone":"Africa/Lusaka",
    "iso:country":"ZM",
    "wof:name":"Mampiana",
    "wof:placetype":"locality"
},
  "geometry": {"coordinates":[22.86667000000001,-16.51667],"type":"Point"}
}