{
  "type": "Feature",
  "properties": {
    "gn:admin1_code":"10.0",
    "gn:asciiname":"Kalimba",
    "gn:country_code":"ZM",
    "gn:dem":615,
    "gn:feature_class":"P",
    "gn:feature_code":"PPL",
    "gn:name":"Kalimba",
    "gn:population":0,
    "gn:timezone":"Africa/Lusaka",
    "iso:country":"ZM",
    "wof:name":"Kalimba",
    "wof:placetype":"locality"
},
  "geometry": {"coordinates":[31.7626,-12.22638],"type":"Point"}
}