{
  "type": "Feature",
  "properties": {
    "gn:admin1_code":"7.0",
    "gn:asciiname":"Mukwelakasasa",
    "gn:country_code":"ZM",
    "gn:dem":1178,
    "gn:feature_class":"P",
    "gn:feature_code":"PPL",
    "gn:name":"Mukwelakasasa",
    "gn:population":0,
    "gn:timezone":"Africa/Lusaka",
    "iso:country":"ZM",
    "wof:name":"Mukwelakasasa",
    "wof:placetype":"locality"
},
  "geometry": {"coordinates":[26.58333,-16.25],"type":"Point"}
}