{
  "type": "Feature",
  "properties": {
    "gn:admin1_code":"2.0",
    "gn:asciiname":"Mulola",
    "gn:country_code":"ZM",
    "gn:dem":1094,
    "gn:feature_class":"P",
    "gn:feature_code":"PPL",
    "gn:name":"Mulola",
    "gn:population":0,
    "gn:timezone":"Africa/Lusaka",
    "iso:country":"ZM",
    "wof:name":"Mulola",
    "wof:placetype":"locality"
},
  "geometry": {"coordinates":[26.15,-14.76667],"type":"Point"}
}