{
  "type": "Feature",
  "properties": {
    "gn:admin1_code":"1.0",
    "gn:asciiname":"Lubasi",
    "gn:country_code":"ZM",
    "gn:dem":1035,
    "gn:feature_class":"P",
    "gn:feature_code":"PPL",
    "gn:name":"Lubasi",
    "gn:population":0,
    "gn:timezone":"Africa/Lusaka",
    "iso:country":"ZM",
    "wof:name":"Lubasi",
    "wof:placetype":"locality"
},
  "geometry": {"coordinates":[22.65,-15.41667],"type":"Point"}
}