{
  "type": "Feature",
  "properties": {
    "gn:admin1_code":"3.0",
    "gn:asciiname":"Langa",
    "gn:country_code":"ZM",
    "gn:dem":1029,
    "gn:feature_class":"P",
    "gn:feature_code":"PPL",
    "gn:name":"Langa",
    "gn:population":0,
    "gn:timezone":"Africa/Lusaka",
    "iso:country":"ZM",
    "wof:name":"Langa",
    "wof:placetype":"locality"
},
  "geometry": {"coordinates":[31.93333,-14.31667],"type":"Point"}
}