{
  "type": "Feature",
  "properties": {
    "gn:admin1_code":"2.0",
    "gn:asciiname":"Bulungu",
    "gn:country_code":"ZM",
    "gn:dem":1127,
    "gn:feature_class":"P",
    "gn:feature_code":"PPL",
    "gn:name":"Bulungu",
    "gn:population":0,
    "gn:timezone":"Africa/Lusaka",
    "iso:country":"ZM",
    "name:und_x_variant":[
        "Bulunga",
        "Bulungu"
    ],
    "wof:name":"Bulungu",
    "wof:placetype":"locality"
},
  "geometry": {"coordinates":[27.83146,-14.7401],"type":"Point"}
}