{
  "type": "Feature",
  "properties": {
    "gn:admin1_code":"6.0",
    "gn:asciiname":"Kalasa",
    "gn:country_code":"ZM",
    "gn:dem":1301,
    "gn:feature_class":"P",
    "gn:feature_code":"PPL",
    "gn:name":"Kalasa",
    "gn:population":0,
    "gn:timezone":"Africa/Lusaka",
    "iso:country":"ZM",
    "name:cat_x_preferred":[
        "Kalasa"
    ],
    "name:kan_x_preferred":[
        "\u0c95\u0cb3\u0cb8"
    ],
    "name:san_x_preferred":[
        "\u0915\u0933\u0938"
    ],
    "name:und_x_variant":[
        "Kavassa",
        "Kalasa"
    ],
    "wof:name":"Kalasa",
    "wof:placetype":"locality"
},
  "geometry": {"coordinates":[25.71667,-12.05],"type":"Point"}
}