{
  "type": "Feature",
  "properties": {
    "gn:admin1_code":"1.0",
    "gn:asciiname":"Njenjema",
    "gn:country_code":"ZM",
    "gn:dem":1138,
    "gn:feature_class":"P",
    "gn:feature_code":"PPL",
    "gn:name":"Njenjema",
    "gn:population":0,
    "gn:timezone":"Africa/Lusaka",
    "iso:country":"ZM",
    "wof:name":"Njenjema",
    "wof:placetype":"locality"
},
  "geometry": {"coordinates":[24.65,-15.18333],"type":"Point"}
}