{
  "type": "Feature",
  "properties": {
    "gn:admin1_code":"7.0",
    "gn:asciiname":"Melross",
    "gn:country_code":"ZM",
    "gn:dem":1279,
    "gn:feature_class":"P",
    "gn:feature_code":"PPL",
    "gn:name":"Melross",
    "gn:population":0,
    "gn:timezone":"Africa/Lusaka",
    "iso:country":"ZM",
    "wof:name":"Melross",
    "wof:placetype":"locality"
},
  "geometry": {"coordinates":[26.55098,-17.04035],"type":"Point"}
}