{
  "type": "Feature",
  "properties": {
    "gn:admin1_code":"1.0",
    "gn:asciiname":"Chinjamba",
    "gn:country_code":"ZM",
    "gn:dem":1166,
    "gn:feature_class":"P",
    "gn:feature_code":"PPL",
    "gn:name":"Chinjamba",
    "gn:population":0,
    "gn:timezone":"Africa/Lusaka",
    "iso:country":"ZM",
    "wof:name":"Chinjamba",
    "wof:placetype":"locality"
},
  "geometry": {"coordinates":[24.96667,-15.66667],"type":"Point"}
}