{
  "type": "Feature",
  "properties": {
    "gn:admin1_code":"1.0",
    "gn:asciiname":"Ndema",
    "gn:country_code":"ZM",
    "gn:dem":1086,
    "gn:feature_class":"P",
    "gn:feature_code":"PPL",
    "gn:name":"Ndema",
    "gn:population":0,
    "gn:timezone":"Africa/Lusaka",
    "iso:country":"ZM",
    "wof:name":"Ndema",
    "wof:placetype":"locality"
},
  "geometry": {"coordinates":[24.85363,-16.15418],"type":"Point"}
}