{
  "type": "Feature",
  "properties": {
    "gn:admin1_code":"7.0",
    "gn:asciiname":"Kanatola",
    "gn:country_code":"ZM",
    "gn:dem":1153,
    "gn:feature_class":"P",
    "gn:feature_code":"PPL",
    "gn:name":"Kanatola",
    "gn:population":0,
    "gn:timezone":"Africa/Lusaka",
    "iso:country":"ZM",
    "wof:name":"Kanatola",
    "wof:placetype":"locality"
},
  "geometry": {"coordinates":[27.45,-16.66667],"type":"Point"}
}