{
  "type": "Feature",
  "properties": {
    "gn:admin1_code":"6.0",
    "gn:asciiname":"Lilanda",
    "gn:country_code":"ZM",
    "gn:dem":1080,
    "gn:feature_class":"P",
    "gn:feature_code":"PPL",
    "gn:name":"Lilanda",
    "gn:population":0,
    "gn:timezone":"Africa/Lusaka",
    "iso:country":"ZM",
    "wof:name":"Lilanda",
    "wof:placetype":"locality"
},
  "geometry": {"coordinates":[23.21667,-13.68333],"type":"Point"}
}