{
  "type": "Feature",
  "properties": {
    "gn:admin1_code":"9.0",
    "gn:asciiname":"Sabao Chapita",
    "gn:country_code":"ZM",
    "gn:dem":721,
    "gn:feature_class":"P",
    "gn:feature_code":"PPL",
    "gn:name":"Sabao Chapita",
    "gn:population":0,
    "gn:timezone":"Africa/Lusaka",
    "iso:country":"ZM",
    "wof:name":"Sabao Chapita",
    "wof:placetype":"locality"
},
  "geometry": {"coordinates":[29.72067,-15.1273],"type":"Point"}
}