{
  "type": "Feature",
  "properties": {
    "gn:admin1_code":"7.0",
    "gn:asciiname":"Masuku",
    "gn:country_code":"ZM",
    "gn:dem":1297,
    "gn:feature_class":"P",
    "gn:feature_code":"PPL",
    "gn:name":"Masuku",
    "gn:population":0,
    "gn:timezone":"Africa/Lusaka",
    "iso:country":"ZM",
    "name:eng_x_preferred":[
        "Masuku"
    ],
    "name:eng_x_variant":[
        "Masuka"
    ],
    "name:und_x_variant":[
        "Masuka"
    ],
    "wof:name":"Masuku",
    "wof:placetype":"locality"
},
  "geometry": {"coordinates":[27.11311,-17.2064],"type":"Point"}
}