{
  "type": "Feature",
  "properties": {
    "gn:admin1_code":"2.0",
    "gn:asciiname":"Mukobeko",
    "gn:country_code":"ZM",
    "gn:dem":1160,
    "gn:feature_class":"P",
    "gn:feature_code":"PPL",
    "gn:name":"Mukobeko",
    "gn:population":0,
    "gn:timezone":"Africa/Lusaka",
    "iso:country":"ZM",
    "wof:name":"Mukobeko",
    "wof:placetype":"locality"
},
  "geometry": {"coordinates":[28.15,-14.36667],"type":"Point"}
}