{
  "type": "Feature",
  "properties": {
    "gn:admin1_code":"7.0",
    "gn:asciiname":"Kamwano",
    "gn:country_code":"ZM",
    "gn:dem":1287,
    "gn:feature_class":"P",
    "gn:feature_code":"PPL",
    "gn:name":"Kamwano",
    "gn:population":0,
    "gn:timezone":"Africa/Lusaka",
    "iso:country":"ZM",
    "wof:name":"Kamwano",
    "wof:placetype":"locality"
},
  "geometry": {"coordinates":[26.56667,-16.56667],"type":"Point"}
}