{
  "type": "Feature",
  "properties": {
    "gn:admin1_code":"2.0",
    "gn:asciiname":"Old Mkushi",
    "gn:country_code":"ZM",
    "gn:dem":1165,
    "gn:feature_class":"P",
    "gn:feature_code":"PPL",
    "gn:name":"Old Mkushi",
    "gn:population":0,
    "gn:timezone":"Africa/Lusaka",
    "iso:country":"ZM",
    "name:und_x_variant":[
        "Mkushi",
        "Old Mkushi"
    ],
    "wof:name":"Old Mkushi",
    "wof:placetype":"locality"
},
  "geometry": {"coordinates":[29.36295,-14.35492],"type":"Point"}
}