{
  "type": "Feature",
  "properties": {
    "gn:admin1_code":"3.0",
    "gn:asciiname":"Chawala",
    "gn:country_code":"ZM",
    "gn:dem":1104,
    "gn:feature_class":"P",
    "gn:feature_code":"PPL",
    "gn:name":"Chawala",
    "gn:population":0,
    "gn:timezone":"Africa/Lusaka",
    "iso:country":"ZM",
    "wof:name":"Chawala",
    "wof:placetype":"locality"
},
  "geometry": {"coordinates":[31.76667,-14.28333],"type":"Point"}
}