{
  "type": "Feature",
  "properties": {
    "gn:admin1_code":"7.0",
    "gn:asciiname":"Mbeza",
    "gn:country_code":"ZM",
    "gn:dem":999,
    "gn:feature_class":"P",
    "gn:feature_code":"PPL",
    "gn:name":"Mbeza",
    "gn:population":0,
    "gn:timezone":"Africa/Lusaka",
    "iso:country":"ZM",
    "wof:name":"Mbeza",
    "wof:placetype":"locality"
},
  "geometry": {"coordinates":[27.01667,-16.06667],"type":"Point"}
}