{
  "type": "Feature",
  "properties": {
    "gn:admin1_code":"1.0",
    "gn:asciiname":"Simangolwa",
    "gn:country_code":"ZM",
    "gn:dem":1047,
    "gn:feature_class":"P",
    "gn:feature_code":"PPL",
    "gn:name":"Simangolwa",
    "gn:population":0,
    "gn:timezone":"Africa/Lusaka",
    "iso:country":"ZM",
    "wof:name":"Simangolwa",
    "wof:placetype":"locality"
},
  "geometry": {"coordinates":[22.13333,-14.83333],"type":"Point"}
}