{
  "type": "Feature",
  "properties": {
    "gn:admin1_code":"1.0",
    "gn:asciiname":"Litulilo",
    "gn:country_code":"ZM",
    "gn:dem":1030,
    "gn:feature_class":"P",
    "gn:feature_code":"PPL",
    "gn:name":"Litulilo",
    "gn:population":0,
    "gn:timezone":"Africa/Lusaka",
    "iso:country":"ZM",
    "wof:name":"Litulilo",
    "wof:placetype":"locality"
},
  "geometry": {"coordinates":[22.64141,-15.4195],"type":"Point"}
}