{
  "type": "Feature",
  "properties": {
    "gn:admin1_code":"6.0",
    "gn:asciiname":"Chifwanakene",
    "gn:country_code":"ZM",
    "gn:dem":1227,
    "gn:feature_class":"P",
    "gn:feature_code":"PPL",
    "gn:name":"Chifwanakene",
    "gn:population":0,
    "gn:timezone":"Africa/Lusaka",
    "iso:country":"ZM",
    "wof:name":"Chifwanakene",
    "wof:placetype":"locality"
},
  "geometry": {"coordinates":[25.56667,-12.26667],"type":"Point"}
}