{
  "type": "Feature",
  "properties": {
    "gn:admin1_code":"10.0",
    "gn:asciiname":"Mundalanga",
    "gn:country_code":"ZM",
    "gn:dem":746,
    "gn:feature_class":"P",
    "gn:feature_code":"PPL",
    "gn:name":"Mundalanga",
    "gn:population":0,
    "gn:timezone":"Africa/Lusaka",
    "iso:country":"ZM",
    "wof:name":"Mundalanga",
    "wof:placetype":"locality"
},
  "geometry": {"coordinates":[33.09623,-11.27391],"type":"Point"}
}