{
  "type": "Feature",
  "properties": {
    "gn:admin1_code":"10.0",
    "gn:asciiname":"Mulopahatundu",
    "gn:country_code":"ZM",
    "gn:dem":544,
    "gn:feature_class":"P",
    "gn:feature_code":"PPL",
    "gn:name":"Mulopahatundu",
    "gn:population":0,
    "gn:timezone":"Africa/Lusaka",
    "iso:country":"ZM",
    "wof:name":"Mulopahatundu",
    "wof:placetype":"locality"
},
  "geometry": {"coordinates":[32.06667,-12.73333],"type":"Point"}
}