{
  "type": "Feature",
  "properties": {
    "gn:admin1_code":"7.0",
    "gn:asciiname":"Sibangani",
    "gn:country_code":"ZM",
    "gn:dem":1053,
    "gn:feature_class":"P",
    "gn:feature_code":"PPL",
    "gn:name":"Sibangani",
    "gn:population":0,
    "gn:timezone":"Africa/Lusaka",
    "iso:country":"ZM",
    "wof:name":"Sibangani",
    "wof:placetype":"locality"
},
  "geometry": {"coordinates":[25.66667,-17.56667],"type":"Point"}
}