{
  "type": "Feature",
  "properties": {
    "gn:admin1_code":"2.0",
    "gn:asciiname":"Alason Cholafula",
    "gn:country_code":"ZM",
    "gn:dem":1279,
    "gn:feature_class":"P",
    "gn:feature_code":"PPL",
    "gn:name":"Alason Cholafula",
    "gn:population":0,
    "gn:timezone":"Africa/Lusaka",
    "iso:country":"ZM",
    "wof:name":"Alason Cholafula",
    "wof:placetype":"locality"
},
  "geometry": {"coordinates":[30.42783,-12.64097],"type":"Point"}
}