{
  "type": "Feature",
  "properties": {
    "gn:admin1_code":"2.0",
    "gn:asciiname":"Chikusu",
    "gn:country_code":"ZM",
    "gn:dem":1014,
    "gn:feature_class":"P",
    "gn:feature_code":"PPL",
    "gn:name":"Chikusu",
    "gn:population":0,
    "gn:timezone":"Africa/Lusaka",
    "iso:country":"ZM",
    "wof:name":"Chikusu",
    "wof:placetype":"locality"
},
  "geometry": {"coordinates":[27.73333,-15.28333],"type":"Point"}
}