{
  "type": "Feature",
  "properties": {
    "gn:admin1_code":"1.0",
    "gn:asciiname":"Liomba",
    "gn:country_code":"ZM",
    "gn:dem":1079,
    "gn:feature_class":"P",
    "gn:feature_code":"PPL",
    "gn:name":"Liomba",
    "gn:population":0,
    "gn:timezone":"Africa/Lusaka",
    "iso:country":"ZM",
    "wof:name":"Liomba",
    "wof:placetype":"locality"
},
  "geometry": {"coordinates":[23.55,-15.51667],"type":"Point"}
}