{
  "type": "Feature",
  "properties": {
    "gn:admin1_code":"10.0",
    "gn:asciiname":"Mutonya",
    "gn:country_code":"ZM",
    "gn:dem":707,
    "gn:feature_class":"P",
    "gn:feature_code":"PPL",
    "gn:name":"Mutonya",
    "gn:population":0,
    "gn:timezone":"Africa/Lusaka",
    "iso:country":"ZM",
    "name:und_x_variant":[
        "Mtonya",
        "Mutonya"
    ],
    "wof:name":"Mutonya",
    "wof:placetype":"locality"
},
  "geometry": {"coordinates":[32.87648,-11.70658],"type":"Point"}
}