{
  "type": "Feature",
  "properties": {
    "gn:admin1_code":"1.0",
    "gn:asciiname":"Simaimpa",
    "gn:country_code":"ZM",
    "gn:dem":1091,
    "gn:feature_class":"P",
    "gn:feature_code":"PPL",
    "gn:name":"Simaimpa",
    "gn:population":0,
    "gn:timezone":"Africa/Lusaka",
    "iso:country":"ZM",
    "wof:name":"Simaimpa",
    "wof:placetype":"locality"
},
  "geometry": {"coordinates":[24.53333,-16.55],"type":"Point"}
}