{
  "type": "Feature",
  "properties": {
    "gn:admin1_code":"8.0",
    "gn:asciiname":"Kasunu",
    "gn:country_code":"ZM",
    "gn:dem":1239,
    "gn:feature_class":"P",
    "gn:feature_code":"PPL",
    "gn:name":"Kasunu",
    "gn:population":0,
    "gn:timezone":"Africa/Lusaka",
    "iso:country":"ZM",
    "wof:name":"Kasunu",
    "wof:placetype":"locality"
},
  "geometry": {"coordinates":[28.73333,-13.31667],"type":"Point"}
}