{
  "type": "Feature",
  "properties": {
    "gn:admin1_code":"1.0",
    "gn:asciiname":"Nyungu",
    "gn:country_code":"ZM",
    "gn:dem":1036,
    "gn:feature_class":"P",
    "gn:feature_code":"PPL",
    "gn:name":"Nyungu",
    "gn:population":0,
    "gn:timezone":"Africa/Lusaka",
    "iso:country":"ZM",
    "wof:name":"Nyungu",
    "wof:placetype":"locality"
},
  "geometry": {"coordinates":[22.35,-14.91667],"type":"Point"}
}