{
  "type": "Feature",
  "properties": {
    "gn:admin1_code":"3.0",
    "gn:asciiname":"Mgwalangwa",
    "gn:country_code":"ZM",
    "gn:dem":1000,
    "gn:feature_class":"P",
    "gn:feature_code":"PPL",
    "gn:name":"Mgwalangwa",
    "gn:population":0,
    "gn:timezone":"Africa/Lusaka",
    "iso:country":"ZM",
    "wof:name":"Mgwalangwa",
    "wof:placetype":"locality"
},
  "geometry": {"coordinates":[32.65653,-13.4783],"type":"Point"}
}