{
  "type": "Feature",
  "properties": {
    "gn:admin1_code":"2.0",
    "gn:asciiname":"Shanga",
    "gn:country_code":"ZM",
    "gn:dem":1300,
    "gn:feature_class":"P",
    "gn:feature_code":"PPL",
    "gn:name":"Shanga",
    "gn:population":0,
    "gn:timezone":"Africa/Lusaka",
    "iso:country":"ZM",
    "wof:name":"Shanga",
    "wof:placetype":"locality"
},
  "geometry": {"coordinates":[29.85,-12.98333],"type":"Point"}
}