{
  "type": "Feature",
  "properties": {
    "gn:admin1_code":"7.0",
    "gn:asciiname":"Kamujoma",
    "gn:country_code":"ZM",
    "gn:dem":987,
    "gn:feature_class":"P",
    "gn:feature_code":"PPL",
    "gn:name":"Kamujoma",
    "gn:population":0,
    "gn:timezone":"Africa/Lusaka",
    "iso:country":"ZM",
    "wof:name":"Kamujoma",
    "wof:placetype":"locality"
},
  "geometry": {"coordinates":[25.48333,-17.41667],"type":"Point"}
}