{
  "type": "Feature",
  "properties": {
    "gn:admin1_code":"10.0",
    "gn:asciiname":"Kabanda",
    "gn:country_code":"ZM",
    "gn:dem":1251,
    "gn:feature_class":"P",
    "gn:feature_code":"PPL",
    "gn:name":"Kabanda",
    "gn:population":0,
    "gn:timezone":"Africa/Lusaka",
    "iso:country":"ZM",
    "wof:name":"Kabanda",
    "wof:placetype":"locality"
},
  "geometry": {"coordinates":[31.29079,-10.84736],"type":"Point"}
}