{
  "type": "Feature",
  "properties": {
    "gn:admin1_code":"8.0",
    "gn:asciiname":"Misundu",
    "gn:country_code":"ZM",
    "gn:dem":1288,
    "gn:feature_class":"P",
    "gn:feature_code":"PPL",
    "gn:name":"Misundu",
    "gn:population":0,
    "gn:timezone":"Africa/Lusaka",
    "iso:country":"ZM",
    "wof:name":"Misundu",
    "wof:placetype":"locality"
},
  "geometry": {"coordinates":[28.59638,-12.83915],"type":"Point"}
}