{
  "type": "Feature",
  "properties": {
    "gn:admin1_code":"5.0",
    "gn:asciiname":"Mwamba",
    "gn:country_code":"ZM",
    "gn:dem":1306,
    "gn:feature_class":"P",
    "gn:feature_code":"PPL",
    "gn:name":"Mwamba",
    "gn:population":0,
    "gn:timezone":"Africa/Lusaka",
    "iso:country":"ZM",
    "name:und_x_variant":[
        "Mwemba",
        "Mwamba"
    ],
    "wof:name":"Mwamba",
    "wof:placetype":"locality"
},
  "geometry": {"coordinates":[31.05709,-10.09774],"type":"Point"}
}