{
  "type": "Feature",
  "properties": {
    "gn:admin1_code":"3.0",
    "gn:asciiname":"Ngapo",
    "gn:country_code":"ZM",
    "gn:dem":1053,
    "gn:feature_class":"P",
    "gn:feature_code":"PPL",
    "gn:name":"Ngapo",
    "gn:population":0,
    "gn:timezone":"Africa/Lusaka",
    "iso:country":"ZM",
    "wof:name":"Ngapo",
    "wof:placetype":"locality"
},
  "geometry": {"coordinates":[32.76667,-13.41667],"type":"Point"}
}