{
  "type": "Feature",
  "properties": {
    "gn:admin1_code":"1.0",
    "gn:asciiname":"Kataya",
    "gn:country_code":"ZM",
    "gn:dem":1023,
    "gn:feature_class":"P",
    "gn:feature_code":"PPL",
    "gn:name":"Kataya",
    "gn:population":0,
    "gn:timezone":"Africa/Lusaka",
    "iso:country":"ZM",
    "name:msa_x_preferred":[
        "Kataya"
    ],
    "wof:name":"Kataya",
    "wof:placetype":"locality"
},
  "geometry": {"coordinates":[22.78333,-15.21667],"type":"Point"}
}