{
  "type": "Feature",
  "properties": {
    "gn:admin1_code":"6.0",
    "gn:asciiname":"Kanyange",
    "gn:country_code":"ZM",
    "gn:dem":1436,
    "gn:feature_class":"P",
    "gn:feature_code":"PPL",
    "gn:name":"Kanyange",
    "gn:population":0,
    "gn:timezone":"Africa/Lusaka",
    "iso:country":"ZM",
    "wof:name":"Kanyange",
    "wof:placetype":"locality"
},
  "geometry": {"coordinates":[24.73333,-11.65],"type":"Point"}
}