{
  "type": "Feature",
  "properties": {
    "gn:admin1_code":"2.0",
    "gn:asciiname":"Sangwi",
    "gn:country_code":"ZM",
    "gn:dem":1244,
    "gn:feature_class":"P",
    "gn:feature_code":"PPL",
    "gn:name":"Sangwi",
    "gn:population":0,
    "gn:timezone":"Africa/Lusaka",
    "iso:country":"ZM",
    "wof:name":"Sangwi",
    "wof:placetype":"locality"
},
  "geometry": {"coordinates":[29.88333,-12.83333],"type":"Point"}
}