{
  "type": "Feature",
  "properties": {
    "gn:admin1_code":"1.0",
    "gn:asciiname":"Lungenda",
    "gn:country_code":"ZM",
    "gn:dem":1172,
    "gn:feature_class":"P",
    "gn:feature_code":"PPL",
    "gn:name":"Lungenda",
    "gn:population":0,
    "gn:timezone":"Africa/Lusaka",
    "iso:country":"ZM",
    "wof:name":"Lungenda",
    "wof:placetype":"locality"
},
  "geometry": {"coordinates":[25.03595,-14.63613],"type":"Point"}
}