{
  "type": "Feature",
  "properties": {
    "gn:admin1_code":"6.0",
    "gn:asciiname":"Kelongwa",
    "gn:country_code":"ZM",
    "gn:dem":1147,
    "gn:feature_class":"P",
    "gn:feature_code":"PPL",
    "gn:name":"Kelongwa",
    "gn:population":0,
    "gn:timezone":"Africa/Lusaka",
    "iso:country":"ZM",
    "wof:name":"Kelongwa",
    "wof:placetype":"locality"
},
  "geometry": {"coordinates":[26.33072,-13.70674],"type":"Point"}
}