{
  "type": "Feature",
  "properties": {
    "gn:admin1_code":"2.0",
    "gn:asciiname":"Nakwassa",
    "gn:country_code":"ZM",
    "gn:dem":1323,
    "gn:feature_class":"P",
    "gn:feature_code":"PPL",
    "gn:name":"Nakwassa",
    "gn:population":0,
    "gn:timezone":"Africa/Lusaka",
    "iso:country":"ZM",
    "wof:name":"Nakwassa",
    "wof:placetype":"locality"
},
  "geometry": {"coordinates":[30.25825,-13.61905],"type":"Point"}
}