{
  "type": "Feature",
  "properties": {
    "gn:admin1_code":"7.0",
    "gn:asciiname":"Mujalanyana",
    "gn:country_code":"ZM",
    "gn:dem":993,
    "gn:feature_class":"P",
    "gn:feature_code":"PPL",
    "gn:name":"Mujalanyana",
    "gn:population":0,
    "gn:timezone":"Africa/Lusaka",
    "iso:country":"ZM",
    "wof:name":"Mujalanyana",
    "wof:placetype":"locality"
},
  "geometry": {"coordinates":[25.51003,-17.44167],"type":"Point"}
}