{
  "type": "Feature",
  "properties": {
    "gn:admin1_code":"6.0",
    "gn:asciiname":"Ipenge",
    "gn:country_code":"ZM",
    "gn:dem":1264,
    "gn:feature_class":"P",
    "gn:feature_code":"PPL",
    "gn:name":"Ipenge",
    "gn:population":0,
    "gn:timezone":"Africa/Lusaka",
    "iso:country":"ZM",
    "wof:name":"Ipenge",
    "wof:placetype":"locality"
},
  "geometry": {"coordinates":[24.18159,-11.2031],"type":"Point"}
}