{
  "type": "Feature",
  "properties": {
    "gn:admin1_code":"2.0",
    "gn:asciiname":"Ngosa Koni",
    "gn:country_code":"ZM",
    "gn:dem":1387,
    "gn:feature_class":"P",
    "gn:feature_code":"PPL",
    "gn:name":"Ngosa Koni",
    "gn:population":0,
    "gn:timezone":"Africa/Lusaka",
    "iso:country":"ZM",
    "name:und_x_variant":[
        "Ngosi Koni",
        "Ngosa Koni"
    ],
    "wof:name":"Ngosa Koni",
    "wof:placetype":"locality"
},
  "geometry": {"coordinates":[29.83333,-13.61667],"type":"Point"}
}