{
  "type": "Feature",
  "properties": {
    "gn:admin1_code":"6.0",
    "gn:asciiname":"Mulanda",
    "gn:country_code":"ZM",
    "gn:dem":1072,
    "gn:feature_class":"P",
    "gn:feature_code":"PPL",
    "gn:name":"Mulanda",
    "gn:population":0,
    "gn:timezone":"Africa/Lusaka",
    "iso:country":"ZM",
    "wof:name":"Mulanda",
    "wof:placetype":"locality"
},
  "geometry": {"coordinates":[23.03473,-13.26764],"type":"Point"}
}