{
  "type": "Feature",
  "properties": {
    "gn:admin1_code":"5.0",
    "gn:asciiname":"Kamfumu",
    "gn:country_code":"ZM",
    "gn:dem":1177,
    "gn:feature_class":"P",
    "gn:feature_code":"PPL",
    "gn:name":"Kamfumu",
    "gn:population":0,
    "gn:timezone":"Africa/Lusaka",
    "iso:country":"ZM",
    "wof:name":"Kamfumu",
    "wof:placetype":"locality"
},
  "geometry": {"coordinates":[29.62841,-10.66706],"type":"Point"}
}