{
  "type": "Feature",
  "properties": {
    "gn:admin1_code":"3.0",
    "gn:asciiname":"Sichitambo",
    "gn:country_code":"ZM",
    "gn:dem":437,
    "gn:feature_class":"P",
    "gn:feature_code":"PPL",
    "gn:name":"Sichitambo",
    "gn:population":0,
    "gn:timezone":"Africa/Lusaka",
    "iso:country":"ZM",
    "wof:name":"Sichitambo",
    "wof:placetype":"locality"
},
  "geometry": {"coordinates":[30.3697,-14.68425],"type":"Point"}
}