{
  "type": "Feature",
  "properties": {
    "gn:admin1_code":"3.0",
    "gn:asciiname":"Kapenda",
    "gn:country_code":"ZM",
    "gn:dem":739,
    "gn:feature_class":"P",
    "gn:feature_code":"PPL",
    "gn:name":"Kapenda",
    "gn:population":0,
    "gn:timezone":"Africa/Lusaka",
    "iso:country":"ZM",
    "wof:name":"Kapenda",
    "wof:placetype":"locality"
},
  "geometry": {"coordinates":[31.55,-13.86667],"type":"Point"}
}