{
  "type": "Feature",
  "properties": {
    "gn:admin1_code":"10.0",
    "gn:asciiname":"Yazaza",
    "gn:country_code":"ZM",
    "gn:dem":1269,
    "gn:feature_class":"P",
    "gn:feature_code":"PPL",
    "gn:name":"Yazaza",
    "gn:population":0,
    "gn:timezone":"Africa/Lusaka",
    "iso:country":"ZM",
    "wof:name":"Yazaza",
    "wof:placetype":"locality"
},
  "geometry": {"coordinates":[32.58843,-10.07881],"type":"Point"}
}