{
  "type": "Feature",
  "properties": {
    "gn:admin1_code":"1.0",
    "gn:asciiname":"Mabote",
    "gn:country_code":"ZM",
    "gn:dem":1056,
    "gn:feature_class":"P",
    "gn:feature_code":"PPL",
    "gn:name":"Mabote",
    "gn:population":0,
    "gn:timezone":"Africa/Lusaka",
    "iso:country":"ZM",
    "name:urd_x_preferred":[
        "\u0645\u0627\u0628\u0648\u0679\u06cc"
    ],
    "wof:name":"Mabote",
    "wof:placetype":"locality"
},
  "geometry": {"coordinates":[24.53333,-16.96667],"type":"Point"}
}