{
  "type": "Feature",
  "properties": {
    "gn:admin1_code":"3.0",
    "gn:asciiname":"Kachenga",
    "gn:country_code":"ZM",
    "gn:dem":659,
    "gn:feature_class":"P",
    "gn:feature_code":"PPL",
    "gn:name":"Kachenga",
    "gn:population":0,
    "gn:timezone":"Africa/Lusaka",
    "iso:country":"ZM",
    "wof:name":"Kachenga",
    "wof:placetype":"locality"
},
  "geometry": {"coordinates":[31.90752,-13.65488],"type":"Point"}
}