{
  "type": "Feature",
  "properties": {
    "iso:country":"ZM",
    "name:bul_x_preferred":[
        "\u0421\u0430\u043c\u0444\u044f"
    ],
    "name:ceb_x_preferred":[
        "Samfya"
    ],
    "name:deu_x_preferred":[
        "Samfya"
    ],
    "name:eng_x_preferred":[
        "Samfya"
    ],
    "name:fra_x_preferred":[
        "Samfya"
    ],
    "name:ita_x_preferred":[
        "Samfya"
    ],
    "name:jpn_x_preferred":[
        "\u30b5\u30e0\u30d2\u30e3"
    ],
    "name:mrj_x_preferred":[
        "\u0421\u0430\u043c\u0444\u044c\u044f"
    ],
    "name:nld_x_preferred":[
        "Samfya"
    ],
    "name:pol_x_preferred":[
        "Samfya"
    ],
    "name:por_x_preferred":[
        "Samfya"
    ],
    "name:ron_x_preferred":[
        "Samfya"
    ],
    "name:spa_x_preferred":[
        "Samfya"
    ],
    "name:zho_x_preferred":[
        "\u85a9\u59c6\u83f2\u4e9e"
    ],
    "qs:gn_country":"ZM",
    "qs:gn_fcode":"PPL",
    "qs:gn_pop":20470,
    "qs:name":"Samfya",
    "qs:name_adm0":"Zambia",
    "qs:name_adm1":"Luapula",
    "qs:photos":0,
    "qs:photos_1k":0,
    "qs:photos_9k":1,
    "qs:photos_9r":1,
    "qs:photos_all":2,
    "qs:photos_sr":0,
    "qs:placetype":"Town",
    "qs:pop_sr":"7",
    "qs:woe_adm0":23425003,
    "wd:wordcount":234,
    "wof:name":"Samfya",
    "wof:placetype":"locality",
    "wof:population":20470
},
  "geometry": {"coordinates":[29.55652,-11.36491],"type":"Point"}
}