{
  "type": "Feature",
  "properties": {
    "gn:admin1_code":"3.0",
    "gn:asciiname":"Chitende",
    "gn:country_code":"ZM",
    "gn:dem":951,
    "gn:feature_class":"P",
    "gn:feature_code":"PPL",
    "gn:name":"Chitende",
    "gn:population":0,
    "gn:timezone":"Africa/Lusaka",
    "iso:country":"ZM",
    "wof:name":"Chitende",
    "wof:placetype":"locality"
},
  "geometry": {"coordinates":[32.97842,-14.06037],"type":"Point"}
}