{
  "type": "Feature",
  "properties": {
    "gn:admin1_code":"1.0",
    "gn:asciiname":"Kachakana",
    "gn:country_code":"ZM",
    "gn:dem":1048,
    "gn:feature_class":"P",
    "gn:feature_code":"PPL",
    "gn:name":"Kachakana",
    "gn:population":0,
    "gn:timezone":"Africa/Lusaka",
    "iso:country":"ZM",
    "wof:name":"Kachakana",
    "wof:placetype":"locality"
},
  "geometry": {"coordinates":[22.51667,-14.28333],"type":"Point"}
}