{
  "type": "Feature",
  "properties": {
    "gn:admin1_code":"10.0",
    "gn:asciiname":"Ndombo",
    "gn:country_code":"ZM",
    "gn:dem":624,
    "gn:feature_class":"P",
    "gn:feature_code":"PPL",
    "gn:name":"Ndombo",
    "gn:population":0,
    "gn:timezone":"Africa/Lusaka",
    "iso:country":"ZM",
    "wof:name":"Ndombo",
    "wof:placetype":"locality"
},
  "geometry": {"coordinates":[31.72626,-12.15373],"type":"Point"}
}