{
  "type": "Feature",
  "properties": {
    "gn:admin1_code":"2.0",
    "gn:asciiname":"Zuze",
    "gn:country_code":"ZM",
    "gn:dem":1132,
    "gn:feature_class":"P",
    "gn:feature_code":"PPL",
    "gn:name":"Zuze",
    "gn:population":0,
    "gn:timezone":"Africa/Lusaka",
    "iso:country":"ZM",
    "wof:name":"Zuze",
    "wof:placetype":"locality"
},
  "geometry": {"coordinates":[28.58333,-14.95],"type":"Point"}
}