{
  "type": "Feature",
  "properties": {
    "gn:admin1_code":"5.0",
    "gn:asciiname":"Chipalo",
    "gn:country_code":"ZM",
    "gn:dem":1480,
    "gn:feature_class":"P",
    "gn:feature_code":"PPL",
    "gn:name":"Chipalo",
    "gn:population":0,
    "gn:timezone":"Africa/Lusaka",
    "iso:country":"ZM",
    "wof:name":"Chipalo",
    "wof:placetype":"locality"
},
  "geometry": {"coordinates":[29.97658,-10.22181],"type":"Point"}
}