{
  "type": "Feature",
  "properties": {
    "gn:admin1_code":"7.0",
    "gn:asciiname":"Mukosivumba",
    "gn:country_code":"ZM",
    "gn:dem":1250,
    "gn:feature_class":"P",
    "gn:feature_code":"PPL",
    "gn:name":"Mukosivumba",
    "gn:population":0,
    "gn:timezone":"Africa/Lusaka",
    "iso:country":"ZM",
    "wof:name":"Mukosivumba",
    "wof:placetype":"locality"
},
  "geometry": {"coordinates":[26.81667,-16.51667],"type":"Point"}
}