{
  "type": "Feature",
  "properties": {
    "gn:admin1_code":"10.0",
    "gn:asciiname":"Kalyanankondo",
    "gn:country_code":"ZM",
    "gn:dem":652,
    "gn:feature_class":"P",
    "gn:feature_code":"PPL",
    "gn:name":"Kalyanankondo",
    "gn:population":0,
    "gn:timezone":"Africa/Lusaka",
    "iso:country":"ZM",
    "name:und_x_variant":[
        "Kulianonkonde",
        "Kalikondo",
        "Kalianankondo",
        "Kalyanankondo"
    ],
    "wof:name":"Kalyanankondo",
    "wof:placetype":"locality"
},
  "geometry": {"coordinates":[32.75102,-11.69858],"type":"Point"}
}