{
  "type": "Feature",
  "properties": {
    "gn:admin1_code":"3.0",
    "gn:asciiname":"Nyachiu",
    "gn:country_code":"ZM",
    "gn:dem":532,
    "gn:feature_class":"P",
    "gn:feature_code":"PPL",
    "gn:name":"Nyachiu",
    "gn:population":0,
    "gn:timezone":"Africa/Lusaka",
    "iso:country":"ZM",
    "name:und_x_variant":[
        "Nyachi",
        "Nyachiu"
    ],
    "wof:name":"Nyachiu",
    "wof:placetype":"locality"
},
  "geometry": {"coordinates":[31.83228,-13.1172],"type":"Point"}
}