{
  "type": "Feature",
  "properties": {
    "gn:admin1_code":"1.0",
    "gn:asciiname":"Yamba",
    "gn:country_code":"ZM",
    "gn:dem":1015,
    "gn:feature_class":"P",
    "gn:feature_code":"PPL",
    "gn:name":"Yamba",
    "gn:population":0,
    "gn:timezone":"Africa/Lusaka",
    "iso:country":"ZM",
    "name:ben_x_preferred":[
        "\u0987\u09df\u09be\u09ae\u09cd\u09ac\u09be"
    ],
    "name:ceb_x_preferred":[
        "Yamba"
    ],
    "name:deu_x_preferred":[
        "Yamba"
    ],
    "name:ell_x_preferred":[
        "\u0393\u03b9\u03ac\u03bc\u03c0\u03b1"
    ],
    "name:fra_x_preferred":[
        "Yamba"
    ],
    "name:heb_x_preferred":[
        "\u05d9\u05d0\u05de\u05d1\u05d4"
    ],
    "name:hin_x_preferred":[
        "\u092f\u093e\u092e\u094d\u092c\u093e"
    ],
    "name:hun_x_preferred":[
        "Yamba"
    ],
    "name:ita_x_preferred":[
        "Yamba"
    ],
    "name:jpn_x_preferred":[
        "\u30e4\u30f3\u30d0"
    ],
    "name:kor_x_preferred":[
        "\uc58c\ubc14"
    ],
    "name:rus_x_preferred":[
        "\u042f\u043c\u0431\u0430"
    ],
    "name:spa_x_preferred":[
        "Yamba"
    ],
    "name:swe_x_preferred":[
        "Yamba"
    ],
    "name:tur_x_preferred":[
        "Yamba"
    ],
    "name:ukr_x_preferred":[
        "\u042f\u043c\u0431\u0430"
    ],
    "name:urd_x_preferred":[
        "\u06cc\u06cc\u0645\u0628\u0627"
    ],
    "name:vie_x_preferred":[
        "Yamba"
    ],
    "name:zho_cn_x_preferred":[
        "\u626c\u5df4"
    ],
    "name:zho_tw_x_preferred":[
        "\u63da\u5df4"
    ],
    "wof:name":"Yamba",
    "wof:placetype":"locality"
},
  "geometry": {"coordinates":[22.78333,-16.55],"type":"Point"}
}