{
  "type": "Feature",
  "properties": {
    "gn:admin1_code":"5.0",
    "gn:asciiname":"Kapandila",
    "gn:country_code":"ZM",
    "gn:dem":1528,
    "gn:feature_class":"P",
    "gn:feature_code":"PPL",
    "gn:name":"Kapandila",
    "gn:population":0,
    "gn:timezone":"Africa/Lusaka",
    "iso:country":"ZM",
    "wof:name":"Kapandila",
    "wof:placetype":"locality"
},
  "geometry": {"coordinates":[31.36667000000001,-8.75],"type":"Point"}
}