{
  "type": "Feature",
  "properties": {
    "gn:admin1_code":"3.0",
    "gn:asciiname":"Katuwa",
    "gn:country_code":"ZM",
    "gn:dem":806,
    "gn:feature_class":"P",
    "gn:feature_code":"PPL",
    "gn:name":"Katuwa",
    "gn:population":0,
    "gn:timezone":"Africa/Lusaka",
    "iso:country":"ZM",
    "wof:name":"Katuwa",
    "wof:placetype":"locality"
},
  "geometry": {"coordinates":[32.41667,-13.41667],"type":"Point"}
}