{
  "type": "Feature",
  "properties": {
    "gn:admin1_code":"6.0",
    "gn:asciiname":"Kapamba",
    "gn:country_code":"ZM",
    "gn:dem":1124,
    "gn:feature_class":"P",
    "gn:feature_code":"PPL",
    "gn:name":"Kapamba",
    "gn:population":0,
    "gn:timezone":"Africa/Lusaka",
    "iso:country":"ZM",
    "wof:name":"Kapamba",
    "wof:placetype":"locality"
},
  "geometry": {"coordinates":[23.71667,-13.45],"type":"Point"}
}