{
  "type": "Feature",
  "properties": {
    "gn:admin1_code":"3.0",
    "gn:asciiname":"Kanyuka",
    "gn:country_code":"ZM",
    "gn:dem":1169,
    "gn:feature_class":"P",
    "gn:feature_code":"PPL",
    "gn:name":"Kanyuka",
    "gn:population":0,
    "gn:timezone":"Africa/Lusaka",
    "iso:country":"ZM",
    "wof:name":"Kanyuka",
    "wof:placetype":"locality"
},
  "geometry": {"coordinates":[32.93556,-12.85077],"type":"Point"}
}