{
  "type": "Feature",
  "properties": {
    "gn:admin1_code":"1.0",
    "gn:asciiname":"Kapumbula",
    "gn:country_code":"ZM",
    "gn:dem":1087,
    "gn:feature_class":"P",
    "gn:feature_code":"PPL",
    "gn:name":"Kapumbula",
    "gn:population":0,
    "gn:timezone":"Africa/Lusaka",
    "iso:country":"ZM",
    "wof:name":"Kapumbula",
    "wof:placetype":"locality"
},
  "geometry": {"coordinates":[23.68333,-15.38333],"type":"Point"}
}