{
  "type": "Feature",
  "properties": {
    "gn:admin1_code":"7.0",
    "gn:asciiname":"Sialwindi",
    "gn:country_code":"ZM",
    "gn:dem":1125,
    "gn:feature_class":"P",
    "gn:feature_code":"PPL",
    "gn:name":"Sialwindi",
    "gn:population":0,
    "gn:timezone":"Africa/Lusaka",
    "iso:country":"ZM",
    "name:und_x_variant":[
        "Harlwindi",
        "Sialwindi"
    ],
    "wof:name":"Sialwindi",
    "wof:placetype":"locality"
},
  "geometry": {"coordinates":[26.73333,-16.38332999999999],"type":"Point"}
}