{
  "type": "Feature",
  "properties": {
    "gn:admin1_code":"6.0",
    "gn:asciiname":"Jimbamba",
    "gn:country_code":"ZM",
    "gn:dem":1418,
    "gn:feature_class":"P",
    "gn:feature_code":"PPL",
    "gn:name":"Jimbamba",
    "gn:population":0,
    "gn:timezone":"Africa/Lusaka",
    "iso:country":"ZM",
    "wof:name":"Jimbamba",
    "wof:placetype":"locality"
},
  "geometry": {"coordinates":[25.0892,-11.25979],"type":"Point"}
}