{
  "type": "Feature",
  "properties": {
    "gn:admin1_code":"2.0",
    "gn:asciiname":"Shimpana",
    "gn:country_code":"ZM",
    "gn:dem":1150,
    "gn:feature_class":"P",
    "gn:feature_code":"PPL",
    "gn:name":"Shimpana",
    "gn:population":0,
    "gn:timezone":"Africa/Lusaka",
    "iso:country":"ZM",
    "wof:name":"Shimpana",
    "wof:placetype":"locality"
},
  "geometry": {"coordinates":[27.76667,-14.88333],"type":"Point"}
}