{
  "type": "Feature",
  "properties": {
    "gn:admin1_code":"10.0",
    "gn:asciiname":"Malema",
    "gn:country_code":"ZM",
    "gn:dem":832,
    "gn:feature_class":"P",
    "gn:feature_code":"PPL",
    "gn:name":"Malema",
    "gn:population":0,
    "gn:timezone":"Africa/Lusaka",
    "iso:country":"ZM",
    "name:cat_x_preferred":[
        "Malema"
    ],
    "name:zho_x_preferred":[
        "\u99ac\u840a\u99ac"
    ],
    "wof:name":"Malema",
    "wof:placetype":"locality"
},
  "geometry": {"coordinates":[33.06667,-10.11667],"type":"Point"}
}