{
  "type": "Feature",
  "properties": {
    "gn:admin1_code":"7.0",
    "gn:asciiname":"Chongo",
    "gn:country_code":"ZM",
    "gn:dem":1057,
    "gn:feature_class":"P",
    "gn:feature_code":"PPL",
    "gn:name":"Chongo",
    "gn:population":0,
    "gn:timezone":"Africa/Lusaka",
    "iso:country":"ZM",
    "wof:name":"Chongo",
    "wof:placetype":"locality"
},
  "geometry": {"coordinates":[27.39734,-16.166],"type":"Point"}
}