{
  "type": "Feature",
  "properties": {
    "gn:admin1_code":"10.0",
    "gn:asciiname":"Chimetu",
    "gn:country_code":"ZM",
    "gn:dem":690,
    "gn:feature_class":"P",
    "gn:feature_code":"PPL",
    "gn:name":"Chimetu",
    "gn:population":0,
    "gn:timezone":"Africa/Lusaka",
    "iso:country":"ZM",
    "wof:name":"Chimetu",
    "wof:placetype":"locality"
},
  "geometry": {"coordinates":[32.83333,-11.71667],"type":"Point"}
}