{
  "type": "Feature",
  "properties": {
    "gn:admin1_code":"3.0",
    "gn:asciiname":"Chiswala",
    "gn:country_code":"ZM",
    "gn:dem":1007,
    "gn:feature_class":"P",
    "gn:feature_code":"PPL",
    "gn:name":"Chiswala",
    "gn:population":0,
    "gn:timezone":"Africa/Lusaka",
    "iso:country":"ZM",
    "wof:name":"Chiswala",
    "wof:placetype":"locality"
},
  "geometry": {"coordinates":[31.15764,-14.57602],"type":"Point"}
}