{
  "type": "Feature",
  "properties": {
    "gn:admin1_code":"3.0",
    "gn:asciiname":"Chimphanamba",
    "gn:country_code":"ZM",
    "gn:dem":963,
    "gn:feature_class":"P",
    "gn:feature_code":"PPL",
    "gn:name":"Chimphanamba",
    "gn:population":0,
    "gn:timezone":"Africa/Lusaka",
    "iso:country":"ZM",
    "wof:name":"Chimphanamba",
    "wof:placetype":"locality"
},
  "geometry": {"coordinates":[31.06006,-14.50474],"type":"Point"}
}