{
  "type": "Feature",
  "properties": {
    "gn:admin1_code":"5.0",
    "gn:asciiname":"Tundulu",
    "gn:country_code":"ZM",
    "gn:dem":1048,
    "gn:feature_class":"P",
    "gn:feature_code":"PPL",
    "gn:name":"Tundulu",
    "gn:population":0,
    "gn:timezone":"Africa/Lusaka",
    "iso:country":"ZM",
    "wof:name":"Tundulu",
    "wof:placetype":"locality"
},
  "geometry": {"coordinates":[29.61072,-9.05111],"type":"Point"}
}