{
  "type": "Feature",
  "properties": {
    "gn:admin1_code":"10.0",
    "gn:asciiname":"Jombe",
    "gn:country_code":"ZM",
    "gn:dem":1363,
    "gn:feature_class":"P",
    "gn:feature_code":"PPL",
    "gn:name":"Jombe",
    "gn:population":0,
    "gn:timezone":"Africa/Lusaka",
    "iso:country":"ZM",
    "wof:name":"Jombe",
    "wof:placetype":"locality"
},
  "geometry": {"coordinates":[33.25592,-10.46623],"type":"Point"}
}