{
  "type": "Feature",
  "properties": {
    "gn:admin1_code":"3.0",
    "gn:asciiname":"Jamu Mkumba",
    "gn:country_code":"ZM",
    "gn:dem":965,
    "gn:feature_class":"P",
    "gn:feature_code":"PPL",
    "gn:name":"Jamu Mkumba",
    "gn:population":0,
    "gn:timezone":"Africa/Lusaka",
    "iso:country":"ZM",
    "wof:name":"Jamu Mkumba",
    "wof:placetype":"locality"
},
  "geometry": {"coordinates":[32.07236,-13.63829],"type":"Point"}
}