{
  "type": "Feature",
  "properties": {
    "gn:admin1_code":"2.0",
    "gn:asciiname":"Mutama",
    "gn:country_code":"ZM",
    "gn:dem":1577,
    "gn:feature_class":"P",
    "gn:feature_code":"PPL",
    "gn:name":"Mutama",
    "gn:population":0,
    "gn:timezone":"Africa/Lusaka",
    "iso:country":"ZM",
    "wof:name":"Mutama",
    "wof:placetype":"locality"
},
  "geometry": {"coordinates":[30.92413,-12.97567],"type":"Point"}
}