{
  "type": "Feature",
  "properties": {
    "gn:admin1_code":"7.0",
    "gn:asciiname":"Shangwa",
    "gn:country_code":"ZM",
    "gn:dem":1083,
    "gn:feature_class":"P",
    "gn:feature_code":"PPL",
    "gn:name":"Shangwa",
    "gn:population":0,
    "gn:timezone":"Africa/Lusaka",
    "iso:country":"ZM",
    "name:und_x_variant":[
        "Kwahangua",
        "Shangwa"
    ],
    "wof:name":"Shangwa",
    "wof:placetype":"locality"
},
  "geometry": {"coordinates":[26.81667,-16.18333],"type":"Point"}
}