{
  "type": "Feature",
  "properties": {
    "gn:admin1_code":"3.0",
    "gn:asciiname":"Mtowe",
    "gn:country_code":"ZM",
    "gn:dem":1008,
    "gn:feature_class":"P",
    "gn:feature_code":"PPL",
    "gn:name":"Mtowe",
    "gn:population":0,
    "gn:timezone":"Africa/Lusaka",
    "iso:country":"ZM",
    "wof:name":"Mtowe",
    "wof:placetype":"locality"
},
  "geometry": {"coordinates":[32.36425999999999,-14.1149],"type":"Point"}
}