{
  "type": "Feature",
  "properties": {
    "gn:admin1_code":"6.0",
    "gn:asciiname":"Muyoyu",
    "gn:country_code":"ZM",
    "gn:dem":1057,
    "gn:feature_class":"P",
    "gn:feature_code":"PPL",
    "gn:name":"Muyoyu",
    "gn:population":0,
    "gn:timezone":"Africa/Lusaka",
    "iso:country":"ZM",
    "name:und_x_variant":[
        "Muyoyo",
        "Muyoyu"
    ],
    "wof:name":"Muyoyu",
    "wof:placetype":"locality"
},
  "geometry": {"coordinates":[23.43333,-14.08333],"type":"Point"}
}