{
  "type": "Feature",
  "properties": {
    "gn:admin1_code":"3.0",
    "gn:asciiname":"Tolongo",
    "gn:country_code":"ZM",
    "gn:dem":1038,
    "gn:feature_class":"P",
    "gn:feature_code":"PPL",
    "gn:name":"Tolongo",
    "gn:population":0,
    "gn:timezone":"Africa/Lusaka",
    "iso:country":"ZM",
    "wof:name":"Tolongo",
    "wof:placetype":"locality"
},
  "geometry": {"coordinates":[31.5616,-14.45936],"type":"Point"}
}