{
  "type": "Feature",
  "properties": {
    "gn:admin1_code":"10.0",
    "gn:asciiname":"Jungu",
    "gn:country_code":"ZM",
    "gn:dem":941,
    "gn:feature_class":"P",
    "gn:feature_code":"PPL",
    "gn:name":"Jungu",
    "gn:population":0,
    "gn:timezone":"Africa/Lusaka",
    "iso:country":"ZM",
    "wof:name":"Jungu",
    "wof:placetype":"locality"
},
  "geometry": {"coordinates":[33.21667,-10.86667],"type":"Point"}
}