{
  "type": "Feature",
  "properties": {
    "gn:admin1_code":"6.0",
    "gn:asciiname":"Mangowa",
    "gn:country_code":"ZM",
    "gn:dem":1038,
    "gn:feature_class":"P",
    "gn:feature_code":"PPL",
    "gn:name":"Mangowa",
    "gn:population":0,
    "gn:timezone":"Africa/Lusaka",
    "iso:country":"ZM",
    "wof:name":"Mangowa",
    "wof:placetype":"locality"
},
  "geometry": {"coordinates":[23.05,-13.38333],"type":"Point"}
}