{
  "type": "Feature",
  "properties": {
    "gn:admin1_code":"8.0",
    "gn:asciiname":"Musakabantu",
    "gn:country_code":"ZM",
    "gn:dem":1182,
    "gn:feature_class":"P",
    "gn:feature_code":"PPL",
    "gn:name":"Musakabantu",
    "gn:population":0,
    "gn:timezone":"Africa/Lusaka",
    "iso:country":"ZM",
    "name:und_x_variant":[
        "Musekabantu",
        "Musakabantu"
    ],
    "wof:name":"Musakabantu",
    "wof:placetype":"locality"
},
  "geometry": {"coordinates":[27.68333,-12.96667],"type":"Point"}
}