{
  "type": "Feature",
  "properties": {
    "gn:admin1_code":"5.0",
    "gn:asciiname":"Malula",
    "gn:country_code":"ZM",
    "gn:dem":1465,
    "gn:feature_class":"P",
    "gn:feature_code":"PPL",
    "gn:name":"Malula",
    "gn:population":0,
    "gn:timezone":"Africa/Lusaka",
    "iso:country":"ZM",
    "name:und_x_variant":[
        "Nsangu",
        "Malula"
    ],
    "wof:name":"Malula",
    "wof:placetype":"locality"
},
  "geometry": {"coordinates":[30.51637,-8.95308],"type":"Point"}
}