{
  "type": "Feature",
  "properties": {
    "gn:admin1_code":"5.0",
    "gn:asciiname":"Chisulo",
    "gn:country_code":"ZM",
    "gn:dem":1434,
    "gn:feature_class":"P",
    "gn:feature_code":"PPL",
    "gn:name":"Chisulo",
    "gn:population":0,
    "gn:timezone":"Africa/Lusaka",
    "iso:country":"ZM",
    "wof:name":"Chisulo",
    "wof:placetype":"locality"
},
  "geometry": {"coordinates":[31.83333,-9.31667],"type":"Point"}
}