{
  "type": "Feature",
  "properties": {
    "gn:admin1_code":"7.0",
    "gn:asciiname":"Kaliangile",
    "gn:country_code":"ZM",
    "gn:dem":480,
    "gn:feature_class":"P",
    "gn:feature_code":"PPL",
    "gn:name":"Kaliangile",
    "gn:population":0,
    "gn:timezone":"Africa/Lusaka",
    "iso:country":"ZM",
    "wof:name":"Kaliangile",
    "wof:placetype":"locality"
},
  "geometry": {"coordinates":[28.56447,-16.2105],"type":"Point"}
}