{
  "type": "Feature",
  "properties": {
    "gn:admin1_code":"6.0",
    "gn:asciiname":"Mbambo",
    "gn:country_code":"ZM",
    "gn:dem":1367,
    "gn:feature_class":"P",
    "gn:feature_code":"PPL",
    "gn:name":"Mbambo",
    "gn:population":0,
    "gn:timezone":"Africa/Lusaka",
    "iso:country":"ZM",
    "wof:name":"Mbambo",
    "wof:placetype":"locality"
},
  "geometry": {"coordinates":[24.08333,-11.68333],"type":"Point"}
}