{
  "type": "Feature",
  "properties": {
    "gn:admin1_code":"6.0",
    "gn:asciiname":"Kapiji",
    "gn:country_code":"ZM",
    "gn:dem":1313,
    "gn:feature_class":"P",
    "gn:feature_code":"PPL",
    "gn:name":"Kapiji",
    "gn:population":0,
    "gn:timezone":"Africa/Lusaka",
    "iso:country":"ZM",
    "wof:name":"Kapiji",
    "wof:placetype":"locality"
},
  "geometry": {"coordinates":[25.86667000000001,-13.18333],"type":"Point"}
}