{
  "type": "Feature",
  "properties": {
    "gn:admin1_code":"5.0",
    "gn:asciiname":"Kakungu",
    "gn:country_code":"ZM",
    "gn:dem":1532,
    "gn:feature_class":"P",
    "gn:feature_code":"PPL",
    "gn:name":"Kakungu",
    "gn:population":0,
    "gn:timezone":"Africa/Lusaka",
    "iso:country":"ZM",
    "wof:name":"Kakungu",
    "wof:placetype":"locality"
},
  "geometry": {"coordinates":[31.71667,-8.95],"type":"Point"}
}