{
  "type": "Feature",
  "properties": {
    "gn:admin1_code":"6.0",
    "gn:asciiname":"Masoji",
    "gn:country_code":"ZM",
    "gn:dem":1084,
    "gn:feature_class":"P",
    "gn:feature_code":"PPL",
    "gn:name":"Masoji",
    "gn:population":0,
    "gn:timezone":"Africa/Lusaka",
    "iso:country":"ZM",
    "name:und_x_variant":[
        "Masozi",
        "Masoji"
    ],
    "wof:name":"Masoji",
    "wof:placetype":"locality"
},
  "geometry": {"coordinates":[22.83333,-13.03333],"type":"Point"}
}