{
  "type": "Feature",
  "properties": {
    "gn:admin1_code":"10.0",
    "gn:asciiname":"Peter",
    "gn:country_code":"ZM",
    "gn:dem":1182,
    "gn:feature_class":"P",
    "gn:feature_code":"PPL",
    "gn:name":"Peter",
    "gn:population":0,
    "gn:timezone":"Africa/Lusaka",
    "iso:country":"ZM",
    "name:ara_x_preferred":[
        "\u0628\u064a\u062a\u0631"
    ],
    "name:bul_x_preferred":[
        "\u041f\u0435\u0442\u044a\u0440"
    ],
    "name:ceb_x_preferred":[
        "Peter"
    ],
    "name:deu_x_preferred":[
        "Peter"
    ],
    "name:fra_x_preferred":[
        "Peter"
    ],
    "name:heb_x_preferred":[
        "\u05e4\u05d8\u05e8"
    ],
    "name:ita_x_preferred":[
        "Peter"
    ],
    "name:jpn_x_preferred":[
        "Peter"
    ],
    "name:nld_x_preferred":[
        "Peter"
    ],
    "name:rus_x_preferred":[
        "\u041f\u0435\u0442\u0435\u0440"
    ],
    "name:slk_x_preferred":[
        "Peter"
    ],
    "name:spa_x_preferred":[
        "Peter"
    ],
    "name:swe_x_preferred":[
        "Peter"
    ],
    "name:tha_x_preferred":[
        "\u0e1b\u0e35\u0e40\u0e15\u0e2d\u0e23\u0e4c"
    ],
    "name:ukr_x_preferred":[
        "\u041f\u0435\u0442\u0435\u0440"
    ],
    "wof:name":"Peter",
    "wof:placetype":"locality"
},
  "geometry": {"coordinates":[33.15,-10.36667],"type":"Point"}
}