{
  "type": "Feature",
  "properties": {
    "gn:admin1_code":"3.0",
    "gn:asciiname":"Mbuwa",
    "gn:country_code":"ZM",
    "gn:dem":1175,
    "gn:feature_class":"P",
    "gn:feature_code":"PPL",
    "gn:name":"Mbuwa",
    "gn:population":0,
    "gn:timezone":"Africa/Lusaka",
    "iso:country":"ZM",
    "wof:name":"Mbuwa",
    "wof:placetype":"locality"
},
  "geometry": {"coordinates":[25.00712,-14.45063],"type":"Point"}
}