{
  "type": "Feature",
  "properties": {
    "gn:admin1_code":"3.0",
    "gn:asciiname":"Ndandamani",
    "gn:country_code":"ZM",
    "gn:dem":1067,
    "gn:feature_class":"P",
    "gn:feature_code":"PPL",
    "gn:name":"Ndandamani",
    "gn:population":0,
    "gn:timezone":"Africa/Lusaka",
    "iso:country":"ZM",
    "wof:name":"Ndandamani",
    "wof:placetype":"locality"
},
  "geometry": {"coordinates":[31.67044000000001,-14.39691],"type":"Point"}
}