{
  "type": "Feature",
  "properties": {
    "gn:admin1_code":"6.0",
    "gn:asciiname":"Kavumbu",
    "gn:country_code":"ZM",
    "gn:dem":1472,
    "gn:feature_class":"P",
    "gn:feature_code":"PPL",
    "gn:name":"Kavumbu",
    "gn:population":0,
    "gn:timezone":"Africa/Lusaka",
    "iso:country":"ZM",
    "wof:name":"Kavumbu",
    "wof:placetype":"locality"
},
  "geometry": {"coordinates":[25.25,-11.76667],"type":"Point"}
}