{
  "type": "Feature",
  "properties": {
    "gn:admin1_code":"3.0",
    "gn:asciiname":"Paundi",
    "gn:country_code":"ZM",
    "gn:dem":1080,
    "gn:feature_class":"P",
    "gn:feature_code":"PPL",
    "gn:name":"Paundi",
    "gn:population":0,
    "gn:timezone":"Africa/Lusaka",
    "iso:country":"ZM",
    "wof:name":"Paundi",
    "wof:placetype":"locality"
},
  "geometry": {"coordinates":[31.82602,-14.292],"type":"Point"}
}