{
  "type": "Feature",
  "properties": {
    "gn:admin1_code":"10.0",
    "gn:asciiname":"Petros",
    "gn:country_code":"ZM",
    "gn:dem":1216,
    "gn:feature_class":"P",
    "gn:feature_code":"PPL",
    "gn:name":"Petros",
    "gn:population":0,
    "gn:timezone":"Africa/Lusaka",
    "iso:country":"ZM",
    "name:ceb_x_preferred":[
        "Petros"
    ],
    "name:deu_x_preferred":[
        "Petros"
    ],
    "name:ell_x_preferred":[
        "\u03a0\u03ad\u03c4\u03c1\u03bf\u03c2"
    ],
    "name:nld_x_preferred":[
        "Petros"
    ],
    "name:rus_x_preferred":[
        "\u041f\u0435\u0442\u0440\u043e\u0441"
    ],
    "name:slk_x_preferred":[
        "Petros"
    ],
    "name:ukr_x_preferred":[
        "\u041f\u0435\u0442\u0440\u043e\u0441"
    ],
    "wof:name":"Petros",
    "wof:placetype":"locality"
},
  "geometry": {"coordinates":[33.43333,-10.56667],"type":"Point"}
}