{
  "type": "Feature",
  "properties": {
    "gn:admin1_code":"10.0",
    "gn:asciiname":"Petros",
    "gn:country_code":"ZM",
    "gn:dem":1216,
    "gn:feature_class":"P",
    "gn:feature_code":"PPL",
    "gn:name":"Petros",
    "gn:population":0,
    "gn:timezone":"Africa/Lusaka",
    "iso:country":"ZM",
    "wof:name":"Petros",
    "wof:placetype":"locality"
},
  "geometry": {"coordinates":[33.43333,-10.56667],"type":"Point"}
}