{
  "type": "Feature",
  "properties": {
    "gn:admin1_code":"3.0",
    "gn:asciiname":"Chipwafu",
    "gn:country_code":"ZM",
    "gn:dem":919,
    "gn:feature_class":"P",
    "gn:feature_code":"PPL",
    "gn:name":"Chipwafu",
    "gn:population":0,
    "gn:timezone":"Africa/Lusaka",
    "iso:country":"ZM",
    "wof:name":"Chipwafu",
    "wof:placetype":"locality"
},
  "geometry": {"coordinates":[31.91667,-13.93333],"type":"Point"}
}