{
  "type": "Feature",
  "properties": {
    "gn:admin1_code":"6.0",
    "gn:asciiname":"Bulelele",
    "gn:country_code":"ZM",
    "gn:dem":1259,
    "gn:feature_class":"P",
    "gn:feature_code":"PPL",
    "gn:name":"Bulelele",
    "gn:population":0,
    "gn:timezone":"Africa/Lusaka",
    "iso:country":"ZM",
    "wof:name":"Bulelele",
    "wof:placetype":"locality"
},
  "geometry": {"coordinates":[25.83333,-13.31667],"type":"Point"}
}