{
  "type": "Feature",
  "properties": {
    "gn:admin1_code":"3.0",
    "gn:asciiname":"Chilekwa",
    "gn:country_code":"ZM",
    "gn:dem":637,
    "gn:feature_class":"P",
    "gn:feature_code":"PPL",
    "gn:name":"Chilekwa",
    "gn:population":0,
    "gn:timezone":"Africa/Lusaka",
    "iso:country":"ZM",
    "name:und_x_variant":[
        "Chilikwa",
        "Chilekwa"
    ],
    "wof:name":"Chilekwa",
    "wof:placetype":"locality"
},
  "geometry": {"coordinates":[31.58333,-13.65],"type":"Point"}
}