{
  "type": "Feature",
  "properties": {
    "gn:admin1_code":"2.0",
    "gn:asciiname":"Mambwe Chisenda",
    "gn:country_code":"ZM",
    "gn:dem":1282,
    "gn:feature_class":"P",
    "gn:feature_code":"PPL",
    "gn:name":"Mambwe Chisenda",
    "gn:population":0,
    "gn:timezone":"Africa/Lusaka",
    "iso:country":"ZM",
    "wof:name":"Mambwe Chisenda",
    "wof:placetype":"locality"
},
  "geometry": {"coordinates":[30.29127,-12.88442],"type":"Point"}
}