{
  "type": "Feature",
  "properties": {
    "gn:admin1_code":"3.0",
    "gn:asciiname":"Malama",
    "gn:country_code":"ZM",
    "gn:dem":546,
    "gn:feature_class":"P",
    "gn:feature_code":"PPL",
    "gn:name":"Malama",
    "gn:population":0,
    "gn:timezone":"Africa/Lusaka",
    "iso:country":"ZM",
    "wof:name":"Malama",
    "wof:placetype":"locality"
},
  "geometry": {"coordinates":[31.57093,-13.51826],"type":"Point"}
}