{
  "type": "Feature",
  "properties": {
    "gn:admin1_code":"7.0",
    "gn:asciiname":"Chilyango",
    "gn:country_code":"ZM",
    "gn:dem":994,
    "gn:feature_class":"P",
    "gn:feature_code":"PPL",
    "gn:name":"Chilyango",
    "gn:population":0,
    "gn:timezone":"Africa/Lusaka",
    "iso:country":"ZM",
    "name:und_x_variant":[
        "Chiliango",
        "Chilyango"
    ],
    "wof:name":"Chilyango",
    "wof:placetype":"locality"
},
  "geometry": {"coordinates":[27.5583,-15.87454],"type":"Point"}
}