{
  "type": "Feature",
  "properties": {
    "gn:admin1_code":"1.0",
    "gn:asciiname":"Imenda",
    "gn:country_code":"ZM",
    "gn:dem":1038,
    "gn:feature_class":"P",
    "gn:feature_code":"PPL",
    "gn:name":"Imenda",
    "gn:population":0,
    "gn:timezone":"Africa/Lusaka",
    "iso:country":"ZM",
    "wof:name":"Imenda",
    "wof:placetype":"locality"
},
  "geometry": {"coordinates":[24.54936,-16.84617],"type":"Point"}
}