{
  "type": "Feature",
  "properties": {
    "gn:admin1_code":"4.0",
    "gn:asciiname":"Kapela",
    "gn:country_code":"ZM",
    "gn:dem":1186,
    "gn:feature_class":"P",
    "gn:feature_code":"PPL",
    "gn:name":"Kapela",
    "gn:population":0,
    "gn:timezone":"Africa/Lusaka",
    "iso:country":"ZM",
    "name:bos_x_preferred":[
        "Kapela"
    ],
    "name:bul_x_preferred":[
        "\u041a\u0430\u043f\u0435\u043b\u0430"
    ],
    "name:ceb_x_preferred":[
        "Kapela"
    ],
    "name:hrv_x_preferred":[
        "Kapela"
    ],
    "name:hye_x_preferred":[
        "\u053f\u0561\u057a\u0565\u056c\u0561"
    ],
    "name:pol_x_preferred":[
        "Kapela"
    ],
    "name:rus_x_preferred":[
        "\u041a\u0430\u043f\u0435\u043b\u0430"
    ],
    "name:slv_x_preferred":[
        "Kapela"
    ],
    "name:srp_x_preferred":[
        "\u041a\u0430\u043f\u0435\u043b\u0430"
    ],
    "name:swe_x_preferred":[
        "Kapela"
    ],
    "name:ukr_x_preferred":[
        "\u041a\u0430\u043f\u0435\u043b\u0430"
    ],
    "wof:name":"Kapela",
    "wof:placetype":"locality"
},
  "geometry": {"coordinates":[29.57798,-11.89806],"type":"Point"}
}