{
  "type": "Feature",
  "properties": {
    "gn:admin1_code":"4.0",
    "gn:asciiname":"Kapela",
    "gn:country_code":"ZM",
    "gn:dem":1186,
    "gn:feature_class":"P",
    "gn:feature_code":"PPL",
    "gn:name":"Kapela",
    "gn:population":0,
    "gn:timezone":"Africa/Lusaka",
    "iso:country":"ZM",
    "wof:name":"Kapela",
    "wof:placetype":"locality"
},
  "geometry": {"coordinates":[29.57798,-11.89806],"type":"Point"}
}