{
  "type": "Feature",
  "properties": {
    "gn:admin1_code":"10.0",
    "gn:asciiname":"Mateyo Kalashila",
    "gn:country_code":"ZM",
    "gn:dem":1512,
    "gn:feature_class":"P",
    "gn:feature_code":"PPL",
    "gn:name":"Mateyo Kalashila",
    "gn:population":0,
    "gn:timezone":"Africa/Lusaka",
    "iso:country":"ZM",
    "wof:name":"Mateyo Kalashila",
    "wof:placetype":"locality"
},
  "geometry": {"coordinates":[30.74937000000001,-12.79174],"type":"Point"}
}