{
  "type": "Feature",
  "properties": {
    "gn:admin1_code":"2.0",
    "gn:asciiname":"Chansa",
    "gn:country_code":"ZM",
    "gn:dem":1567,
    "gn:feature_class":"P",
    "gn:feature_code":"PPL",
    "gn:name":"Chansa",
    "gn:population":0,
    "gn:timezone":"Africa/Lusaka",
    "iso:country":"ZM",
    "name:ceb_x_preferred":[
        "Chansa"
    ],
    "name:deu_x_preferred":[
        "Chansa"
    ],
    "name:rus_x_preferred":[
        "\u0427\u0430\u043d\u0441\u0430"
    ],
    "wof:name":"Chansa",
    "wof:placetype":"locality"
},
  "geometry": {"coordinates":[30.64838,-12.96696],"type":"Point"}
}