{
  "type": "Feature",
  "properties": {
    "gn:admin1_code":"1.0",
    "gn:asciiname":"Simulyankumba",
    "gn:country_code":"ZM",
    "gn:dem":1153,
    "gn:feature_class":"P",
    "gn:feature_code":"PPL",
    "gn:name":"Simulyankumba",
    "gn:population":0,
    "gn:timezone":"Africa/Lusaka",
    "iso:country":"ZM",
    "wof:name":"Simulyankumba",
    "wof:placetype":"locality"
},
  "geometry": {"coordinates":[24.68333,-15.18333],"type":"Point"}
}