{
  "type": "Feature",
  "properties": {
    "gn:admin1_code":"1.0",
    "gn:asciiname":"Kamilende Kuta",
    "gn:country_code":"ZM",
    "gn:dem":1065,
    "gn:feature_class":"P",
    "gn:feature_code":"PPL",
    "gn:name":"Kamilende Kuta",
    "gn:population":0,
    "gn:timezone":"Africa/Lusaka",
    "iso:country":"ZM",
    "name:und_x_variant":[
        "Kamilende",
        "Kamilenge",
        "Kamilende Kuta"
    ],
    "wof:name":"Kamilende Kuta",
    "wof:placetype":"locality"
},
  "geometry": {"coordinates":[23.54326,-14.12377],"type":"Point"}
}