{
  "type": "Feature",
  "properties": {
    "gn:admin1_code":"2.0",
    "gn:asciiname":"Axon Chintu",
    "gn:country_code":"ZM",
    "gn:dem":1404,
    "gn:feature_class":"P",
    "gn:feature_code":"PPL",
    "gn:name":"Axon Chintu",
    "gn:population":0,
    "gn:timezone":"Africa/Lusaka",
    "iso:country":"ZM",
    "wof:name":"Axon Chintu",
    "wof:placetype":"locality"
},
  "geometry": {"coordinates":[30.88058,-13.21331],"type":"Point"}
}