{
  "type": "Feature",
  "properties": {
    "gn:admin1_code":"7.0",
    "gn:asciiname":"Kabulamwanda",
    "gn:country_code":"ZM",
    "gn:dem":989,
    "gn:feature_class":"P",
    "gn:feature_code":"PPL",
    "gn:name":"Kabulamwanda",
    "gn:population":0,
    "gn:timezone":"Africa/Lusaka",
    "iso:country":"ZM",
    "wof:name":"Kabulamwanda",
    "wof:placetype":"locality"
},
  "geometry": {"coordinates":[26.90899000000001,-15.86824],"type":"Point"}
}