{
  "type": "Feature",
  "properties": {
    "gn:admin1_code":"6.0",
    "gn:asciiname":"Kapungu",
    "gn:country_code":"ZM",
    "gn:dem":1106,
    "gn:feature_class":"P",
    "gn:feature_code":"PPL",
    "gn:name":"Kapungu",
    "gn:population":0,
    "gn:timezone":"Africa/Lusaka",
    "iso:country":"ZM",
    "wof:name":"Kapungu",
    "wof:placetype":"locality"
},
  "geometry": {"coordinates":[24.20632,-13.26099],"type":"Point"}
}