{
  "type": "Feature",
  "properties": {
    "gn:admin1_code":"6.0",
    "gn:asciiname":"Nyamutinta",
    "gn:country_code":"ZM",
    "gn:dem":1428,
    "gn:feature_class":"P",
    "gn:feature_code":"PPL",
    "gn:name":"Nyamutinta",
    "gn:population":0,
    "gn:timezone":"Africa/Lusaka",
    "iso:country":"ZM",
    "wof:name":"Nyamutinta",
    "wof:placetype":"locality"
},
  "geometry": {"coordinates":[24.83333,-11.41667],"type":"Point"}
}