{
  "type": "Feature",
  "properties": {
    "gn:admin1_code":"2.0",
    "gn:asciiname":"Kanche Bokoshi",
    "gn:country_code":"ZM",
    "gn:dem":1335,
    "gn:feature_class":"P",
    "gn:feature_code":"PPL",
    "gn:name":"Kanche Bokoshi",
    "gn:population":0,
    "gn:timezone":"Africa/Lusaka",
    "iso:country":"ZM",
    "wof:name":"Kanche Bokoshi",
    "wof:placetype":"locality"
},
  "geometry": {"coordinates":[30.45341,-12.75079],"type":"Point"}
}