{
  "type": "Feature",
  "properties": {
    "gn:admin1_code":"1.0",
    "gn:asciiname":"Sitambangula",
    "gn:country_code":"ZM",
    "gn:dem":1053,
    "gn:feature_class":"P",
    "gn:feature_code":"PPL",
    "gn:name":"Sitambangula",
    "gn:population":0,
    "gn:timezone":"Africa/Lusaka",
    "iso:country":"ZM",
    "wof:name":"Sitambangula",
    "wof:placetype":"locality"
},
  "geometry": {"coordinates":[23.58333,-14.51667],"type":"Point"}
}