{
  "type": "Feature",
  "properties": {
    "gn:admin1_code":"10.0",
    "gn:asciiname":"Chikanda",
    "gn:country_code":"ZM",
    "gn:dem":1518,
    "gn:feature_class":"P",
    "gn:feature_code":"PPL",
    "gn:name":"Chikanda",
    "gn:population":0,
    "gn:timezone":"Africa/Lusaka",
    "iso:country":"ZM",
    "wof:name":"Chikanda",
    "wof:placetype":"locality"
},
  "geometry": {"coordinates":[30.88333,-12.71667],"type":"Point"}
}