{
  "type": "Feature",
  "properties": {
    "gn:admin1_code":"5.0",
    "gn:asciiname":"Noah",
    "gn:country_code":"ZM",
    "gn:dem":1587,
    "gn:feature_class":"P",
    "gn:feature_code":"PPL",
    "gn:name":"Noah",
    "gn:population":0,
    "gn:timezone":"Africa/Lusaka",
    "iso:country":"ZM",
    "wof:name":"Noah",
    "wof:placetype":"locality"
},
  "geometry": {"coordinates":[31.66667,-8.91667],"type":"Point"}
}