{
  "type": "Feature",
  "properties": {
    "gn:admin1_code":"1.0",
    "gn:asciiname":"Sinyanga",
    "gn:country_code":"ZM",
    "gn:dem":1026,
    "gn:feature_class":"P",
    "gn:feature_code":"PPL",
    "gn:name":"Sinyanga",
    "gn:population":0,
    "gn:timezone":"Africa/Lusaka",
    "iso:country":"ZM",
    "wof:name":"Sinyanga",
    "wof:placetype":"locality"
},
  "geometry": {"coordinates":[24.98333,-16.76667],"type":"Point"}
}