{
  "type": "Feature",
  "properties": {
    "gn:admin1_code":"6.0",
    "gn:asciiname":"Kachaka",
    "gn:country_code":"ZM",
    "gn:dem":1075,
    "gn:feature_class":"P",
    "gn:feature_code":"PPL",
    "gn:name":"Kachaka",
    "gn:population":0,
    "gn:timezone":"Africa/Lusaka",
    "iso:country":"ZM",
    "wof:name":"Kachaka",
    "wof:placetype":"locality"
},
  "geometry": {"coordinates":[23.09143,-13.48964],"type":"Point"}
}