{
  "type": "Feature",
  "properties": {
    "gn:admin1_code":"1.0",
    "gn:asciiname":"Sheba",
    "gn:country_code":"ZM",
    "gn:dem":1059,
    "gn:feature_class":"P",
    "gn:feature_code":"PPL",
    "gn:name":"Sheba",
    "gn:population":0,
    "gn:timezone":"Africa/Lusaka",
    "iso:country":"ZM",
    "name:ara_x_preferred":[
        "\u0645\u0645\u0644\u0643\u0629 \u0633\u0628\u0623"
    ],
    "name:aze_x_preferred":[
        "S\u0259ba d\u00f6vl\u0259ti"
    ],
    "name:bak_x_preferred":[
        "\u0421\u04d9\u0431\u0430 \u0431\u0430\u0442\u0448\u0430\u043b\u044b\u0493\u044b"
    ],
    "name:bel_x_preferred":[
        "\u0421\u0430\u0431\u0435\u0439\u0441\u043a\u0430\u0435 \u0446\u0430\u0440\u0441\u0442\u0432\u0430"
    ],
    "name:bod_x_preferred":[
        "\u0f66\u0f7a\u0f0b\u0f56\u0f0d"
    ],
    "name:ces_x_preferred":[
        "S\u00e1ba"
    ],
    "name:dan_x_preferred":[
        "Saba"
    ],
    "name:deu_x_preferred":[
        "Saba"
    ],
    "name:epo_x_preferred":[
        "Re\u011dlando \u015ceba"
    ],
    "name:eus_x_preferred":[
        "Sabako Erresuma"
    ],
    "name:fas_x_preferred":[
        "\u0633\u0628\u0627"
    ],
    "name:fin_x_preferred":[
        "Saban kuningaskunta"
    ],
    "name:heb_x_preferred":[
        "\u05e9\u05d1\u05d0"
    ],
    "name:hrv_x_preferred":[
        "Sabejsko kraljevstvo"
    ],
    "name:hun_x_preferred":[
        "Szab\u00e1"
    ],
    "name:ind_x_preferred":[
        "Kerajaan Saba"
    ],
    "name:jpn_x_preferred":[
        "\u30b7\u30d0\u738b\u56fd"
    ],
    "name:kat_x_preferred":[
        "\u10e1\u10d0\u10d1\u10d8\u10e1 \u10e1\u10d0\u10db\u10d4\u10e4\u10dd"
    ],
    "name:lat_x_preferred":[
        "Saba"
    ],
    "name:nld_x_preferred":[
        "Seba"
    ],
    "name:nno_x_preferred":[
        "Saba"
    ],
    "name:nor_x_preferred":[
        "Saba"
    ],
    "name:pol_x_preferred":[
        "Kr\u00f3lestwo Saba"
    ],
    "name:por_x_preferred":[
        "Sab\u00e1"
    ],
    "name:rus_x_preferred":[
        "\u0421\u0430\u0431\u0435\u0439\u0441\u043a\u043e\u0435 \u0446\u0430\u0440\u0441\u0442\u0432\u043e"
    ],
    "name:slv_x_preferred":[
        "Sabsko kraljestvo"
    ],
    "name:sqi_x_preferred":[
        "Saba"
    ],
    "name:srp_x_preferred":[
        "\u0421\u0430\u0431\u0435\u0458\u0441\u043a\u043e \u043a\u0440\u0430\u0459\u0435\u0432\u0441\u0442\u0432\u043e"
    ],
    "name:swe_x_preferred":[
        "Saba"
    ],
    "name:ukr_x_preferred":[
        "\u0421\u0430\u0431\u0435\u0439\u0441\u044c\u043a\u0435 \u0446\u0430\u0440\u0441\u0442\u0432\u043e"
    ],
    "name:urd_x_preferred":[
        "\u0645\u0645\u0644\u06a9\u062a \u0633\u0628\u0627"
    ],
    "name:uzb_x_preferred":[
        "Saba"
    ],
    "name:zho_x_preferred":[
        "\u793a\u5df4\u738b\u570b"
    ],
    "wof:name":"Sheba",
    "wof:placetype":"locality"
},
  "geometry": {"coordinates":[23.18333,-15.33333],"type":"Point"}
}