{
  "type": "Feature",
  "properties": {
    "gn:admin1_code":"8.0",
    "gn:asciiname":"Nchinke",
    "gn:country_code":"ZM",
    "gn:dem":1275,
    "gn:feature_class":"P",
    "gn:feature_code":"PPL",
    "gn:name":"Nchinke",
    "gn:population":0,
    "gn:timezone":"Africa/Lusaka",
    "iso:country":"ZM",
    "name:und_x_variant":[
        "Chinka",
        "Chinke",
        "Nchinke"
    ],
    "wof:name":"Nchinke",
    "wof:placetype":"locality"
},
  "geometry": {"coordinates":[27.04109,-12.81884],"type":"Point"}
}