{
  "type": "Feature",
  "properties": {
    "gn:admin1_code":"10.0",
    "gn:asciiname":"Malipilo",
    "gn:country_code":"ZM",
    "gn:dem":1502,
    "gn:feature_class":"P",
    "gn:feature_code":"PPL",
    "gn:name":"Malipilo",
    "gn:population":0,
    "gn:timezone":"Africa/Lusaka",
    "iso:country":"ZM",
    "name:und_x_variant":[
        "Matipilo",
        "Malipilo"
    ],
    "wof:name":"Malipilo",
    "wof:placetype":"locality"
},
  "geometry": {"coordinates":[31.91921,-11.16576],"type":"Point"}
}