{
  "type": "Feature",
  "properties": {
    "gn:admin1_code":"1.0",
    "gn:asciiname":"Kanono",
    "gn:country_code":"ZM",
    "gn:dem":1026,
    "gn:feature_class":"P",
    "gn:feature_code":"PPL",
    "gn:name":"Kanono",
    "gn:population":0,
    "gn:timezone":"Africa/Lusaka",
    "iso:country":"ZM",
    "wof:name":"Kanono",
    "wof:placetype":"locality"
},
  "geometry": {"coordinates":[25.05,-16.66667],"type":"Point"}
}