{
  "type": "Feature",
  "properties": {
    "gn:admin1_code":"1.0",
    "gn:asciiname":"Kambwembwe",
    "gn:country_code":"ZM",
    "gn:dem":1116,
    "gn:feature_class":"P",
    "gn:feature_code":"PPL",
    "gn:name":"Kambwembwe",
    "gn:population":0,
    "gn:timezone":"Africa/Lusaka",
    "iso:country":"ZM",
    "wof:name":"Kambwembwe",
    "wof:placetype":"locality"
},
  "geometry": {"coordinates":[24.58333,-14.01667],"type":"Point"}
}