{
  "type": "Feature",
  "properties": {
    "gn:admin1_code":"3.0",
    "gn:asciiname":"Kamphata",
    "gn:country_code":"ZM",
    "gn:dem":843,
    "gn:feature_class":"P",
    "gn:feature_code":"PPL",
    "gn:name":"Kamphata",
    "gn:population":0,
    "gn:timezone":"Africa/Lusaka",
    "iso:country":"ZM",
    "wof:name":"Kamphata",
    "wof:placetype":"locality"
},
  "geometry": {"coordinates":[30.90874,-14.57789],"type":"Point"}
}