{
  "type": "Feature",
  "properties": {
    "gn:admin1_code":"2.0",
    "gn:asciiname":"Lyumbo",
    "gn:country_code":"ZM",
    "gn:dem":1137,
    "gn:feature_class":"P",
    "gn:feature_code":"PPL",
    "gn:name":"Lyumbo",
    "gn:population":0,
    "gn:timezone":"Africa/Lusaka",
    "iso:country":"ZM",
    "name:und_x_variant":[
        "Liumbo",
        "Lyumbo"
    ],
    "wof:name":"Lyumbo",
    "wof:placetype":"locality"
},
  "geometry": {"coordinates":[28.65,-14.98333],"type":"Point"}
}