{
  "type": "Feature",
  "properties": {
    "gn:admin1_code":"3.0",
    "gn:asciiname":"Kawalala",
    "gn:country_code":"ZM",
    "gn:dem":1075,
    "gn:feature_class":"P",
    "gn:feature_code":"PPL",
    "gn:name":"Kawalala",
    "gn:population":0,
    "gn:timezone":"Africa/Lusaka",
    "iso:country":"ZM",
    "wof:name":"Kawalala",
    "wof:placetype":"locality"
},
  "geometry": {"coordinates":[31.80801,-14.19957],"type":"Point"}
}