{
  "type": "Feature",
  "properties": {
    "gn:admin1_code":"5.0",
    "gn:asciiname":"Chilumba-Kotuli",
    "gn:country_code":"ZM",
    "gn:dem":1242,
    "gn:feature_class":"P",
    "gn:feature_code":"PPL",
    "gn:name":"Chilumba-Kotuli",
    "gn:population":0,
    "gn:timezone":"Africa/Lusaka",
    "iso:country":"ZM",
    "name:und_x_variant":[
        "Chilumbe-Kotuli",
        "Chilumba-Kotuli"
    ],
    "wof:name":"Chilumba-Kotuli",
    "wof:placetype":"locality"
},
  "geometry": {"coordinates":[30.93333,-10.56667],"type":"Point"}
}