{
  "type": "Feature",
  "properties": {
    "gn:admin1_code":"1.0",
    "gn:asciiname":"Piti",
    "gn:country_code":"ZM",
    "gn:dem":1107,
    "gn:feature_class":"P",
    "gn:feature_code":"PPL",
    "gn:name":"Piti",
    "gn:population":0,
    "gn:timezone":"Africa/Lusaka",
    "iso:country":"ZM",
    "name:ceb_x_preferred":[
        "Piti"
    ],
    "name:pol_x_preferred":[
        "Piti"
    ],
    "name:swe_x_preferred":[
        "Piti"
    ],
    "wof:name":"Piti",
    "wof:placetype":"locality"
},
  "geometry": {"coordinates":[24.77228,-16.55753],"type":"Point"}
}