{
  "type": "Feature",
  "properties": {
    "gn:admin1_code":"2.0",
    "gn:asciiname":"Saulo Chintu",
    "gn:country_code":"ZM",
    "gn:dem":1592,
    "gn:feature_class":"P",
    "gn:feature_code":"PPL",
    "gn:name":"Saulo Chintu",
    "gn:population":0,
    "gn:timezone":"Africa/Lusaka",
    "iso:country":"ZM",
    "wof:name":"Saulo Chintu",
    "wof:placetype":"locality"
},
  "geometry": {"coordinates":[30.71667,-12.93333],"type":"Point"}
}