{
  "type": "Feature",
  "properties": {
    "gn:admin1_code":"2.0",
    "gn:asciiname":"Shikanka",
    "gn:country_code":"ZM",
    "gn:dem":1155,
    "gn:feature_class":"P",
    "gn:feature_code":"PPL",
    "gn:name":"Shikanka",
    "gn:population":0,
    "gn:timezone":"Africa/Lusaka",
    "iso:country":"ZM",
    "wof:name":"Shikanka",
    "wof:placetype":"locality"
},
  "geometry": {"coordinates":[28.15,-14.61667],"type":"Point"}
}