{
  "type": "Feature",
  "properties": {
    "gn:admin1_code":"1.0",
    "gn:asciiname":"Chikoka",
    "gn:country_code":"ZM",
    "gn:dem":1134,
    "gn:feature_class":"P",
    "gn:feature_code":"PPL",
    "gn:name":"Chikoka",
    "gn:population":0,
    "gn:timezone":"Africa/Lusaka",
    "iso:country":"ZM",
    "wof:name":"Chikoka",
    "wof:placetype":"locality"
},
  "geometry": {"coordinates":[24.75,-15.58333],"type":"Point"}
}