{
  "type": "Feature",
  "properties": {
    "gn:admin1_code":"1.0",
    "gn:asciiname":"Kaposhi",
    "gn:country_code":"ZM",
    "gn:dem":1100,
    "gn:feature_class":"P",
    "gn:feature_code":"PPL",
    "gn:name":"Kaposhi",
    "gn:population":0,
    "gn:timezone":"Africa/Lusaka",
    "iso:country":"ZM",
    "wof:name":"Kaposhi",
    "wof:placetype":"locality"
},
  "geometry": {"coordinates":[24.03333,-14.03333],"type":"Point"}
}