{
  "type": "Feature",
  "properties": {
    "gn:admin1_code":"1.0",
    "gn:asciiname":"Muhini",
    "gn:country_code":"ZM",
    "gn:dem":1061,
    "gn:feature_class":"P",
    "gn:feature_code":"PPL",
    "gn:name":"Muhini",
    "gn:population":0,
    "gn:timezone":"Africa/Lusaka",
    "iso:country":"ZM",
    "wof:name":"Muhini",
    "wof:placetype":"locality"
},
  "geometry": {"coordinates":[23.66667,-14.45],"type":"Point"}
}