{
  "type": "Feature",
  "properties": {
    "gn:admin1_code":"7.0",
    "gn:asciiname":"Shabalu",
    "gn:country_code":"ZM",
    "gn:dem":1042,
    "gn:feature_class":"P",
    "gn:feature_code":"PPL",
    "gn:name":"Shabalu",
    "gn:population":0,
    "gn:timezone":"Africa/Lusaka",
    "iso:country":"ZM",
    "name:und_x_variant":[
        "Shabaalu",
        "Shabalu"
    ],
    "wof:name":"Shabalu",
    "wof:placetype":"locality"
},
  "geometry": {"coordinates":[26.05,-16.03333],"type":"Point"}
}