{
  "type": "Feature",
  "properties": {
    "gn:admin1_code":"3.0",
    "gn:asciiname":"Chisengu",
    "gn:country_code":"ZM",
    "gn:dem":512,
    "gn:feature_class":"P",
    "gn:feature_code":"PPL",
    "gn:name":"Chisengu",
    "gn:population":0,
    "gn:timezone":"Africa/Lusaka",
    "iso:country":"ZM",
    "name:und_x_variant":[
        "Chisengo",
        "Chisengu"
    ],
    "wof:name":"Chisengu",
    "wof:placetype":"locality"
},
  "geometry": {"coordinates":[31.07937,-13.88337],"type":"Point"}
}