{
  "type": "Feature",
  "properties": {
    "gn:admin1_code":"2.0",
    "gn:asciiname":"Mwapi Mutamuna",
    "gn:country_code":"ZM",
    "gn:dem":1498,
    "gn:feature_class":"P",
    "gn:feature_code":"PPL",
    "gn:name":"Mwapi Mutamuna",
    "gn:population":0,
    "gn:timezone":"Africa/Lusaka",
    "iso:country":"ZM",
    "name:und_x_variant":[
        "Mwapi Mulamuna",
        "Mwapi Mutamuna"
    ],
    "wof:name":"Mwapi Mutamuna",
    "wof:placetype":"locality"
},
  "geometry": {"coordinates":[30.4351,-13.17394],"type":"Point"}
}