{
  "type": "Feature",
  "properties": {
    "gn:admin1_code":"3.0",
    "gn:asciiname":"Ntambo",
    "gn:country_code":"ZM",
    "gn:dem":903,
    "gn:feature_class":"P",
    "gn:feature_code":"PPL",
    "gn:name":"Ntambo",
    "gn:population":0,
    "gn:timezone":"Africa/Lusaka",
    "iso:country":"ZM",
    "wof:name":"Ntambo",
    "wof:placetype":"locality"
},
  "geometry": {"coordinates":[31.02457,-14.58111],"type":"Point"}
}