{
  "type": "Feature",
  "properties": {
    "gn:admin1_code":"7.0",
    "gn:asciiname":"Simupingula",
    "gn:country_code":"ZM",
    "gn:dem":1184,
    "gn:feature_class":"P",
    "gn:feature_code":"PPL",
    "gn:name":"Simupingula",
    "gn:population":0,
    "gn:timezone":"Africa/Lusaka",
    "iso:country":"ZM",
    "wof:name":"Simupingula",
    "wof:placetype":"locality"
},
  "geometry": {"coordinates":[26.13333,-16.75],"type":"Point"}
}