{
  "type": "Feature",
  "properties": {
    "gn:admin1_code":"10.0",
    "gn:asciiname":"Barton",
    "gn:country_code":"ZM",
    "gn:dem":1434,
    "gn:feature_class":"P",
    "gn:feature_code":"PPL",
    "gn:name":"Barton",
    "gn:population":0,
    "gn:timezone":"Africa/Lusaka",
    "iso:country":"ZM",
    "wof:name":"Barton",
    "wof:placetype":"locality"
},
  "geometry": {"coordinates":[32.60333,-9.39726],"type":"Point"}
}