{
  "type": "Feature",
  "properties": {
    "gn:admin1_code":"10.0",
    "gn:asciiname":"Barton",
    "gn:country_code":"ZM",
    "gn:dem":1434,
    "gn:feature_class":"P",
    "gn:feature_code":"PPL",
    "gn:name":"Barton",
    "gn:population":0,
    "gn:timezone":"Africa/Lusaka",
    "iso:country":"ZM",
    "name:ara_x_preferred":[
        "\u0628\u0627\u0631\u062a\u0648\u0646"
    ],
    "name:bel_x_preferred":[
        "\u0411\u0430\u0440\u0442\u0430\u043d"
    ],
    "name:cat_x_preferred":[
        "Barton"
    ],
    "name:ceb_x_preferred":[
        "Barton"
    ],
    "name:ces_x_preferred":[
        "Barton"
    ],
    "name:deu_x_preferred":[
        "Barton"
    ],
    "name:fas_x_preferred":[
        "\u0628\u0627\u0631\u062a\u0648\u0646"
    ],
    "name:fra_x_preferred":[
        "Barton"
    ],
    "name:heb_x_preferred":[
        "\u05d1\u05d0\u05e8\u05d8\u05d5\u05df"
    ],
    "name:ita_x_preferred":[
        "Barton"
    ],
    "name:jpn_x_preferred":[
        "\u30d0\u30fc\u30c8\u30f3"
    ],
    "name:nds_x_preferred":[
        "Barton"
    ],
    "name:nld_x_preferred":[
        "Barton"
    ],
    "name:pol_x_preferred":[
        "Barton"
    ],
    "name:por_x_preferred":[
        "Barton"
    ],
    "name:rus_x_preferred":[
        "\u0411\u0430\u0440\u0442\u043e\u043d"
    ],
    "name:spa_x_preferred":[
        "Barton"
    ],
    "name:srp_x_preferred":[
        "\u0411\u0430\u0440\u0442\u043e\u043d"
    ],
    "name:swe_x_preferred":[
        "Barton"
    ],
    "name:ukr_x_preferred":[
        "\u0411\u0430\u0440\u0442\u043e\u043d"
    ],
    "name:urd_x_preferred":[
        "\u0628\u0627\u0631\u0679\u0646"
    ],
    "name:vol_x_preferred":[
        "Barton"
    ],
    "wof:name":"Barton",
    "wof:placetype":"locality"
},
  "geometry": {"coordinates":[32.60333,-9.39726],"type":"Point"}
}