{
  "type": "Feature",
  "properties": {
    "gn:admin1_code":"2.0",
    "gn:asciiname":"Chakumana",
    "gn:country_code":"ZM",
    "gn:dem":1489,
    "gn:feature_class":"P",
    "gn:feature_code":"PPL",
    "gn:name":"Chakumana",
    "gn:population":0,
    "gn:timezone":"Africa/Lusaka",
    "iso:country":"ZM",
    "wof:name":"Chakumana",
    "wof:placetype":"locality"
},
  "geometry": {"coordinates":[30.70873,-12.87365],"type":"Point"}
}