{
  "type": "Feature",
  "properties": {
    "gn:admin1_code":"5.0",
    "gn:asciiname":"Nkonkela",
    "gn:country_code":"ZM",
    "gn:dem":1294,
    "gn:feature_class":"P",
    "gn:feature_code":"PPL",
    "gn:name":"Nkonkela",
    "gn:population":0,
    "gn:timezone":"Africa/Lusaka",
    "iso:country":"ZM",
    "wof:name":"Nkonkela",
    "wof:placetype":"locality"
},
  "geometry": {"coordinates":[31.23333,-10.26667],"type":"Point"}
}