{
  "type": "Feature",
  "properties": {
    "gn:admin1_code":"3.0",
    "gn:asciiname":"Chikalema",
    "gn:country_code":"ZM",
    "gn:dem":1195,
    "gn:feature_class":"P",
    "gn:feature_code":"PPL",
    "gn:name":"Chikalema",
    "gn:population":0,
    "gn:timezone":"Africa/Lusaka",
    "iso:country":"ZM",
    "wof:name":"Chikalema",
    "wof:placetype":"locality"
},
  "geometry": {"coordinates":[33.15161,-12.58332],"type":"Point"}
}