{
  "type": "Feature",
  "properties": {
    "gn:admin1_code":"3.0",
    "gn:asciiname":"Songwe",
    "gn:country_code":"ZM",
    "gn:dem":885,
    "gn:feature_class":"P",
    "gn:feature_code":"PPL",
    "gn:name":"Songwe",
    "gn:population":0,
    "gn:timezone":"Africa/Lusaka",
    "iso:country":"ZM",
    "wof:name":"Songwe",
    "wof:placetype":"locality"
},
  "geometry": {"coordinates":[31.90453,-13.91328],"type":"Point"}
}