{
  "type": "Feature",
  "properties": {
    "gn:admin1_code":"1.0",
    "gn:asciiname":"Aongola",
    "gn:country_code":"ZM",
    "gn:dem":1086,
    "gn:feature_class":"P",
    "gn:feature_code":"PPL",
    "gn:name":"Aongola",
    "gn:population":0,
    "gn:timezone":"Africa/Lusaka",
    "iso:country":"ZM",
    "wof:name":"Aongola",
    "wof:placetype":"locality"
},
  "geometry": {"coordinates":[23.48333,-15.31667],"type":"Point"}
}