{
  "type": "Feature",
  "properties": {
    "gn:admin1_code":"3.0",
    "gn:asciiname":"Masuma",
    "gn:country_code":"ZM",
    "gn:dem":692,
    "gn:feature_class":"P",
    "gn:feature_code":"PPL",
    "gn:name":"Masuma",
    "gn:population":0,
    "gn:timezone":"Africa/Lusaka",
    "iso:country":"ZM",
    "wof:name":"Masuma",
    "wof:placetype":"locality"
},
  "geometry": {"coordinates":[32.23333,-12.98333],"type":"Point"}
}