{
  "type": "Feature",
  "properties": {
    "gn:admin1_code":"1.0",
    "gn:asciiname":"Chiligwa",
    "gn:country_code":"ZM",
    "gn:dem":959,
    "gn:feature_class":"P",
    "gn:feature_code":"PPL",
    "gn:name":"Chiligwa",
    "gn:population":0,
    "gn:timezone":"Africa/Lusaka",
    "iso:country":"ZM",
    "wof:name":"Chiligwa",
    "wof:placetype":"locality"
},
  "geometry": {"coordinates":[23.9219,-16.96415],"type":"Point"}
}