{
  "type": "Feature",
  "properties": {
    "gn:admin1_code":"2.0",
    "gn:asciiname":"Maloni Chimulasa",
    "gn:country_code":"ZM",
    "gn:dem":1430,
    "gn:feature_class":"P",
    "gn:feature_code":"PPL",
    "gn:name":"Maloni Chimulasa",
    "gn:population":0,
    "gn:timezone":"Africa/Lusaka",
    "iso:country":"ZM",
    "wof:name":"Maloni Chimulasa",
    "wof:placetype":"locality"
},
  "geometry": {"coordinates":[30.41343,-12.94286],"type":"Point"}
}