{
  "type": "Feature",
  "properties": {
    "gn:admin1_code":"5.0",
    "gn:asciiname":"Teleka",
    "gn:country_code":"ZM",
    "gn:dem":796,
    "gn:feature_class":"P",
    "gn:feature_code":"PPL",
    "gn:name":"Teleka",
    "gn:population":0,
    "gn:timezone":"Africa/Lusaka",
    "iso:country":"ZM",
    "wof:name":"Teleka",
    "wof:placetype":"locality"
},
  "geometry": {"coordinates":[30.46667,-8.51667],"type":"Point"}
}