{
  "type": "Feature",
  "properties": {
    "gn:admin1_code":"2.0",
    "gn:asciiname":"Ndaupala",
    "gn:country_code":"ZM",
    "gn:dem":1490,
    "gn:feature_class":"P",
    "gn:feature_code":"PPL",
    "gn:name":"Ndaupala",
    "gn:population":0,
    "gn:timezone":"Africa/Lusaka",
    "iso:country":"ZM",
    "wof:name":"Ndaupala",
    "wof:placetype":"locality"
},
  "geometry": {"coordinates":[30.67441,-12.8765],"type":"Point"}
}