{
  "type": "Feature",
  "properties": {
    "gn:admin1_code":"9.0",
    "gn:asciiname":"Kakunumakuna",
    "gn:country_code":"ZM",
    "gn:dem":1084,
    "gn:feature_class":"P",
    "gn:feature_code":"PPL",
    "gn:name":"Kakunumakuna",
    "gn:population":0,
    "gn:timezone":"Africa/Lusaka",
    "iso:country":"ZM",
    "wof:name":"Kakunumakuna",
    "wof:placetype":"locality"
},
  "geometry": {"coordinates":[29.35,-15.11667],"type":"Point"}
}