{
  "type": "Feature",
  "properties": {
    "gn:admin1_code":"1.0",
    "gn:asciiname":"Sinuma",
    "gn:country_code":"ZM",
    "gn:dem":1080,
    "gn:feature_class":"P",
    "gn:feature_code":"PPL",
    "gn:name":"Sinuma",
    "gn:population":0,
    "gn:timezone":"Africa/Lusaka",
    "iso:country":"ZM",
    "wof:name":"Sinuma",
    "wof:placetype":"locality"
},
  "geometry": {"coordinates":[24.58333,-16.86667000000001],"type":"Point"}
}