{
  "type": "Feature",
  "properties": {
    "gn:admin1_code":"7.0",
    "gn:asciiname":"Runde",
    "gn:country_code":"ZM",
    "gn:dem":1031,
    "gn:feature_class":"P",
    "gn:feature_code":"PPL",
    "gn:name":"Runde",
    "gn:population":0,
    "gn:timezone":"Africa/Lusaka",
    "iso:country":"ZM",
    "name:ceb_x_preferred":[
        "Runde"
    ],
    "name:deu_x_preferred":[
        "Runde"
    ],
    "name:est_x_preferred":[
        "Runde"
    ],
    "name:fra_x_preferred":[
        "Runde"
    ],
    "name:hye_x_preferred":[
        "\u054c\u0578\u0582\u0576\u0576\u0565"
    ],
    "name:nld_x_preferred":[
        "Runde"
    ],
    "name:nno_x_preferred":[
        "Runde"
    ],
    "name:nor_x_preferred":[
        "Runde"
    ],
    "name:rus_x_preferred":[
        "\u0420\u0443\u043d\u043d\u0435"
    ],
    "wof:name":"Runde",
    "wof:placetype":"locality"
},
  "geometry": {"coordinates":[27.61667000000001,-16.03333],"type":"Point"}
}