{
  "type": "Feature",
  "properties": {
    "gn:admin1_code":"2.0",
    "gn:asciiname":"Karenda",
    "gn:country_code":"ZM",
    "gn:dem":1275,
    "gn:feature_class":"P",
    "gn:feature_code":"PPL",
    "gn:name":"Karenda",
    "gn:population":0,
    "gn:timezone":"Africa/Lusaka",
    "iso:country":"ZM",
    "wof:name":"Karenda",
    "wof:placetype":"locality"
},
  "geometry": {"coordinates":[26.88333,-14.71667],"type":"Point"}
}