{
  "type": "Feature",
  "properties": {
    "gn:admin1_code":"3.0",
    "gn:asciiname":"Naimbika",
    "gn:country_code":"ZM",
    "gn:dem":539,
    "gn:feature_class":"P",
    "gn:feature_code":"PPL",
    "gn:name":"Naimbika",
    "gn:population":0,
    "gn:timezone":"Africa/Lusaka",
    "iso:country":"ZM",
    "wof:name":"Naimbika",
    "wof:placetype":"locality"
},
  "geometry": {"coordinates":[31.58333,-13.45],"type":"Point"}
}