{
  "type": "Feature",
  "properties": {
    "gn:admin1_code":"9.0",
    "gn:asciiname":"Kabwata",
    "gn:country_code":"ZM",
    "gn:dem":1073,
    "gn:feature_class":"P",
    "gn:feature_code":"PPL",
    "gn:name":"Kabwata",
    "gn:population":0,
    "gn:timezone":"Africa/Lusaka",
    "iso:country":"ZM",
    "wof:name":"Kabwata",
    "wof:placetype":"locality"
},
  "geometry": {"coordinates":[28.71667,-15.41667],"type":"Point"}
}