{
  "type": "Feature",
  "properties": {
    "gn:admin1_code":"2.0",
    "gn:asciiname":"Dauti",
    "gn:country_code":"ZM",
    "gn:dem":1162,
    "gn:feature_class":"P",
    "gn:feature_code":"PPL",
    "gn:name":"Dauti",
    "gn:population":0,
    "gn:timezone":"Africa/Lusaka",
    "iso:country":"ZM",
    "name:sqi_x_preferred":[
        "Dauti"
    ],
    "wof:name":"Dauti",
    "wof:placetype":"locality"
},
  "geometry": {"coordinates":[27.8834,-14.82813],"type":"Point"}
}