{
  "type": "Feature",
  "properties": {
    "gn:admin1_code":"7.0",
    "gn:asciiname":"Lubanje",
    "gn:country_code":"ZM",
    "gn:dem":1192,
    "gn:feature_class":"P",
    "gn:feature_code":"PPL",
    "gn:name":"Lubanje",
    "gn:population":0,
    "gn:timezone":"Africa/Lusaka",
    "iso:country":"ZM",
    "wof:name":"Lubanje",
    "wof:placetype":"locality"
},
  "geometry": {"coordinates":[27.51667,-16.58333],"type":"Point"}
}