{
  "type": "Feature",
  "properties": {
    "gn:admin1_code":"1.0",
    "gn:asciiname":"Sipula",
    "gn:country_code":"ZM",
    "gn:dem":1074,
    "gn:feature_class":"P",
    "gn:feature_code":"PPL",
    "gn:name":"Sipula",
    "gn:population":0,
    "gn:timezone":"Africa/Lusaka",
    "iso:country":"ZM",
    "wof:name":"Sipula",
    "wof:placetype":"locality"
},
  "geometry": {"coordinates":[24.23333,-16.73333],"type":"Point"}
}