{
  "type": "Feature",
  "properties": {
    "gn:admin1_code":"3.0",
    "gn:asciiname":"Mkumpha",
    "gn:country_code":"ZM",
    "gn:dem":974,
    "gn:feature_class":"P",
    "gn:feature_code":"PPL",
    "gn:name":"Mkumpha",
    "gn:population":0,
    "gn:timezone":"Africa/Lusaka",
    "iso:country":"ZM",
    "wof:name":"Mkumpha",
    "wof:placetype":"locality"
},
  "geometry": {"coordinates":[31.70307,-14.06864],"type":"Point"}
}