{
  "type": "Feature",
  "properties": {
    "gn:admin1_code":"1.0",
    "gn:asciiname":"Wenda",
    "gn:country_code":"ZM",
    "gn:dem":1137,
    "gn:feature_class":"P",
    "gn:feature_code":"PPL",
    "gn:name":"Wenda",
    "gn:population":0,
    "gn:timezone":"Africa/Lusaka",
    "iso:country":"ZM",
    "wof:name":"Wenda",
    "wof:placetype":"locality"
},
  "geometry": {"coordinates":[24.26667,-15.25],"type":"Point"}
}