{
  "type": "Feature",
  "properties": {
    "gn:admin1_code":"1.0",
    "gn:asciiname":"Kalenga",
    "gn:country_code":"ZM",
    "gn:dem":1028,
    "gn:feature_class":"P",
    "gn:feature_code":"PPL",
    "gn:name":"Kalenga",
    "gn:population":0,
    "gn:timezone":"Africa/Lusaka",
    "iso:country":"ZM",
    "wof:name":"Kalenga",
    "wof:placetype":"locality"
},
  "geometry": {"coordinates":[22.75,-15.15],"type":"Point"}
}