{
  "type": "Feature",
  "properties": {
    "gn:admin1_code":"6.0",
    "gn:asciiname":"Sachinyemba",
    "gn:country_code":"ZM",
    "gn:dem":1087,
    "gn:feature_class":"P",
    "gn:feature_code":"PPL",
    "gn:name":"Sachinyemba",
    "gn:population":0,
    "gn:timezone":"Africa/Lusaka",
    "iso:country":"ZM",
    "wof:name":"Sachinyemba",
    "wof:placetype":"locality"
},
  "geometry": {"coordinates":[22.21667,-13.15],"type":"Point"}
}