{
  "type": "Feature",
  "properties": {
    "gn:admin1_code":"2.0",
    "gn:asciiname":"Martin Nandu",
    "gn:country_code":"ZM",
    "gn:dem":1333,
    "gn:feature_class":"P",
    "gn:feature_code":"PPL",
    "gn:name":"Martin Nandu",
    "gn:population":0,
    "gn:timezone":"Africa/Lusaka",
    "iso:country":"ZM",
    "wof:name":"Martin Nandu",
    "wof:placetype":"locality"
},
  "geometry": {"coordinates":[30.46335,-12.82764],"type":"Point"}
}