{
  "type": "Feature",
  "properties": {
    "gn:admin1_code":"1.0",
    "gn:asciiname":"Mabuku",
    "gn:country_code":"ZM",
    "gn:dem":984,
    "gn:feature_class":"P",
    "gn:feature_code":"PPL",
    "gn:name":"Mabuku",
    "gn:population":0,
    "gn:timezone":"Africa/Lusaka",
    "iso:country":"ZM",
    "wof:name":"Mabuku",
    "wof:placetype":"locality"
},
  "geometry": {"coordinates":[25.14479,-16.78887000000001],"type":"Point"}
}