{
  "type": "Feature",
  "properties": {
    "gn:admin1_code":"2.0",
    "gn:asciiname":"Timeo Kunda",
    "gn:country_code":"ZM",
    "gn:dem":1462,
    "gn:feature_class":"P",
    "gn:feature_code":"PPL",
    "gn:name":"Timeo Kunda",
    "gn:population":0,
    "gn:timezone":"Africa/Lusaka",
    "iso:country":"ZM",
    "wof:name":"Timeo Kunda",
    "wof:placetype":"locality"
},
  "geometry": {"coordinates":[30.66653,-12.86349],"type":"Point"}
}