{
  "type": "Feature",
  "properties": {
    "gn:admin1_code":"5.0",
    "gn:asciiname":"Katebula",
    "gn:country_code":"ZM",
    "gn:dem":1457,
    "gn:feature_class":"P",
    "gn:feature_code":"PPL",
    "gn:name":"Katebula",
    "gn:population":0,
    "gn:timezone":"Africa/Lusaka",
    "iso:country":"ZM",
    "wof:name":"Katebula",
    "wof:placetype":"locality"
},
  "geometry": {"coordinates":[31.17824,-9.68408],"type":"Point"}
}