{
  "type": "Feature",
  "properties": {
    "gn:admin1_code":"6.0",
    "gn:asciiname":"Chimbila",
    "gn:country_code":"ZM",
    "gn:dem":1407,
    "gn:feature_class":"P",
    "gn:feature_code":"PPL",
    "gn:name":"Chimbila",
    "gn:population":0,
    "gn:timezone":"Africa/Lusaka",
    "iso:country":"ZM",
    "wof:name":"Chimbila",
    "wof:placetype":"locality"
},
  "geometry": {"coordinates":[24.28333,-11.23333],"type":"Point"}
}