{
  "type": "Feature",
  "properties": {
    "gn:admin1_code":"3.0",
    "gn:asciiname":"Kampende",
    "gn:country_code":"ZM",
    "gn:dem":1012,
    "gn:feature_class":"P",
    "gn:feature_code":"PPL",
    "gn:name":"Kampende",
    "gn:population":0,
    "gn:timezone":"Africa/Lusaka",
    "iso:country":"ZM",
    "wof:name":"Kampende",
    "wof:placetype":"locality"
},
  "geometry": {"coordinates":[31.15014,-14.56165],"type":"Point"}
}