{
  "type": "Feature",
  "properties": {
    "iso:country":"ZM",
    "qs:gn_country":"ZM",
    "qs:gn_fcode":"PPLX",
    "qs:gn_pop":0,
    "qs:name":"Matero",
    "qs:name_adm0":"Zambia",
    "qs:name_adm1":"Lusaka",
    "qs:photos":1,
    "qs:photos_1k":1,
    "qs:photos_9k":1,
    "qs:photos_9r":1,
    "qs:photos_all":1,
    "qs:photos_sr":1,
    "qs:placetype":"Suburb",
    "qs:pop_sr":"0",
    "qs:woe_adm0":23425003,
    "wd:wordcount":23,
    "wof:name":"Matero",
    "wof:placetype":"neighbourhood"
},
  "geometry": {"coordinates":[28.26667,-15.38333],"type":"Point"}
}