{
  "type": "Feature",
  "properties": {
    "gn:admin1_code":"3.0",
    "gn:asciiname":"Mumba",
    "gn:country_code":"ZM",
    "gn:dem":906,
    "gn:feature_class":"P",
    "gn:feature_code":"PPL",
    "gn:name":"Mumba",
    "gn:population":0,
    "gn:timezone":"Africa/Lusaka",
    "iso:country":"ZM",
    "name:ceb_x_preferred":[
        "Mumba"
    ],
    "name:deu_x_preferred":[
        "Mumba"
    ],
    "name:ita_x_preferred":[
        "Mumba"
    ],
    "name:swe_x_preferred":[
        "Mumba"
    ],
    "wof:name":"Mumba",
    "wof:placetype":"locality"
},
  "geometry": {"coordinates":[31.75903,-13.9405],"type":"Point"}
}