{
  "type": "Feature",
  "properties": {
    "gn:admin1_code":"4.0",
    "gn:asciiname":"Mungulube",
    "gn:country_code":"ZM",
    "gn:dem":1187,
    "gn:feature_class":"P",
    "gn:feature_code":"PPL",
    "gn:name":"Mungulube",
    "gn:population":0,
    "gn:timezone":"Africa/Lusaka",
    "iso:country":"ZM",
    "name:und_x_variant":[
        "Munguruwe",
        "Mungulube"
    ],
    "wof:name":"Mungulube",
    "wof:placetype":"locality"
},
  "geometry": {"coordinates":[29.44981,-11.61704],"type":"Point"}
}