{
  "type": "Feature",
  "properties": {
    "gn:admin1_code":"6.0",
    "gn:asciiname":"Sachilambo",
    "gn:country_code":"ZM",
    "gn:dem":1059,
    "gn:feature_class":"P",
    "gn:feature_code":"PPL",
    "gn:name":"Sachilambo",
    "gn:population":0,
    "gn:timezone":"Africa/Lusaka",
    "iso:country":"ZM",
    "wof:name":"Sachilambo",
    "wof:placetype":"locality"
},
  "geometry": {"coordinates":[23.25,-14.06667],"type":"Point"}
}