{
  "type": "Feature",
  "properties": {
    "gn:admin1_code":"3.0",
    "gn:asciiname":"Jowelo",
    "gn:country_code":"ZM",
    "gn:dem":943,
    "gn:feature_class":"P",
    "gn:feature_code":"PPL",
    "gn:name":"Jowelo",
    "gn:population":0,
    "gn:timezone":"Africa/Lusaka",
    "iso:country":"ZM",
    "wof:name":"Jowelo",
    "wof:placetype":"locality"
},
  "geometry": {"coordinates":[32.11163,-14.29913],"type":"Point"}
}