{
  "type": "Feature",
  "properties": {
    "gn:admin1_code":"7.0",
    "gn:asciiname":"Oligonkezya",
    "gn:country_code":"ZM",
    "gn:dem":766,
    "gn:feature_class":"P",
    "gn:feature_code":"PPL",
    "gn:name":"Oligonkezya",
    "gn:population":0,
    "gn:timezone":"Africa/Lusaka",
    "iso:country":"ZM",
    "name:und_x_variant":[
        "Oligonkezia",
        "Oligonkezya"
    ],
    "wof:name":"Oligonkezya",
    "wof:placetype":"locality"
},
  "geometry": {"coordinates":[27.81667,-16.55],"type":"Point"}
}