{
  "type": "Feature",
  "properties": {
    "gn:admin1_code":"2.0",
    "gn:asciiname":"Lamak Miya",
    "gn:country_code":"ZM",
    "gn:dem":1604,
    "gn:feature_class":"P",
    "gn:feature_code":"PPL",
    "gn:name":"Lamak Miya",
    "gn:population":0,
    "gn:timezone":"Africa/Lusaka",
    "iso:country":"ZM",
    "wof:name":"Lamak Miya",
    "wof:placetype":"locality"
},
  "geometry": {"coordinates":[30.89565,-13.05697],"type":"Point"}
}