{
  "type": "Feature",
  "properties": {
    "gn:admin1_code":"1.0",
    "gn:asciiname":"Kachoncho",
    "gn:country_code":"ZM",
    "gn:dem":1174,
    "gn:feature_class":"P",
    "gn:feature_code":"PPL",
    "gn:name":"Kachoncho",
    "gn:population":0,
    "gn:timezone":"Africa/Lusaka",
    "iso:country":"ZM",
    "wof:name":"Kachoncho",
    "wof:placetype":"locality"
},
  "geometry": {"coordinates":[24.95604,-14.57558],"type":"Point"}
}