{
  "type": "Feature",
  "properties": {
    "gn:admin1_code":"3.0",
    "gn:asciiname":"Mkomera",
    "gn:country_code":"ZM",
    "gn:dem":690,
    "gn:feature_class":"P",
    "gn:feature_code":"PPL",
    "gn:name":"Mkomera",
    "gn:population":0,
    "gn:timezone":"Africa/Lusaka",
    "iso:country":"ZM",
    "wof:name":"Mkomera",
    "wof:placetype":"locality"
},
  "geometry": {"coordinates":[31.91667,-13.68333],"type":"Point"}
}