{
  "type": "Feature",
  "properties": {
    "gn:admin1_code":"10.0",
    "gn:asciiname":"Kasumba",
    "gn:country_code":"ZM",
    "gn:dem":1400,
    "gn:feature_class":"P",
    "gn:feature_code":"PPL",
    "gn:name":"Kasumba",
    "gn:population":0,
    "gn:timezone":"Africa/Lusaka",
    "iso:country":"ZM",
    "wof:name":"Kasumba",
    "wof:placetype":"locality"
},
  "geometry": {"coordinates":[31.53333,-11.98333],"type":"Point"}
}