{
  "type": "Feature",
  "properties": {
    "gn:admin1_code":"7.0",
    "gn:asciiname":"Mobola",
    "gn:country_code":"ZM",
    "gn:dem":1158,
    "gn:feature_class":"P",
    "gn:feature_code":"PPL",
    "gn:name":"Mobola",
    "gn:population":0,
    "gn:timezone":"Africa/Lusaka",
    "iso:country":"ZM",
    "name:und_x_variant":[
        "Mobolo",
        "Mobola"
    ],
    "wof:name":"Mobola",
    "wof:placetype":"locality"
},
  "geometry": {"coordinates":[26.69843,-16.24276],"type":"Point"}
}