{
  "type": "Feature",
  "properties": {
    "gn:admin1_code":"4.0",
    "gn:asciiname":"Kalungwisi",
    "gn:country_code":"ZM",
    "gn:dem":969,
    "gn:feature_class":"P",
    "gn:feature_code":"PPL",
    "gn:name":"Kalungwisi",
    "gn:population":0,
    "gn:timezone":"Africa/Lusaka",
    "iso:country":"ZM",
    "wof:name":"Kalungwisi",
    "wof:placetype":"locality"
},
  "geometry": {"coordinates":[29.03333,-9.03333],"type":"Point"}
}