{
  "type": "Feature",
  "properties": {
    "gn:admin1_code":"1.0",
    "gn:asciiname":"Simwalanya",
    "gn:country_code":"ZM",
    "gn:dem":1012,
    "gn:feature_class":"P",
    "gn:feature_code":"PPL",
    "gn:name":"Simwalanya",
    "gn:population":0,
    "gn:timezone":"Africa/Lusaka",
    "iso:country":"ZM",
    "wof:name":"Simwalanya",
    "wof:placetype":"locality"
},
  "geometry": {"coordinates":[24.51667,-17.11667000000001],"type":"Point"}
}