{
  "type": "Feature",
  "properties": {
    "gn:admin1_code":"1.0",
    "gn:asciiname":"Kataba",
    "gn:country_code":"ZM",
    "gn:dem":1182,
    "gn:feature_class":"P",
    "gn:feature_code":"PPL",
    "gn:name":"Kataba",
    "gn:population":0,
    "gn:timezone":"Africa/Lusaka",
    "iso:country":"ZM",
    "name:ceb_x_preferred":[
        "Kataba"
    ],
    "name:deu_x_preferred":[
        "Kataba"
    ],
    "name:tgl_x_preferred":[
        "Kataba"
    ],
    "wof:name":"Kataba",
    "wof:placetype":"locality"
},
  "geometry": {"coordinates":[25.09418,-16.07875],"type":"Point"}
}