{
  "type": "Feature",
  "properties": {
    "gn:admin1_code":"6.0",
    "gn:asciiname":"Sengelenge",
    "gn:country_code":"ZM",
    "gn:dem":1168,
    "gn:feature_class":"P",
    "gn:feature_code":"PPL",
    "gn:name":"Sengelenge",
    "gn:population":0,
    "gn:timezone":"Africa/Lusaka",
    "iso:country":"ZM",
    "wof:name":"Sengelenge",
    "wof:placetype":"locality"
},
  "geometry": {"coordinates":[24.28333,-12.83333],"type":"Point"}
}