{
  "type": "Feature",
  "properties": {
    "gn:admin1_code":"3.0",
    "gn:asciiname":"Kazowo",
    "gn:country_code":"ZM",
    "gn:dem":947,
    "gn:feature_class":"P",
    "gn:feature_code":"PPL",
    "gn:name":"Kazowo",
    "gn:population":0,
    "gn:timezone":"Africa/Lusaka",
    "iso:country":"ZM",
    "wof:name":"Kazowo",
    "wof:placetype":"locality"
},
  "geometry": {"coordinates":[31.25,-14.28333],"type":"Point"}
}