{
  "type": "Feature",
  "properties": {
    "gn:admin1_code":"3.0",
    "gn:asciiname":"Malanda",
    "gn:country_code":"ZM",
    "gn:dem":1066,
    "gn:feature_class":"P",
    "gn:feature_code":"PPL",
    "gn:name":"Malanda",
    "gn:population":0,
    "gn:timezone":"Africa/Lusaka",
    "iso:country":"ZM",
    "name:und_x_variant":[
        "Malenga",
        "Malanda"
    ],
    "wof:name":"Malanda",
    "wof:placetype":"locality"
},
  "geometry": {"coordinates":[31.71667,-14.41667],"type":"Point"}
}