{
  "type": "Feature",
  "properties": {
    "gn:admin1_code":"1.0",
    "gn:asciiname":"Simasiku",
    "gn:country_code":"ZM",
    "gn:dem":1041,
    "gn:feature_class":"P",
    "gn:feature_code":"PPL",
    "gn:name":"Simasiku",
    "gn:population":0,
    "gn:timezone":"Africa/Lusaka",
    "iso:country":"ZM",
    "wof:name":"Simasiku",
    "wof:placetype":"locality"
},
  "geometry": {"coordinates":[22.31667,-14.68333],"type":"Point"}
}