{
  "type": "Feature",
  "properties": {
    "gn:admin1_code":"8.0",
    "gn:asciiname":"Kumbwe",
    "gn:country_code":"ZM",
    "gn:dem":1277,
    "gn:feature_class":"P",
    "gn:feature_code":"PPL",
    "gn:name":"Kumbwe",
    "gn:population":0,
    "gn:timezone":"Africa/Lusaka",
    "iso:country":"ZM",
    "name:und_x_variant":[
        "Kumbwi",
        "Kumbwe"
    ],
    "wof:name":"Kumbwe",
    "wof:placetype":"locality"
},
  "geometry": {"coordinates":[27.45,-12.81667],"type":"Point"}
}