{
  "type": "Feature",
  "properties": {
    "gn:admin1_code":"3.0",
    "gn:asciiname":"Luo",
    "gn:country_code":"ZM",
    "gn:dem":1015,
    "gn:feature_class":"P",
    "gn:feature_code":"PPL",
    "gn:name":"Luo",
    "gn:population":0,
    "gn:timezone":"Africa/Lusaka",
    "iso:country":"ZM",
    "wof:name":"Luo",
    "wof:placetype":"locality"
},
  "geometry": {"coordinates":[31.28333,-14.45],"type":"Point"}
}