{
  "type": "Feature",
  "properties": {
    "gn:admin1_code":"3.0",
    "gn:asciiname":"Luo",
    "gn:country_code":"ZM",
    "gn:dem":1015,
    "gn:feature_class":"P",
    "gn:feature_code":"PPL",
    "gn:name":"Luo",
    "gn:population":0,
    "gn:timezone":"Africa/Lusaka",
    "iso:country":"ZM",
    "name:bre_x_preferred":[
        "Luo"
    ],
    "name:ceb_x_preferred":[
        "Luo"
    ],
    "name:cym_x_preferred":[
        "Luo"
    ],
    "name:dan_x_preferred":[
        "Luo"
    ],
    "name:deu_x_preferred":[
        "Luo"
    ],
    "name:fra_x_preferred":[
        "Luo"
    ],
    "name:lit_x_preferred":[
        "Luo"
    ],
    "name:nld_x_preferred":[
        "Luo"
    ],
    "name:nor_x_preferred":[
        "Luo"
    ],
    "name:rus_x_preferred":[
        "\u041b\u0443\u043e"
    ],
    "name:swa_x_preferred":[
        "Luo"
    ],
    "name:swe_x_preferred":[
        "Luo"
    ],
    "wof:name":"Luo",
    "wof:placetype":"locality"
},
  "geometry": {"coordinates":[31.28333,-14.45],"type":"Point"}
}