{
  "type": "Feature",
  "properties": {
    "gn:admin1_code":"7.0",
    "gn:asciiname":"Kanjonja",
    "gn:country_code":"ZM",
    "gn:dem":600,
    "gn:feature_class":"P",
    "gn:feature_code":"PPL",
    "gn:name":"Kanjonja",
    "gn:population":0,
    "gn:timezone":"Africa/Lusaka",
    "iso:country":"ZM",
    "name:eng_x_preferred":[
        "Kanjonja"
    ],
    "name:eng_x_variant":[
        "Kajonja"
    ],
    "wof:name":"Kanjonja",
    "wof:placetype":"locality"
},
  "geometry": {"coordinates":[27.20085,-17.36701],"type":"Point"}
}