{
  "type": "Feature",
  "properties": {
    "gn:admin1_code":"1.0",
    "gn:asciiname":"Sianga",
    "gn:country_code":"ZM",
    "gn:dem":1044,
    "gn:feature_class":"P",
    "gn:feature_code":"PPL",
    "gn:name":"Sianga",
    "gn:population":0,
    "gn:timezone":"Africa/Lusaka",
    "iso:country":"ZM",
    "wof:name":"Sianga",
    "wof:placetype":"locality"
},
  "geometry": {"coordinates":[22.66667,-15.68333],"type":"Point"}
}