{
  "type": "Feature",
  "properties": {
    "gn:admin1_code":"3.0",
    "gn:asciiname":"Kanyanyata",
    "gn:country_code":"ZM",
    "gn:dem":1148,
    "gn:feature_class":"P",
    "gn:feature_code":"PPL",
    "gn:name":"Kanyanyata",
    "gn:population":0,
    "gn:timezone":"Africa/Lusaka",
    "iso:country":"ZM",
    "wof:name":"Kanyanyata",
    "wof:placetype":"locality"
},
  "geometry": {"coordinates":[33.14432,-12.11498],"type":"Point"}
}