{
  "type": "Feature",
  "properties": {
    "gn:admin1_code":"7.0",
    "gn:asciiname":"Kalobola",
    "gn:country_code":"ZM",
    "gn:dem":1142,
    "gn:feature_class":"P",
    "gn:feature_code":"PPL",
    "gn:name":"Kalobola",
    "gn:population":0,
    "gn:timezone":"Africa/Lusaka",
    "iso:country":"ZM",
    "wof:name":"Kalobola",
    "wof:placetype":"locality"
},
  "geometry": {"coordinates":[27.76667,-15.95],"type":"Point"}
}