{
  "type": "Feature",
  "properties": {
    "gn:admin1_code":"3.0",
    "gn:asciiname":"Malombola",
    "gn:country_code":"ZM",
    "gn:dem":724,
    "gn:feature_class":"P",
    "gn:feature_code":"PPL",
    "gn:name":"Malombola",
    "gn:population":0,
    "gn:timezone":"Africa/Lusaka",
    "iso:country":"ZM",
    "name:und_x_variant":[
        "Malombora",
        "Malombola"
    ],
    "wof:name":"Malombola",
    "wof:placetype":"locality"
},
  "geometry": {"coordinates":[31.81667,-13.63333],"type":"Point"}
}