{
  "type": "Feature",
  "properties": {
    "gn:admin1_code":"1.0",
    "gn:asciiname":"Simazina",
    "gn:country_code":"ZM",
    "gn:dem":1070,
    "gn:feature_class":"P",
    "gn:feature_code":"PPL",
    "gn:name":"Simazina",
    "gn:population":0,
    "gn:timezone":"Africa/Lusaka",
    "iso:country":"ZM",
    "wof:name":"Simazina",
    "wof:placetype":"locality"
},
  "geometry": {"coordinates":[24.85,-16.83333],"type":"Point"}
}