{
  "type": "Feature",
  "properties": {
    "gn:admin1_code":"8.0",
    "gn:asciiname":"Mukushi",
    "gn:country_code":"ZM",
    "gn:dem":1276,
    "gn:feature_class":"P",
    "gn:feature_code":"PPL",
    "gn:name":"Mukushi",
    "gn:population":0,
    "gn:timezone":"Africa/Lusaka",
    "iso:country":"ZM",
    "wof:name":"Mukushi",
    "wof:placetype":"locality"
},
  "geometry": {"coordinates":[28.76667,-13.01667],"type":"Point"}
}