{
  "type": "Feature",
  "properties": {
    "gn:admin1_code":"5.0",
    "gn:asciiname":"Sikalala",
    "gn:country_code":"ZM",
    "gn:dem":1284,
    "gn:feature_class":"P",
    "gn:feature_code":"PPL",
    "gn:name":"Sikalala",
    "gn:population":0,
    "gn:timezone":"Africa/Lusaka",
    "iso:country":"ZM",
    "wof:name":"Sikalala",
    "wof:placetype":"locality"
},
  "geometry": {"coordinates":[30.68333,-9.06667],"type":"Point"}
}