{
  "type": "Feature",
  "properties": {
    "gn:admin1_code":"4.0",
    "gn:asciiname":"Bahati",
    "gn:country_code":"ZM",
    "gn:dem":1293,
    "gn:feature_class":"P",
    "gn:feature_code":"PPL",
    "gn:name":"Bahati",
    "gn:population":0,
    "gn:timezone":"Africa/Lusaka",
    "iso:country":"ZM",
    "wof:name":"Bahati",
    "wof:placetype":"locality"
},
  "geometry": {"coordinates":[28.81501,-11.01024],"type":"Point"}
}