{
  "type": "Feature",
  "properties": {
    "gn:admin1_code":"2.0",
    "gn:asciiname":"Chimoto",
    "gn:country_code":"ZM",
    "gn:dem":1182,
    "gn:feature_class":"P",
    "gn:feature_code":"PPL",
    "gn:name":"Chimoto",
    "gn:population":0,
    "gn:timezone":"Africa/Lusaka",
    "iso:country":"ZM",
    "name:und_x_variant":[
        "Chimutu",
        "Chimufu",
        "Chimoto"
    ],
    "wof:name":"Chimoto",
    "wof:placetype":"locality"
},
  "geometry": {"coordinates":[27.09775,-15.03454],"type":"Point"}
}