{
  "type": "Feature",
  "properties": {
    "gn:admin1_code":"3.0",
    "gn:asciiname":"Chisonso",
    "gn:country_code":"ZM",
    "gn:dem":934,
    "gn:feature_class":"P",
    "gn:feature_code":"PPL",
    "gn:name":"Chisonso",
    "gn:population":0,
    "gn:timezone":"Africa/Lusaka",
    "iso:country":"ZM",
    "wof:name":"Chisonso",
    "wof:placetype":"locality"
},
  "geometry": {"coordinates":[31.26716,-14.37657],"type":"Point"}
}