{
  "type": "Feature",
  "properties": {
    "gn:admin1_code":"1.0",
    "gn:asciiname":"Samusole",
    "gn:country_code":"ZM",
    "gn:dem":1069,
    "gn:feature_class":"P",
    "gn:feature_code":"PPL",
    "gn:name":"Samusole",
    "gn:population":0,
    "gn:timezone":"Africa/Lusaka",
    "iso:country":"ZM",
    "wof:name":"Samusole",
    "wof:placetype":"locality"
},
  "geometry": {"coordinates":[23.43333,-15.78333],"type":"Point"}
}