{
  "type": "Feature",
  "properties": {
    "gn:admin1_code":"5.0",
    "gn:asciiname":"Menga",
    "gn:country_code":"ZM",
    "gn:dem":1235,
    "gn:feature_class":"P",
    "gn:feature_code":"PPL",
    "gn:name":"Menga",
    "gn:population":0,
    "gn:timezone":"Africa/Lusaka",
    "iso:country":"ZM",
    "wof:name":"Menga",
    "wof:placetype":"locality"
},
  "geometry": {"coordinates":[30.96667,-10.83333],"type":"Point"}
}