{
  "type": "Feature",
  "properties": {
    "gn:admin1_code":"5.0",
    "gn:asciiname":"Pembamoto",
    "gn:country_code":"ZM",
    "gn:dem":974,
    "gn:feature_class":"P",
    "gn:feature_code":"PPL",
    "gn:name":"Pembamoto",
    "gn:population":0,
    "gn:timezone":"Africa/Lusaka",
    "iso:country":"ZM",
    "wof:name":"Pembamoto",
    "wof:placetype":"locality"
},
  "geometry": {"coordinates":[30.08424,-8.57085],"type":"Point"}
}