{
  "type": "Feature",
  "properties": {
    "gn:admin1_code":"2.0",
    "gn:asciiname":"Mikondo",
    "gn:country_code":"ZM",
    "gn:dem":1205,
    "gn:feature_class":"P",
    "gn:feature_code":"PPL",
    "gn:name":"Mikondo",
    "gn:population":0,
    "gn:timezone":"Africa/Lusaka",
    "iso:country":"ZM",
    "wof:name":"Mikondo",
    "wof:placetype":"locality"
},
  "geometry": {"coordinates":[27.16327,-14.70457],"type":"Point"}
}