{
  "type": "Feature",
  "properties": {
    "gn:admin1_code":"1.0",
    "gn:asciiname":"Mundia",
    "gn:country_code":"ZM",
    "gn:dem":1026,
    "gn:feature_class":"P",
    "gn:feature_code":"PPL",
    "gn:name":"Mundia",
    "gn:population":0,
    "gn:timezone":"Africa/Lusaka",
    "iso:country":"ZM",
    "name:bpy_x_preferred":[
        "\u09ae\u09c1\u09a8\u09cd\u09a6\u09bf\u09af\u09bc\u09be"
    ],
    "name:ita_x_preferred":[
        "Mundia"
    ],
    "name:msa_x_preferred":[
        "Mundia"
    ],
    "name:new_x_preferred":[
        "\u092e\u0941\u0928\u094d\u0926\u093f\u092f\u093e"
    ],
    "name:nld_x_preferred":[
        "Mundia"
    ],
    "name:pol_x_preferred":[
        "Mundia"
    ],
    "name:por_x_preferred":[
        "Mundia"
    ],
    "name:urd_x_preferred":[
        "\u0645\u0646\u062f\u06cc\u0627"
    ],
    "name:vie_x_preferred":[
        "Mundia"
    ],
    "name:zho_x_preferred":[
        "\u8499\u8fea\u4e9a"
    ],
    "wof:name":"Mundia",
    "wof:placetype":"locality"
},
  "geometry": {"coordinates":[23.15,-14.75],"type":"Point"}
}