{
  "type": "Feature",
  "properties": {
    "gn:admin1_code":"2.0",
    "gn:asciiname":"Chiti",
    "gn:country_code":"ZM",
    "gn:dem":1044,
    "gn:feature_class":"P",
    "gn:feature_code":"PPL",
    "gn:name":"Chiti",
    "gn:population":0,
    "gn:timezone":"Africa/Lusaka",
    "iso:country":"ZM",
    "name:ceb_x_preferred":[
        "Chiti"
    ],
    "name:fra_x_preferred":[
        "Chiti"
    ],
    "name:mai_x_preferred":[
        "\u091a\u093f\u0924\u0940"
    ],
    "name:msa_x_preferred":[
        "Chiti"
    ],
    "name:nep_x_preferred":[
        "\u091a\u093f\u0924\u0940"
    ],
    "name:new_x_preferred":[
        "\u091a\u093f\u0924\u0940"
    ],
    "name:pol_x_preferred":[
        "Chiti"
    ],
    "wof:name":"Chiti",
    "wof:placetype":"locality"
},
  "geometry": {"coordinates":[29.84672,-14.04248],"type":"Point"}
}