{
  "type": "Feature",
  "properties": {
    "gn:admin1_code":"3.0",
    "gn:asciiname":"Kalembo",
    "gn:country_code":"ZM",
    "gn:dem":1138,
    "gn:feature_class":"P",
    "gn:feature_code":"PPL",
    "gn:name":"Kalembo",
    "gn:population":0,
    "gn:timezone":"Africa/Lusaka",
    "iso:country":"ZM",
    "wof:name":"Kalembo",
    "wof:placetype":"locality"
},
  "geometry": {"coordinates":[33.16667,-12.05],"type":"Point"}
}