{
  "type": "Feature",
  "properties": {
    "gn:admin1_code":"7.0",
    "gn:asciiname":"Kandundwe",
    "gn:country_code":"ZM",
    "gn:dem":1004,
    "gn:feature_class":"P",
    "gn:feature_code":"PPL",
    "gn:name":"Kandundwe",
    "gn:population":0,
    "gn:timezone":"Africa/Lusaka",
    "iso:country":"ZM",
    "name:und_x_variant":[
        "Kendundwa",
        "Kandundwe"
    ],
    "wof:name":"Kandundwe",
    "wof:placetype":"locality"
},
  "geometry": {"coordinates":[26.05,-15.78333],"type":"Point"}
}