{
  "type": "Feature",
  "properties": {
    "gn:admin1_code":"2.0",
    "gn:asciiname":"Kampumba",
    "gn:country_code":"ZM",
    "gn:dem":1109,
    "gn:feature_class":"P",
    "gn:feature_code":"PPL",
    "gn:name":"Kampumba",
    "gn:population":0,
    "gn:timezone":"Africa/Lusaka",
    "iso:country":"ZM",
    "wof:name":"Kampumba",
    "wof:placetype":"locality"
},
  "geometry": {"coordinates":[29.02369,-14.55397],"type":"Point"}
}