{
  "type": "Feature",
  "properties": {
    "gn:admin1_code":"3.0",
    "gn:asciiname":"Chiwama",
    "gn:country_code":"ZM",
    "gn:dem":1057,
    "gn:feature_class":"P",
    "gn:feature_code":"PPL",
    "gn:name":"Chiwama",
    "gn:population":0,
    "gn:timezone":"Africa/Lusaka",
    "iso:country":"ZM",
    "wof:name":"Chiwama",
    "wof:placetype":"locality"
},
  "geometry": {"coordinates":[32.88333,-13.25],"type":"Point"}
}