{
  "type": "Feature",
  "properties": {
    "gn:admin1_code":"5.0",
    "gn:asciiname":"Malama",
    "gn:country_code":"ZM",
    "gn:dem":1202,
    "gn:feature_class":"P",
    "gn:feature_code":"PPL",
    "gn:name":"Malama",
    "gn:population":0,
    "gn:timezone":"Africa/Lusaka",
    "iso:country":"ZM",
    "wof:name":"Malama",
    "wof:placetype":"locality"
},
  "geometry": {"coordinates":[31.17286,-10.89644],"type":"Point"}
}