{
  "type": "Feature",
  "properties": {
    "gn:admin1_code":"1.0",
    "gn:asciiname":"Atanga",
    "gn:country_code":"ZM",
    "gn:dem":1020,
    "gn:feature_class":"P",
    "gn:feature_code":"PPL",
    "gn:name":"Atanga",
    "gn:population":0,
    "gn:timezone":"Africa/Lusaka",
    "iso:country":"ZM",
    "wof:name":"Atanga",
    "wof:placetype":"locality"
},
  "geometry": {"coordinates":[22.85,-15.35],"type":"Point"}
}