{
  "type": "Feature",
  "properties": {
    "gn:admin1_code":"10.0",
    "gn:asciiname":"Mpangala",
    "gn:country_code":"ZM",
    "gn:dem":1257,
    "gn:feature_class":"P",
    "gn:feature_code":"PPL",
    "gn:name":"Mpangala",
    "gn:population":0,
    "gn:timezone":"Africa/Lusaka",
    "iso:country":"ZM",
    "wof:name":"Mpangala",
    "wof:placetype":"locality"
},
  "geometry": {"coordinates":[32.81667,-9.83333],"type":"Point"}
}