{
  "type": "Feature",
  "properties": {
    "gn:admin1_code":"3.0",
    "gn:asciiname":"Kakoma",
    "gn:country_code":"ZM",
    "gn:dem":962,
    "gn:feature_class":"P",
    "gn:feature_code":"PPL",
    "gn:name":"Kakoma",
    "gn:population":0,
    "gn:timezone":"Africa/Lusaka",
    "iso:country":"ZM",
    "wof:name":"Kakoma",
    "wof:placetype":"locality"
},
  "geometry": {"coordinates":[32.65,-13.45],"type":"Point"}
}