{
  "type": "Feature",
  "properties": {
    "gn:admin1_code":"2.0",
    "gn:asciiname":"Joni Kafwenya",
    "gn:country_code":"ZM",
    "gn:dem":1458,
    "gn:feature_class":"P",
    "gn:feature_code":"PPL",
    "gn:name":"Joni Kafwenya",
    "gn:population":0,
    "gn:timezone":"Africa/Lusaka",
    "iso:country":"ZM",
    "wof:name":"Joni Kafwenya",
    "wof:placetype":"locality"
},
  "geometry": {"coordinates":[30.90973,-13.21303],"type":"Point"}
}