{
  "type": "Feature",
  "properties": {
    "gn:admin1_code":"3.0",
    "gn:asciiname":"Nyamalani",
    "gn:country_code":"ZM",
    "gn:dem":1164,
    "gn:feature_class":"P",
    "gn:feature_code":"PPL",
    "gn:name":"Nyamalani",
    "gn:population":0,
    "gn:timezone":"Africa/Lusaka",
    "iso:country":"ZM",
    "wof:name":"Nyamalani",
    "wof:placetype":"locality"
},
  "geometry": {"coordinates":[32.96667,-12.63333],"type":"Point"}
}