{
  "type": "Feature",
  "properties": {
    "gn:admin1_code":"6.0",
    "gn:asciiname":"Kanongesha",
    "gn:country_code":"ZM",
    "gn:dem":1412,
    "gn:feature_class":"P",
    "gn:feature_code":"PPL",
    "gn:name":"Kanongesha",
    "gn:population":0,
    "gn:timezone":"Africa/Lusaka",
    "iso:country":"ZM",
    "wof:name":"Kanongesha",
    "wof:placetype":"locality"
},
  "geometry": {"coordinates":[24.06186,-11.72242],"type":"Point"}
}