{
  "type": "Feature",
  "properties": {
    "gn:admin1_code":"2.0",
    "gn:asciiname":"Mulaya",
    "gn:country_code":"ZM",
    "gn:dem":1372,
    "gn:feature_class":"P",
    "gn:feature_code":"PPL",
    "gn:name":"Mulaya",
    "gn:population":0,
    "gn:timezone":"Africa/Lusaka",
    "iso:country":"ZM",
    "wof:name":"Mulaya",
    "wof:placetype":"locality"
},
  "geometry": {"coordinates":[30.11667000000001,-13.13333],"type":"Point"}
}