{
  "type": "Feature",
  "properties": {
    "gn:admin1_code":"1.0",
    "gn:asciiname":"Ngazima",
    "gn:country_code":"ZM",
    "gn:dem":1045,
    "gn:feature_class":"P",
    "gn:feature_code":"PPL",
    "gn:name":"Ngazima",
    "gn:population":0,
    "gn:timezone":"Africa/Lusaka",
    "iso:country":"ZM",
    "wof:name":"Ngazima",
    "wof:placetype":"locality"
},
  "geometry": {"coordinates":[24.11667000000001,-16.01667],"type":"Point"}
}