{
  "type": "Feature",
  "properties": {
    "gn:admin1_code":"3.0",
    "gn:asciiname":"Chikuwe",
    "gn:country_code":"ZM",
    "gn:dem":946,
    "gn:feature_class":"P",
    "gn:feature_code":"PPL",
    "gn:name":"Chikuwe",
    "gn:population":0,
    "gn:timezone":"Africa/Lusaka",
    "iso:country":"ZM",
    "wof:name":"Chikuwe",
    "wof:placetype":"locality"
},
  "geometry": {"coordinates":[32.43096,-13.51368],"type":"Point"}
}