{
  "type": "Feature",
  "properties": {
    "gn:admin1_code":"3.0",
    "gn:asciiname":"Chizikwe",
    "gn:country_code":"ZM",
    "gn:dem":663,
    "gn:feature_class":"P",
    "gn:feature_code":"PPL",
    "gn:name":"Chizikwe",
    "gn:population":0,
    "gn:timezone":"Africa/Lusaka",
    "iso:country":"ZM",
    "wof:name":"Chizikwe",
    "wof:placetype":"locality"
},
  "geometry": {"coordinates":[31.03333,-14.08333],"type":"Point"}
}