{
  "type": "Feature",
  "properties": {
    "gn:admin1_code":"9.0",
    "gn:asciiname":"Chilanga Township",
    "gn:country_code":"ZM",
    "gn:dem":1198,
    "gn:feature_class":"P",
    "gn:feature_code":"PPL",
    "gn:name":"Chilanga Township",
    "gn:population":0,
    "gn:timezone":"Africa/Lusaka",
    "iso:country":"ZM",
    "wof:name":"Chilanga Township",
    "wof:placetype":"locality"
},
  "geometry": {"coordinates":[28.2701,-15.57079],"type":"Point"}
}