{
  "type": "Feature",
  "properties": {
    "gn:admin1_code":"8.0",
    "gn:asciiname":"Chiwelwa",
    "gn:country_code":"ZM",
    "gn:dem":1247,
    "gn:feature_class":"P",
    "gn:feature_code":"PPL",
    "gn:name":"Chiwelwa",
    "gn:population":0,
    "gn:timezone":"Africa/Lusaka",
    "iso:country":"ZM",
    "wof:name":"Chiwelwa",
    "wof:placetype":"locality"
},
  "geometry": {"coordinates":[29.78333,-9.68333],"type":"Point"}
}