{
  "type": "Feature",
  "properties": {
    "gn:admin1_code":"5.0",
    "gn:asciiname":"Kafwanka",
    "gn:country_code":"ZM",
    "gn:dem":1020,
    "gn:feature_class":"P",
    "gn:feature_code":"PPL",
    "gn:name":"Kafwanka",
    "gn:population":0,
    "gn:timezone":"Africa/Lusaka",
    "iso:country":"ZM",
    "wof:name":"Kafwanka",
    "wof:placetype":"locality"
},
  "geometry": {"coordinates":[29.91107,-8.7051],"type":"Point"}
}