{
  "type": "Feature",
  "properties": {
    "gn:admin1_code":"1.0",
    "gn:asciiname":"Ndonda",
    "gn:country_code":"ZM",
    "gn:dem":1046,
    "gn:feature_class":"P",
    "gn:feature_code":"PPL",
    "gn:name":"Ndonda",
    "gn:population":0,
    "gn:timezone":"Africa/Lusaka",
    "iso:country":"ZM",
    "wof:name":"Ndonda",
    "wof:placetype":"locality"
},
  "geometry": {"coordinates":[23.73333,-14.55],"type":"Point"}
}