{
  "type": "Feature",
  "properties": {
    "gn:admin1_code":"6.0",
    "gn:asciiname":"Chiyeke",
    "gn:country_code":"ZM",
    "gn:dem":1049,
    "gn:feature_class":"P",
    "gn:feature_code":"PPL",
    "gn:name":"Chiyeke",
    "gn:population":0,
    "gn:timezone":"Africa/Lusaka",
    "iso:country":"ZM",
    "name:und_x_variant":[
        "Chieke",
        "Chiyeke"
    ],
    "wof:name":"Chiyeke",
    "wof:placetype":"locality"
},
  "geometry": {"coordinates":[22.75,-13.18333],"type":"Point"}
}