{
  "type": "Feature",
  "properties": {
    "gn:admin1_code":"7.0",
    "gn:asciiname":"Chilapi",
    "gn:country_code":"ZM",
    "gn:dem":592,
    "gn:feature_class":"P",
    "gn:feature_code":"PPL",
    "gn:name":"Chilapi",
    "gn:population":0,
    "gn:timezone":"Africa/Lusaka",
    "iso:country":"ZM",
    "name:und_x_variant":[
        "Chilopi",
        "Chilapi"
    ],
    "wof:name":"Chilapi",
    "wof:placetype":"locality"
},
  "geometry": {"coordinates":[28.05447,-16.4707],"type":"Point"}
}