{
  "type": "Feature",
  "properties": {
    "gn:admin1_code":"3.0",
    "gn:asciiname":"Changwe",
    "gn:country_code":"ZM",
    "gn:dem":597,
    "gn:feature_class":"P",
    "gn:feature_code":"PPL",
    "gn:name":"Changwe",
    "gn:population":0,
    "gn:timezone":"Africa/Lusaka",
    "iso:country":"ZM",
    "wof:name":"Changwe",
    "wof:placetype":"locality"
},
  "geometry": {"coordinates":[30.98559,-14.0495],"type":"Point"}
}