{
  "type": "Feature",
  "properties": {
    "gn:admin1_code":"2.0",
    "gn:asciiname":"Jamu Kasamika",
    "gn:country_code":"ZM",
    "gn:dem":1252,
    "gn:feature_class":"P",
    "gn:feature_code":"PPL",
    "gn:name":"Jamu Kasamika",
    "gn:population":0,
    "gn:timezone":"Africa/Lusaka",
    "iso:country":"ZM",
    "wof:name":"Jamu Kasamika",
    "wof:placetype":"locality"
},
  "geometry": {"coordinates":[30.26444,-12.79837],"type":"Point"}
}