{
  "type": "Feature",
  "properties": {
    "gn:admin1_code":"1.0",
    "gn:asciiname":"Lishumi",
    "gn:country_code":"ZM",
    "gn:dem":956,
    "gn:feature_class":"P",
    "gn:feature_code":"PPL",
    "gn:name":"Lishumi",
    "gn:population":0,
    "gn:timezone":"Africa/Lusaka",
    "iso:country":"ZM",
    "wof:name":"Lishumi",
    "wof:placetype":"locality"
},
  "geometry": {"coordinates":[24.26667,-17.46667],"type":"Point"}
}