{
  "type": "Feature",
  "properties": {
    "gn:admin1_code":"3.0",
    "gn:asciiname":"Chidiamero",
    "gn:country_code":"ZM",
    "gn:dem":1106,
    "gn:feature_class":"P",
    "gn:feature_code":"PPL",
    "gn:name":"Chidiamero",
    "gn:population":0,
    "gn:timezone":"Africa/Lusaka",
    "iso:country":"ZM",
    "wof:name":"Chidiamero",
    "wof:placetype":"locality"
},
  "geometry": {"coordinates":[33.11667,-12.01667],"type":"Point"}
}