{
  "type": "Feature",
  "properties": {
    "gn:admin1_code":"2.0",
    "gn:asciiname":"Chitunami",
    "gn:country_code":"ZM",
    "gn:dem":1124,
    "gn:feature_class":"P",
    "gn:feature_code":"PPL",
    "gn:name":"Chitunami",
    "gn:population":0,
    "gn:timezone":"Africa/Lusaka",
    "iso:country":"ZM",
    "wof:name":"Chitunami",
    "wof:placetype":"locality"
},
  "geometry": {"coordinates":[27.20307,-14.39429],"type":"Point"}
}