{
  "type": "Feature",
  "properties": {
    "gn:admin1_code":"6.0",
    "gn:asciiname":"Kalengwa",
    "gn:country_code":"ZM",
    "gn:dem":1073,
    "gn:feature_class":"P",
    "gn:feature_code":"PPL",
    "gn:name":"Kalengwa",
    "gn:population":0,
    "gn:timezone":"Africa/Lusaka",
    "iso:country":"ZM",
    "name:und_x_variant":[
        "Kalengwe",
        "Kalengwa"
    ],
    "wof:name":"Kalengwa",
    "wof:placetype":"locality"
},
  "geometry": {"coordinates":[22.48333,-13.51667],"type":"Point"}
}