{
  "type": "Feature",
  "properties": {
    "gn:admin1_code":"10.0",
    "gn:asciiname":"Kalimbila",
    "gn:country_code":"ZM",
    "gn:dem":732,
    "gn:feature_class":"P",
    "gn:feature_code":"PPL",
    "gn:name":"Kalimbila",
    "gn:population":0,
    "gn:timezone":"Africa/Lusaka",
    "iso:country":"ZM",
    "wof:name":"Kalimbila",
    "wof:placetype":"locality"
},
  "geometry": {"coordinates":[32.91667,-10.53333],"type":"Point"}
}