{
  "type": "Feature",
  "properties": {
    "gn:admin1_code":"10.0",
    "gn:asciiname":"Chitole",
    "gn:country_code":"ZM",
    "gn:dem":1372,
    "gn:feature_class":"P",
    "gn:feature_code":"PPL",
    "gn:name":"Chitole",
    "gn:population":0,
    "gn:timezone":"Africa/Lusaka",
    "iso:country":"ZM",
    "name:und_x_variant":[
        "Chilole",
        "Chikole",
        "Chitole"
    ],
    "wof:name":"Chitole",
    "wof:placetype":"locality"
},
  "geometry": {"coordinates":[31.95768,-11.38883],"type":"Point"}
}