{
  "type": "Feature",
  "properties": {
    "gn:admin1_code":"6.0",
    "gn:asciiname":"Mize",
    "gn:country_code":"ZM",
    "gn:dem":1065,
    "gn:feature_class":"P",
    "gn:feature_code":"PPL",
    "gn:name":"Mize",
    "gn:population":0,
    "gn:timezone":"Africa/Lusaka",
    "iso:country":"ZM",
    "name:ceb_x_preferred":[
        "Mize"
    ],
    "name:deu_x_preferred":[
        "Mize"
    ],
    "name:fra_x_preferred":[
        "Mize"
    ],
    "name:swe_x_preferred":[
        "Mize"
    ],
    "wof:name":"Mize",
    "wof:placetype":"locality"
},
  "geometry": {"coordinates":[23.05,-13.53333],"type":"Point"}
}