{
  "type": "Feature",
  "properties": {
    "gn:admin1_code":"1.0",
    "gn:asciiname":"Munyunya",
    "gn:country_code":"ZM",
    "gn:dem":1111,
    "gn:feature_class":"P",
    "gn:feature_code":"PPL",
    "gn:name":"Munyunya",
    "gn:population":0,
    "gn:timezone":"Africa/Lusaka",
    "iso:country":"ZM",
    "wof:name":"Munyunya",
    "wof:placetype":"locality"
},
  "geometry": {"coordinates":[23.88333,-14.86667],"type":"Point"}
}