{
  "type": "Feature",
  "properties": {
    "gn:admin1_code":"3.0",
    "gn:asciiname":"Kamono",
    "gn:country_code":"ZM",
    "gn:dem":913,
    "gn:feature_class":"P",
    "gn:feature_code":"PPL",
    "gn:name":"Kamono",
    "gn:population":0,
    "gn:timezone":"Africa/Lusaka",
    "iso:country":"ZM",
    "wof:name":"Kamono",
    "wof:placetype":"locality"
},
  "geometry": {"coordinates":[31.05,-14.63333],"type":"Point"}
}