{
  "type": "Feature",
  "properties": {
    "gn:admin1_code":"6.0",
    "gn:asciiname":"Kayuwa",
    "gn:country_code":"ZM",
    "gn:dem":1073,
    "gn:feature_class":"P",
    "gn:feature_code":"PPL",
    "gn:name":"Kayuwa",
    "gn:population":0,
    "gn:timezone":"Africa/Lusaka",
    "iso:country":"ZM",
    "wof:name":"Kayuwa",
    "wof:placetype":"locality"
},
  "geometry": {"coordinates":[22.38333,-13.58333],"type":"Point"}
}