{
  "type": "Feature",
  "properties": {
    "gn:admin1_code":"1.0",
    "gn:asciiname":"Lwanda",
    "gn:country_code":"ZM",
    "gn:dem":1027,
    "gn:feature_class":"P",
    "gn:feature_code":"PPL",
    "gn:name":"Lwanda",
    "gn:population":0,
    "gn:timezone":"Africa/Lusaka",
    "iso:country":"ZM",
    "wof:name":"Lwanda",
    "wof:placetype":"locality"
},
  "geometry": {"coordinates":[22.71667,-15.11667],"type":"Point"}
}