{
  "type": "Feature",
  "properties": {
    "gn:admin1_code":"3.0",
    "gn:asciiname":"Mlolo",
    "gn:country_code":"ZM",
    "gn:dem":991,
    "gn:feature_class":"P",
    "gn:feature_code":"PPL",
    "gn:name":"Mlolo",
    "gn:population":0,
    "gn:timezone":"Africa/Lusaka",
    "iso:country":"ZM",
    "wof:name":"Mlolo",
    "wof:placetype":"locality"
},
  "geometry": {"coordinates":[32.33882,-14.2337],"type":"Point"}
}