{
  "type": "Feature",
  "properties": {
    "gn:admin1_code":"3.0",
    "gn:asciiname":"Chambwe",
    "gn:country_code":"ZM",
    "gn:dem":787,
    "gn:feature_class":"P",
    "gn:feature_code":"PPL",
    "gn:name":"Chambwe",
    "gn:population":0,
    "gn:timezone":"Africa/Lusaka",
    "iso:country":"ZM",
    "wof:name":"Chambwe",
    "wof:placetype":"locality"
},
  "geometry": {"coordinates":[30.82921,-14.63748],"type":"Point"}
}