{
  "type": "Feature",
  "properties": {
    "gn:admin1_code":"3.0",
    "gn:asciiname":"Menso",
    "gn:country_code":"ZM",
    "gn:dem":827,
    "gn:feature_class":"P",
    "gn:feature_code":"PPL",
    "gn:name":"Menso",
    "gn:population":0,
    "gn:timezone":"Africa/Lusaka",
    "iso:country":"ZM",
    "wof:name":"Menso",
    "wof:placetype":"locality"
},
  "geometry": {"coordinates":[30.90535,-14.52663],"type":"Point"}
}