{
  "type": "Feature",
  "properties": {
    "gn:admin1_code":"4.0",
    "gn:asciiname":"Mabumba",
    "gn:country_code":"ZM",
    "gn:dem":1244,
    "gn:feature_class":"P",
    "gn:feature_code":"PPL",
    "gn:name":"Mabumba",
    "gn:population":0,
    "gn:timezone":"Africa/Lusaka",
    "iso:country":"ZM",
    "name:und_x_variant":[
        "Maumba",
        "Mabumba"
    ],
    "wof:name":"Mabumba",
    "wof:placetype":"locality"
},
  "geometry": {"coordinates":[29.05238,-11.26277],"type":"Point"}
}