{
  "type": "Feature",
  "properties": {
    "gn:admin1_code":"8.0",
    "gn:asciiname":"Mpupwa",
    "gn:country_code":"ZM",
    "gn:dem":1216,
    "gn:feature_class":"P",
    "gn:feature_code":"PPL",
    "gn:name":"Mpupwa",
    "gn:population":0,
    "gn:timezone":"Africa/Lusaka",
    "iso:country":"ZM",
    "wof:name":"Mpupwa",
    "wof:placetype":"locality"
},
  "geometry": {"coordinates":[28.52427,-13.21783],"type":"Point"}
}