{
  "type": "Feature",
  "properties": {
    "gn:admin1_code":"0.0",
    "gn:asciiname":"Nkomeshya",
    "gn:country_code":"ZM",
    "gn:dem":1037,
    "gn:feature_class":"P",
    "gn:feature_code":"PPL",
    "gn:name":"Nkomeshya",
    "gn:population":0,
    "gn:timezone":"Africa/Lusaka",
    "iso:country":"ZM",
    "wof:name":"Nkomeshya",
    "wof:placetype":"locality"
},
  "geometry": {"coordinates":[28.71667,-15.38333],"type":"Point"}
}