{
  "type": "Feature",
  "properties": {
    "gn:admin1_code":"3.0",
    "gn:asciiname":"Chikalawa",
    "gn:country_code":"ZM",
    "gn:dem":909,
    "gn:feature_class":"P",
    "gn:feature_code":"PPL",
    "gn:name":"Chikalawa",
    "gn:population":0,
    "gn:timezone":"Africa/Lusaka",
    "iso:country":"ZM",
    "wof:name":"Chikalawa",
    "wof:placetype":"locality"
},
  "geometry": {"coordinates":[31.05997,-14.61513],"type":"Point"}
}