{
  "type": "Feature",
  "properties": {
    "gn:admin1_code":"3.0",
    "gn:asciiname":"Kasonkore",
    "gn:country_code":"ZM",
    "gn:dem":1401,
    "gn:feature_class":"P",
    "gn:feature_code":"PPL",
    "gn:name":"Kasonkore",
    "gn:population":0,
    "gn:timezone":"Africa/Lusaka",
    "iso:country":"ZM",
    "wof:name":"Kasonkore",
    "wof:placetype":"locality"
},
  "geometry": {"coordinates":[33.43333,-12.43333],"type":"Point"}
}