{
  "type": "Feature",
  "properties": {
    "gn:admin1_code":"7.0",
    "gn:asciiname":"Chuluka",
    "gn:country_code":"ZM",
    "gn:dem":1030,
    "gn:feature_class":"P",
    "gn:feature_code":"PPL",
    "gn:name":"Chuluka",
    "gn:population":0,
    "gn:timezone":"Africa/Lusaka",
    "iso:country":"ZM",
    "wof:name":"Chuluka",
    "wof:placetype":"locality"
},
  "geometry": {"coordinates":[26.95,-16.13332999999999],"type":"Point"}
}