{
  "type": "Feature",
  "properties": {
    "gn:admin1_code":"8.0",
    "gn:asciiname":"Mwema Nyala",
    "gn:country_code":"ZM",
    "gn:dem":1238,
    "gn:feature_class":"P",
    "gn:feature_code":"PPL",
    "gn:name":"Mwema Nyala",
    "gn:population":0,
    "gn:timezone":"Africa/Lusaka",
    "iso:country":"ZM",
    "wof:name":"Mwema Nyala",
    "wof:placetype":"locality"
},
  "geometry": {"coordinates":[28.53333,-13.33333],"type":"Point"}
}