{
  "type": "Feature",
  "properties": {
    "gn:admin1_code":"10.0",
    "gn:asciiname":"Mnkwinda",
    "gn:country_code":"ZM",
    "gn:dem":625,
    "gn:feature_class":"P",
    "gn:feature_code":"PPL",
    "gn:name":"Mnkwinda",
    "gn:population":0,
    "gn:timezone":"Africa/Lusaka",
    "iso:country":"ZM",
    "wof:name":"Mnkwinda",
    "wof:placetype":"locality"
},
  "geometry": {"coordinates":[32.485,-12.14596],"type":"Point"}
}