{
  "type": "Feature",
  "properties": {
    "gn:admin1_code":"1.0",
    "gn:asciiname":"Lianda",
    "gn:country_code":"ZM",
    "gn:dem":1167,
    "gn:feature_class":"P",
    "gn:feature_code":"PPL",
    "gn:name":"Lianda",
    "gn:population":0,
    "gn:timezone":"Africa/Lusaka",
    "iso:country":"ZM",
    "wof:name":"Lianda",
    "wof:placetype":"locality"
},
  "geometry": {"coordinates":[24.86667000000001,-15.68333],"type":"Point"}
}