{
  "type": "Feature",
  "properties": {
    "gn:admin1_code":"2.0",
    "gn:asciiname":"James Mupela",
    "gn:country_code":"ZM",
    "gn:dem":1483,
    "gn:feature_class":"P",
    "gn:feature_code":"PPL",
    "gn:name":"James Mupela",
    "gn:population":0,
    "gn:timezone":"Africa/Lusaka",
    "iso:country":"ZM",
    "wof:name":"James Mupela",
    "wof:placetype":"locality"
},
  "geometry": {"coordinates":[30.60829,-12.96793],"type":"Point"}
}