{
  "type": "Feature",
  "properties": {
    "gn:admin1_code":"7.0",
    "gn:asciiname":"Nega Nega",
    "gn:country_code":"ZM",
    "gn:dem":1005,
    "gn:feature_class":"P",
    "gn:feature_code":"PPL",
    "gn:name":"Nega Nega",
    "gn:population":0,
    "gn:timezone":"Africa/Lusaka",
    "iso:country":"ZM",
    "wof:name":"Nega Nega",
    "wof:placetype":"locality"
},
  "geometry": {"coordinates":[28.03333,-15.83333],"type":"Point"}
}