{
  "type": "Feature",
  "properties": {
    "gn:admin1_code":"2.0",
    "gn:asciiname":"Chibale",
    "gn:country_code":"ZM",
    "gn:dem":1608,
    "gn:feature_class":"P",
    "gn:feature_code":"PPL",
    "gn:name":"Chibale",
    "gn:population":0,
    "gn:timezone":"Africa/Lusaka",
    "iso:country":"ZM",
    "wof:name":"Chibale",
    "wof:placetype":"locality"
},
  "geometry": {"coordinates":[30.89048,-13.05681],"type":"Point"}
}