{
  "type": "Feature",
  "properties": {
    "gn:admin1_code":"10.0",
    "gn:asciiname":"Chidulika",
    "gn:country_code":"ZM",
    "gn:dem":1206,
    "gn:feature_class":"P",
    "gn:feature_code":"PPL",
    "gn:name":"Chidulika",
    "gn:population":0,
    "gn:timezone":"Africa/Lusaka",
    "iso:country":"ZM",
    "wof:name":"Chidulika",
    "wof:placetype":"locality"
},
  "geometry": {"coordinates":[33.45,-10.56667],"type":"Point"}
}