{
  "type": "Feature",
  "properties": {
    "gn:admin1_code":"7.0",
    "gn:asciiname":"Musungwa",
    "gn:country_code":"ZM",
    "gn:dem":996,
    "gn:feature_class":"P",
    "gn:feature_code":"PPL",
    "gn:name":"Musungwa",
    "gn:population":0,
    "gn:timezone":"Africa/Lusaka",
    "iso:country":"ZM",
    "wof:name":"Musungwa",
    "wof:placetype":"locality"
},
  "geometry": {"coordinates":[26.09846,-15.89432],"type":"Point"}
}