{
  "type": "Feature",
  "properties": {
    "gn:admin1_code":"5.0",
    "gn:asciiname":"Mukumi",
    "gn:country_code":"ZM",
    "gn:dem":1411,
    "gn:feature_class":"P",
    "gn:feature_code":"PPL",
    "gn:name":"Mukumi",
    "gn:population":0,
    "gn:timezone":"Africa/Lusaka",
    "iso:country":"ZM",
    "wof:name":"Mukumi",
    "wof:placetype":"locality"
},
  "geometry": {"coordinates":[30.58333,-9.96667],"type":"Point"}
}