{
  "type": "Feature",
  "properties": {
    "gn:admin1_code":"5.0",
    "gn:asciiname":"Alloleya",
    "gn:country_code":"ZM",
    "gn:dem":1354,
    "gn:feature_class":"P",
    "gn:feature_code":"PPL",
    "gn:name":"Alloleya",
    "gn:population":0,
    "gn:timezone":"Africa/Lusaka",
    "iso:country":"ZM",
    "wof:name":"Alloleya",
    "wof:placetype":"locality"
},
  "geometry": {"coordinates":[31.05,-9.45],"type":"Point"}
}