{
  "type": "Feature",
  "properties": {
    "gn:admin1_code":"10.0",
    "gn:asciiname":"Katumba",
    "gn:country_code":"ZM",
    "gn:dem":1355,
    "gn:feature_class":"P",
    "gn:feature_code":"PPL",
    "gn:name":"Katumba",
    "gn:population":0,
    "gn:timezone":"Africa/Lusaka",
    "iso:country":"ZM",
    "wof:name":"Katumba",
    "wof:placetype":"locality"
},
  "geometry": {"coordinates":[31.25476,-11.44589],"type":"Point"}
}