{
  "type": "Feature",
  "properties": {
    "gn:admin1_code":"2.0",
    "gn:asciiname":"Mwachilenga",
    "gn:country_code":"ZM",
    "gn:dem":1050,
    "gn:feature_class":"P",
    "gn:feature_code":"PPL",
    "gn:name":"Mwachilenga",
    "gn:population":0,
    "gn:timezone":"Africa/Lusaka",
    "iso:country":"ZM",
    "wof:name":"Mwachilenga",
    "wof:placetype":"locality"
},
  "geometry": {"coordinates":[27.81667,-15.06667],"type":"Point"}
}