{
  "type": "Feature",
  "properties": {
    "gn:admin1_code":"5.0",
    "gn:asciiname":"Chelu",
    "gn:country_code":"ZM",
    "gn:dem":1464,
    "gn:feature_class":"P",
    "gn:feature_code":"PPL",
    "gn:name":"Chelu",
    "gn:population":0,
    "gn:timezone":"Africa/Lusaka",
    "iso:country":"ZM",
    "name:und_x_variant":[
        "Chelo",
        "Chelu"
    ],
    "wof:name":"Chelu",
    "wof:placetype":"locality"
},
  "geometry": {"coordinates":[30.05973,-9.28879],"type":"Point"}
}