{
  "type": "Feature",
  "properties": {
    "gn:admin1_code":"6.0",
    "gn:asciiname":"Satumba",
    "gn:country_code":"ZM",
    "gn:dem":1064,
    "gn:feature_class":"P",
    "gn:feature_code":"PPL",
    "gn:name":"Satumba",
    "gn:population":0,
    "gn:timezone":"Africa/Lusaka",
    "iso:country":"ZM",
    "wof:name":"Satumba",
    "wof:placetype":"locality"
},
  "geometry": {"coordinates":[23.08333,-13.86667],"type":"Point"}
}