{
  "type": "Feature",
  "properties": {
    "gn:admin1_code":"10.0",
    "gn:asciiname":"Simulemba",
    "gn:country_code":"ZM",
    "gn:dem":685,
    "gn:feature_class":"P",
    "gn:feature_code":"PPL",
    "gn:name":"Simulemba",
    "gn:population":0,
    "gn:timezone":"Africa/Lusaka",
    "iso:country":"ZM",
    "wof:name":"Simulemba",
    "wof:placetype":"locality"
},
  "geometry": {"coordinates":[32.8923,-11.59302],"type":"Point"}
}