{
  "type": "Feature",
  "properties": {
    "gn:admin1_code":"10.0",
    "gn:asciiname":"Malusa",
    "gn:country_code":"ZM",
    "gn:dem":1521,
    "gn:feature_class":"P",
    "gn:feature_code":"PPL",
    "gn:name":"Malusa",
    "gn:population":0,
    "gn:timezone":"Africa/Lusaka",
    "iso:country":"ZM",
    "name:und_x_variant":[
        "Marusa",
        "Malusa"
    ],
    "wof:name":"Malusa",
    "wof:placetype":"locality"
},
  "geometry": {"coordinates":[33.61667,-10.51667],"type":"Point"}
}