{
  "type": "Feature",
  "properties": {
    "gn:admin1_code":"10.0",
    "gn:asciiname":"Chifofma",
    "gn:country_code":"ZM",
    "gn:dem":1488,
    "gn:feature_class":"P",
    "gn:feature_code":"PPL",
    "gn:name":"Chifofma",
    "gn:population":0,
    "gn:timezone":"Africa/Lusaka",
    "iso:country":"ZM",
    "wof:name":"Chifofma",
    "wof:placetype":"locality"
},
  "geometry": {"coordinates":[31.76992000000001,-10.98977],"type":"Point"}
}