{
  "type": "Feature",
  "properties": {
    "gn:admin1_code":"7.0",
    "gn:asciiname":"Tongo",
    "gn:country_code":"ZM",
    "gn:dem":1108,
    "gn:feature_class":"P",
    "gn:feature_code":"PPL",
    "gn:name":"Tongo",
    "gn:population":0,
    "gn:timezone":"Africa/Lusaka",
    "iso:country":"ZM",
    "name:und_x_variant":[
        "Tonko",
        "Tongo"
    ],
    "wof:name":"Tongo",
    "wof:placetype":"locality"
},
  "geometry": {"coordinates":[26.38333,-15.33333],"type":"Point"}
}