{
  "type": "Feature",
  "properties": {
    "gn:admin1_code":"1.0",
    "gn:asciiname":"Sikatema",
    "gn:country_code":"ZM",
    "gn:dem":1167,
    "gn:feature_class":"P",
    "gn:feature_code":"PPL",
    "gn:name":"Sikatema",
    "gn:population":0,
    "gn:timezone":"Africa/Lusaka",
    "iso:country":"ZM",
    "wof:name":"Sikatema",
    "wof:placetype":"locality"
},
  "geometry": {"coordinates":[24.88333,-15.91667],"type":"Point"}
}