{
  "type": "Feature",
  "properties": {
    "gn:admin1_code":"10.0",
    "gn:asciiname":"Mwenikambangwa",
    "gn:country_code":"ZM",
    "gn:dem":800,
    "gn:feature_class":"P",
    "gn:feature_code":"PPL",
    "gn:name":"Mwenikambangwa",
    "gn:population":0,
    "gn:timezone":"Africa/Lusaka",
    "iso:country":"ZM",
    "name:und_x_variant":[
        "Kambanga",
        "Mwenikambangwa"
    ],
    "wof:name":"Mwenikambangwa",
    "wof:placetype":"locality"
},
  "geometry": {"coordinates":[33.03333,-10.25],"type":"Point"}
}