{
  "type": "Feature",
  "properties": {
    "gn:admin1_code":"9.0",
    "gn:asciiname":"Shipanuka",
    "gn:country_code":"ZM",
    "gn:dem":1068,
    "gn:feature_class":"P",
    "gn:feature_code":"PPL",
    "gn:name":"Shipanuka",
    "gn:population":0,
    "gn:timezone":"Africa/Lusaka",
    "iso:country":"ZM",
    "wof:name":"Shipanuka",
    "wof:placetype":"locality"
},
  "geometry": {"coordinates":[28.76667,-15.46667],"type":"Point"}
}