{
  "type": "Feature",
  "properties": {
    "gn:admin1_code":"3.0",
    "gn:asciiname":"Msiri",
    "gn:country_code":"ZM",
    "gn:dem":1013,
    "gn:feature_class":"P",
    "gn:feature_code":"PPL",
    "gn:name":"Msiri",
    "gn:population":0,
    "gn:timezone":"Africa/Lusaka",
    "iso:country":"ZM",
    "name:fra_x_preferred":[
        "M'Siri"
    ],
    "name:ita_x_preferred":[
        "M'Siri"
    ],
    "name:por_x_preferred":[
        "Msiri"
    ],
    "name:rus_x_preferred":[
        "\u041c\u0441\u0438\u0440\u0438"
    ],
    "name:und_x_variant":[
        "Msawiri"
    ],
    "wof:name":"Msiri",
    "wof:placetype":"locality"
},
  "geometry": {"coordinates":[31.31667,-14.48333],"type":"Point"}
}