{
  "type": "Feature",
  "properties": {
    "gn:admin1_code":"2.0",
    "gn:asciiname":"Masaka Shimukuni",
    "gn:country_code":"ZM",
    "gn:dem":1146,
    "gn:feature_class":"P",
    "gn:feature_code":"PPL",
    "gn:name":"Masaka Shimukuni",
    "gn:population":0,
    "gn:timezone":"Africa/Lusaka",
    "iso:country":"ZM",
    "wof:name":"Masaka Shimukuni",
    "wof:placetype":"locality"
},
  "geometry": {"coordinates":[27.91379,-14.76243],"type":"Point"}
}