{
  "type": "Feature",
  "properties": {
    "gn:admin1_code":"6.0",
    "gn:asciiname":"Lilekeleke",
    "gn:country_code":"ZM",
    "gn:dem":1062,
    "gn:feature_class":"P",
    "gn:feature_code":"PPL",
    "gn:name":"Lilekeleke",
    "gn:population":0,
    "gn:timezone":"Africa/Lusaka",
    "iso:country":"ZM",
    "wof:name":"Lilekeleke",
    "wof:placetype":"locality"
},
  "geometry": {"coordinates":[23.06667,-13.88333],"type":"Point"}
}