{
  "type": "Feature",
  "properties": {
    "gn:admin1_code":"6.0",
    "gn:asciiname":"Muloji",
    "gn:country_code":"ZM",
    "gn:dem":1072,
    "gn:feature_class":"P",
    "gn:feature_code":"PPL",
    "gn:name":"Muloji",
    "gn:population":0,
    "gn:timezone":"Africa/Lusaka",
    "iso:country":"ZM",
    "name:und_x_variant":[
        "Murozi",
        "Muloji"
    ],
    "wof:name":"Muloji",
    "wof:placetype":"locality"
},
  "geometry": {"coordinates":[22.67481,-13.12399],"type":"Point"}
}