{
  "type": "Feature",
  "properties": {
    "gn:admin1_code":"3.0",
    "gn:asciiname":"Luembe",
    "gn:country_code":"ZM",
    "gn:dem":433,
    "gn:feature_class":"P",
    "gn:feature_code":"PPL",
    "gn:name":"Luembe",
    "gn:population":0,
    "gn:timezone":"Africa/Lusaka",
    "iso:country":"ZM",
    "wof:name":"Luembe",
    "wof:placetype":"locality"
},
  "geometry": {"coordinates":[30.45272000000001,-14.4293],"type":"Point"}
}