{
  "type": "Feature",
  "properties": {
    "gn:admin1_code":"8.0",
    "gn:asciiname":"Muketi",
    "gn:country_code":"ZM",
    "gn:dem":1220,
    "gn:feature_class":"P",
    "gn:feature_code":"PPL",
    "gn:name":"Muketi",
    "gn:population":0,
    "gn:timezone":"Africa/Lusaka",
    "iso:country":"ZM",
    "wof:name":"Muketi",
    "wof:placetype":"locality"
},
  "geometry": {"coordinates":[27.36667000000001,-12.91667],"type":"Point"}
}