{
  "type": "Feature",
  "properties": {
    "gn:admin1_code":"7.0",
    "gn:asciiname":"Silumo",
    "gn:country_code":"ZM",
    "gn:dem":514,
    "gn:feature_class":"P",
    "gn:feature_code":"PPL",
    "gn:name":"Silumo",
    "gn:population":0,
    "gn:timezone":"Africa/Lusaka",
    "iso:country":"ZM",
    "name:eng_x_preferred":[
        "Silumo"
    ],
    "wof:name":"Silumo",
    "wof:placetype":"locality"
},
  "geometry": {"coordinates":[27.35,-17.28333],"type":"Point"}
}