{
  "type": "Feature",
  "properties": {
    "gn:admin1_code":"6.0",
    "gn:asciiname":"Kawana",
    "gn:country_code":"ZM",
    "gn:dem":1342,
    "gn:feature_class":"P",
    "gn:feature_code":"PPL",
    "gn:name":"Kawana",
    "gn:population":0,
    "gn:timezone":"Africa/Lusaka",
    "iso:country":"ZM",
    "name:deu_x_preferred":[
        "Kawana"
    ],
    "name:und_x_variant":[
        "Kowana",
        "Kawana"
    ],
    "wof:name":"Kawana",
    "wof:placetype":"locality"
},
  "geometry": {"coordinates":[25.94506,-13.09],"type":"Point"}
}