{
  "type": "Feature",
  "properties": {
    "gn:admin1_code":"3.0",
    "gn:asciiname":"Chilandu",
    "gn:country_code":"ZM",
    "gn:dem":805,
    "gn:feature_class":"P",
    "gn:feature_code":"PPL",
    "gn:name":"Chilandu",
    "gn:population":0,
    "gn:timezone":"Africa/Lusaka",
    "iso:country":"ZM",
    "name:und_x_variant":[
        "Chirenda",
        "Chilandu"
    ],
    "wof:name":"Chilandu",
    "wof:placetype":"locality"
},
  "geometry": {"coordinates":[31.27577,-14.03705],"type":"Point"}
}