{
  "type": "Feature",
  "properties": {
    "iso:country":"ZM",
    "name:ara_x_preferred":[
        "\u0631\u064a\u0641\u0631\u0633\u0627\u064a\u062f"
    ],
    "name:cat_x_preferred":[
        "Riverside"
    ],
    "name:ceb_x_preferred":[
        "Riverside"
    ],
    "name:ces_x_preferred":[
        "Riverside"
    ],
    "name:cor_x_preferred":[
        "Riverside"
    ],
    "name:deu_x_preferred":[
        "Riverside"
    ],
    "name:epo_x_preferred":[
        "Riverside"
    ],
    "name:fas_x_preferred":[
        "\u0631\u06cc\u0648\u0631\u0633\u0627\u06cc\u062f"
    ],
    "name:fin_x_preferred":[
        "Riverside"
    ],
    "name:fra_x_preferred":[
        "Riverside"
    ],
    "name:gla_x_preferred":[
        "Riverside"
    ],
    "name:hun_x_preferred":[
        "Riverside"
    ],
    "name:ita_x_preferred":[
        "Riverside"
    ],
    "name:jpn_x_preferred":[
        "\u30ea\u30d0\u30fc\u30b5\u30a4\u30c9"
    ],
    "name:kor_x_preferred":[
        "\ub9ac\ubc84\uc0ac\uc774\ub4dc"
    ],
    "name:nld_x_preferred":[
        "Riverside"
    ],
    "name:pol_x_preferred":[
        "Riverside"
    ],
    "name:por_x_preferred":[
        "Riverside"
    ],
    "name:rus_x_preferred":[
        "\u0420\u0438\u0432\u0435\u0440\u0441\u0430\u0439\u0434"
    ],
    "name:spa_x_preferred":[
        "Riverside"
    ],
    "name:srp_x_preferred":[
        "\u0420\u0438\u0432\u0435\u0440\u0441\u0430\u0458\u0434"
    ],
    "name:swe_x_preferred":[
        "Riverside"
    ],
    "name:tur_x_preferred":[
        "Riverside"
    ],
    "name:urd_x_preferred":[
        "\u0631\u0648\u0631\u0633\u0627\u0626\u06cc\u0688"
    ],
    "name:vol_x_preferred":[
        "Riverside"
    ],
    "name:zho_x_preferred":[
        "\u91cc\u5f17\u8cfd\u5fb7"
    ],
    "qs:gn_country":"ZM",
    "qs:gn_fcode":"PPLX",
    "qs:gn_pop":0,
    "qs:name":"Riverside",
    "qs:name_adm0":"Zambia",
    "qs:name_adm1":"Southern",
    "qs:photos":733,
    "qs:photos_1k":149,
    "qs:photos_9k":3,
    "qs:photos_9r":5,
    "qs:photos_all":733,
    "qs:photos_sr":8,
    "qs:placetype":"Town",
    "qs:pop_sr":"0",
    "qs:woe_adm0":23425003,
    "wof:name":"Riverside",
    "wof:placetype":"locality"
},
  "geometry": {"coordinates":[25.85,-17.86667],"type":"Point"}
}