{
  "type": "Feature",
  "properties": {
    "iso:country":"ZM",
    "qs:gn_country":"ZM",
    "qs:gn_fcode":"PPLX",
    "qs:gn_pop":0,
    "qs:name":"Riverside",
    "qs:name_adm0":"Zambia",
    "qs:name_adm1":"Southern",
    "qs:photos":733,
    "qs:photos_1k":149,
    "qs:photos_9k":3,
    "qs:photos_9r":5,
    "qs:photos_all":733,
    "qs:photos_sr":8,
    "qs:placetype":"Town",
    "qs:pop_sr":"0",
    "qs:woe_adm0":23425003,
    "wof:name":"Riverside",
    "wof:placetype":"locality"
},
  "geometry": {"coordinates":[25.85,-17.86667],"type":"Point"}
}