{
  "type": "Feature",
  "properties": {
    "gn:admin1_code":"4.0",
    "gn:asciiname":"Chama",
    "gn:country_code":"ZM",
    "gn:dem":1209,
    "gn:feature_class":"P",
    "gn:feature_code":"PPL",
    "gn:name":"Chama",
    "gn:population":0,
    "gn:timezone":"Africa/Lusaka",
    "iso:country":"ZM",
    "name:ceb_x_preferred":[
        "Chama"
    ],
    "name:deu_x_preferred":[
        "Chama"
    ],
    "name:ita_x_preferred":[
        "Chama"
    ],
    "name:nld_x_preferred":[
        "Chama"
    ],
    "name:pol_x_preferred":[
        "Chama"
    ],
    "name:por_x_preferred":[
        "Chama"
    ],
    "name:spa_x_preferred":[
        "Chama"
    ],
    "name:swa_x_preferred":[
        "Chama"
    ],
    "name:swe_x_preferred":[
        "Chama"
    ],
    "name:vol_x_preferred":[
        "Chama"
    ],
    "wof:name":"Chama",
    "wof:placetype":"locality"
},
  "geometry": {"coordinates":[29.42549,-9.77969],"type":"Point"}
}