{
  "type": "Feature",
  "properties": {
    "gn:admin1_code":"2.0",
    "gn:asciiname":"Machisa Kabinda",
    "gn:country_code":"ZM",
    "gn:dem":1475,
    "gn:feature_class":"P",
    "gn:feature_code":"PPL",
    "gn:name":"Machisa Kabinda",
    "gn:population":0,
    "gn:timezone":"Africa/Lusaka",
    "iso:country":"ZM",
    "wof:name":"Machisa Kabinda",
    "wof:placetype":"locality"
},
  "geometry": {"coordinates":[30.61191,-12.93016],"type":"Point"}
}