{
  "type": "Feature",
  "properties": {
    "gn:admin1_code":"3.0",
    "gn:asciiname":"Kamuzi",
    "gn:country_code":"ZM",
    "gn:dem":1124,
    "gn:feature_class":"P",
    "gn:feature_code":"PPL",
    "gn:name":"Kamuzi",
    "gn:population":0,
    "gn:timezone":"Africa/Lusaka",
    "iso:country":"ZM",
    "wof:name":"Kamuzi",
    "wof:placetype":"locality"
},
  "geometry": {"coordinates":[33.26667,-11.78333],"type":"Point"}
}