{
  "type": "Feature",
  "properties": {
    "gn:admin1_code":"2.0",
    "gn:asciiname":"Lusengo",
    "gn:country_code":"ZM",
    "gn:dem":1327,
    "gn:feature_class":"P",
    "gn:feature_code":"PPL",
    "gn:name":"Lusengo",
    "gn:population":0,
    "gn:timezone":"Africa/Lusaka",
    "iso:country":"ZM",
    "wof:name":"Lusengo",
    "wof:placetype":"locality"
},
  "geometry": {"coordinates":[29.93333,-13.18333],"type":"Point"}
}