{
  "type": "Feature",
  "properties": {
    "gn:admin1_code":"2.0",
    "gn:asciiname":"Mukamulimba",
    "gn:country_code":"ZM",
    "gn:dem":1165,
    "gn:feature_class":"P",
    "gn:feature_code":"PPL",
    "gn:name":"Mukamulimba",
    "gn:population":0,
    "gn:timezone":"Africa/Lusaka",
    "iso:country":"ZM",
    "name:und_x_variant":[
        "Mukamulimbo",
        "Mukamulimba"
    ],
    "wof:name":"Mukamulimba",
    "wof:placetype":"locality"
},
  "geometry": {"coordinates":[27.96906,-14.81077],"type":"Point"}
}