{
  "type": "Feature",
  "properties": {
    "gn:admin1_code":"3.0",
    "gn:asciiname":"Old Petauke",
    "gn:country_code":"ZM",
    "gn:dem":761,
    "gn:feature_class":"P",
    "gn:feature_code":"PPL",
    "gn:name":"Old Petauke",
    "gn:population":0,
    "gn:timezone":"Africa/Lusaka",
    "iso:country":"ZM",
    "wof:name":"Old Petauke",
    "wof:placetype":"locality"
},
  "geometry": {"coordinates":[31.0863,-14.0392],"type":"Point"}
}