{
  "type": "Feature",
  "properties": {
    "gn:admin1_code":"3.0",
    "gn:asciiname":"Ndeketya",
    "gn:country_code":"ZM",
    "gn:dem":998,
    "gn:feature_class":"P",
    "gn:feature_code":"PPL",
    "gn:name":"Ndeketya",
    "gn:population":0,
    "gn:timezone":"Africa/Lusaka",
    "iso:country":"ZM",
    "wof:name":"Ndeketya",
    "wof:placetype":"locality"
},
  "geometry": {"coordinates":[31.31667,-14.26667],"type":"Point"}
}