{
  "type": "Feature",
  "properties": {
    "gn:admin1_code":"7.0",
    "gn:asciiname":"Siamusambo",
    "gn:country_code":"ZM",
    "gn:dem":1148,
    "gn:feature_class":"P",
    "gn:feature_code":"PPL",
    "gn:name":"Siamusambo",
    "gn:population":0,
    "gn:timezone":"Africa/Lusaka",
    "iso:country":"ZM",
    "wof:name":"Siamusambo",
    "wof:placetype":"locality"
},
  "geometry": {"coordinates":[25.98333,-17.46667],"type":"Point"}
}