{
  "type": "Feature",
  "properties": {
    "gn:admin1_code":"2.0",
    "gn:asciiname":"Akim Makosa",
    "gn:country_code":"ZM",
    "gn:dem":1261,
    "gn:feature_class":"P",
    "gn:feature_code":"PPL",
    "gn:name":"Akim Makosa",
    "gn:population":0,
    "gn:timezone":"Africa/Lusaka",
    "iso:country":"ZM",
    "wof:name":"Akim Makosa",
    "wof:placetype":"locality"
},
  "geometry": {"coordinates":[30.43359,-12.60985],"type":"Point"}
}