{
  "type": "Feature",
  "properties": {
    "gn:admin1_code":"7.0",
    "gn:asciiname":"Makangala",
    "gn:country_code":"ZM",
    "gn:dem":1152,
    "gn:feature_class":"P",
    "gn:feature_code":"PPL",
    "gn:name":"Makangala",
    "gn:population":0,
    "gn:timezone":"Africa/Lusaka",
    "iso:country":"ZM",
    "name:und_x_variant":[
        "Makangara",
        "Makangala"
    ],
    "wof:name":"Makangala",
    "wof:placetype":"locality"
},
  "geometry": {"coordinates":[26.71667,-16.36667000000001],"type":"Point"}
}