{
  "type": "Feature",
  "properties": {
    "gn:admin1_code":"2.0",
    "gn:asciiname":"Mwanakabwata",
    "gn:country_code":"ZM",
    "gn:dem":1121,
    "gn:feature_class":"P",
    "gn:feature_code":"PPL",
    "gn:name":"Mwanakabwata",
    "gn:population":0,
    "gn:timezone":"Africa/Lusaka",
    "iso:country":"ZM",
    "wof:name":"Mwanakabwata",
    "wof:placetype":"locality"
},
  "geometry": {"coordinates":[27.50764,-14.45478],"type":"Point"}
}