{
  "type": "Feature",
  "properties": {
    "gn:admin1_code":"10.0",
    "gn:asciiname":"Lot",
    "gn:country_code":"ZM",
    "gn:dem":1338,
    "gn:feature_class":"P",
    "gn:feature_code":"PPL",
    "gn:name":"Lot",
    "gn:population":0,
    "gn:timezone":"Africa/Lusaka",
    "iso:country":"ZM",
    "wof:name":"Lot",
    "wof:placetype":"locality"
},
  "geometry": {"coordinates":[33.51667,-10.41667],"type":"Point"}
}