{
  "type": "Feature",
  "properties": {
    "gn:admin1_code":"2.0",
    "gn:asciiname":"Chimasa Kanyanda",
    "gn:country_code":"ZM",
    "gn:dem":1576,
    "gn:feature_class":"P",
    "gn:feature_code":"PPL",
    "gn:name":"Chimasa Kanyanda",
    "gn:population":0,
    "gn:timezone":"Africa/Lusaka",
    "iso:country":"ZM",
    "wof:name":"Chimasa Kanyanda",
    "wof:placetype":"locality"
},
  "geometry": {"coordinates":[30.74834,-12.93466],"type":"Point"}
}