{
  "type": "Feature",
  "properties": {
    "gn:admin1_code":"2.0",
    "gn:asciiname":"Nkole",
    "gn:country_code":"ZM",
    "gn:dem":1239,
    "gn:feature_class":"P",
    "gn:feature_code":"PPL",
    "gn:name":"Nkole",
    "gn:population":0,
    "gn:timezone":"Africa/Lusaka",
    "iso:country":"ZM",
    "wof:name":"Nkole",
    "wof:placetype":"locality"
},
  "geometry": {"coordinates":[28.72755,-13.79819],"type":"Point"}
}