{
  "type": "Feature",
  "properties": {
    "gn:admin1_code":"3.0",
    "gn:asciiname":"Zoza",
    "gn:country_code":"ZM",
    "gn:dem":1182,
    "gn:feature_class":"P",
    "gn:feature_code":"PPL",
    "gn:name":"Zoza",
    "gn:population":0,
    "gn:timezone":"Africa/Lusaka",
    "iso:country":"ZM",
    "name:und_x_variant":[
        "Zozo",
        "Zoza"
    ],
    "wof:name":"Zoza",
    "wof:placetype":"locality"
},
  "geometry": {"coordinates":[33.21387,-12.12948],"type":"Point"}
}