{
  "type": "Feature",
  "properties": {
    "gn:admin1_code":"2.0",
    "gn:asciiname":"Samuel Chipepe",
    "gn:country_code":"ZM",
    "gn:dem":1461,
    "gn:feature_class":"P",
    "gn:feature_code":"PPL",
    "gn:name":"Samuel Chipepe",
    "gn:population":0,
    "gn:timezone":"Africa/Lusaka",
    "iso:country":"ZM",
    "wof:name":"Samuel Chipepe",
    "wof:placetype":"locality"
},
  "geometry": {"coordinates":[30.60948,-12.89152],"type":"Point"}
}