{
  "type": "Feature",
  "properties": {
    "gn:admin1_code":"3.0",
    "gn:asciiname":"Kachingwe",
    "gn:country_code":"ZM",
    "gn:dem":1161,
    "gn:feature_class":"P",
    "gn:feature_code":"PPL",
    "gn:name":"Kachingwe",
    "gn:population":0,
    "gn:timezone":"Africa/Lusaka",
    "iso:country":"ZM",
    "wof:name":"Kachingwe",
    "wof:placetype":"locality"
},
  "geometry": {"coordinates":[32.0984,-13.94635],"type":"Point"}
}