{
  "type": "Feature",
  "properties": {
    "gn:admin1_code":"1.0",
    "gn:asciiname":"Mavua",
    "gn:country_code":"ZM",
    "gn:dem":1054,
    "gn:feature_class":"P",
    "gn:feature_code":"PPL",
    "gn:name":"Mavua",
    "gn:population":0,
    "gn:timezone":"Africa/Lusaka",
    "iso:country":"ZM",
    "name:und_x_variant":[
        "Mabua",
        "Mavua"
    ],
    "wof:name":"Mavua",
    "wof:placetype":"locality"
},
  "geometry": {"coordinates":[22.31483,-15.4246],"type":"Point"}
}