{
  "type": "Feature",
  "properties": {
    "gn:admin1_code":"1.0",
    "gn:asciiname":"Bwambo",
    "gn:country_code":"ZM",
    "gn:dem":1155,
    "gn:feature_class":"P",
    "gn:feature_code":"PPL",
    "gn:name":"Bwambo",
    "gn:population":0,
    "gn:timezone":"Africa/Lusaka",
    "iso:country":"ZM",
    "wof:name":"Bwambo",
    "wof:placetype":"locality"
},
  "geometry": {"coordinates":[25.01667,-16.21667],"type":"Point"}
}