{
  "type": "Feature",
  "properties": {
    "gn:admin1_code":"2.0",
    "gn:asciiname":"Nkomesha",
    "gn:country_code":"ZM",
    "gn:dem":1155,
    "gn:feature_class":"P",
    "gn:feature_code":"PPL",
    "gn:name":"Nkomesha",
    "gn:population":0,
    "gn:timezone":"Africa/Lusaka",
    "iso:country":"ZM",
    "name:und_x_variant":[
        "Nkomeshyo",
        "Nkomesha"
    ],
    "wof:name":"Nkomesha",
    "wof:placetype":"locality"
},
  "geometry": {"coordinates":[27.96667,-14.75],"type":"Point"}
}