{
  "type": "Feature",
  "properties": {
    "gn:admin1_code":"2.0",
    "gn:asciiname":"Dutchman Machende",
    "gn:country_code":"ZM",
    "gn:dem":1176,
    "gn:feature_class":"P",
    "gn:feature_code":"PPL",
    "gn:name":"Dutchman Machende",
    "gn:population":0,
    "gn:timezone":"Africa/Lusaka",
    "iso:country":"ZM",
    "wof:name":"Dutchman Machende",
    "wof:placetype":"locality"
},
  "geometry": {"coordinates":[30.05,-12.31667],"type":"Point"}
}