{
  "type": "Feature",
  "properties": {
    "gn:admin1_code":"7.0",
    "gn:asciiname":"Chinungu",
    "gn:country_code":"ZM",
    "gn:dem":659,
    "gn:feature_class":"P",
    "gn:feature_code":"PPL",
    "gn:name":"Chinungu",
    "gn:population":0,
    "gn:timezone":"Africa/Lusaka",
    "iso:country":"ZM",
    "wof:name":"Chinungu",
    "wof:placetype":"locality"
},
  "geometry": {"coordinates":[28.28333,-16.31667],"type":"Point"}
}