{
  "type": "Feature",
  "properties": {
    "gn:admin1_code":"3.0",
    "gn:asciiname":"Kanukawanga",
    "gn:country_code":"ZM",
    "gn:dem":845,
    "gn:feature_class":"P",
    "gn:feature_code":"PPL",
    "gn:name":"Kanukawanga",
    "gn:population":0,
    "gn:timezone":"Africa/Lusaka",
    "iso:country":"ZM",
    "wof:name":"Kanukawanga",
    "wof:placetype":"locality"
},
  "geometry": {"coordinates":[30.28333,-14.51667],"type":"Point"}
}