{
  "type": "Feature",
  "properties": {
    "gn:admin1_code":"2.0",
    "gn:asciiname":"Mayunda",
    "gn:country_code":"ZM",
    "gn:dem":1212,
    "gn:feature_class":"P",
    "gn:feature_code":"PPL",
    "gn:name":"Mayunda",
    "gn:population":0,
    "gn:timezone":"Africa/Lusaka",
    "iso:country":"ZM",
    "wof:name":"Mayunda",
    "wof:placetype":"locality"
},
  "geometry": {"coordinates":[28.33333,-14.03333],"type":"Point"}
}