{
  "type": "Feature",
  "properties": {
    "gn:admin1_code":"1.0",
    "gn:asciiname":"Lipemba",
    "gn:country_code":"ZM",
    "gn:dem":1050,
    "gn:feature_class":"P",
    "gn:feature_code":"PPL",
    "gn:name":"Lipemba",
    "gn:population":0,
    "gn:timezone":"Africa/Lusaka",
    "iso:country":"ZM",
    "wof:name":"Lipemba",
    "wof:placetype":"locality"
},
  "geometry": {"coordinates":[22.93333,-14.08333],"type":"Point"}
}