{
  "type": "Feature",
  "properties": {
    "gn:admin1_code":"5.0",
    "gn:asciiname":"Muyimbwe",
    "gn:country_code":"ZM",
    "gn:dem":1327,
    "gn:feature_class":"P",
    "gn:feature_code":"PPL",
    "gn:name":"Muyimbwe",
    "gn:population":0,
    "gn:timezone":"Africa/Lusaka",
    "iso:country":"ZM",
    "wof:name":"Muyimbwe",
    "wof:placetype":"locality"
},
  "geometry": {"coordinates":[31.23333,-10.13333],"type":"Point"}
}