{
  "type": "Feature",
  "properties": {
    "gn:admin1_code":"6.0",
    "gn:asciiname":"Lisese",
    "gn:country_code":"ZM",
    "gn:dem":1063,
    "gn:feature_class":"P",
    "gn:feature_code":"PPL",
    "gn:name":"Lisese",
    "gn:population":0,
    "gn:timezone":"Africa/Lusaka",
    "iso:country":"ZM",
    "name:und_x_variant":[
        "Lisheshe",
        "Lisese"
    ],
    "wof:name":"Lisese",
    "wof:placetype":"locality"
},
  "geometry": {"coordinates":[22.76667,-13.58333],"type":"Point"}
}