{
  "type": "Feature",
  "properties": {
    "gn:admin1_code":"1.0",
    "gn:asciiname":"Mate",
    "gn:country_code":"ZM",
    "gn:dem":1014,
    "gn:feature_class":"P",
    "gn:feature_code":"PPL",
    "gn:name":"Mate",
    "gn:population":0,
    "gn:timezone":"Africa/Lusaka",
    "iso:country":"ZM",
    "name:ast_x_preferred":[
        "Mate"
    ],
    "name:ceb_x_preferred":[
        "Mate"
    ],
    "name:deu_x_preferred":[
        "Mate"
    ],
    "name:fas_x_preferred":[
        "\u0645\u0627\u062a\u0647"
    ],
    "name:fra_x_preferred":[
        "Mate"
    ],
    "name:heb_x_preferred":[
        "\u05de\u05d8\u05d4"
    ],
    "name:hrv_x_preferred":[
        "Mate"
    ],
    "name:ita_x_preferred":[
        "Mate"
    ],
    "name:jpn_x_preferred":[
        "\u30e1\u30a4\u30c8"
    ],
    "name:lav_x_preferred":[
        "Yerba mate"
    ],
    "name:nld_x_preferred":[
        "Mate"
    ],
    "name:rus_x_preferred":[
        "\u041c\u0430\u0442\u0435"
    ],
    "name:sco_x_preferred":[
        "Mate"
    ],
    "name:slv_x_preferred":[
        "Mate"
    ],
    "name:spa_x_preferred":[
        "Mate"
    ],
    "name:swe_x_preferred":[
        "Mate"
    ],
    "name:tgl_x_preferred":[
        "Mate"
    ],
    "name:ukr_x_preferred":[
        "\u041c\u0430\u0442\u0435"
    ],
    "wof:name":"Mate",
    "wof:placetype":"locality"
},
  "geometry": {"coordinates":[23.36667000000001,-16.45],"type":"Point"}
}