{
  "type": "Feature",
  "properties": {
    "gn:admin1_code":"1.0",
    "gn:asciiname":"Mate",
    "gn:country_code":"ZM",
    "gn:dem":1014,
    "gn:feature_class":"P",
    "gn:feature_code":"PPL",
    "gn:name":"Mate",
    "gn:population":0,
    "gn:timezone":"Africa/Lusaka",
    "iso:country":"ZM",
    "wof:name":"Mate",
    "wof:placetype":"locality"
},
  "geometry": {"coordinates":[23.36667000000001,-16.45],"type":"Point"}
}