{
  "type": "Feature",
  "properties": {
    "gn:admin1_code":"10.0",
    "gn:asciiname":"Chanda",
    "gn:country_code":"ZM",
    "gn:dem":1304,
    "gn:feature_class":"P",
    "gn:feature_code":"PPL",
    "gn:name":"Chanda",
    "gn:population":0,
    "gn:timezone":"Africa/Lusaka",
    "iso:country":"ZM",
    "wof:name":"Chanda",
    "wof:placetype":"locality"
},
  "geometry": {"coordinates":[32.07197,-11.35296],"type":"Point"}
}