{
  "type": "Feature",
  "properties": {
    "gn:admin1_code":"3.0",
    "gn:asciiname":"Njuga",
    "gn:country_code":"ZM",
    "gn:dem":1020,
    "gn:feature_class":"P",
    "gn:feature_code":"PPL",
    "gn:name":"Njuga",
    "gn:population":0,
    "gn:timezone":"Africa/Lusaka",
    "iso:country":"ZM",
    "name:und_x_variant":[
        "Juga",
        "Njunga",
        "Njuga"
    ],
    "wof:name":"Njuga",
    "wof:placetype":"locality"
},
  "geometry": {"coordinates":[31.9182,-14.23008],"type":"Point"}
}