{
  "type": "Feature",
  "properties": {
    "gn:admin1_code":"6.0",
    "gn:asciiname":"Sakutalika",
    "gn:country_code":"ZM",
    "gn:dem":1055,
    "gn:feature_class":"P",
    "gn:feature_code":"PPL",
    "gn:name":"Sakutalika",
    "gn:population":0,
    "gn:timezone":"Africa/Lusaka",
    "iso:country":"ZM",
    "wof:name":"Sakutalika",
    "wof:placetype":"locality"
},
  "geometry": {"coordinates":[22.76667,-13.65],"type":"Point"}
}