{
  "type": "Feature",
  "properties": {
    "gn:admin1_code":"10.0",
    "gn:asciiname":"Sindano",
    "gn:country_code":"ZM",
    "gn:dem":1628,
    "gn:feature_class":"P",
    "gn:feature_code":"PPL",
    "gn:name":"Sindano",
    "gn:population":0,
    "gn:timezone":"Africa/Lusaka",
    "iso:country":"ZM",
    "name:und_x_variant":[
        "Sindane",
        "Sindano"
    ],
    "wof:name":"Sindano",
    "wof:placetype":"locality"
},
  "geometry": {"coordinates":[32.82815,-9.37068],"type":"Point"}
}