{
  "type": "Feature",
  "properties": {
    "gn:admin1_code":"2.0",
    "gn:asciiname":"Mboronsa",
    "gn:country_code":"ZM",
    "gn:dem":939,
    "gn:feature_class":"P",
    "gn:feature_code":"PPL",
    "gn:name":"Mboronsa",
    "gn:population":0,
    "gn:timezone":"Africa/Lusaka",
    "iso:country":"ZM",
    "wof:name":"Mboronsa",
    "wof:placetype":"locality"
},
  "geometry": {"coordinates":[30.01667,-14.08333],"type":"Point"}
}