{
  "type": "Feature",
  "properties": {
    "gn:admin1_code":"7.0",
    "gn:asciiname":"Chinkuli",
    "gn:country_code":"ZM",
    "gn:dem":1067,
    "gn:feature_class":"P",
    "gn:feature_code":"PPL",
    "gn:name":"Chinkuli",
    "gn:population":0,
    "gn:timezone":"Africa/Lusaka",
    "iso:country":"ZM",
    "name:und_x_variant":[
        "Chinkuri",
        "Chinkuli"
    ],
    "wof:name":"Chinkuli",
    "wof:placetype":"locality"
},
  "geometry": {"coordinates":[26.41667,-15.41667],"type":"Point"}
}