{
  "type": "Feature",
  "properties": {
    "gn:admin1_code":"2.0",
    "gn:asciiname":"Panga",
    "gn:country_code":"ZM",
    "gn:dem":1291,
    "gn:feature_class":"P",
    "gn:feature_code":"PPL",
    "gn:name":"Panga",
    "gn:population":0,
    "gn:timezone":"Africa/Lusaka",
    "iso:country":"ZM",
    "wof:name":"Panga",
    "wof:placetype":"locality"
},
  "geometry": {"coordinates":[30.46667,-12.73333],"type":"Point"}
}