{
  "type": "Feature",
  "properties": {
    "gn:admin1_code":"3.0",
    "gn:asciiname":"Nyankwaya",
    "gn:country_code":"ZM",
    "gn:dem":745,
    "gn:feature_class":"P",
    "gn:feature_code":"PPL",
    "gn:name":"Nyankwaya",
    "gn:population":0,
    "gn:timezone":"Africa/Lusaka",
    "iso:country":"ZM",
    "wof:name":"Nyankwaya",
    "wof:placetype":"locality"
},
  "geometry": {"coordinates":[30.80067,-14.54119],"type":"Point"}
}