{
  "type": "Feature",
  "properties": {
    "gn:admin1_code":"1.0",
    "gn:asciiname":"Singoma",
    "gn:country_code":"ZM",
    "gn:dem":1088,
    "gn:feature_class":"P",
    "gn:feature_code":"PPL",
    "gn:name":"Singoma",
    "gn:population":0,
    "gn:timezone":"Africa/Lusaka",
    "iso:country":"ZM",
    "wof:name":"Singoma",
    "wof:placetype":"locality"
},
  "geometry": {"coordinates":[23.95,-15.28333],"type":"Point"}
}