{
  "type": "Feature",
  "properties": {
    "gn:admin1_code":"1.0",
    "gn:asciiname":"Kachana",
    "gn:country_code":"ZM",
    "gn:dem":1081,
    "gn:feature_class":"P",
    "gn:feature_code":"PPL",
    "gn:name":"Kachana",
    "gn:population":0,
    "gn:timezone":"Africa/Lusaka",
    "iso:country":"ZM",
    "wof:name":"Kachana",
    "wof:placetype":"locality"
},
  "geometry": {"coordinates":[24.28333,-14.58333],"type":"Point"}
}