{
  "type": "Feature",
  "properties": {
    "gn:admin1_code":"3.0",
    "gn:asciiname":"Mankomba",
    "gn:country_code":"ZM",
    "gn:dem":944,
    "gn:feature_class":"P",
    "gn:feature_code":"PPL",
    "gn:name":"Mankomba",
    "gn:population":0,
    "gn:timezone":"Africa/Lusaka",
    "iso:country":"ZM",
    "name:und_x_variant":[
        "Mankhomba",
        "Mankomba"
    ],
    "wof:name":"Mankomba",
    "wof:placetype":"locality"
},
  "geometry": {"coordinates":[31.26667,-14.38333],"type":"Point"}
}