{
  "type": "Feature",
  "properties": {
    "gn:admin1_code":"1.0",
    "gn:asciiname":"Lifumbo",
    "gn:country_code":"ZM",
    "gn:dem":1177,
    "gn:feature_class":"P",
    "gn:feature_code":"PPL",
    "gn:name":"Lifumbo",
    "gn:population":0,
    "gn:timezone":"Africa/Lusaka",
    "iso:country":"ZM",
    "wof:name":"Lifumbo",
    "wof:placetype":"locality"
},
  "geometry": {"coordinates":[24.91667,-14.88333],"type":"Point"}
}