{
  "type": "Feature",
  "properties": {
    "gn:admin1_code":"5.0",
    "gn:asciiname":"Sindano",
    "gn:country_code":"ZM",
    "gn:dem":1413,
    "gn:feature_class":"P",
    "gn:feature_code":"PPL",
    "gn:name":"Sindano",
    "gn:population":0,
    "gn:timezone":"Africa/Lusaka",
    "iso:country":"ZM",
    "wof:name":"Sindano",
    "wof:placetype":"locality"
},
  "geometry": {"coordinates":[31.96667,-9.33333],"type":"Point"}
}