{
  "type": "Feature",
  "properties": {
    "gn:admin1_code":"1.0",
    "gn:asciiname":"Kingama",
    "gn:country_code":"ZM",
    "gn:dem":1169,
    "gn:feature_class":"P",
    "gn:feature_code":"PPL",
    "gn:name":"Kingama",
    "gn:population":0,
    "gn:timezone":"Africa/Lusaka",
    "iso:country":"ZM",
    "wof:name":"Kingama",
    "wof:placetype":"locality"
},
  "geometry": {"coordinates":[24.94327,-14.8383],"type":"Point"}
}