{
  "type": "Feature",
  "properties": {
    "gn:admin1_code":"1.0",
    "gn:asciiname":"Sakakuwa",
    "gn:country_code":"ZM",
    "gn:dem":1045,
    "gn:feature_class":"P",
    "gn:feature_code":"PPL",
    "gn:name":"Sakakuwa",
    "gn:population":0,
    "gn:timezone":"Africa/Lusaka",
    "iso:country":"ZM",
    "wof:name":"Sakakuwa",
    "wof:placetype":"locality"
},
  "geometry": {"coordinates":[24.20844,-16.28497999999999],"type":"Point"}
}