{
  "type": "Feature",
  "properties": {
    "gn:admin1_code":"3.0",
    "gn:asciiname":"Chaima",
    "gn:country_code":"ZM",
    "gn:dem":783,
    "gn:feature_class":"P",
    "gn:feature_code":"PPL",
    "gn:name":"Chaima",
    "gn:population":0,
    "gn:timezone":"Africa/Lusaka",
    "iso:country":"ZM",
    "wof:name":"Chaima",
    "wof:placetype":"locality"
},
  "geometry": {"coordinates":[32.67083,-14.13307],"type":"Point"}
}