{
  "type": "Feature",
  "properties": {
    "gn:admin1_code":"3.0",
    "gn:asciiname":"Katimba",
    "gn:country_code":"ZM",
    "gn:dem":815,
    "gn:feature_class":"P",
    "gn:feature_code":"PPL",
    "gn:name":"Katimba",
    "gn:population":0,
    "gn:timezone":"Africa/Lusaka",
    "iso:country":"ZM",
    "wof:name":"Katimba",
    "wof:placetype":"locality"
},
  "geometry": {"coordinates":[31.74519,-13.61823],"type":"Point"}
}