{
  "type": "Feature",
  "properties": {
    "gn:admin1_code":"7.0",
    "gn:asciiname":"Kasiya",
    "gn:country_code":"ZM",
    "gn:dem":1195,
    "gn:feature_class":"P",
    "gn:feature_code":"PPL",
    "gn:name":"Kasiya",
    "gn:population":0,
    "gn:timezone":"Africa/Lusaka",
    "iso:country":"ZM",
    "wof:name":"Kasiya",
    "wof:placetype":"locality"
},
  "geometry": {"coordinates":[27.28333,-16.55],"type":"Point"}
}