{
  "type": "Feature",
  "properties": {
    "gn:admin1_code":"1.0",
    "gn:asciiname":"Sililo",
    "gn:country_code":"ZM",
    "gn:dem":974,
    "gn:feature_class":"P",
    "gn:feature_code":"PPL",
    "gn:name":"Sililo",
    "gn:population":0,
    "gn:timezone":"Africa/Lusaka",
    "iso:country":"ZM",
    "wof:name":"Sililo",
    "wof:placetype":"locality"
},
  "geometry": {"coordinates":[24.1254,-16.89081],"type":"Point"}
}