{
  "type": "Feature",
  "properties": {
    "gn:admin1_code":"7.0",
    "gn:asciiname":"Kakamba",
    "gn:country_code":"ZM",
    "gn:dem":1132,
    "gn:feature_class":"P",
    "gn:feature_code":"PPL",
    "gn:name":"Kakamba",
    "gn:population":0,
    "gn:timezone":"Africa/Lusaka",
    "iso:country":"ZM",
    "name:und_x_variant":[
        "Lakamba",
        "Kakamba"
    ],
    "wof:name":"Kakamba",
    "wof:placetype":"locality"
},
  "geometry": {"coordinates":[25.96667,-17.31667],"type":"Point"}
}