{
  "type": "Feature",
  "properties": {
    "gn:admin1_code":"3.0",
    "gn:asciiname":"Kaimbonye",
    "gn:country_code":"ZM",
    "gn:dem":1137,
    "gn:feature_class":"P",
    "gn:feature_code":"PPL",
    "gn:name":"Kaimbonye",
    "gn:population":0,
    "gn:timezone":"Africa/Lusaka",
    "iso:country":"ZM",
    "wof:name":"Kaimbonye",
    "wof:placetype":"locality"
},
  "geometry": {"coordinates":[33.21667,-11.83333],"type":"Point"}
}