{
  "type": "Feature",
  "properties": {
    "gn:admin1_code":"4.0",
    "gn:asciiname":"Kaloka",
    "gn:country_code":"ZM",
    "gn:dem":1163,
    "gn:feature_class":"P",
    "gn:feature_code":"PPL",
    "gn:name":"Kaloka",
    "gn:population":0,
    "gn:timezone":"Africa/Lusaka",
    "iso:country":"ZM",
    "wof:name":"Kaloka",
    "wof:placetype":"locality"
},
  "geometry": {"coordinates":[29.37478,-12.40349],"type":"Point"}
}