{
  "type": "Feature",
  "properties": {
    "gn:admin1_code":"4.0",
    "gn:asciiname":"Kapolwa",
    "gn:country_code":"ZM",
    "gn:dem":1155,
    "gn:feature_class":"P",
    "gn:feature_code":"PPL",
    "gn:name":"Kapolwa",
    "gn:population":0,
    "gn:timezone":"Africa/Lusaka",
    "iso:country":"ZM",
    "wof:name":"Kapolwa",
    "wof:placetype":"locality"
},
  "geometry": {"coordinates":[29.26667,-11.43333],"type":"Point"}
}