{
  "type": "Feature",
  "properties": {
    "gn:admin1_code":"1.0",
    "gn:asciiname":"Kapau",
    "gn:country_code":"ZM",
    "gn:dem":1022,
    "gn:feature_class":"P",
    "gn:feature_code":"PPL",
    "gn:name":"Kapau",
    "gn:population":0,
    "gn:timezone":"Africa/Lusaka",
    "iso:country":"ZM",
    "wof:name":"Kapau",
    "wof:placetype":"locality"
},
  "geometry": {"coordinates":[23.73333,-16.85],"type":"Point"}
}