{
  "type": "Feature",
  "properties": {
    "gn:admin1_code":"3.0",
    "gn:asciiname":"Chipasula",
    "gn:country_code":"ZM",
    "gn:dem":1261,
    "gn:feature_class":"P",
    "gn:feature_code":"PPL",
    "gn:name":"Chipasula",
    "gn:population":0,
    "gn:timezone":"Africa/Lusaka",
    "iso:country":"ZM",
    "wof:name":"Chipasula",
    "wof:placetype":"locality"
},
  "geometry": {"coordinates":[33.40412,-12.35522],"type":"Point"}
}