{
  "type": "Feature",
  "properties": {
    "gn:admin1_code":"3.0",
    "gn:asciiname":"Mwase Mpangwe",
    "gn:country_code":"ZM",
    "gn:dem":1035,
    "gn:feature_class":"P",
    "gn:feature_code":"PPL",
    "gn:name":"Mwase Mpangwe",
    "gn:population":0,
    "gn:timezone":"Africa/Lusaka",
    "iso:country":"ZM",
    "wof:name":"Mwase Mpangwe",
    "wof:placetype":"locality"
},
  "geometry": {"coordinates":[32.91451,-13.02091],"type":"Point"}
}