{
  "type": "Feature",
  "properties": {
    "gn:admin1_code":"6.0",
    "gn:asciiname":"Mumena",
    "gn:country_code":"ZM",
    "gn:dem":1306,
    "gn:feature_class":"P",
    "gn:feature_code":"PPL",
    "gn:name":"Mumena",
    "gn:population":0,
    "gn:timezone":"Africa/Lusaka",
    "iso:country":"ZM",
    "name:und_x_variant":[
        "Munena",
        "Mumena"
    ],
    "wof:name":"Mumena",
    "wof:placetype":"locality"
},
  "geometry": {"coordinates":[26.15338,-12.54173],"type":"Point"}
}