{
  "type": "Feature",
  "properties": {
    "gn:admin1_code":"3.0",
    "gn:asciiname":"Chikusi",
    "gn:country_code":"ZM",
    "gn:dem":1030,
    "gn:feature_class":"P",
    "gn:feature_code":"PPL",
    "gn:name":"Chikusi",
    "gn:population":0,
    "gn:timezone":"Africa/Lusaka",
    "iso:country":"ZM",
    "wof:name":"Chikusi",
    "wof:placetype":"locality"
},
  "geometry": {"coordinates":[31.96667,-14.38333],"type":"Point"}
}