{
  "type": "Feature",
  "properties": {
    "gn:admin1_code":"5.0",
    "gn:asciiname":"Samson",
    "gn:country_code":"ZM",
    "gn:dem":1616,
    "gn:feature_class":"P",
    "gn:feature_code":"PPL",
    "gn:name":"Samson",
    "gn:population":0,
    "gn:timezone":"Africa/Lusaka",
    "iso:country":"ZM",
    "wof:name":"Samson",
    "wof:placetype":"locality"
},
  "geometry": {"coordinates":[31.86667000000001,-9.05],"type":"Point"}
}