{
  "type": "Feature",
  "properties": {
    "gn:admin1_code":"1.0",
    "gn:asciiname":"Samahongo",
    "gn:country_code":"ZM",
    "gn:dem":1057,
    "gn:feature_class":"P",
    "gn:feature_code":"PPL",
    "gn:name":"Samahongo",
    "gn:population":0,
    "gn:timezone":"Africa/Lusaka",
    "iso:country":"ZM",
    "wof:name":"Samahongo",
    "wof:placetype":"locality"
},
  "geometry": {"coordinates":[22.23333,-13.98333],"type":"Point"}
}