{
  "type": "Feature",
  "properties": {
    "gn:admin1_code":"3.0",
    "gn:asciiname":"Chikuni",
    "gn:country_code":"ZM",
    "gn:dem":1173,
    "gn:feature_class":"P",
    "gn:feature_code":"PPL",
    "gn:name":"Chikuni",
    "gn:population":0,
    "gn:timezone":"Africa/Lusaka",
    "iso:country":"ZM",
    "wof:name":"Chikuni",
    "wof:placetype":"locality"
},
  "geometry": {"coordinates":[33.26667,-12.41667],"type":"Point"}
}