{
  "type": "Feature",
  "properties": {
    "gn:admin1_code":"6.0",
    "gn:asciiname":"Kasalya",
    "gn:country_code":"ZM",
    "gn:dem":1127,
    "gn:feature_class":"P",
    "gn:feature_code":"PPL",
    "gn:name":"Kasalya",
    "gn:population":0,
    "gn:timezone":"Africa/Lusaka",
    "iso:country":"ZM",
    "wof:name":"Kasalya",
    "wof:placetype":"locality"
},
  "geometry": {"coordinates":[23.96667,-13.36667],"type":"Point"}
}