{
  "type": "Feature",
  "properties": {
    "gn:admin1_code":"10.0",
    "gn:asciiname":"Kalyata",
    "gn:country_code":"ZM",
    "gn:dem":1515,
    "gn:feature_class":"P",
    "gn:feature_code":"PPL",
    "gn:name":"Kalyata",
    "gn:population":0,
    "gn:timezone":"Africa/Lusaka",
    "iso:country":"ZM",
    "name:und_x_variant":[
        "Kariata",
        "Kalyata"
    ],
    "wof:name":"Kalyata",
    "wof:placetype":"locality"
},
  "geometry": {"coordinates":[32.48333,-9.18333],"type":"Point"}
}