{
  "type": "Feature",
  "properties": {
    "gn:admin1_code":"10.0",
    "gn:asciiname":"Kapampa",
    "gn:country_code":"ZM",
    "gn:dem":595,
    "gn:feature_class":"P",
    "gn:feature_code":"PPL",
    "gn:name":"Kapampa",
    "gn:population":0,
    "gn:timezone":"Africa/Lusaka",
    "iso:country":"ZM",
    "wof:name":"Kapampa",
    "wof:placetype":"locality"
},
  "geometry": {"coordinates":[32.05,-12.35],"type":"Point"}
}