{
  "type": "Feature",
  "properties": {
    "gn:admin1_code":"2.0",
    "gn:asciiname":"Akim Kosoma",
    "gn:country_code":"ZM",
    "gn:dem":1293,
    "gn:feature_class":"P",
    "gn:feature_code":"PPL",
    "gn:name":"Akim Kosoma",
    "gn:population":0,
    "gn:timezone":"Africa/Lusaka",
    "iso:country":"ZM",
    "wof:name":"Akim Kosoma",
    "wof:placetype":"locality"
},
  "geometry": {"coordinates":[30.33467000000001,-12.80767],"type":"Point"}
}