{
  "type": "Feature",
  "properties": {
    "gn:admin1_code":"1.0",
    "gn:asciiname":"Tepa",
    "gn:country_code":"ZM",
    "gn:dem":1027,
    "gn:feature_class":"P",
    "gn:feature_code":"PPL",
    "gn:name":"Tepa",
    "gn:population":0,
    "gn:timezone":"Africa/Lusaka",
    "iso:country":"ZM",
    "wof:name":"Tepa",
    "wof:placetype":"locality"
},
  "geometry": {"coordinates":[22.93333,-14.58333],"type":"Point"}
}