{
  "type": "Feature",
  "properties": {
    "gn:admin1_code":"3.0",
    "gn:asciiname":"Chiwanga",
    "gn:country_code":"ZM",
    "gn:dem":956,
    "gn:feature_class":"P",
    "gn:feature_code":"PPL",
    "gn:name":"Chiwanga",
    "gn:population":0,
    "gn:timezone":"Africa/Lusaka",
    "iso:country":"ZM",
    "wof:name":"Chiwanga",
    "wof:placetype":"locality"
},
  "geometry": {"coordinates":[31.72759000000001,-14.05605],"type":"Point"}
}