{
  "type": "Feature",
  "properties": {
    "gn:admin1_code":"5.0",
    "gn:asciiname":"Pepo",
    "gn:country_code":"ZM",
    "gn:dem":1211,
    "gn:feature_class":"P",
    "gn:feature_code":"PPL",
    "gn:name":"Pepo",
    "gn:population":0,
    "gn:timezone":"Africa/Lusaka",
    "iso:country":"ZM",
    "name:fin_x_preferred":[
        "Pepo"
    ],
    "name:por_x_preferred":[
        "Pepo"
    ],
    "name:und_x_variant":[
        "Kupepo"
    ],
    "wof:name":"Pepo",
    "wof:placetype":"locality"
},
  "geometry": {"coordinates":[31.13187000000001,-10.59524],"type":"Point"}
}