{
  "type": "Feature",
  "properties": {
    "gn:admin1_code":"5.0",
    "gn:asciiname":"Kashinka",
    "gn:country_code":"ZM",
    "gn:dem":1252,
    "gn:feature_class":"P",
    "gn:feature_code":"PPL",
    "gn:name":"Kashinka",
    "gn:population":0,
    "gn:timezone":"Africa/Lusaka",
    "iso:country":"ZM",
    "wof:name":"Kashinka",
    "wof:placetype":"locality"
},
  "geometry": {"coordinates":[30.46804,-10.44703],"type":"Point"}
}