{
  "type": "Feature",
  "properties": {
    "gn:admin1_code":"1.0",
    "gn:asciiname":"Sichimwa",
    "gn:country_code":"ZM",
    "gn:dem":971,
    "gn:feature_class":"P",
    "gn:feature_code":"PPL",
    "gn:name":"Sichimwa",
    "gn:population":0,
    "gn:timezone":"Africa/Lusaka",
    "iso:country":"ZM",
    "wof:name":"Sichimwa",
    "wof:placetype":"locality"
},
  "geometry": {"coordinates":[24.71667,-17.28333],"type":"Point"}
}