{
  "type": "Feature",
  "properties": {
    "gn:admin1_code":"9.0",
    "gn:asciiname":"Shabwalala",
    "gn:country_code":"ZM",
    "gn:dem":1052,
    "gn:feature_class":"P",
    "gn:feature_code":"PPL",
    "gn:name":"Shabwalala",
    "gn:population":0,
    "gn:timezone":"Africa/Lusaka",
    "iso:country":"ZM",
    "wof:name":"Shabwalala",
    "wof:placetype":"locality"
},
  "geometry": {"coordinates":[27.93333,-15.26667],"type":"Point"}
}