{
  "type": "Feature",
  "properties": {
    "gn:admin1_code":"2.0",
    "gn:asciiname":"Liyangula",
    "gn:country_code":"ZM",
    "gn:dem":1222,
    "gn:feature_class":"P",
    "gn:feature_code":"PPL",
    "gn:name":"Liyangula",
    "gn:population":0,
    "gn:timezone":"Africa/Lusaka",
    "iso:country":"ZM",
    "wof:name":"Liyangula",
    "wof:placetype":"locality"
},
  "geometry": {"coordinates":[29.46667,-14.45],"type":"Point"}
}