{
  "type": "Feature",
  "properties": {
    "gn:admin1_code":"6.0",
    "gn:asciiname":"Chinyama",
    "gn:country_code":"ZM",
    "gn:dem":1080,
    "gn:feature_class":"P",
    "gn:feature_code":"PPL",
    "gn:name":"Chinyama",
    "gn:population":0,
    "gn:timezone":"Africa/Lusaka",
    "iso:country":"ZM",
    "name:und_x_variant":[
        "Sinyama",
        "Chinyama"
    ],
    "wof:name":"Chinyama",
    "wof:placetype":"locality"
},
  "geometry": {"coordinates":[22.38333,-13.45],"type":"Point"}
}