{
  "type": "Feature",
  "properties": {
    "gn:admin1_code":"3.0",
    "gn:asciiname":"Mbangombe",
    "gn:country_code":"ZM",
    "gn:dem":1033,
    "gn:feature_class":"P",
    "gn:feature_code":"PPL",
    "gn:name":"Mbangombe",
    "gn:population":0,
    "gn:timezone":"Africa/Lusaka",
    "iso:country":"ZM",
    "wof:name":"Mbangombe",
    "wof:placetype":"locality"
},
  "geometry": {"coordinates":[32.15,-13.86667],"type":"Point"}
}