{
  "type": "Feature",
  "properties": {
    "gn:admin1_code":"3.0",
    "gn:asciiname":"Manokola",
    "gn:country_code":"ZM",
    "gn:dem":638,
    "gn:feature_class":"P",
    "gn:feature_code":"PPL",
    "gn:name":"Manokola",
    "gn:population":0,
    "gn:timezone":"Africa/Lusaka",
    "iso:country":"ZM",
    "name:und_x_variant":[
        "Mahokora",
        "Manokola"
    ],
    "wof:name":"Manokola",
    "wof:placetype":"locality"
},
  "geometry": {"coordinates":[31.90839,-13.60371],"type":"Point"}
}