{
  "type": "Feature",
  "properties": {
    "gn:admin1_code":"10.0",
    "gn:asciiname":"Kabinga",
    "gn:country_code":"ZM",
    "gn:dem":1198,
    "gn:feature_class":"P",
    "gn:feature_code":"PPL",
    "gn:name":"Kabinga",
    "gn:population":0,
    "gn:timezone":"Africa/Lusaka",
    "iso:country":"ZM",
    "name:und_x_variant":[
        "Kavinga",
        "Kabinga"
    ],
    "wof:name":"Kabinga",
    "wof:placetype":"locality"
},
  "geometry": {"coordinates":[30.78333,-11.18333],"type":"Point"}
}