{
  "type": "Feature",
  "properties": {
    "gn:admin1_code":"2.0",
    "gn:asciiname":"Kalangambala",
    "gn:country_code":"ZM",
    "gn:dem":1153,
    "gn:feature_class":"P",
    "gn:feature_code":"PPL",
    "gn:name":"Kalangambala",
    "gn:population":0,
    "gn:timezone":"Africa/Lusaka",
    "iso:country":"ZM",
    "wof:name":"Kalangambala",
    "wof:placetype":"locality"
},
  "geometry": {"coordinates":[27.96667,-14.95],"type":"Point"}
}