{
  "type": "Feature",
  "properties": {
    "gn:admin1_code":"10.0",
    "gn:asciiname":"Kasongo",
    "gn:country_code":"ZM",
    "gn:dem":1358,
    "gn:feature_class":"P",
    "gn:feature_code":"PPL",
    "gn:name":"Kasongo",
    "gn:population":0,
    "gn:timezone":"Africa/Lusaka",
    "iso:country":"ZM",
    "wof:name":"Kasongo",
    "wof:placetype":"locality"
},
  "geometry": {"coordinates":[31.2359,-11.32309],"type":"Point"}
}