{
  "type": "Feature",
  "properties": {
    "gn:admin1_code":"7.0",
    "gn:asciiname":"Nyimba",
    "gn:country_code":"ZM",
    "gn:dem":980,
    "gn:feature_class":"P",
    "gn:feature_code":"PPL",
    "gn:name":"Nyimba",
    "gn:population":0,
    "gn:timezone":"Africa/Lusaka",
    "iso:country":"ZM",
    "name:ara_x_preferred":[
        "\u0646\u064a\u0645\u0628\u0627"
    ],
    "name:ben_x_preferred":[
        "\u09a8\u09bf\u09ae\u09cd\u09ac\u09bf\u09df\u09be"
    ],
    "name:deu_x_preferred":[
        "Nyimba"
    ],
    "name:ell_x_preferred":[
        "\u039d\u03b3\u03af\u03bc\u03c0\u03b1"
    ],
    "name:fas_x_preferred":[
        "\u0646\u06cc\u06cc\u0645\u0628\u0627"
    ],
    "name:heb_x_preferred":[
        "\u05e0\u05d9\u05d9\u05de\u05d1\u05d4"
    ],
    "name:hin_x_preferred":[
        "\u0928\u093e\u0908\u092e\u094d\u092c\u093e"
    ],
    "name:hun_x_preferred":[
        "Nyimba"
    ],
    "name:ind_x_preferred":[
        "Nyimba"
    ],
    "name:kor_x_preferred":[
        "\ub2d8\ubc14"
    ],
    "name:por_x_preferred":[
        "Nyimba"
    ],
    "name:rus_x_preferred":[
        "\u041d\u0438\u043c\u0431\u0430"
    ],
    "name:spa_x_preferred":[
        "Nyimba"
    ],
    "name:swe_x_preferred":[
        "Nyimba"
    ],
    "name:tur_x_preferred":[
        "Nyimba"
    ],
    "name:ukr_x_preferred":[
        "\u041d\u044c\u0457\u043c\u0431\u0430"
    ],
    "name:urd_x_preferred":[
        "\u0646\u0627\u0626\u06cc\u0645\u0628\u0627"
    ],
    "name:vie_x_preferred":[
        "Nyimba"
    ],
    "wof:name":"Nyimba",
    "wof:placetype":"locality"
},
  "geometry": {"coordinates":[27.28333,-15.73333],"type":"Point"}
}