{
  "type": "Feature",
  "properties": {
    "gn:admin1_code":"10.0",
    "gn:asciiname":"Malisawa",
    "gn:country_code":"ZM",
    "gn:dem":1266,
    "gn:feature_class":"P",
    "gn:feature_code":"PPL",
    "gn:name":"Malisawa",
    "gn:population":0,
    "gn:timezone":"Africa/Lusaka",
    "iso:country":"ZM",
    "wof:name":"Malisawa",
    "wof:placetype":"locality"
},
  "geometry": {"coordinates":[32.35,-9.31667],"type":"Point"}
}