{
  "type": "Feature",
  "properties": {
    "gn:admin1_code":"1.0",
    "gn:asciiname":"Makulukuse",
    "gn:country_code":"ZM",
    "gn:dem":1028,
    "gn:feature_class":"P",
    "gn:feature_code":"PPL",
    "gn:name":"Makulukuse",
    "gn:population":0,
    "gn:timezone":"Africa/Lusaka",
    "iso:country":"ZM",
    "wof:name":"Makulukuse",
    "wof:placetype":"locality"
},
  "geometry": {"coordinates":[23.18333,-14.75],"type":"Point"}
}