{
  "type": "Feature",
  "properties": {
    "gn:admin1_code":"2.0",
    "gn:asciiname":"Mwando Chipewa",
    "gn:country_code":"ZM",
    "gn:dem":1219,
    "gn:feature_class":"P",
    "gn:feature_code":"PPL",
    "gn:name":"Mwando Chipewa",
    "gn:population":0,
    "gn:timezone":"Africa/Lusaka",
    "iso:country":"ZM",
    "wof:name":"Mwando Chipewa",
    "wof:placetype":"locality"
},
  "geometry": {"coordinates":[29.9239,-12.72363],"type":"Point"}
}