{
  "type": "Feature",
  "properties": {
    "gn:admin1_code":"1.0",
    "gn:asciiname":"Luampa",
    "gn:country_code":"ZM",
    "gn:dem":1120,
    "gn:feature_class":"P",
    "gn:feature_code":"PPL",
    "gn:name":"Luampa",
    "gn:population":0,
    "gn:timezone":"Africa/Lusaka",
    "iso:country":"ZM",
    "wof:name":"Luampa",
    "wof:placetype":"locality"
},
  "geometry": {"coordinates":[24.41667,-15.05],"type":"Point"}
}