{
  "type": "Feature",
  "properties": {
    "gn:admin1_code":"3.0",
    "gn:asciiname":"Chimsali",
    "gn:country_code":"ZM",
    "gn:dem":1015,
    "gn:feature_class":"P",
    "gn:feature_code":"PPL",
    "gn:name":"Chimsali",
    "gn:population":0,
    "gn:timezone":"Africa/Lusaka",
    "iso:country":"ZM",
    "name:und_x_variant":[
        "Chimsa",
        "Chimsali"
    ],
    "wof:name":"Chimsali",
    "wof:placetype":"locality"
},
  "geometry": {"coordinates":[31.88333,-14.41667],"type":"Point"}
}