{
  "type": "Feature",
  "properties": {
    "gn:admin1_code":"5.0",
    "gn:asciiname":"Kalandanya",
    "gn:country_code":"ZM",
    "gn:dem":1739,
    "gn:feature_class":"P",
    "gn:feature_code":"PPL",
    "gn:name":"Kalandanya",
    "gn:population":0,
    "gn:timezone":"Africa/Lusaka",
    "iso:country":"ZM",
    "wof:name":"Kalandanya",
    "wof:placetype":"locality"
},
  "geometry": {"coordinates":[31.55,-8.86667],"type":"Point"}
}