{
  "type": "Feature",
  "properties": {
    "gn:admin1_code":"5.0",
    "gn:asciiname":"Mutengo",
    "gn:country_code":"ZM",
    "gn:dem":1563,
    "gn:feature_class":"P",
    "gn:feature_code":"PPL",
    "gn:name":"Mutengo",
    "gn:population":0,
    "gn:timezone":"Africa/Lusaka",
    "iso:country":"ZM",
    "wof:name":"Mutengo",
    "wof:placetype":"locality"
},
  "geometry": {"coordinates":[31.18589,-9.34855],"type":"Point"}
}