{
  "type": "Feature",
  "properties": {
    "gn:admin1_code":"8.0",
    "gn:asciiname":"Lusalya",
    "gn:country_code":"ZM",
    "gn:dem":1278,
    "gn:feature_class":"P",
    "gn:feature_code":"PPL",
    "gn:name":"Lusalya",
    "gn:population":0,
    "gn:timezone":"Africa/Lusaka",
    "iso:country":"ZM",
    "name:und_x_variant":[
        "Lusaya",
        "Lusalya"
    ],
    "wof:name":"Lusalya",
    "wof:placetype":"locality"
},
  "geometry": {"coordinates":[28.73333,-12.93333],"type":"Point"}
}