{
  "type": "Feature",
  "properties": {
    "gn:admin1_code":"1.0",
    "gn:asciiname":"Kahare",
    "gn:country_code":"ZM",
    "gn:dem":1172,
    "gn:feature_class":"P",
    "gn:feature_code":"PPL",
    "gn:name":"Kahare",
    "gn:population":0,
    "gn:timezone":"Africa/Lusaka",
    "iso:country":"ZM",
    "name:und_x_variant":[
        "Kahari",
        "Kahare"
    ],
    "wof:name":"Kahare",
    "wof:placetype":"locality"
},
  "geometry": {"coordinates":[25.24984,-15.05115],"type":"Point"}
}