{
  "type": "Feature",
  "properties": {
    "gn:admin1_code":"9.0",
    "gn:asciiname":"Kasinsa",
    "gn:country_code":"ZM",
    "gn:dem":366,
    "gn:feature_class":"P",
    "gn:feature_code":"PPL",
    "gn:name":"Kasinsa",
    "gn:population":0,
    "gn:timezone":"Africa/Lusaka",
    "iso:country":"ZM",
    "wof:name":"Kasinsa",
    "wof:placetype":"locality"
},
  "geometry": {"coordinates":[30.21667,-15.13333],"type":"Point"}
}