{
  "type": "Feature",
  "properties": {
    "gn:admin1_code":"5.0",
    "gn:asciiname":"Chifungo",
    "gn:country_code":"ZM",
    "gn:dem":1531,
    "gn:feature_class":"P",
    "gn:feature_code":"PPL",
    "gn:name":"Chifungo",
    "gn:population":0,
    "gn:timezone":"Africa/Lusaka",
    "iso:country":"ZM",
    "name:und_x_variant":[
        "Chifunge",
        "Chifungo"
    ],
    "wof:name":"Chifungo",
    "wof:placetype":"locality"
},
  "geometry": {"coordinates":[30.76516,-8.88455],"type":"Point"}
}