{
  "type": "Feature",
  "properties": {
    "gn:admin1_code":"1.0",
    "gn:asciiname":"Mwabinga",
    "gn:country_code":"ZM",
    "gn:dem":1028,
    "gn:feature_class":"P",
    "gn:feature_code":"PPL",
    "gn:name":"Mwabinga",
    "gn:population":0,
    "gn:timezone":"Africa/Lusaka",
    "iso:country":"ZM",
    "wof:name":"Mwabinga",
    "wof:placetype":"locality"
},
  "geometry": {"coordinates":[22.35,-16.16667],"type":"Point"}
}