{
  "type": "Feature",
  "properties": {
    "gn:admin1_code":"5.0",
    "gn:asciiname":"Shimumbi",
    "gn:country_code":"ZM",
    "gn:dem":1207,
    "gn:feature_class":"P",
    "gn:feature_code":"PPL",
    "gn:name":"Shimumbi",
    "gn:population":0,
    "gn:timezone":"Africa/Lusaka",
    "iso:country":"ZM",
    "wof:name":"Shimumbi",
    "wof:placetype":"locality"
},
  "geometry": {"coordinates":[30.40114,-10.70204],"type":"Point"}
}