{
  "type": "Feature",
  "properties": {
    "gn:admin1_code":"2.0",
    "gn:asciiname":"Mayaya",
    "gn:country_code":"ZM",
    "gn:dem":1196,
    "gn:feature_class":"P",
    "gn:feature_code":"PPL",
    "gn:name":"Mayaya",
    "gn:population":0,
    "gn:timezone":"Africa/Lusaka",
    "iso:country":"ZM",
    "wof:name":"Mayaya",
    "wof:placetype":"locality"
},
  "geometry": {"coordinates":[28.28333,-14.15],"type":"Point"}
}