{
  "type": "Feature",
  "properties": {
    "gn:admin1_code":"1.0",
    "gn:asciiname":"Linyotwa",
    "gn:country_code":"ZM",
    "gn:dem":1050,
    "gn:feature_class":"P",
    "gn:feature_code":"PPL",
    "gn:name":"Linyotwa",
    "gn:population":0,
    "gn:timezone":"Africa/Lusaka",
    "iso:country":"ZM",
    "wof:name":"Linyotwa",
    "wof:placetype":"locality"
},
  "geometry": {"coordinates":[22.51667,-15.03333],"type":"Point"}
}