{
  "type": "Feature",
  "properties": {
    "gn:admin1_code":"8.0",
    "gn:asciiname":"Chibuluma",
    "gn:country_code":"ZM",
    "gn:dem":1270,
    "gn:feature_class":"P",
    "gn:feature_code":"PPL",
    "gn:name":"Chibuluma",
    "gn:population":0,
    "gn:timezone":"Africa/Lusaka",
    "iso:country":"ZM",
    "wof:name":"Chibuluma",
    "wof:placetype":"locality"
},
  "geometry": {"coordinates":[28.13585,-12.85134],"type":"Point"}
}