{
  "type": "Feature",
  "properties": {
    "gn:admin1_code":"2.0",
    "gn:asciiname":"Kambobe",
    "gn:country_code":"ZM",
    "gn:dem":1459,
    "gn:feature_class":"P",
    "gn:feature_code":"PPL",
    "gn:name":"Kambobe",
    "gn:population":0,
    "gn:timezone":"Africa/Lusaka",
    "iso:country":"ZM",
    "name:und_x_variant":[
        "Kamboed",
        "Kambobe"
    ],
    "wof:name":"Kambobe",
    "wof:placetype":"locality"
},
  "geometry": {"coordinates":[30.64178,-12.897],"type":"Point"}
}