{
  "type": "Feature",
  "properties": {
    "gn:admin1_code":"3.0",
    "gn:asciiname":"Mishoro",
    "gn:country_code":"ZM",
    "gn:dem":1044,
    "gn:feature_class":"P",
    "gn:feature_code":"PPL",
    "gn:name":"Mishoro",
    "gn:population":0,
    "gn:timezone":"Africa/Lusaka",
    "iso:country":"ZM",
    "wof:name":"Mishoro",
    "wof:placetype":"locality"
},
  "geometry": {"coordinates":[32.7723,-13.44662],"type":"Point"}
}