{
  "type": "Feature",
  "properties": {
    "gn:admin1_code":"3.0",
    "gn:asciiname":"Malunga",
    "gn:country_code":"ZM",
    "gn:dem":1085,
    "gn:feature_class":"P",
    "gn:feature_code":"PPL",
    "gn:name":"Malunga",
    "gn:population":0,
    "gn:timezone":"Africa/Lusaka",
    "iso:country":"ZM",
    "name:mai_x_preferred":[
        "\u092e\u0932\u0941\u0919\u094d\u0917"
    ],
    "name:nep_x_preferred":[
        "\u092e\u0932\u0941\u0919\u094d\u0917"
    ],
    "name:por_x_preferred":[
        "Malunga"
    ],
    "wof:name":"Malunga",
    "wof:placetype":"locality"
},
  "geometry": {"coordinates":[32.76667,-13.46667],"type":"Point"}
}