{
  "type": "Feature",
  "properties": {
    "gn:admin1_code":"1.0",
    "gn:asciiname":"Namakando",
    "gn:country_code":"ZM",
    "gn:dem":1035,
    "gn:feature_class":"P",
    "gn:feature_code":"PPL",
    "gn:name":"Namakando",
    "gn:population":0,
    "gn:timezone":"Africa/Lusaka",
    "iso:country":"ZM",
    "wof:name":"Namakando",
    "wof:placetype":"locality"
},
  "geometry": {"coordinates":[22.55,-14.76667],"type":"Point"}
}