{
  "type": "Feature",
  "properties": {
    "gn:admin1_code":"3.0",
    "gn:asciiname":"Chinda",
    "gn:country_code":"ZM",
    "gn:dem":704,
    "gn:feature_class":"P",
    "gn:feature_code":"PPL",
    "gn:name":"Chinda",
    "gn:population":0,
    "gn:timezone":"Africa/Lusaka",
    "iso:country":"ZM",
    "name:fra_x_preferred":[
        "Chinda"
    ],
    "name:ita_x_preferred":[
        "Chinda"
    ],
    "name:nld_x_preferred":[
        "Chinda"
    ],
    "name:por_x_preferred":[
        "Chinda"
    ],
    "name:spa_x_preferred":[
        "Chinda"
    ],
    "name:und_x_variant":[
        "Chindo",
        "Chinda"
    ],
    "wof:name":"Chinda",
    "wof:placetype":"locality"
},
  "geometry": {"coordinates":[31.78333,-13.71667],"type":"Point"}
}