{
  "type": "Feature",
  "properties": {
    "gn:admin1_code":"8.0",
    "gn:asciiname":"Saleni",
    "gn:country_code":"ZM",
    "gn:dem":1332,
    "gn:feature_class":"P",
    "gn:feature_code":"PPL",
    "gn:name":"Saleni",
    "gn:population":0,
    "gn:timezone":"Africa/Lusaka",
    "iso:country":"ZM",
    "name:und_x_variant":[
        "Sareni",
        "Saleni"
    ],
    "wof:name":"Saleni",
    "wof:placetype":"locality"
},
  "geometry": {"coordinates":[27.66667,-12.35],"type":"Point"}
}