{
  "type": "Feature",
  "properties": {
    "gn:admin1_code":"10.0",
    "gn:asciiname":"Musamba",
    "gn:country_code":"ZM",
    "gn:dem":836,
    "gn:feature_class":"P",
    "gn:feature_code":"PPL",
    "gn:name":"Musamba",
    "gn:population":0,
    "gn:timezone":"Africa/Lusaka",
    "iso:country":"ZM",
    "wof:name":"Musamba",
    "wof:placetype":"locality"
},
  "geometry": {"coordinates":[32.68333,-10.46667],"type":"Point"}
}