{
  "type": "Feature",
  "properties": {
    "gn:admin1_code":"3.0",
    "gn:asciiname":"Chipako",
    "gn:country_code":"ZM",
    "gn:dem":599,
    "gn:feature_class":"P",
    "gn:feature_code":"PPL",
    "gn:name":"Chipako",
    "gn:population":0,
    "gn:timezone":"Africa/Lusaka",
    "iso:country":"ZM",
    "name:und_x_variant":[
        "Noah Chixapo",
        "Chipako"
    ],
    "wof:name":"Chipako",
    "wof:placetype":"locality"
},
  "geometry": {"coordinates":[31.93333,-13.41667],"type":"Point"}
}