{
  "type": "Feature",
  "properties": {
    "gn:admin1_code":"1.0",
    "gn:asciiname":"Kashepwa",
    "gn:country_code":"ZM",
    "gn:dem":1081,
    "gn:feature_class":"P",
    "gn:feature_code":"PPL",
    "gn:name":"Kashepwa",
    "gn:population":0,
    "gn:timezone":"Africa/Lusaka",
    "iso:country":"ZM",
    "wof:name":"Kashepwa",
    "wof:placetype":"locality"
},
  "geometry": {"coordinates":[23.56667,-14.13333],"type":"Point"}
}