{
  "type": "Feature",
  "properties": {
    "gn:admin1_code":"5.0",
    "gn:asciiname":"Shikankulwa",
    "gn:country_code":"ZM",
    "gn:dem":1181,
    "gn:feature_class":"P",
    "gn:feature_code":"PPL",
    "gn:name":"Shikankulwa",
    "gn:population":0,
    "gn:timezone":"Africa/Lusaka",
    "iso:country":"ZM",
    "wof:name":"Shikankulwa",
    "wof:placetype":"locality"
},
  "geometry": {"coordinates":[30.15536,-11.04042],"type":"Point"}
}