{
  "type": "Feature",
  "properties": {
    "gn:admin1_code":"8.0",
    "gn:asciiname":"Malisawa",
    "gn:country_code":"ZM",
    "gn:dem":1245,
    "gn:feature_class":"P",
    "gn:feature_code":"PPL",
    "gn:name":"Malisawa",
    "gn:population":0,
    "gn:timezone":"Africa/Lusaka",
    "iso:country":"ZM",
    "name:und_x_variant":[
        "Matisowa",
        "Malisawa"
    ],
    "wof:name":"Malisawa",
    "wof:placetype":"locality"
},
  "geometry": {"coordinates":[27.41667,-12.85],"type":"Point"}
}