{
  "type": "Feature",
  "properties": {
    "gn:admin1_code":"3.0",
    "gn:asciiname":"Chikungwa",
    "gn:country_code":"ZM",
    "gn:dem":969,
    "gn:feature_class":"P",
    "gn:feature_code":"PPL",
    "gn:name":"Chikungwa",
    "gn:population":0,
    "gn:timezone":"Africa/Lusaka",
    "iso:country":"ZM",
    "wof:name":"Chikungwa",
    "wof:placetype":"locality"
},
  "geometry": {"coordinates":[31.26667,-14.21667],"type":"Point"}
}