{
  "type": "Feature",
  "properties": {
    "gn:admin1_code":"7.0",
    "gn:asciiname":"Shamutika",
    "gn:country_code":"ZM",
    "gn:dem":1127,
    "gn:feature_class":"P",
    "gn:feature_code":"PPL",
    "gn:name":"Shamutika",
    "gn:population":0,
    "gn:timezone":"Africa/Lusaka",
    "iso:country":"ZM",
    "name:und_x_variant":[
        "Siamutika",
        "Shamutika"
    ],
    "wof:name":"Shamutika",
    "wof:placetype":"locality"
},
  "geometry": {"coordinates":[26.63333,-16.21667],"type":"Point"}
}