{
  "type": "Feature",
  "properties": {
    "gn:admin1_code":"6.0",
    "gn:asciiname":"Kambelembele",
    "gn:country_code":"ZM",
    "gn:dem":1043,
    "gn:feature_class":"P",
    "gn:feature_code":"PPL",
    "gn:name":"Kambelembele",
    "gn:population":0,
    "gn:timezone":"Africa/Lusaka",
    "iso:country":"ZM",
    "wof:name":"Kambelembele",
    "wof:placetype":"locality"
},
  "geometry": {"coordinates":[22.98333,-13.25],"type":"Point"}
}