{
  "type": "Feature",
  "properties": {
    "gn:admin1_code":"10.0",
    "gn:asciiname":"Musekawalya",
    "gn:country_code":"ZM",
    "gn:dem":1245,
    "gn:feature_class":"P",
    "gn:feature_code":"PPL",
    "gn:name":"Musekawalya",
    "gn:population":0,
    "gn:timezone":"Africa/Lusaka",
    "iso:country":"ZM",
    "wof:name":"Musekawalya",
    "wof:placetype":"locality"
},
  "geometry": {"coordinates":[32.63333,-9.76667],"type":"Point"}
}