{
  "type": "Feature",
  "properties": {
    "gn:admin1_code":"3.0",
    "gn:asciiname":"Changala",
    "gn:country_code":"ZM",
    "gn:dem":1001,
    "gn:feature_class":"P",
    "gn:feature_code":"PPL",
    "gn:name":"Changala",
    "gn:population":0,
    "gn:timezone":"Africa/Lusaka",
    "iso:country":"ZM",
    "wof:name":"Changala",
    "wof:placetype":"locality"
},
  "geometry": {"coordinates":[32.44723,-14.25314],"type":"Point"}
}