{
  "type": "Feature",
  "properties": {
    "gn:admin1_code":"7.0",
    "gn:asciiname":"Siamunali",
    "gn:country_code":"ZM",
    "gn:dem":770,
    "gn:feature_class":"P",
    "gn:feature_code":"PPL",
    "gn:name":"Siamunali",
    "gn:population":0,
    "gn:timezone":"Africa/Lusaka",
    "iso:country":"ZM",
    "wof:name":"Siamunali",
    "wof:placetype":"locality"
},
  "geometry": {"coordinates":[27.76609,-16.58671],"type":"Point"}
}