{
  "type": "Feature",
  "properties": {
    "gn:admin1_code":"2.0",
    "gn:asciiname":"Shikatende",
    "gn:country_code":"ZM",
    "gn:dem":990,
    "gn:feature_class":"P",
    "gn:feature_code":"PPL",
    "gn:name":"Shikatende",
    "gn:population":0,
    "gn:timezone":"Africa/Lusaka",
    "iso:country":"ZM",
    "wof:name":"Shikatende",
    "wof:placetype":"locality"
},
  "geometry": {"coordinates":[27.71667,-15.46667],"type":"Point"}
}