{
  "type": "Feature",
  "properties": {
    "gn:admin1_code":"1.0",
    "gn:asciiname":"Mwanamwalie Induna",
    "gn:country_code":"ZM",
    "gn:dem":1066,
    "gn:feature_class":"P",
    "gn:feature_code":"PPL",
    "gn:name":"Mwanamwalie Induna",
    "gn:population":0,
    "gn:timezone":"Africa/Lusaka",
    "iso:country":"ZM",
    "wof:name":"Mwanamwalie Induna",
    "wof:placetype":"locality"
},
  "geometry": {"coordinates":[23.98333,-16.36667000000001],"type":"Point"}
}