{
  "type": "Feature",
  "properties": {
    "gn:admin1_code":"0.0",
    "gn:asciiname":"Luvemba",
    "gn:country_code":"ZM",
    "gn:dem":1160,
    "gn:feature_class":"P",
    "gn:feature_code":"PPL",
    "gn:name":"Luvemba",
    "gn:population":0,
    "gn:timezone":"Africa/Lusaka",
    "iso:country":"ZM",
    "wof:name":"Luvemba",
    "wof:placetype":"locality"
},
  "geometry": {"coordinates":[28.58333,-15.43333],"type":"Point"}
}