{
  "type": "Feature",
  "properties": {
    "gn:admin1_code":"4.0",
    "gn:asciiname":"Chitembo",
    "gn:country_code":"ZM",
    "gn:dem":1177,
    "gn:feature_class":"P",
    "gn:feature_code":"PPL",
    "gn:name":"Chitembo",
    "gn:population":0,
    "gn:timezone":"Africa/Lusaka",
    "iso:country":"ZM",
    "name:azb_x_preferred":[
        "\u0634\u06cc\u062a\u0645\u0628\u0648"
    ],
    "name:cat_x_preferred":[
        "Chitembo"
    ],
    "name:deu_x_preferred":[
        "Chitembo"
    ],
    "name:fas_x_preferred":[
        "\u0634\u06cc\u062a\u0645\u0628\u0648"
    ],
    "name:ita_x_preferred":[
        "Chitembo"
    ],
    "name:msa_x_preferred":[
        "Chitembo"
    ],
    "name:por_x_preferred":[
        "Chitembo"
    ],
    "name:rus_x_preferred":[
        "\u0428\u0438\u0442\u0435\u043c\u0431\u043e"
    ],
    "name:spa_x_preferred":[
        "Chitembo"
    ],
    "name:zho_x_preferred":[
        "\u5e0c\u6ed5\u535a"
    ],
    "wof:name":"Chitembo",
    "wof:placetype":"locality"
},
  "geometry": {"coordinates":[29.60855,-11.16381],"type":"Point"}
}