{
  "type": "Feature",
  "properties": {
    "gn:admin1_code":"2.0",
    "gn:asciiname":"Makuwa",
    "gn:country_code":"ZM",
    "gn:dem":1143,
    "gn:feature_class":"P",
    "gn:feature_code":"PPL",
    "gn:name":"Makuwa",
    "gn:population":0,
    "gn:timezone":"Africa/Lusaka",
    "iso:country":"ZM",
    "wof:name":"Makuwa",
    "wof:placetype":"locality"
},
  "geometry": {"coordinates":[28.11667000000001,-14.26667],"type":"Point"}
}