{
  "type": "Feature",
  "properties": {
    "gn:admin1_code":"2.0",
    "gn:asciiname":"Ndabala",
    "gn:country_code":"ZM",
    "gn:dem":1433,
    "gn:feature_class":"P",
    "gn:feature_code":"PPL",
    "gn:name":"Ndabala",
    "gn:population":0,
    "gn:timezone":"Africa/Lusaka",
    "iso:country":"ZM",
    "wof:name":"Ndabala",
    "wof:placetype":"locality"
},
  "geometry": {"coordinates":[29.95,-13.36667],"type":"Point"}
}