{
  "type": "Feature",
  "properties": {
    "gn:admin1_code":"7.0",
    "gn:asciiname":"Nansenga",
    "gn:country_code":"ZM",
    "gn:dem":991,
    "gn:feature_class":"P",
    "gn:feature_code":"PPL",
    "gn:name":"Nansenga",
    "gn:population":0,
    "gn:timezone":"Africa/Lusaka",
    "iso:country":"ZM",
    "wof:name":"Nansenga",
    "wof:placetype":"locality"
},
  "geometry": {"coordinates":[26.71882,-15.51731],"type":"Point"}
}