{
  "type": "Feature",
  "properties": {
    "gn:admin1_code":"10.0",
    "gn:asciiname":"Samson Mulambya",
    "gn:country_code":"ZM",
    "gn:dem":857,
    "gn:feature_class":"P",
    "gn:feature_code":"PPL",
    "gn:name":"Samson Mulambya",
    "gn:population":0,
    "gn:timezone":"Africa/Lusaka",
    "iso:country":"ZM",
    "name:und_x_variant":[
        "Samson Mulamba",
        "Samson Mulambya"
    ],
    "wof:name":"Samson Mulambya",
    "wof:placetype":"locality"
},
  "geometry": {"coordinates":[33.01667,-10.16667],"type":"Point"}
}