{
  "type": "Feature",
  "properties": {
    "gn:admin1_code":"3.0",
    "gn:asciiname":"Tambarala",
    "gn:country_code":"ZM",
    "gn:dem":1302,
    "gn:feature_class":"P",
    "gn:feature_code":"PPL",
    "gn:name":"Tambarala",
    "gn:population":0,
    "gn:timezone":"Africa/Lusaka",
    "iso:country":"ZM",
    "wof:name":"Tambarala",
    "wof:placetype":"locality"
},
  "geometry": {"coordinates":[33.44512,-12.34522],"type":"Point"}
}