{
  "type": "Feature",
  "properties": {
    "gn:admin1_code":"1.0",
    "gn:asciiname":"Shamanga",
    "gn:country_code":"ZM",
    "gn:dem":1157,
    "gn:feature_class":"P",
    "gn:feature_code":"PPL",
    "gn:name":"Shamanga",
    "gn:population":0,
    "gn:timezone":"Africa/Lusaka",
    "iso:country":"ZM",
    "wof:name":"Shamanga",
    "wof:placetype":"locality"
},
  "geometry": {"coordinates":[24.88172,-14.90853],"type":"Point"}
}