{
  "type": "Feature",
  "properties": {
    "gn:admin1_code":"10.0",
    "gn:asciiname":"Mutuna",
    "gn:country_code":"ZM",
    "gn:dem":1112,
    "gn:feature_class":"P",
    "gn:feature_code":"PPL",
    "gn:name":"Mutuna",
    "gn:population":0,
    "gn:timezone":"Africa/Lusaka",
    "iso:country":"ZM",
    "name:und_x_variant":[
        "Motuna",
        "Mutuna"
    ],
    "wof:name":"Mutuna",
    "wof:placetype":"locality"
},
  "geometry": {"coordinates":[31.91667,-11.76667],"type":"Point"}
}