{
  "type": "Feature",
  "properties": {
    "gn:admin1_code":"1.0",
    "gn:asciiname":"Tukumina",
    "gn:country_code":"ZM",
    "gn:dem":1141,
    "gn:feature_class":"P",
    "gn:feature_code":"PPL",
    "gn:name":"Tukumina",
    "gn:population":0,
    "gn:timezone":"Africa/Lusaka",
    "iso:country":"ZM",
    "wof:name":"Tukumina",
    "wof:placetype":"locality"
},
  "geometry": {"coordinates":[24.45,-14.63333],"type":"Point"}
}