{
  "type": "Feature",
  "properties": {
    "gn:admin1_code":"2.0",
    "gn:asciiname":"Sibune",
    "gn:country_code":"ZM",
    "gn:dem":1594,
    "gn:feature_class":"P",
    "gn:feature_code":"PPL",
    "gn:name":"Sibune",
    "gn:population":0,
    "gn:timezone":"Africa/Lusaka",
    "iso:country":"ZM",
    "wof:name":"Sibune",
    "wof:placetype":"locality"
},
  "geometry": {"coordinates":[30.7885,-13.09625],"type":"Point"}
}