{
  "type": "Feature",
  "properties": {
    "gn:admin1_code":"3.0",
    "gn:asciiname":"Sawaza",
    "gn:country_code":"ZM",
    "gn:dem":886,
    "gn:feature_class":"P",
    "gn:feature_code":"PPL",
    "gn:name":"Sawaza",
    "gn:population":0,
    "gn:timezone":"Africa/Lusaka",
    "iso:country":"ZM",
    "wof:name":"Sawaza",
    "wof:placetype":"locality"
},
  "geometry": {"coordinates":[32.37867,-13.57307],"type":"Point"}
}