{
  "type": "Feature",
  "properties": {
    "gn:admin1_code":"7.0",
    "gn:asciiname":"Belemu",
    "gn:country_code":"ZM",
    "gn:dem":998,
    "gn:feature_class":"P",
    "gn:feature_code":"PPL",
    "gn:name":"Belemu",
    "gn:population":0,
    "gn:timezone":"Africa/Lusaka",
    "iso:country":"ZM",
    "wof:name":"Belemu",
    "wof:placetype":"locality"
},
  "geometry": {"coordinates":[25.54924,-17.42452],"type":"Point"}
}