{
  "type": "Feature",
  "properties": {
    "gn:admin1_code":"3.0",
    "gn:asciiname":"Mwase",
    "gn:country_code":"ZM",
    "gn:dem":1190,
    "gn:feature_class":"P",
    "gn:feature_code":"PPL",
    "gn:name":"Mwase",
    "gn:population":0,
    "gn:timezone":"Africa/Lusaka",
    "iso:country":"ZM",
    "wof:name":"Mwase",
    "wof:placetype":"locality"
},
  "geometry": {"coordinates":[33.31667,-12.45],"type":"Point"}
}