{
  "type": "Feature",
  "properties": {
    "gn:admin1_code":"5.0",
    "gn:asciiname":"Museshya",
    "gn:country_code":"ZM",
    "gn:dem":938,
    "gn:feature_class":"P",
    "gn:feature_code":"PPL",
    "gn:name":"Museshya",
    "gn:population":0,
    "gn:timezone":"Africa/Lusaka",
    "iso:country":"ZM",
    "name:und_x_variant":[
        "Musesha",
        "Museshya"
    ],
    "wof:name":"Museshya",
    "wof:placetype":"locality"
},
  "geometry": {"coordinates":[29.43333,-8.96667],"type":"Point"}
}