{
  "type": "Feature",
  "properties": {
    "gn:admin1_code":"3.0",
    "gn:asciiname":"Kabeza",
    "gn:country_code":"ZM",
    "gn:dem":920,
    "gn:feature_class":"P",
    "gn:feature_code":"PPL",
    "gn:name":"Kabeza",
    "gn:population":0,
    "gn:timezone":"Africa/Lusaka",
    "iso:country":"ZM",
    "wof:name":"Kabeza",
    "wof:placetype":"locality"
},
  "geometry": {"coordinates":[31.07154,-14.57498],"type":"Point"}
}