{
  "type": "Feature",
  "properties": {
    "gn:admin1_code":"5.0",
    "gn:asciiname":"Mwafi",
    "gn:country_code":"ZM",
    "gn:dem":1365,
    "gn:feature_class":"P",
    "gn:feature_code":"PPL",
    "gn:name":"Mwafi",
    "gn:population":0,
    "gn:timezone":"Africa/Lusaka",
    "iso:country":"ZM",
    "wof:name":"Mwafi",
    "wof:placetype":"locality"
},
  "geometry": {"coordinates":[31.15273,-10.03174],"type":"Point"}
}