{
  "type": "Feature",
  "properties": {
    "gn:admin1_code":"9.0",
    "gn:asciiname":"Chipungu",
    "gn:country_code":"ZM",
    "gn:dem":1118,
    "gn:feature_class":"P",
    "gn:feature_code":"PPL",
    "gn:name":"Chipungu",
    "gn:population":0,
    "gn:timezone":"Africa/Lusaka",
    "iso:country":"ZM",
    "wof:name":"Chipungu",
    "wof:placetype":"locality"
},
  "geometry": {"coordinates":[29.05188,-15.35587],"type":"Point"}
}