{
  "type": "Feature",
  "properties": {
    "gn:admin1_code":"3.0",
    "gn:asciiname":"Kayanzya",
    "gn:country_code":"ZM",
    "gn:dem":968,
    "gn:feature_class":"P",
    "gn:feature_code":"PPL",
    "gn:name":"Kayanzya",
    "gn:population":0,
    "gn:timezone":"Africa/Lusaka",
    "iso:country":"ZM",
    "wof:name":"Kayanzya",
    "wof:placetype":"locality"
},
  "geometry": {"coordinates":[31.38333,-14.43333],"type":"Point"}
}