{
  "type": "Feature",
  "properties": {
    "gn:admin1_code":"10.0",
    "gn:asciiname":"Kambwe",
    "gn:country_code":"ZM",
    "gn:dem":1443,
    "gn:feature_class":"P",
    "gn:feature_code":"PPL",
    "gn:name":"Kambwe",
    "gn:population":0,
    "gn:timezone":"Africa/Lusaka",
    "iso:country":"ZM",
    "name:und_x_variant":[
        "Kaambwe",
        "Kambwe"
    ],
    "wof:name":"Kambwe",
    "wof:placetype":"locality"
},
  "geometry": {"coordinates":[32.86667,-9.45],"type":"Point"}
}