{
  "type": "Feature",
  "properties": {
    "gn:admin1_code":"2.0",
    "gn:asciiname":"David Mufakala",
    "gn:country_code":"ZM",
    "gn:dem":1599,
    "gn:feature_class":"P",
    "gn:feature_code":"PPL",
    "gn:name":"David Mufakala",
    "gn:population":0,
    "gn:timezone":"Africa/Lusaka",
    "iso:country":"ZM",
    "wof:name":"David Mufakala",
    "wof:placetype":"locality"
},
  "geometry": {"coordinates":[30.95055,-13.02198],"type":"Point"}
}