{
  "type": "Feature",
  "properties": {
    "gn:admin1_code":"9.0",
    "gn:asciiname":"Turners",
    "gn:country_code":"ZM",
    "gn:dem":1276,
    "gn:feature_class":"P",
    "gn:feature_code":"PPL",
    "gn:name":"Turners",
    "gn:population":0,
    "gn:timezone":"Africa/Lusaka",
    "iso:country":"ZM",
    "name:ara_x_preferred":[
        "\u062a\u0648\u0631\u0646\u0631\u0632"
    ],
    "name:fra_x_preferred":[
        "Turnverein"
    ],
    "name:jpn_x_preferred":[
        "\u30c8\u30a5\u30eb\u30ca\u30fc"
    ],
    "wof:name":"Turners",
    "wof:placetype":"locality"
},
  "geometry": {"coordinates":[28.25,-15.45],"type":"Point"}
}