{
  "type": "Feature",
  "properties": {
    "gn:admin1_code":"2.0",
    "gn:asciiname":"Mwanamuweshi",
    "gn:country_code":"ZM",
    "gn:dem":1129,
    "gn:feature_class":"P",
    "gn:feature_code":"PPL",
    "gn:name":"Mwanamuweshi",
    "gn:population":0,
    "gn:timezone":"Africa/Lusaka",
    "iso:country":"ZM",
    "wof:name":"Mwanamuweshi",
    "wof:placetype":"locality"
},
  "geometry": {"coordinates":[27.31728,-14.09527],"type":"Point"}
}