{
  "type": "Feature",
  "properties": {
    "gn:admin1_code":"2.0",
    "gn:asciiname":"Franki Chisenga",
    "gn:country_code":"ZM",
    "gn:dem":1271,
    "gn:feature_class":"P",
    "gn:feature_code":"PPL",
    "gn:name":"Franki Chisenga",
    "gn:population":0,
    "gn:timezone":"Africa/Lusaka",
    "iso:country":"ZM",
    "wof:name":"Franki Chisenga",
    "wof:placetype":"locality"
},
  "geometry": {"coordinates":[30.28047,-12.86792],"type":"Point"}
}