{
  "type": "Feature",
  "properties": {
    "gn:admin1_code":"1.0",
    "gn:asciiname":"Malala",
    "gn:country_code":"ZM",
    "gn:dem":1089,
    "gn:feature_class":"P",
    "gn:feature_code":"PPL",
    "gn:name":"Malala",
    "gn:population":0,
    "gn:timezone":"Africa/Lusaka",
    "iso:country":"ZM",
    "wof:name":"Malala",
    "wof:placetype":"locality"
},
  "geometry": {"coordinates":[24.81816,-16.28834],"type":"Point"}
}