{
  "type": "Feature",
  "properties": {
    "gn:admin1_code":"2.0",
    "gn:asciiname":"Chesenga Kasoma",
    "gn:country_code":"ZM",
    "gn:dem":1466,
    "gn:feature_class":"P",
    "gn:feature_code":"PPL",
    "gn:name":"Chesenga Kasoma",
    "gn:population":0,
    "gn:timezone":"Africa/Lusaka",
    "iso:country":"ZM",
    "wof:name":"Chesenga Kasoma",
    "wof:placetype":"locality"
},
  "geometry": {"coordinates":[30.43536,-13.20925],"type":"Point"}
}