{
  "type": "Feature",
  "properties": {
    "gn:admin1_code":"1.0",
    "gn:asciiname":"Kufukeka",
    "gn:country_code":"ZM",
    "gn:dem":1029,
    "gn:feature_class":"P",
    "gn:feature_code":"PPL",
    "gn:name":"Kufukeka",
    "gn:population":0,
    "gn:timezone":"Africa/Lusaka",
    "iso:country":"ZM",
    "wof:name":"Kufukeka",
    "wof:placetype":"locality"
},
  "geometry": {"coordinates":[22.31667,-16.21667],"type":"Point"}
}