{
  "type": "Feature",
  "properties": {
    "gn:admin1_code":"7.0",
    "gn:asciiname":"Shikabuwa",
    "gn:country_code":"ZM",
    "gn:dem":986,
    "gn:feature_class":"P",
    "gn:feature_code":"PPL",
    "gn:name":"Shikabuwa",
    "gn:population":0,
    "gn:timezone":"Africa/Lusaka",
    "iso:country":"ZM",
    "wof:name":"Shikabuwa",
    "wof:placetype":"locality"
},
  "geometry": {"coordinates":[26.93053,-15.4503],"type":"Point"}
}