{
  "type": "Feature",
  "properties": {
    "gn:admin1_code":"5.0",
    "gn:asciiname":"Mulenga",
    "gn:country_code":"ZM",
    "gn:dem":1534,
    "gn:feature_class":"P",
    "gn:feature_code":"PPL",
    "gn:name":"Mulenga",
    "gn:population":0,
    "gn:timezone":"Africa/Lusaka",
    "iso:country":"ZM",
    "wof:name":"Mulenga",
    "wof:placetype":"locality"
},
  "geometry": {"coordinates":[31.19194,-9.49793],"type":"Point"}
}