{
  "type": "Feature",
  "properties": {
    "gn:admin1_code":"4.0",
    "gn:asciiname":"Mupoposhi",
    "gn:country_code":"ZM",
    "gn:dem":1196,
    "gn:feature_class":"P",
    "gn:feature_code":"PPL",
    "gn:name":"Mupoposhi",
    "gn:population":0,
    "gn:timezone":"Africa/Lusaka",
    "iso:country":"ZM",
    "wof:name":"Mupoposhi",
    "wof:placetype":"locality"
},
  "geometry": {"coordinates":[29.46667,-9.65],"type":"Point"}
}