{
  "type": "Feature",
  "properties": {
    "gn:admin1_code":"3.0",
    "gn:asciiname":"Kandule",
    "gn:country_code":"ZM",
    "gn:dem":778,
    "gn:feature_class":"P",
    "gn:feature_code":"PPL",
    "gn:name":"Kandule",
    "gn:population":0,
    "gn:timezone":"Africa/Lusaka",
    "iso:country":"ZM",
    "wof:name":"Kandule",
    "wof:placetype":"locality"
},
  "geometry": {"coordinates":[30.8847,-14.47413],"type":"Point"}
}