{
  "type": "Feature",
  "properties": {
    "gn:admin1_code":"10.0",
    "gn:asciiname":"Chikwanda",
    "gn:country_code":"ZM",
    "gn:dem":1374,
    "gn:feature_class":"P",
    "gn:feature_code":"PPL",
    "gn:name":"Chikwanda",
    "gn:population":0,
    "gn:timezone":"Africa/Lusaka",
    "iso:country":"ZM",
    "wof:name":"Chikwanda",
    "wof:placetype":"locality"
},
  "geometry": {"coordinates":[32.73333,-10.06667],"type":"Point"}
}