{
  "type": "Feature",
  "properties": {
    "gn:admin1_code":"1.0",
    "gn:asciiname":"Mwanaliongolo",
    "gn:country_code":"ZM",
    "gn:dem":971,
    "gn:feature_class":"P",
    "gn:feature_code":"PPL",
    "gn:name":"Mwanaliongolo",
    "gn:population":0,
    "gn:timezone":"Africa/Lusaka",
    "iso:country":"ZM",
    "wof:name":"Mwanaliongolo",
    "wof:placetype":"locality"
},
  "geometry": {"coordinates":[24.06667,-17.06667],"type":"Point"}
}