{
  "type": "Feature",
  "properties": {
    "gn:admin1_code":"1.0",
    "gn:asciiname":"Lilapo",
    "gn:country_code":"ZM",
    "gn:dem":1015,
    "gn:feature_class":"P",
    "gn:feature_code":"PPL",
    "gn:name":"Lilapo",
    "gn:population":0,
    "gn:timezone":"Africa/Lusaka",
    "iso:country":"ZM",
    "wof:name":"Lilapo",
    "wof:placetype":"locality"
},
  "geometry": {"coordinates":[22.56667,-16.63332999999999],"type":"Point"}
}