{
  "type": "Feature",
  "properties": {
    "gn:admin1_code":"10.0",
    "gn:asciiname":"Muyeteka",
    "gn:country_code":"ZM",
    "gn:dem":813,
    "gn:feature_class":"P",
    "gn:feature_code":"PPL",
    "gn:name":"Muyeteka",
    "gn:population":0,
    "gn:timezone":"Africa/Lusaka",
    "iso:country":"ZM",
    "name:und_x_variant":[
        "Muyeleka",
        "Muyeteka"
    ],
    "wof:name":"Muyeteka",
    "wof:placetype":"locality"
},
  "geometry": {"coordinates":[33.04848,-10.15778],"type":"Point"}
}