{
  "type": "Feature",
  "properties": {
    "gn:admin1_code":"2.0",
    "gn:asciiname":"Dixon Malwita",
    "gn:country_code":"ZM",
    "gn:dem":1573,
    "gn:feature_class":"P",
    "gn:feature_code":"PPL",
    "gn:name":"Dixon Malwita",
    "gn:population":0,
    "gn:timezone":"Africa/Lusaka",
    "iso:country":"ZM",
    "wof:name":"Dixon Malwita",
    "wof:placetype":"locality"
},
  "geometry": {"coordinates":[30.81508,-13.13615],"type":"Point"}
}