{
  "type": "Feature",
  "properties": {
    "gn:admin1_code":"2.0",
    "gn:asciiname":"Lupenga",
    "gn:country_code":"ZM",
    "gn:dem":1173,
    "gn:feature_class":"P",
    "gn:feature_code":"PPL",
    "gn:name":"Lupenga",
    "gn:population":0,
    "gn:timezone":"Africa/Lusaka",
    "iso:country":"ZM",
    "wof:name":"Lupenga",
    "wof:placetype":"locality"
},
  "geometry": {"coordinates":[28.4013,-13.89066],"type":"Point"}
}