{
  "type": "Feature",
  "properties": {
    "gn:admin1_code":"5.0",
    "gn:asciiname":"Lyapa Kapaso",
    "gn:country_code":"ZM",
    "gn:dem":1345,
    "gn:feature_class":"P",
    "gn:feature_code":"PPL",
    "gn:name":"Lyapa Kapaso",
    "gn:population":0,
    "gn:timezone":"Africa/Lusaka",
    "iso:country":"ZM",
    "name:und_x_variant":[
        "Lyapa Kapasu",
        "Lyapa Kapaso"
    ],
    "wof:name":"Lyapa Kapaso",
    "wof:placetype":"locality"
},
  "geometry": {"coordinates":[30.93333,-8.95],"type":"Point"}
}