{
  "type": "Feature",
  "properties": {
    "gn:admin1_code":"8.0",
    "gn:asciiname":"Pitila",
    "gn:country_code":"ZM",
    "gn:dem":1250,
    "gn:feature_class":"P",
    "gn:feature_code":"PPL",
    "gn:name":"Pitila",
    "gn:population":0,
    "gn:timezone":"Africa/Lusaka",
    "iso:country":"ZM",
    "wof:name":"Pitila",
    "wof:placetype":"locality"
},
  "geometry": {"coordinates":[28.66325,-12.88108],"type":"Point"}
}