{
  "type": "Feature",
  "properties": {
    "gn:admin1_code":"1.0",
    "gn:asciiname":"Sakamata",
    "gn:country_code":"ZM",
    "gn:dem":1164,
    "gn:feature_class":"P",
    "gn:feature_code":"PPL",
    "gn:name":"Sakamata",
    "gn:population":0,
    "gn:timezone":"Africa/Lusaka",
    "iso:country":"ZM",
    "wof:name":"Sakamata",
    "wof:placetype":"locality"
},
  "geometry": {"coordinates":[24.85,-16.26667],"type":"Point"}
}