{
  "type": "Feature",
  "properties": {
    "gn:admin1_code":"3.0",
    "gn:asciiname":"Chonzola",
    "gn:country_code":"ZM",
    "gn:dem":587,
    "gn:feature_class":"P",
    "gn:feature_code":"PPL",
    "gn:name":"Chonzola",
    "gn:population":0,
    "gn:timezone":"Africa/Lusaka",
    "iso:country":"ZM",
    "wof:name":"Chonzola",
    "wof:placetype":"locality"
},
  "geometry": {"coordinates":[31.92385,-13.39813],"type":"Point"}
}