{
  "type": "Feature",
  "properties": {
    "gn:admin1_code":"1.0",
    "gn:asciiname":"Ndandanga",
    "gn:country_code":"ZM",
    "gn:dem":1096,
    "gn:feature_class":"P",
    "gn:feature_code":"PPL",
    "gn:name":"Ndandanga",
    "gn:population":0,
    "gn:timezone":"Africa/Lusaka",
    "iso:country":"ZM",
    "wof:name":"Ndandanga",
    "wof:placetype":"locality"
},
  "geometry": {"coordinates":[24.48333,-15.06667],"type":"Point"}
}