{
  "type": "Feature",
  "properties": {
    "gn:admin1_code":"3.0",
    "gn:asciiname":"Karenga",
    "gn:country_code":"ZM",
    "gn:dem":856,
    "gn:feature_class":"P",
    "gn:feature_code":"PPL",
    "gn:name":"Karenga",
    "gn:population":0,
    "gn:timezone":"Africa/Lusaka",
    "iso:country":"ZM",
    "wof:name":"Karenga",
    "wof:placetype":"locality"
},
  "geometry": {"coordinates":[31.79208,-13.97413],"type":"Point"}
}