{
  "type": "Feature",
  "properties": {
    "gn:admin1_code":"5.0",
    "gn:asciiname":"Samamba",
    "gn:country_code":"ZM",
    "gn:dem":1515,
    "gn:feature_class":"P",
    "gn:feature_code":"PPL",
    "gn:name":"Samamba",
    "gn:population":0,
    "gn:timezone":"Africa/Lusaka",
    "iso:country":"ZM",
    "wof:name":"Samamba",
    "wof:placetype":"locality"
},
  "geometry": {"coordinates":[31.78222,-9.38088],"type":"Point"}
}