{
  "type": "Feature",
  "properties": {
    "gn:admin1_code":"3.0",
    "gn:asciiname":"Ntambazina",
    "gn:country_code":"ZM",
    "gn:dem":959,
    "gn:feature_class":"P",
    "gn:feature_code":"PPL",
    "gn:name":"Ntambazina",
    "gn:population":0,
    "gn:timezone":"Africa/Lusaka",
    "iso:country":"ZM",
    "name:und_x_variant":[
        "Nthambazina",
        "Ntambazina"
    ],
    "wof:name":"Ntambazina",
    "wof:placetype":"locality"
},
  "geometry": {"coordinates":[32.66667,-13.43333],"type":"Point"}
}