{
  "type": "Feature",
  "properties": {
    "gn:admin1_code":"2.0",
    "gn:asciiname":"Sekayo",
    "gn:country_code":"ZM",
    "gn:dem":1448,
    "gn:feature_class":"P",
    "gn:feature_code":"PPL",
    "gn:name":"Sekayo",
    "gn:population":0,
    "gn:timezone":"Africa/Lusaka",
    "iso:country":"ZM",
    "wof:name":"Sekayo",
    "wof:placetype":"locality"
},
  "geometry": {"coordinates":[30.38703,-13.01499],"type":"Point"}
}