{
  "type": "Feature",
  "properties": {
    "gn:admin1_code":"5.0",
    "gn:asciiname":"Kasakalawe",
    "gn:country_code":"ZM",
    "gn:dem":801,
    "gn:feature_class":"P",
    "gn:feature_code":"PPL",
    "gn:name":"Kasakalawe",
    "gn:population":0,
    "gn:timezone":"Africa/Lusaka",
    "iso:country":"ZM",
    "wof:name":"Kasakalawe",
    "wof:placetype":"locality"
},
  "geometry": {"coordinates":[31.08333,-8.78333],"type":"Point"}
}