{
  "type": "Feature",
  "properties": {
    "gn:admin1_code":"2.0",
    "gn:asciiname":"Nandolesha",
    "gn:country_code":"ZM",
    "gn:dem":1351,
    "gn:feature_class":"P",
    "gn:feature_code":"PPL",
    "gn:name":"Nandolesha",
    "gn:population":0,
    "gn:timezone":"Africa/Lusaka",
    "iso:country":"ZM",
    "wof:name":"Nandolesha",
    "wof:placetype":"locality"
},
  "geometry": {"coordinates":[30.41132,-12.74146],"type":"Point"}
}