{
  "type": "Feature",
  "properties": {
    "gn:admin1_code":"3.0",
    "gn:asciiname":"Mayekeya",
    "gn:country_code":"ZM",
    "gn:dem":1193,
    "gn:feature_class":"P",
    "gn:feature_code":"PPL",
    "gn:name":"Mayekeya",
    "gn:population":0,
    "gn:timezone":"Africa/Lusaka",
    "iso:country":"ZM",
    "wof:name":"Mayekeya",
    "wof:placetype":"locality"
},
  "geometry": {"coordinates":[33.31667,-12.36667],"type":"Point"}
}