{
  "type": "Feature",
  "properties": {
    "gn:admin1_code":"1.0",
    "gn:asciiname":"Kabila",
    "gn:country_code":"ZM",
    "gn:dem":1106,
    "gn:feature_class":"P",
    "gn:feature_code":"PPL",
    "gn:name":"Kabila",
    "gn:population":0,
    "gn:timezone":"Africa/Lusaka",
    "iso:country":"ZM",
    "wof:name":"Kabila",
    "wof:placetype":"locality"
},
  "geometry": {"coordinates":[24.11667000000001,-15.46667],"type":"Point"}
}