{
  "type": "Feature",
  "properties": {
    "gn:admin1_code":"1.0",
    "gn:asciiname":"Kabila",
    "gn:country_code":"ZM",
    "gn:dem":1106,
    "gn:feature_class":"P",
    "gn:feature_code":"PPL",
    "gn:name":"Kabila",
    "gn:population":0,
    "gn:timezone":"Africa/Lusaka",
    "iso:country":"ZM",
    "name:ceb_x_preferred":[
        "Kabila"
    ],
    "name:ces_x_preferred":[
        "Kabila"
    ],
    "name:deu_x_preferred":[
        "Kabila"
    ],
    "name:est_x_preferred":[
        "Kabila"
    ],
    "name:fra_x_preferred":[
        "Kabila"
    ],
    "name:nds_x_preferred":[
        "Kabila"
    ],
    "name:nld_x_preferred":[
        "Kabila"
    ],
    "name:pol_x_preferred":[
        "Kabila"
    ],
    "name:por_x_preferred":[
        "Kabila"
    ],
    "name:rus_x_preferred":[
        "\u041a\u0430\u0431\u0438\u043b\u0430"
    ],
    "name:sco_x_preferred":[
        "Kabila"
    ],
    "name:slk_x_preferred":[
        "Kabila"
    ],
    "name:swe_x_preferred":[
        "Kabila"
    ],
    "name:vol_x_preferred":[
        "Kabila"
    ],
    "name:zho_x_preferred":[
        "\u5361\u6bd4\u62c9"
    ],
    "wof:name":"Kabila",
    "wof:placetype":"locality"
},
  "geometry": {"coordinates":[24.11667000000001,-15.46667],"type":"Point"}
}