{
  "type": "Feature",
  "properties": {
    "gn:admin1_code":"1.0",
    "gn:asciiname":"Benda",
    "gn:country_code":"ZM",
    "gn:dem":1127,
    "gn:feature_class":"P",
    "gn:feature_code":"PPL",
    "gn:name":"Benda",
    "gn:population":0,
    "gn:timezone":"Africa/Lusaka",
    "iso:country":"ZM",
    "name:cat_x_preferred":[
        "Benda"
    ],
    "name:ceb_x_preferred":[
        "Benda"
    ],
    "name:ces_x_preferred":[
        "Benda"
    ],
    "name:deu_x_preferred":[
        "Benda"
    ],
    "name:eus_x_preferred":[
        "Benda"
    ],
    "name:fra_x_preferred":[
        "Benda"
    ],
    "name:glg_x_preferred":[
        "Benda"
    ],
    "name:heb_x_preferred":[
        "\u05d1\u05e0\u05d3\u05d4"
    ],
    "name:ind_x_preferred":[
        "Benda"
    ],
    "name:ita_x_preferred":[
        "Benda"
    ],
    "name:jpn_x_preferred":[
        "\u30d9\u30f3\u30c0"
    ],
    "name:nld_x_preferred":[
        "Benda"
    ],
    "name:pol_x_preferred":[
        "Benda"
    ],
    "name:por_x_preferred":[
        "Benda"
    ],
    "name:rus_x_preferred":[
        "\u0411\u0435\u043d\u0434\u0430"
    ],
    "name:slv_x_preferred":[
        "Benda"
    ],
    "name:swe_x_preferred":[
        "Benda"
    ],
    "name:ukr_x_preferred":[
        "\u0411\u0435\u043d\u0434\u0430"
    ],
    "wof:name":"Benda",
    "wof:placetype":"locality"
},
  "geometry": {"coordinates":[23.95,-14.68333],"type":"Point"}
}