{
  "type": "Feature",
  "properties": {
    "gn:admin1_code":"2.0",
    "gn:asciiname":"Kate Kisenga",
    "gn:country_code":"ZM",
    "gn:dem":1302,
    "gn:feature_class":"P",
    "gn:feature_code":"PPL",
    "gn:name":"Kate Kisenga",
    "gn:population":0,
    "gn:timezone":"Africa/Lusaka",
    "iso:country":"ZM",
    "wof:name":"Kate Kisenga",
    "wof:placetype":"locality"
},
  "geometry": {"coordinates":[30.34115,-12.80767],"type":"Point"}
}