{
  "type": "Feature",
  "properties": {
    "gn:admin1_code":"3.0",
    "gn:asciiname":"Duwulu",
    "gn:country_code":"ZM",
    "gn:dem":1170,
    "gn:feature_class":"P",
    "gn:feature_code":"PPL",
    "gn:name":"Duwulu",
    "gn:population":0,
    "gn:timezone":"Africa/Lusaka",
    "iso:country":"ZM",
    "wof:name":"Duwulu",
    "wof:placetype":"locality"
},
  "geometry": {"coordinates":[33.25,-12.38333],"type":"Point"}
}