{
  "type": "Feature",
  "properties": {
    "gn:admin1_code":"6.0",
    "gn:asciiname":"Sanjongo",
    "gn:country_code":"ZM",
    "gn:dem":1054,
    "gn:feature_class":"P",
    "gn:feature_code":"PPL",
    "gn:name":"Sanjongo",
    "gn:population":0,
    "gn:timezone":"Africa/Lusaka",
    "iso:country":"ZM",
    "name:und_x_variant":[
        "Sanjonjo",
        "Sanjongo"
    ],
    "wof:name":"Sanjongo",
    "wof:placetype":"locality"
},
  "geometry": {"coordinates":[22.66641,-13.0732],"type":"Point"}
}