{
  "type": "Feature",
  "properties": {
    "gn:admin1_code":"1.0",
    "gn:asciiname":"Muketwa",
    "gn:country_code":"ZM",
    "gn:dem":1009,
    "gn:feature_class":"P",
    "gn:feature_code":"PPL",
    "gn:name":"Muketwa",
    "gn:population":0,
    "gn:timezone":"Africa/Lusaka",
    "iso:country":"ZM",
    "wof:name":"Muketwa",
    "wof:placetype":"locality"
},
  "geometry": {"coordinates":[24.41667,-17.38332999999999],"type":"Point"}
}