{
  "type": "Feature",
  "properties": {
    "gn:admin1_code":"5.0",
    "gn:asciiname":"Kawimbe",
    "gn:country_code":"ZM",
    "gn:dem":1691,
    "gn:feature_class":"P",
    "gn:feature_code":"PPL",
    "gn:name":"Kawimbe",
    "gn:population":0,
    "gn:timezone":"Africa/Lusaka",
    "iso:country":"ZM",
    "wof:name":"Kawimbe",
    "wof:placetype":"locality"
},
  "geometry": {"coordinates":[31.52506,-8.82699],"type":"Point"}
}