{
  "type": "Feature",
  "properties": {
    "gn:admin1_code":"1.0",
    "gn:asciiname":"Munyambale",
    "gn:country_code":"ZM",
    "gn:dem":1075,
    "gn:feature_class":"P",
    "gn:feature_code":"PPL",
    "gn:name":"Munyambale",
    "gn:population":0,
    "gn:timezone":"Africa/Lusaka",
    "iso:country":"ZM",
    "wof:name":"Munyambale",
    "wof:placetype":"locality"
},
  "geometry": {"coordinates":[24.63333,-14.01667],"type":"Point"}
}