{
  "type": "Feature",
  "properties": {
    "gn:admin1_code":"10.0",
    "gn:asciiname":"Marandika",
    "gn:country_code":"ZM",
    "gn:dem":1102,
    "gn:feature_class":"P",
    "gn:feature_code":"PPL",
    "gn:name":"Marandika",
    "gn:population":0,
    "gn:timezone":"Africa/Lusaka",
    "iso:country":"ZM",
    "name:und_x_variant":[
        "Malindika",
        "Marandika"
    ],
    "wof:name":"Marandika",
    "wof:placetype":"locality"
},
  "geometry": {"coordinates":[33.12917,-11.76448],"type":"Point"}
}