{
  "type": "Feature",
  "properties": {
    "gn:admin1_code":"9.0",
    "gn:asciiname":"Mbofwana",
    "gn:country_code":"ZM",
    "gn:dem":612,
    "gn:feature_class":"P",
    "gn:feature_code":"PPL",
    "gn:name":"Mbofwana",
    "gn:population":0,
    "gn:timezone":"Africa/Lusaka",
    "iso:country":"ZM",
    "wof:name":"Mbofwana",
    "wof:placetype":"locality"
},
  "geometry": {"coordinates":[29.81667,-15.18333],"type":"Point"}
}