{
  "type": "Feature",
  "properties": {
    "gn:admin1_code":"10.0",
    "gn:asciiname":"Tunduwa",
    "gn:country_code":"ZM",
    "gn:dem":1315,
    "gn:feature_class":"P",
    "gn:feature_code":"PPL",
    "gn:name":"Tunduwa",
    "gn:population":0,
    "gn:timezone":"Africa/Lusaka",
    "iso:country":"ZM",
    "name:und_x_variant":[
        "Tundua",
        "Tunduwa"
    ],
    "wof:name":"Tunduwa",
    "wof:placetype":"locality"
},
  "geometry": {"coordinates":[31.16667,-11.81667],"type":"Point"}
}