{
  "type": "Feature",
  "properties": {
    "gn:admin1_code":"7.0",
    "gn:admin2_code":"9072525",
    "gn:asciiname":"Sinazeze",
    "gn:country_code":"ZM",
    "gn:dem":576,
    "gn:feature_class":"P",
    "gn:feature_code":"PPL",
    "gn:name":"Sinazeze",
    "gn:population":0,
    "gn:timezone":"Africa/Lusaka",
    "iso:country":"ZM",
    "name:eng_x_preferred":[
        "Sinazeze"
    ],
    "name:eng_x_variant":[
        "Sinazezi"
    ],
    "wof:name":"Sinazeze",
    "wof:placetype":"locality"
},
  "geometry": {"coordinates":[27.40522,-17.14567000000001],"type":"Point"}
}