{
  "type": "Feature",
  "properties": {
    "gn:admin1_code":"3.0",
    "gn:asciiname":"Philip",
    "gn:country_code":"ZM",
    "gn:dem":873,
    "gn:feature_class":"P",
    "gn:feature_code":"PPL",
    "gn:name":"Philip",
    "gn:population":0,
    "gn:timezone":"Africa/Lusaka",
    "iso:country":"ZM",
    "wof:name":"Philip",
    "wof:placetype":"locality"
},
  "geometry": {"coordinates":[30.93333,-14.58333],"type":"Point"}
}