{
  "type": "Feature",
  "properties": {
    "gn:admin1_code":"3.0",
    "gn:asciiname":"Philip",
    "gn:country_code":"ZM",
    "gn:dem":873,
    "gn:feature_class":"P",
    "gn:feature_code":"PPL",
    "gn:name":"Philip",
    "gn:population":0,
    "gn:timezone":"Africa/Lusaka",
    "iso:country":"ZM",
    "name:aze_x_preferred":[
        "Filip"
    ],
    "name:bos_x_preferred":[
        "Philip"
    ],
    "name:bul_x_preferred":[
        "\u0424\u0438\u043b\u0438\u043f"
    ],
    "name:cat_x_preferred":[
        "Filip"
    ],
    "name:ceb_x_preferred":[
        "Philip"
    ],
    "name:cym_x_preferred":[
        "Philip"
    ],
    "name:deu_x_preferred":[
        "Filip"
    ],
    "name:fas_x_preferred":[
        "\u0641\u06cc\u0644\u06cc\u067e"
    ],
    "name:fra_x_preferred":[
        "Philip"
    ],
    "name:heb_x_preferred":[
        "\u05e4\u05d9\u05dc\u05d9\u05e4"
    ],
    "name:hye_x_preferred":[
        "\u0556\u056b\u056c\u056b\u057a"
    ],
    "name:ita_x_preferred":[
        "Filip"
    ],
    "name:jpn_x_preferred":[
        "\u30d5\u30a3\u30ea\u30c3\u30d7"
    ],
    "name:kat_x_preferred":[
        "\u10e4\u10d8\u10da\u10d8\u10de\u10d8"
    ],
    "name:mkd_x_preferred":[
        "\u0424\u0438\u043b\u0438\u043f"
    ],
    "name:nds_x_preferred":[
        "Filip"
    ],
    "name:ron_x_preferred":[
        "Filip"
    ],
    "name:rus_x_preferred":[
        "\u0424\u0438\u043b\u0438\u043f"
    ],
    "name:slk_x_preferred":[
        "Filip"
    ],
    "name:slv_x_preferred":[
        "Filip"
    ],
    "name:spa_x_preferred":[
        "Philip"
    ],
    "name:srp_x_preferred":[
        "\u0424\u0438\u043b\u0438\u043f"
    ],
    "name:tur_x_preferred":[
        "Filip"
    ],
    "name:ukr_x_preferred":[
        "\u0424\u0456\u043b\u0456\u043f"
    ],
    "wof:name":"Philip",
    "wof:placetype":"locality"
},
  "geometry": {"coordinates":[30.93333,-14.58333],"type":"Point"}
}