{
  "type": "Feature",
  "properties": {
    "gn:admin1_code":"1.0",
    "gn:asciiname":"Kaba Hill",
    "gn:country_code":"ZM",
    "gn:dem":1077,
    "gn:feature_class":"P",
    "gn:feature_code":"PPL",
    "gn:name":"Kaba Hill",
    "gn:population":0,
    "gn:timezone":"Africa/Lusaka",
    "iso:country":"ZM",
    "wof:name":"Kaba Hill",
    "wof:placetype":"locality"
},
  "geometry": {"coordinates":[23.6893,-14.81729],"type":"Point"}
}