{
  "type": "Feature",
  "properties": {
    "gn:admin1_code":"5.0",
    "gn:asciiname":"Mbazo",
    "gn:country_code":"ZM",
    "gn:dem":1520,
    "gn:feature_class":"P",
    "gn:feature_code":"PPL",
    "gn:name":"Mbazo",
    "gn:population":0,
    "gn:timezone":"Africa/Lusaka",
    "iso:country":"ZM",
    "wof:name":"Mbazo",
    "wof:placetype":"locality"
},
  "geometry": {"coordinates":[30.69261,-8.88036],"type":"Point"}
}