{
  "type": "Feature",
  "properties": {
    "gn:admin1_code":"3.0",
    "gn:asciiname":"Laban",
    "gn:country_code":"ZM",
    "gn:dem":1012,
    "gn:feature_class":"P",
    "gn:feature_code":"PPL",
    "gn:name":"Laban",
    "gn:population":0,
    "gn:timezone":"Africa/Lusaka",
    "iso:country":"ZM",
    "wof:name":"Laban",
    "wof:placetype":"locality"
},
  "geometry": {"coordinates":[32.71524,-13.44407],"type":"Point"}
}