{
  "type": "Feature",
  "properties": {
    "gn:admin1_code":"1.0",
    "gn:asciiname":"Simatongo",
    "gn:country_code":"ZM",
    "gn:dem":1039,
    "gn:feature_class":"P",
    "gn:feature_code":"PPL",
    "gn:name":"Simatongo",
    "gn:population":0,
    "gn:timezone":"Africa/Lusaka",
    "iso:country":"ZM",
    "wof:name":"Simatongo",
    "wof:placetype":"locality"
},
  "geometry": {"coordinates":[22.38333,-14.73333],"type":"Point"}
}