{
  "type": "Feature",
  "properties": {
    "gn:admin1_code":"10.0",
    "gn:asciiname":"Mungwiara",
    "gn:country_code":"ZM",
    "gn:dem":782,
    "gn:feature_class":"P",
    "gn:feature_code":"PPL",
    "gn:name":"Mungwiara",
    "gn:population":0,
    "gn:timezone":"Africa/Lusaka",
    "iso:country":"ZM",
    "wof:name":"Mungwiara",
    "wof:placetype":"locality"
},
  "geometry": {"coordinates":[33.15,-11.28333],"type":"Point"}
}