{
  "type": "Feature",
  "properties": {
    "gn:admin1_code":"10.0",
    "gn:asciiname":"Kaombwe",
    "gn:country_code":"ZM",
    "gn:dem":1442,
    "gn:feature_class":"P",
    "gn:feature_code":"PPL",
    "gn:name":"Kaombwe",
    "gn:population":0,
    "gn:timezone":"Africa/Lusaka",
    "iso:country":"ZM",
    "wof:name":"Kaombwe",
    "wof:placetype":"locality"
},
  "geometry": {"coordinates":[32.88214,-9.46021],"type":"Point"}
}