{
  "type": "Feature",
  "properties": {
    "gn:admin1_code":"3.0",
    "gn:asciiname":"Chiwaya",
    "gn:country_code":"ZM",
    "gn:dem":839,
    "gn:feature_class":"P",
    "gn:feature_code":"PPL",
    "gn:name":"Chiwaya",
    "gn:population":0,
    "gn:timezone":"Africa/Lusaka",
    "iso:country":"ZM",
    "name:und_x_variant":[
        "Chiwayu",
        "Chiwaya"
    ],
    "wof:name":"Chiwaya",
    "wof:placetype":"locality"
},
  "geometry": {"coordinates":[32.46189,-13.44649],"type":"Point"}
}