{
  "type": "Feature",
  "properties": {
    "gn:admin1_code":"10.0",
    "gn:asciiname":"Mpianakunda",
    "gn:country_code":"ZM",
    "gn:dem":671,
    "gn:feature_class":"P",
    "gn:feature_code":"PPL",
    "gn:name":"Mpianakunda",
    "gn:population":0,
    "gn:timezone":"Africa/Lusaka",
    "iso:country":"ZM",
    "wof:name":"Mpianakunda",
    "wof:placetype":"locality"
},
  "geometry": {"coordinates":[32.80349,-11.22845],"type":"Point"}
}