{
  "type": "Feature",
  "properties": {
    "gn:admin1_code":"3.0",
    "gn:asciiname":"Mwachalo",
    "gn:country_code":"ZM",
    "gn:dem":961,
    "gn:feature_class":"P",
    "gn:feature_code":"PPL",
    "gn:name":"Mwachalo",
    "gn:population":0,
    "gn:timezone":"Africa/Lusaka",
    "iso:country":"ZM",
    "name:und_x_variant":[
        "Mwachara",
        "Mwachalo"
    ],
    "wof:name":"Mwachalo",
    "wof:placetype":"locality"
},
  "geometry": {"coordinates":[31.06667,-14.36667],"type":"Point"}
}