{
  "type": "Feature",
  "properties": {
    "gn:admin1_code":"7.0",
    "gn:asciiname":"Muchanta",
    "gn:country_code":"ZM",
    "gn:dem":1044,
    "gn:feature_class":"P",
    "gn:feature_code":"PPL",
    "gn:name":"Muchanta",
    "gn:population":0,
    "gn:timezone":"Africa/Lusaka",
    "iso:country":"ZM",
    "wof:name":"Muchanta",
    "wof:placetype":"locality"
},
  "geometry": {"coordinates":[27.96667,-16.35],"type":"Point"}
}