{
  "type": "Feature",
  "properties": {
    "gn:admin1_code":"5.0",
    "gn:asciiname":"Luena",
    "gn:country_code":"ZM",
    "gn:dem":1204,
    "gn:feature_class":"P",
    "gn:feature_code":"PPL",
    "gn:name":"Luena",
    "gn:population":0,
    "gn:timezone":"Africa/Lusaka",
    "iso:country":"ZM",
    "wof:name":"Luena",
    "wof:placetype":"locality"
},
  "geometry": {"coordinates":[30.20517000000001,-10.65024],"type":"Point"}
}