{
  "type": "Feature",
  "properties": {
    "gn:admin1_code":"5.0",
    "gn:asciiname":"Luena",
    "gn:country_code":"ZM",
    "gn:dem":1204,
    "gn:feature_class":"P",
    "gn:feature_code":"PPL",
    "gn:name":"Luena",
    "gn:population":0,
    "gn:timezone":"Africa/Lusaka",
    "iso:country":"ZM",
    "name:ceb_x_preferred":[
        "Luena"
    ],
    "name:deu_x_preferred":[
        "Luena"
    ],
    "name:fra_x_preferred":[
        "Luena"
    ],
    "name:hun_x_preferred":[
        "Luena"
    ],
    "name:ita_x_preferred":[
        "Luena"
    ],
    "name:nld_x_preferred":[
        "Luena"
    ],
    "name:pol_x_preferred":[
        "Luena"
    ],
    "name:por_x_preferred":[
        "Luena"
    ],
    "name:rus_x_preferred":[
        "\u041b\u0443\u044d\u043d\u0430"
    ],
    "name:swe_x_preferred":[
        "Luena"
    ],
    "name:war_x_preferred":[
        "Luena"
    ],
    "wof:name":"Luena",
    "wof:placetype":"locality"
},
  "geometry": {"coordinates":[30.20517000000001,-10.65024],"type":"Point"}
}