{
  "type": "Feature",
  "properties": {
    "gn:admin1_code":"1.0",
    "gn:asciiname":"Kafukufuku",
    "gn:country_code":"ZM",
    "gn:dem":1056,
    "gn:feature_class":"P",
    "gn:feature_code":"PPL",
    "gn:name":"Kafukufuku",
    "gn:population":0,
    "gn:timezone":"Africa/Lusaka",
    "iso:country":"ZM",
    "wof:name":"Kafukufuku",
    "wof:placetype":"locality"
},
  "geometry": {"coordinates":[23.61667000000001,-14.05],"type":"Point"}
}