{
  "type": "Feature",
  "properties": {
    "gn:admin1_code":"1.0",
    "gn:asciiname":"Limbwembwele",
    "gn:country_code":"ZM",
    "gn:dem":1091,
    "gn:feature_class":"P",
    "gn:feature_code":"PPL",
    "gn:name":"Limbwembwele",
    "gn:population":0,
    "gn:timezone":"Africa/Lusaka",
    "iso:country":"ZM",
    "wof:name":"Limbwembwele",
    "wof:placetype":"locality"
},
  "geometry": {"coordinates":[24.13333,-13.93333],"type":"Point"}
}