{
  "type": "Feature",
  "properties": {
    "gn:admin1_code":"6.0",
    "gn:asciiname":"China",
    "gn:country_code":"ZM",
    "gn:dem":1297,
    "gn:feature_class":"P",
    "gn:feature_code":"PPL",
    "gn:name":"China",
    "gn:population":0,
    "gn:timezone":"Africa/Lusaka",
    "iso:country":"ZM",
    "wof:name":"China",
    "wof:placetype":"locality"
},
  "geometry": {"coordinates":[24.21667,-11.18333],"type":"Point"}
}