{
  "type": "Feature",
  "properties": {
    "gn:admin1_code":"4.0",
    "gn:asciiname":"Lubuko",
    "gn:country_code":"ZM",
    "gn:dem":1228,
    "gn:feature_class":"P",
    "gn:feature_code":"PPL",
    "gn:name":"Lubuko",
    "gn:population":0,
    "gn:timezone":"Africa/Lusaka",
    "iso:country":"ZM",
    "name:und_x_variant":[
        "Luwuko",
        "Lubuka",
        "Lubuko"
    ],
    "wof:name":"Lubuko",
    "wof:placetype":"locality"
},
  "geometry": {"coordinates":[28.99681,-11.23481],"type":"Point"}
}