{
  "type": "Feature",
  "properties": {
    "gn:admin1_code":"8.0",
    "gn:asciiname":"Fundi",
    "gn:country_code":"ZM",
    "gn:dem":1249,
    "gn:feature_class":"P",
    "gn:feature_code":"PPL",
    "gn:name":"Fundi",
    "gn:population":0,
    "gn:timezone":"Africa/Lusaka",
    "iso:country":"ZM",
    "name:ceb_x_preferred":[
        "Fundi"
    ],
    "name:deu_x_preferred":[
        "Fundi"
    ],
    "name:fra_x_preferred":[
        "Fundi"
    ],
    "name:swe_x_preferred":[
        "Fundi"
    ],
    "wof:name":"Fundi",
    "wof:placetype":"locality"
},
  "geometry": {"coordinates":[28.64602,-12.88667],"type":"Point"}
}