{
  "type": "Feature",
  "properties": {
    "gn:admin1_code":"3.0",
    "gn:asciiname":"Kawalika",
    "gn:country_code":"ZM",
    "gn:dem":585,
    "gn:feature_class":"P",
    "gn:feature_code":"PPL",
    "gn:name":"Kawalika",
    "gn:population":0,
    "gn:timezone":"Africa/Lusaka",
    "iso:country":"ZM",
    "wof:name":"Kawalika",
    "wof:placetype":"locality"
},
  "geometry": {"coordinates":[31.92496,-13.39007],"type":"Point"}
}