{
  "type": "Feature",
  "properties": {
    "gn:admin1_code":"2.0",
    "gn:asciiname":"Wile",
    "gn:country_code":"ZM",
    "gn:dem":1424,
    "gn:feature_class":"P",
    "gn:feature_code":"PPL",
    "gn:name":"Wile",
    "gn:population":0,
    "gn:timezone":"Africa/Lusaka",
    "iso:country":"ZM",
    "wof:name":"Wile",
    "wof:placetype":"locality"
},
  "geometry": {"coordinates":[30.65264,-13.16961],"type":"Point"}
}