{
  "type": "Feature",
  "properties": {
    "gn:admin1_code":"3.0",
    "gn:asciiname":"Samwele",
    "gn:country_code":"ZM",
    "gn:dem":928,
    "gn:feature_class":"P",
    "gn:feature_code":"PPL",
    "gn:name":"Samwele",
    "gn:population":0,
    "gn:timezone":"Africa/Lusaka",
    "iso:country":"ZM",
    "wof:name":"Samwele",
    "wof:placetype":"locality"
},
  "geometry": {"coordinates":[32.13333,-13.76667],"type":"Point"}
}