{
  "type": "Feature",
  "properties": {
    "gn:admin1_code":"2.0",
    "gn:asciiname":"Shambosi",
    "gn:country_code":"ZM",
    "gn:dem":998,
    "gn:feature_class":"P",
    "gn:feature_code":"PPL",
    "gn:name":"Shambosi",
    "gn:population":0,
    "gn:timezone":"Africa/Lusaka",
    "iso:country":"ZM",
    "wof:name":"Shambosi",
    "wof:placetype":"locality"
},
  "geometry": {"coordinates":[27.23333,-15.43333],"type":"Point"}
}