{
  "type": "Feature",
  "properties": {
    "gn:admin1_code":"7.0",
    "gn:asciiname":"Pokuma",
    "gn:country_code":"ZM",
    "gn:dem":1052,
    "gn:feature_class":"P",
    "gn:feature_code":"PPL",
    "gn:name":"Pokuma",
    "gn:population":0,
    "gn:timezone":"Africa/Lusaka",
    "iso:country":"ZM",
    "wof:name":"Pokuma",
    "wof:placetype":"locality"
},
  "geometry": {"coordinates":[26.76211,-17.78302],"type":"Point"}
}