{
  "type": "Feature",
  "properties": {
    "gn:admin1_code":"1.0",
    "gn:asciiname":"Kafula",
    "gn:country_code":"ZM",
    "gn:dem":1113,
    "gn:feature_class":"P",
    "gn:feature_code":"PPL",
    "gn:name":"Kafula",
    "gn:population":0,
    "gn:timezone":"Africa/Lusaka",
    "iso:country":"ZM",
    "wof:name":"Kafula",
    "wof:placetype":"locality"
},
  "geometry": {"coordinates":[24.06667,-15.08333],"type":"Point"}
}