{
  "type": "Feature",
  "properties": {
    "gn:admin1_code":"2.0",
    "gn:asciiname":"Bikilionde",
    "gn:country_code":"ZM",
    "gn:dem":1367,
    "gn:feature_class":"P",
    "gn:feature_code":"PPL",
    "gn:name":"Bikilionde",
    "gn:population":0,
    "gn:timezone":"Africa/Lusaka",
    "iso:country":"ZM",
    "wof:name":"Bikilionde",
    "wof:placetype":"locality"
},
  "geometry": {"coordinates":[30.6811,-13.18354],"type":"Point"}
}