{
  "type": "Feature",
  "properties": {
    "gn:admin1_code":"4.0",
    "gn:asciiname":"Ndoba",
    "gn:country_code":"ZM",
    "gn:dem":1172,
    "gn:feature_class":"P",
    "gn:feature_code":"PPL",
    "gn:name":"Ndoba",
    "gn:population":0,
    "gn:timezone":"Africa/Lusaka",
    "iso:country":"ZM",
    "wof:name":"Ndoba",
    "wof:placetype":"locality"
},
  "geometry": {"coordinates":[29.52125,-11.26696],"type":"Point"}
}