{
  "type": "Feature",
  "properties": {
    "gn:admin1_code":"6.0",
    "gn:asciiname":"Nama",
    "gn:country_code":"ZM",
    "gn:dem":1146,
    "gn:feature_class":"P",
    "gn:feature_code":"PPL",
    "gn:name":"Nama",
    "gn:population":0,
    "gn:timezone":"Africa/Lusaka",
    "iso:country":"ZM",
    "wof:name":"Nama",
    "wof:placetype":"locality"
},
  "geometry": {"coordinates":[24.21287,-12.78439],"type":"Point"}
}