{
  "type": "Feature",
  "properties": {
    "gn:admin1_code":"6.0",
    "gn:asciiname":"Nama",
    "gn:country_code":"ZM",
    "gn:dem":1146,
    "gn:feature_class":"P",
    "gn:feature_code":"PPL",
    "gn:name":"Nama",
    "gn:population":0,
    "gn:timezone":"Africa/Lusaka",
    "iso:country":"ZM",
    "name:ceb_x_preferred":[
        "Nama"
    ],
    "name:deu_x_preferred":[
        "Nama"
    ],
    "name:ell_x_preferred":[
        "\u039d\u03ac\u03bc\u03b1"
    ],
    "name:fin_x_preferred":[
        "Nama"
    ],
    "name:fra_x_preferred":[
        "Nama"
    ],
    "name:nld_x_preferred":[
        "Nama"
    ],
    "name:pol_x_preferred":[
        "Nama"
    ],
    "name:por_x_preferred":[
        "Nama"
    ],
    "name:swe_x_preferred":[
        "Nama"
    ],
    "wof:name":"Nama",
    "wof:placetype":"locality"
},
  "geometry": {"coordinates":[24.21287,-12.78439],"type":"Point"}
}