{
  "type": "Feature",
  "properties": {
    "gn:admin1_code":"1.0",
    "gn:asciiname":"Luampa Kuta",
    "gn:country_code":"ZM",
    "gn:dem":1123,
    "gn:feature_class":"P",
    "gn:feature_code":"PPL",
    "gn:name":"Luampa Kuta",
    "gn:population":0,
    "gn:timezone":"Africa/Lusaka",
    "iso:country":"ZM",
    "name:und_x_variant":[
        "Luampa",
        "Luampa Kuta"
    ],
    "wof:name":"Luampa Kuta",
    "wof:placetype":"locality"
},
  "geometry": {"coordinates":[24.72927,-15.43111],"type":"Point"}
}