{
  "type": "Feature",
  "properties": {
    "gn:admin1_code":"10.0",
    "gn:asciiname":"Nkala",
    "gn:country_code":"ZM",
    "gn:dem":1436,
    "gn:feature_class":"P",
    "gn:feature_code":"PPL",
    "gn:name":"Nkala",
    "gn:population":0,
    "gn:timezone":"Africa/Lusaka",
    "iso:country":"ZM",
    "name:und_x_variant":[
        "Kala",
        "Nkala"
    ],
    "wof:name":"Nkala",
    "wof:placetype":"locality"
},
  "geometry": {"coordinates":[32.51549,-10.134],"type":"Point"}
}