{
  "type": "Feature",
  "properties": {
    "gn:admin1_code":"9.0",
    "gn:asciiname":"Chiogoma",
    "gn:country_code":"ZM",
    "gn:dem":1179,
    "gn:feature_class":"P",
    "gn:feature_code":"PPL",
    "gn:name":"Chiogoma",
    "gn:population":0,
    "gn:timezone":"Africa/Lusaka",
    "iso:country":"ZM",
    "wof:name":"Chiogoma",
    "wof:placetype":"locality"
},
  "geometry": {"coordinates":[28.55,-15.43333],"type":"Point"}
}