{
  "type": "Feature",
  "properties": {
    "gn:admin1_code":"5.0",
    "gn:asciiname":"Musaka",
    "gn:country_code":"ZM",
    "gn:dem":1470,
    "gn:feature_class":"P",
    "gn:feature_code":"PPL",
    "gn:name":"Musaka",
    "gn:population":0,
    "gn:timezone":"Africa/Lusaka",
    "iso:country":"ZM",
    "wof:name":"Musaka",
    "wof:placetype":"locality"
},
  "geometry": {"coordinates":[30.99022,-8.84351],"type":"Point"}
}