{
  "type": "Feature",
  "properties": {
    "gn:admin1_code":"3.0",
    "gn:asciiname":"Mpango",
    "gn:country_code":"ZM",
    "gn:dem":812,
    "gn:feature_class":"P",
    "gn:feature_code":"PPL",
    "gn:name":"Mpango",
    "gn:population":0,
    "gn:timezone":"Africa/Lusaka",
    "iso:country":"ZM",
    "wof:name":"Mpango",
    "wof:placetype":"locality"
},
  "geometry": {"coordinates":[31.28341,-14.05512],"type":"Point"}
}