{
  "type": "Feature",
  "properties": {
    "gn:admin1_code":"3.0",
    "gn:asciiname":"Kamtibulila",
    "gn:country_code":"ZM",
    "gn:dem":1102,
    "gn:feature_class":"P",
    "gn:feature_code":"PPL",
    "gn:name":"Kamtibulila",
    "gn:population":0,
    "gn:timezone":"Africa/Lusaka",
    "iso:country":"ZM",
    "wof:name":"Kamtibulila",
    "wof:placetype":"locality"
},
  "geometry": {"coordinates":[32.1782,-14.05201],"type":"Point"}
}