{
  "type": "Feature",
  "properties": {
    "gn:admin1_code":"8.0",
    "gn:asciiname":"Wusikili",
    "gn:country_code":"ZM",
    "gn:dem":1227,
    "gn:feature_class":"P",
    "gn:feature_code":"PPL",
    "gn:name":"Wusikili",
    "gn:population":0,
    "gn:timezone":"Africa/Lusaka",
    "iso:country":"ZM",
    "wof:name":"Wusikili",
    "wof:placetype":"locality"
},
  "geometry": {"coordinates":[28.21667,-12.85],"type":"Point"}
}