{
  "type": "Feature",
  "properties": {
    "gn:admin1_code":"1.0",
    "gn:asciiname":"Lilenge",
    "gn:country_code":"ZM",
    "gn:dem":1027,
    "gn:feature_class":"P",
    "gn:feature_code":"PPL",
    "gn:name":"Lilenge",
    "gn:population":0,
    "gn:timezone":"Africa/Lusaka",
    "iso:country":"ZM",
    "wof:name":"Lilenge",
    "wof:placetype":"locality"
},
  "geometry": {"coordinates":[23.18333,-14.73333],"type":"Point"}
}