{
  "type": "Feature",
  "properties": {
    "gn:admin1_code":"1.0",
    "gn:asciiname":"Nomai",
    "gn:country_code":"ZM",
    "gn:dem":1080,
    "gn:feature_class":"P",
    "gn:feature_code":"PPL",
    "gn:name":"Nomai",
    "gn:population":0,
    "gn:timezone":"Africa/Lusaka",
    "iso:country":"ZM",
    "name:und_x_variant":[
        "Namai",
        "Nomai"
    ],
    "wof:name":"Nomai",
    "wof:placetype":"locality"
},
  "geometry": {"coordinates":[23.23333,-15.31667],"type":"Point"}
}