{
  "type": "Feature",
  "properties": {
    "gn:admin1_code":"7.0",
    "gn:asciiname":"Nanzhila",
    "gn:country_code":"ZM",
    "gn:dem":1004,
    "gn:feature_class":"P",
    "gn:feature_code":"PPL",
    "gn:name":"Nanzhila",
    "gn:population":0,
    "gn:timezone":"Africa/Lusaka",
    "iso:country":"ZM",
    "wof:name":"Nanzhila",
    "wof:placetype":"locality"
},
  "geometry": {"coordinates":[26.09138,-16.07736],"type":"Point"}
}