{
  "type": "Feature",
  "properties": {
    "gn:admin1_code":"5.0",
    "gn:asciiname":"Semu",
    "gn:country_code":"ZM",
    "gn:dem":1650,
    "gn:feature_class":"P",
    "gn:feature_code":"PPL",
    "gn:name":"Semu",
    "gn:population":0,
    "gn:timezone":"Africa/Lusaka",
    "iso:country":"ZM",
    "wof:name":"Semu",
    "wof:placetype":"locality"
},
  "geometry": {"coordinates":[31.56667,-9.28333],"type":"Point"}
}