{
  "type": "Feature",
  "properties": {
    "gn:admin1_code":"3.0",
    "gn:asciiname":"Mawanda",
    "gn:country_code":"ZM",
    "gn:dem":961,
    "gn:feature_class":"P",
    "gn:feature_code":"PPL",
    "gn:name":"Mawanda",
    "gn:population":0,
    "gn:timezone":"Africa/Lusaka",
    "iso:country":"ZM",
    "name:und_x_variant":[
        "Mawano",
        "Mawanu",
        "Mawanda"
    ],
    "wof:name":"Mawanda",
    "wof:placetype":"locality"
},
  "geometry": {"coordinates":[32.12625,-14.27816],"type":"Point"}
}