{
  "type": "Feature",
  "properties": {
    "gn:admin1_code":"3.0",
    "gn:asciiname":"Makalaje",
    "gn:country_code":"ZM",
    "gn:dem":1168,
    "gn:feature_class":"P",
    "gn:feature_code":"PPL",
    "gn:name":"Makalaje",
    "gn:population":0,
    "gn:timezone":"Africa/Lusaka",
    "iso:country":"ZM",
    "wof:name":"Makalaje",
    "wof:placetype":"locality"
},
  "geometry": {"coordinates":[33.22908,-11.98749],"type":"Point"}
}