{
  "type": "Feature",
  "properties": {
    "gn:admin1_code":"1.0",
    "gn:asciiname":"Liembane",
    "gn:country_code":"ZM",
    "gn:dem":1071,
    "gn:feature_class":"P",
    "gn:feature_code":"PPL",
    "gn:name":"Liembane",
    "gn:population":0,
    "gn:timezone":"Africa/Lusaka",
    "iso:country":"ZM",
    "wof:name":"Liembane",
    "wof:placetype":"locality"
},
  "geometry": {"coordinates":[23.71667,-15.23333],"type":"Point"}
}