{
  "type": "Feature",
  "properties": {
    "gn:admin1_code":"10.0",
    "gn:asciiname":"Chipepeya",
    "gn:country_code":"ZM",
    "gn:dem":991,
    "gn:feature_class":"P",
    "gn:feature_code":"PPL",
    "gn:name":"Chipepeya",
    "gn:population":0,
    "gn:timezone":"Africa/Lusaka",
    "iso:country":"ZM",
    "name:und_x_variant":[
        "Chipipeya",
        "Chipepeya"
    ],
    "wof:name":"Chipepeya",
    "wof:placetype":"locality"
},
  "geometry": {"coordinates":[32.77936,-10.19215],"type":"Point"}
}