{
  "type": "Feature",
  "properties": {
    "gn:admin1_code":"2.0",
    "gn:asciiname":"Chibuye Lisandi",
    "gn:country_code":"ZM",
    "gn:dem":1274,
    "gn:feature_class":"P",
    "gn:feature_code":"PPL",
    "gn:name":"Chibuye Lisandi",
    "gn:population":0,
    "gn:timezone":"Africa/Lusaka",
    "iso:country":"ZM",
    "wof:name":"Chibuye Lisandi",
    "wof:placetype":"locality"
},
  "geometry": {"coordinates":[30.2835,-12.86814],"type":"Point"}
}