{
  "type": "Feature",
  "properties": {
    "gn:admin1_code":"1.0",
    "gn:asciiname":"Singetengende",
    "gn:country_code":"ZM",
    "gn:dem":1040,
    "gn:feature_class":"P",
    "gn:feature_code":"PPL",
    "gn:name":"Singetengende",
    "gn:population":0,
    "gn:timezone":"Africa/Lusaka",
    "iso:country":"ZM",
    "wof:name":"Singetengende",
    "wof:placetype":"locality"
},
  "geometry": {"coordinates":[22.18333,-15.65],"type":"Point"}
}