{
  "type": "Feature",
  "properties": {
    "gn:admin1_code":"3.0",
    "gn:asciiname":"Mbisi",
    "gn:country_code":"ZM",
    "gn:dem":979,
    "gn:feature_class":"P",
    "gn:feature_code":"PPL",
    "gn:name":"Mbisi",
    "gn:population":0,
    "gn:timezone":"Africa/Lusaka",
    "iso:country":"ZM",
    "wof:name":"Mbisi",
    "wof:placetype":"locality"
},
  "geometry": {"coordinates":[31.10279,-14.65825],"type":"Point"}
}