{
  "type": "Feature",
  "properties": {
    "gn:admin1_code":"5.0",
    "gn:asciiname":"Mibanga",
    "gn:country_code":"ZM",
    "gn:dem":1318,
    "gn:feature_class":"P",
    "gn:feature_code":"PPL",
    "gn:name":"Mibanga",
    "gn:population":0,
    "gn:timezone":"Africa/Lusaka",
    "iso:country":"ZM",
    "wof:name":"Mibanga",
    "wof:placetype":"locality"
},
  "geometry": {"coordinates":[31.00062,-10.16841],"type":"Point"}
}