{
  "type": "Feature",
  "properties": {
    "gn:admin1_code":"3.0",
    "gn:asciiname":"Ndombi",
    "gn:country_code":"ZM",
    "gn:dem":1057,
    "gn:feature_class":"P",
    "gn:feature_code":"PPL",
    "gn:name":"Ndombi",
    "gn:population":0,
    "gn:timezone":"Africa/Lusaka",
    "iso:country":"ZM",
    "name:und_x_variant":[
        "Ndombe",
        "Ndombi"
    ],
    "wof:name":"Ndombi",
    "wof:placetype":"locality"
},
  "geometry": {"coordinates":[31.56667,-14.45],"type":"Point"}
}