{
  "type": "Feature",
  "properties": {
    "gn:admin1_code":"3.0",
    "gn:asciiname":"Mjoro",
    "gn:country_code":"ZM",
    "gn:dem":986,
    "gn:feature_class":"P",
    "gn:feature_code":"PPL",
    "gn:name":"Mjoro",
    "gn:population":0,
    "gn:timezone":"Africa/Lusaka",
    "iso:country":"ZM",
    "wof:name":"Mjoro",
    "wof:placetype":"locality"
},
  "geometry": {"coordinates":[32.21218,-14.17084],"type":"Point"}
}