{
  "type": "Feature",
  "properties": {
    "gn:admin1_code":"5.0",
    "gn:asciiname":"Mfuwe",
    "gn:country_code":"ZM",
    "gn:dem":537,
    "gn:feature_class":"P",
    "gn:feature_code":"PPL",
    "gn:name":"Mfuwe",
    "gn:population":0,
    "gn:timezone":"Africa/Lusaka",
    "iso:country":"ZM",
    "wof:name":"Mfuwe",
    "wof:placetype":"locality"
},
  "geometry": {"coordinates":[31.92275,-12.89498],"type":"Point"}
}