{
  "type": "Feature",
  "properties": {
    "gn:admin1_code":"6.0",
    "gn:asciiname":"Kakwanda",
    "gn:country_code":"ZM",
    "gn:dem":1035,
    "gn:feature_class":"P",
    "gn:feature_code":"PPL",
    "gn:name":"Kakwanda",
    "gn:population":0,
    "gn:timezone":"Africa/Lusaka",
    "iso:country":"ZM",
    "wof:name":"Kakwanda",
    "wof:placetype":"locality"
},
  "geometry": {"coordinates":[23.33333,-14.16667],"type":"Point"}
}