{
  "type": "Feature",
  "properties": {
    "gn:admin1_code":"7.0",
    "gn:asciiname":"Tobonte",
    "gn:country_code":"ZM",
    "gn:dem":526,
    "gn:feature_class":"P",
    "gn:feature_code":"PPL",
    "gn:name":"Tobonte",
    "gn:population":0,
    "gn:timezone":"Africa/Lusaka",
    "iso:country":"ZM",
    "name:eng_x_preferred":[
        "Tobonte"
    ],
    "name:eng_x_variant":[
        "Tobote"
    ],
    "name:und_x_variant":[
        "Tobote"
    ],
    "wof:name":"Tobonte",
    "wof:placetype":"locality"
},
  "geometry": {"coordinates":[27.48333,-17.08333],"type":"Point"}
}