{
  "type": "Feature",
  "properties": {
    "gn:admin1_code":"2.0",
    "gn:asciiname":"Malambanyama",
    "gn:country_code":"ZM",
    "gn:dem":1146,
    "gn:feature_class":"P",
    "gn:feature_code":"PPL",
    "gn:name":"Malambanyama",
    "gn:population":0,
    "gn:timezone":"Africa/Lusaka",
    "iso:country":"ZM",
    "name:und_x_variant":[
        "Malanbanyama",
        "Malambanyama"
    ],
    "wof:name":"Malambanyama",
    "wof:placetype":"locality"
},
  "geometry": {"coordinates":[27.70601,-14.86115],"type":"Point"}
}