{
  "type": "Feature",
  "properties": {
    "gn:admin1_code":"2.0",
    "gn:asciiname":"Lauli Chimpali",
    "gn:country_code":"ZM",
    "gn:dem":1555,
    "gn:feature_class":"P",
    "gn:feature_code":"PPL",
    "gn:name":"Lauli Chimpali",
    "gn:population":0,
    "gn:timezone":"Africa/Lusaka",
    "iso:country":"ZM",
    "wof:name":"Lauli Chimpali",
    "wof:placetype":"locality"
},
  "geometry": {"coordinates":[30.73071,-12.90712],"type":"Point"}
}