{
  "type": "Feature",
  "properties": {
    "gn:admin1_code":"10.0",
    "gn:asciiname":"Munyika",
    "gn:country_code":"ZM",
    "gn:dem":1318,
    "gn:feature_class":"P",
    "gn:feature_code":"PPL",
    "gn:name":"Munyika",
    "gn:population":0,
    "gn:timezone":"Africa/Lusaka",
    "iso:country":"ZM",
    "wof:name":"Munyika",
    "wof:placetype":"locality"
},
  "geometry": {"coordinates":[32.78333,-9.78333],"type":"Point"}
}