{
  "type": "Feature",
  "properties": {
    "gn:admin1_code":"4.0",
    "gn:asciiname":"Chisukulu",
    "gn:country_code":"ZM",
    "gn:dem":931,
    "gn:feature_class":"P",
    "gn:feature_code":"PPL",
    "gn:name":"Chisukulu",
    "gn:population":0,
    "gn:timezone":"Africa/Lusaka",
    "iso:country":"ZM",
    "name:und_x_variant":[
        "Kisukulu",
        "Chisukulu"
    ],
    "wof:name":"Chisukulu",
    "wof:placetype":"locality"
},
  "geometry": {"coordinates":[28.40012,-9.24879],"type":"Point"}
}