{
  "type": "Feature",
  "properties": {
    "gn:admin1_code":"2.0",
    "gn:asciiname":"Mululuma",
    "gn:country_code":"ZM",
    "gn:dem":1219,
    "gn:feature_class":"P",
    "gn:feature_code":"PPL",
    "gn:name":"Mululuma",
    "gn:population":0,
    "gn:timezone":"Africa/Lusaka",
    "iso:country":"ZM",
    "wof:name":"Mululuma",
    "wof:placetype":"locality"
},
  "geometry": {"coordinates":[27.30146,-14.7173],"type":"Point"}
}