{
  "type": "Feature",
  "properties": {
    "gn:admin1_code":"6.0",
    "gn:asciiname":"Lusongwa",
    "gn:country_code":"ZM",
    "gn:dem":1131,
    "gn:feature_class":"P",
    "gn:feature_code":"PPL",
    "gn:name":"Lusongwa",
    "gn:population":0,
    "gn:timezone":"Africa/Lusaka",
    "iso:country":"ZM",
    "wof:name":"Lusongwa",
    "wof:placetype":"locality"
},
  "geometry": {"coordinates":[24.22548,-13.03653],"type":"Point"}
}