{
  "type": "Feature",
  "properties": {
    "gn:admin1_code":"2.0",
    "gn:asciiname":"Goliati Museya",
    "gn:country_code":"ZM",
    "gn:dem":1531,
    "gn:feature_class":"P",
    "gn:feature_code":"PPL",
    "gn:name":"Goliati Museya",
    "gn:population":0,
    "gn:timezone":"Africa/Lusaka",
    "iso:country":"ZM",
    "wof:name":"Goliati Museya",
    "wof:placetype":"locality"
},
  "geometry": {"coordinates":[30.73503,-12.87758],"type":"Point"}
}