{
  "type": "Feature",
  "properties": {
    "gn:admin1_code":"1.0",
    "gn:asciiname":"Ilutake",
    "gn:country_code":"ZM",
    "gn:dem":1068,
    "gn:feature_class":"P",
    "gn:feature_code":"PPL",
    "gn:name":"Ilutake",
    "gn:population":0,
    "gn:timezone":"Africa/Lusaka",
    "iso:country":"ZM",
    "wof:name":"Ilutake",
    "wof:placetype":"locality"
},
  "geometry": {"coordinates":[23.46667,-15.75],"type":"Point"}
}