{
  "type": "Feature",
  "properties": {
    "gn:admin1_code":"1.0",
    "gn:asciiname":"Muwaneyi",
    "gn:country_code":"ZM",
    "gn:dem":1019,
    "gn:feature_class":"P",
    "gn:feature_code":"PPL",
    "gn:name":"Muwaneyi",
    "gn:population":0,
    "gn:timezone":"Africa/Lusaka",
    "iso:country":"ZM",
    "wof:name":"Muwaneyi",
    "wof:placetype":"locality"
},
  "geometry": {"coordinates":[22.66667,-14.96667],"type":"Point"}
}