{
  "type": "Feature",
  "properties": {
    "gn:admin1_code":"3.0",
    "gn:asciiname":"Sasawala",
    "gn:country_code":"ZM",
    "gn:dem":973,
    "gn:feature_class":"P",
    "gn:feature_code":"PPL",
    "gn:name":"Sasawala",
    "gn:population":0,
    "gn:timezone":"Africa/Lusaka",
    "iso:country":"ZM",
    "name:und_x_variant":[
        "Sasawara",
        "Sasawala"
    ],
    "wof:name":"Sasawala",
    "wof:placetype":"locality"
},
  "geometry": {"coordinates":[31.58333,-14.08333],"type":"Point"}
}