{
  "type": "Feature",
  "properties": {
    "gn:admin1_code":"6.0",
    "gn:asciiname":"Chingi",
    "gn:country_code":"ZM",
    "gn:dem":1082,
    "gn:feature_class":"P",
    "gn:feature_code":"PPL",
    "gn:name":"Chingi",
    "gn:population":0,
    "gn:timezone":"Africa/Lusaka",
    "iso:country":"ZM",
    "wof:name":"Chingi",
    "wof:placetype":"locality"
},
  "geometry": {"coordinates":[22.73041,-13.0041],"type":"Point"}
}