{
  "type": "Feature",
  "properties": {
    "gn:admin1_code":"3.0",
    "gn:asciiname":"Ndevu",
    "gn:country_code":"ZM",
    "gn:dem":417,
    "gn:feature_class":"P",
    "gn:feature_code":"PPL",
    "gn:name":"Ndevu",
    "gn:population":0,
    "gn:timezone":"Africa/Lusaka",
    "iso:country":"ZM",
    "wof:name":"Ndevu",
    "wof:placetype":"locality"
},
  "geometry": {"coordinates":[30.46964,-14.43113],"type":"Point"}
}