{
  "type": "Feature",
  "properties": {
    "gn:admin1_code":"3.0",
    "gn:asciiname":"Khoza",
    "gn:country_code":"ZM",
    "gn:dem":966,
    "gn:feature_class":"P",
    "gn:feature_code":"PPL",
    "gn:name":"Khoza",
    "gn:population":0,
    "gn:timezone":"Africa/Lusaka",
    "iso:country":"ZM",
    "wof:name":"Khoza",
    "wof:placetype":"locality"
},
  "geometry": {"coordinates":[31.7154,-14.07127],"type":"Point"}
}