{
  "type": "Feature",
  "properties": {
    "gn:admin1_code":"2.0",
    "gn:asciiname":"Piluka",
    "gn:country_code":"ZM",
    "gn:dem":1145,
    "gn:feature_class":"P",
    "gn:feature_code":"PPL",
    "gn:name":"Piluka",
    "gn:population":0,
    "gn:timezone":"Africa/Lusaka",
    "iso:country":"ZM",
    "wof:name":"Piluka",
    "wof:placetype":"locality"
},
  "geometry": {"coordinates":[28.13333,-14.26667],"type":"Point"}
}