{
  "type": "Feature",
  "properties": {
    "gn:admin1_code":"1.0",
    "gn:asciiname":"Sibinda",
    "gn:country_code":"ZM",
    "gn:dem":1063,
    "gn:feature_class":"P",
    "gn:feature_code":"PPL",
    "gn:name":"Sibinda",
    "gn:population":0,
    "gn:timezone":"Africa/Lusaka",
    "iso:country":"ZM",
    "wof:name":"Sibinda",
    "wof:placetype":"locality"
},
  "geometry": {"coordinates":[23.31667,-15.36667],"type":"Point"}
}