{
  "type": "Feature",
  "properties": {
    "gn:admin1_code":"1.0",
    "gn:asciiname":"Nambula",
    "gn:country_code":"ZM",
    "gn:dem":1011,
    "gn:feature_class":"P",
    "gn:feature_code":"PPL",
    "gn:name":"Nambula",
    "gn:population":0,
    "gn:timezone":"Africa/Lusaka",
    "iso:country":"ZM",
    "wof:name":"Nambula",
    "wof:placetype":"locality"
},
  "geometry": {"coordinates":[23.15,-15.45],"type":"Point"}
}