{
  "type": "Feature",
  "properties": {
    "gn:admin1_code":"7.0",
    "gn:asciiname":"Moyo",
    "gn:country_code":"ZM",
    "gn:dem":569,
    "gn:feature_class":"P",
    "gn:feature_code":"PPL",
    "gn:name":"Moyo",
    "gn:population":0,
    "gn:timezone":"Africa/Lusaka",
    "iso:country":"ZM",
    "name:ceb_x_preferred":[
        "Moyo"
    ],
    "name:deu_x_preferred":[
        "Moyo"
    ],
    "name:fra_x_preferred":[
        "Moyo"
    ],
    "name:ita_x_preferred":[
        "Moyo"
    ],
    "name:swe_x_preferred":[
        "Moyo"
    ],
    "wof:name":"Moyo",
    "wof:placetype":"locality"
},
  "geometry": {"coordinates":[27.98333,-16.73333],"type":"Point"}
}