{
  "type": "Feature",
  "properties": {
    "gn:admin1_code":"7.0",
    "gn:asciiname":"Moyo",
    "gn:country_code":"ZM",
    "gn:dem":569,
    "gn:feature_class":"P",
    "gn:feature_code":"PPL",
    "gn:name":"Moyo",
    "gn:population":0,
    "gn:timezone":"Africa/Lusaka",
    "iso:country":"ZM",
    "name:ara_x_preferred":[
        "\u0645\u0648\u064a\u0648"
    ],
    "name:ben_x_preferred":[
        "\u09ae\u09cb\u09df\u09cb"
    ],
    "name:ceb_x_preferred":[
        "Moyo"
    ],
    "name:deu_x_preferred":[
        "Moyo"
    ],
    "name:ell_x_preferred":[
        "M\u03ccyo"
    ],
    "name:fas_x_preferred":[
        "\u0645\u0648\u06cc\u0648"
    ],
    "name:fra_x_preferred":[
        "Moyo"
    ],
    "name:heb_x_preferred":[
        "\u05de\u05d5\u05d6\u05d9\u05e8\u05d9\u05d9\u05d4"
    ],
    "name:hin_x_preferred":[
        "\u092e\u094b\u092f\u094b"
    ],
    "name:hun_x_preferred":[
        "Moyo"
    ],
    "name:ind_x_preferred":[
        "Moyo"
    ],
    "name:ita_x_preferred":[
        "Moyo"
    ],
    "name:kor_x_preferred":[
        "\ubaa8\uc694"
    ],
    "name:pol_x_preferred":[
        "Moyo"
    ],
    "name:por_x_preferred":[
        "Moyo"
    ],
    "name:spa_x_preferred":[
        "Moyo"
    ],
    "name:swe_x_preferred":[
        "Moyo"
    ],
    "name:tur_x_preferred":[
        "Moyo"
    ],
    "name:ukr_x_preferred":[
        "\u041c\u043e\u0439\u043e"
    ],
    "name:vie_x_preferred":[
        "Moyo"
    ],
    "name:zho_cn_x_preferred":[
        "\u83ab\u7ea6"
    ],
    "name:zho_tw_x_preferred":[
        "\u83ab\u7d04"
    ],
    "wof:name":"Moyo",
    "wof:placetype":"locality"
},
  "geometry": {"coordinates":[27.98333,-16.73333],"type":"Point"}
}