{
  "type": "Feature",
  "properties": {
    "gn:admin1_code":"4.0",
    "gn:asciiname":"Nsamba",
    "gn:country_code":"ZM",
    "gn:dem":1174,
    "gn:feature_class":"P",
    "gn:feature_code":"PPL",
    "gn:name":"Nsamba",
    "gn:population":0,
    "gn:timezone":"Africa/Lusaka",
    "iso:country":"ZM",
    "wof:name":"Nsamba",
    "wof:placetype":"locality"
},
  "geometry": {"coordinates":[30.31667,-11.55],"type":"Point"}
}