{
  "type": "Feature",
  "properties": {
    "gn:admin1_code":"7.0",
    "gn:asciiname":"Pora",
    "gn:country_code":"ZM",
    "gn:dem":1068,
    "gn:feature_class":"P",
    "gn:feature_code":"PPL",
    "gn:name":"Pora",
    "gn:population":0,
    "gn:timezone":"Africa/Lusaka",
    "iso:country":"ZM",
    "wof:name":"Pora",
    "wof:placetype":"locality"
},
  "geometry": {"coordinates":[26.05,-17.61667000000001],"type":"Point"}
}