{
  "type": "Feature",
  "properties": {
    "gn:admin1_code":"2.0",
    "gn:asciiname":"Sati Chawe",
    "gn:country_code":"ZM",
    "gn:dem":1515,
    "gn:feature_class":"P",
    "gn:feature_code":"PPL",
    "gn:name":"Sati Chawe",
    "gn:population":0,
    "gn:timezone":"Africa/Lusaka",
    "iso:country":"ZM",
    "name:und_x_variant":[
        "Sati Chalwe",
        "Sati Chawe"
    ],
    "wof:name":"Sati Chawe",
    "wof:placetype":"locality"
},
  "geometry": {"coordinates":[30.92926,-13.16963],"type":"Point"}
}