{
  "type": "Feature",
  "properties": {
    "gn:admin1_code":"1.0",
    "gn:asciiname":"Wainya",
    "gn:country_code":"ZM",
    "gn:dem":1018,
    "gn:feature_class":"P",
    "gn:feature_code":"PPL",
    "gn:name":"Wainya",
    "gn:population":0,
    "gn:timezone":"Africa/Lusaka",
    "iso:country":"ZM",
    "wof:name":"Wainya",
    "wof:placetype":"locality"
},
  "geometry": {"coordinates":[22.86667000000001,-15.36667],"type":"Point"}
}