{
  "type": "Feature",
  "properties": {
    "gn:admin1_code":"3.0",
    "gn:asciiname":"Mwanamomba",
    "gn:country_code":"ZM",
    "gn:dem":415,
    "gn:feature_class":"P",
    "gn:feature_code":"PPL",
    "gn:name":"Mwanamomba",
    "gn:population":0,
    "gn:timezone":"Africa/Lusaka",
    "iso:country":"ZM",
    "wof:name":"Mwanamomba",
    "wof:placetype":"locality"
},
  "geometry": {"coordinates":[30.08013,-14.6875],"type":"Point"}
}