{
  "type": "Feature",
  "properties": {
    "gn:admin1_code":"2.0",
    "gn:asciiname":"Kashishi",
    "gn:country_code":"ZM",
    "gn:dem":1388,
    "gn:feature_class":"P",
    "gn:feature_code":"PPL",
    "gn:name":"Kashishi",
    "gn:population":0,
    "gn:timezone":"Africa/Lusaka",
    "iso:country":"ZM",
    "wof:name":"Kashishi",
    "wof:placetype":"locality"
},
  "geometry": {"coordinates":[30.24697,-13.00536],"type":"Point"}
}