{
  "type": "Feature",
  "properties": {
    "gn:admin1_code":"10.0",
    "gn:asciiname":"Nganga",
    "gn:country_code":"ZM",
    "gn:dem":688,
    "gn:feature_class":"P",
    "gn:feature_code":"PPL",
    "gn:name":"Nganga",
    "gn:population":0,
    "gn:timezone":"Africa/Lusaka",
    "iso:country":"ZM",
    "name:kor_x_preferred":[
        "\uc751\uac15\uac00"
    ],
    "name:lin_x_preferred":[
        "Nganga"
    ],
    "name:por_x_preferred":[
        "Nganga"
    ],
    "wof:name":"Nganga",
    "wof:placetype":"locality"
},
  "geometry": {"coordinates":[33.01667,-11.03333],"type":"Point"}
}