{
  "type": "Feature",
  "properties": {
    "gn:admin1_code":"8.0",
    "gn:asciiname":"Buchi and Kamitondo",
    "gn:country_code":"ZM",
    "gn:dem":1228,
    "gn:feature_class":"P",
    "gn:feature_code":"PPL",
    "gn:name":"Buchi and Kamitondo",
    "gn:population":0,
    "gn:timezone":"Africa/Lusaka",
    "iso:country":"ZM",
    "wof:name":"Buchi and Kamitondo",
    "wof:placetype":"locality"
},
  "geometry": {"coordinates":[28.21667,-12.78333],"type":"Point"}
}