{
  "type": "Feature",
  "properties": {
    "gn:admin1_code":"2.0",
    "gn:asciiname":"Kanchule",
    "gn:country_code":"ZM",
    "gn:dem":1422,
    "gn:feature_class":"P",
    "gn:feature_code":"PPL",
    "gn:name":"Kanchule",
    "gn:population":0,
    "gn:timezone":"Africa/Lusaka",
    "iso:country":"ZM",
    "wof:name":"Kanchule",
    "wof:placetype":"locality"
},
  "geometry": {"coordinates":[30.44124,-12.91115],"type":"Point"}
}