{
  "type": "Feature",
  "properties": {
    "gn:admin1_code":"6.0",
    "gn:asciiname":"Kabemba",
    "gn:country_code":"ZM",
    "gn:dem":1123,
    "gn:feature_class":"P",
    "gn:feature_code":"PPL",
    "gn:name":"Kabemba",
    "gn:population":0,
    "gn:timezone":"Africa/Lusaka",
    "iso:country":"ZM",
    "wof:name":"Kabemba",
    "wof:placetype":"locality"
},
  "geometry": {"coordinates":[24.99282,-13.71519],"type":"Point"}
}