{
  "type": "Feature",
  "properties": {
    "gn:admin1_code":"2.0",
    "gn:asciiname":"Lubinga",
    "gn:country_code":"ZM",
    "gn:dem":1159,
    "gn:feature_class":"P",
    "gn:feature_code":"PPL",
    "gn:name":"Lubinga",
    "gn:population":0,
    "gn:timezone":"Africa/Lusaka",
    "iso:country":"ZM",
    "wof:name":"Lubinga",
    "wof:placetype":"locality"
},
  "geometry": {"coordinates":[27.18333,-14.56667],"type":"Point"}
}