{
  "type": "Feature",
  "properties": {
    "gn:admin1_code":"1.0",
    "gn:asciiname":"Bungana",
    "gn:country_code":"ZM",
    "gn:dem":1177,
    "gn:feature_class":"P",
    "gn:feature_code":"PPL",
    "gn:name":"Bungana",
    "gn:population":0,
    "gn:timezone":"Africa/Lusaka",
    "iso:country":"ZM",
    "wof:name":"Bungana",
    "wof:placetype":"locality"
},
  "geometry": {"coordinates":[25.00406,-14.62966],"type":"Point"}
}