{
  "type": "Feature",
  "properties": {
    "gn:admin1_code":"1.0",
    "gn:asciiname":"Shindika",
    "gn:country_code":"ZM",
    "gn:dem":1178,
    "gn:feature_class":"P",
    "gn:feature_code":"PPL",
    "gn:name":"Shindika",
    "gn:population":0,
    "gn:timezone":"Africa/Lusaka",
    "iso:country":"ZM",
    "wof:name":"Shindika",
    "wof:placetype":"locality"
},
  "geometry": {"coordinates":[25.06667,-15.75],"type":"Point"}
}