{
  "type": "Feature",
  "properties": {
    "gn:admin1_code":"3.0",
    "gn:asciiname":"Ntalazya",
    "gn:country_code":"ZM",
    "gn:dem":601,
    "gn:feature_class":"P",
    "gn:feature_code":"PPL",
    "gn:name":"Ntalazya",
    "gn:population":0,
    "gn:timezone":"Africa/Lusaka",
    "iso:country":"ZM",
    "name:und_x_variant":[
        "Ntalaziya",
        "Ntalazya"
    ],
    "wof:name":"Ntalazya",
    "wof:placetype":"locality"
},
  "geometry": {"coordinates":[31.94532,-13.4804],"type":"Point"}
}