{
  "type": "Feature",
  "properties": {
    "gn:admin1_code":"7.0",
    "gn:asciiname":"Siabwenga",
    "gn:country_code":"ZM",
    "gn:dem":788,
    "gn:feature_class":"P",
    "gn:feature_code":"PPL",
    "gn:name":"Siabwenga",
    "gn:population":0,
    "gn:timezone":"Africa/Lusaka",
    "iso:country":"ZM",
    "wof:name":"Siabwenga",
    "wof:placetype":"locality"
},
  "geometry": {"coordinates":[27.91667,-16.65],"type":"Point"}
}