{
  "type": "Feature",
  "properties": {
    "gn:admin1_code":"6.0",
    "gn:asciiname":"Mupala",
    "gn:country_code":"ZM",
    "gn:dem":1369,
    "gn:feature_class":"P",
    "gn:feature_code":"PPL",
    "gn:name":"Mupala",
    "gn:population":0,
    "gn:timezone":"Africa/Lusaka",
    "iso:country":"ZM",
    "wof:name":"Mupala",
    "wof:placetype":"locality"
},
  "geometry": {"coordinates":[25.08333,-12.01667],"type":"Point"}
}