{
  "type": "Feature",
  "properties": {
    "gn:admin1_code":"7.0",
    "gn:asciiname":"Kashimbi",
    "gn:country_code":"ZM",
    "gn:dem":1031,
    "gn:feature_class":"P",
    "gn:feature_code":"PPL",
    "gn:name":"Kashimbi",
    "gn:population":0,
    "gn:timezone":"Africa/Lusaka",
    "iso:country":"ZM",
    "wof:name":"Kashimbi",
    "wof:placetype":"locality"
},
  "geometry": {"coordinates":[28.25021,-15.90071],"type":"Point"}
}