{
  "type": "Feature",
  "properties": {
    "gn:admin1_code":"10.0",
    "gn:asciiname":"Mwami",
    "gn:country_code":"ZM",
    "gn:dem":649,
    "gn:feature_class":"P",
    "gn:feature_code":"PPL",
    "gn:name":"Mwami",
    "gn:population":0,
    "gn:timezone":"Africa/Lusaka",
    "iso:country":"ZM",
    "name:bar_x_preferred":[
        "Mwami"
    ],
    "name:cat_x_preferred":[
        "Mwami"
    ],
    "name:est_x_preferred":[
        "Mwami"
    ],
    "name:fra_x_preferred":[
        "Mwami"
    ],
    "name:hun_x_preferred":[
        "Mwami"
    ],
    "name:jpn_x_preferred":[
        "\u30e0\u30ef\u30df"
    ],
    "name:lit_x_preferred":[
        "Mvamis"
    ],
    "name:oci_x_preferred":[
        "Mwami"
    ],
    "name:spa_x_preferred":[
        "Mwami"
    ],
    "name:und_x_variant":[
        "Mwame",
        "Mwami"
    ],
    "wof:name":"Mwami",
    "wof:placetype":"locality"
},
  "geometry": {"coordinates":[32.86667,-11.38333],"type":"Point"}
}