{
  "type": "Feature",
  "properties": {
    "gn:admin1_code":"2.0",
    "gn:asciiname":"Luchena",
    "gn:country_code":"ZM",
    "gn:dem":619,
    "gn:feature_class":"P",
    "gn:feature_code":"PPL",
    "gn:name":"Luchena",
    "gn:population":0,
    "gn:timezone":"Africa/Lusaka",
    "iso:country":"ZM",
    "wof:name":"Luchena",
    "wof:placetype":"locality"
},
  "geometry": {"coordinates":[30.66667,-13.55],"type":"Point"}
}