{
  "type": "Feature",
  "properties": {
    "gn:admin1_code":"5.0",
    "gn:asciiname":"Chikombe",
    "gn:country_code":"ZM",
    "gn:dem":1412,
    "gn:feature_class":"P",
    "gn:feature_code":"PPL",
    "gn:name":"Chikombe",
    "gn:population":0,
    "gn:timezone":"Africa/Lusaka",
    "iso:country":"ZM",
    "wof:name":"Chikombe",
    "wof:placetype":"locality"
},
  "geometry": {"coordinates":[31.33333,-9.66667],"type":"Point"}
}