{
  "type": "Feature",
  "properties": {
    "gn:admin1_code":"3.0",
    "gn:asciiname":"Kacherere",
    "gn:country_code":"ZM",
    "gn:dem":913,
    "gn:feature_class":"P",
    "gn:feature_code":"PPL",
    "gn:name":"Kacherere",
    "gn:population":0,
    "gn:timezone":"Africa/Lusaka",
    "iso:country":"ZM",
    "name:und_x_variant":[
        "Kachelela",
        "Kacherere"
    ],
    "wof:name":"Kacherere",
    "wof:placetype":"locality"
},
  "geometry": {"coordinates":[31.25417,-14.18082],"type":"Point"}
}