{
  "type": "Feature",
  "properties": {
    "gn:admin1_code":"3.0",
    "gn:asciiname":"Msangwa",
    "gn:country_code":"ZM",
    "gn:dem":1040,
    "gn:feature_class":"P",
    "gn:feature_code":"PPL",
    "gn:name":"Msangwa",
    "gn:population":0,
    "gn:timezone":"Africa/Lusaka",
    "iso:country":"ZM",
    "wof:name":"Msangwa",
    "wof:placetype":"locality"
},
  "geometry": {"coordinates":[31.98333,-14.33333],"type":"Point"}
}