{
  "type": "Feature",
  "properties": {
    "gn:admin1_code":"2.0",
    "gn:asciiname":"Malila",
    "gn:country_code":"ZM",
    "gn:dem":1154,
    "gn:feature_class":"P",
    "gn:feature_code":"PPL",
    "gn:name":"Malila",
    "gn:population":0,
    "gn:timezone":"Africa/Lusaka",
    "iso:country":"ZM",
    "wof:name":"Malila",
    "wof:placetype":"locality"
},
  "geometry": {"coordinates":[28.17142,-13.90341],"type":"Point"}
}