{
  "type": "Feature",
  "properties": {
    "gn:admin1_code":"7.0",
    "gn:asciiname":"Siatubi",
    "gn:country_code":"ZM",
    "gn:dem":1098,
    "gn:feature_class":"P",
    "gn:feature_code":"PPL",
    "gn:name":"Siatubi",
    "gn:population":0,
    "gn:timezone":"Africa/Lusaka",
    "iso:country":"ZM",
    "wof:name":"Siatubi",
    "wof:placetype":"locality"
},
  "geometry": {"coordinates":[25.86748,-17.39122],"type":"Point"}
}