{
  "type": "Feature",
  "properties": {
    "gn:admin1_code":"5.0",
    "gn:asciiname":"Sementi",
    "gn:country_code":"ZM",
    "gn:dem":1681,
    "gn:feature_class":"P",
    "gn:feature_code":"PPL",
    "gn:name":"Sementi",
    "gn:population":0,
    "gn:timezone":"Africa/Lusaka",
    "iso:country":"ZM",
    "wof:name":"Sementi",
    "wof:placetype":"locality"
},
  "geometry": {"coordinates":[31.47566,-9.21047],"type":"Point"}
}