{
  "type": "Feature",
  "properties": {
    "gn:admin1_code":"3.0",
    "gn:asciiname":"Chingolo",
    "gn:country_code":"ZM",
    "gn:dem":649,
    "gn:feature_class":"P",
    "gn:feature_code":"PPL",
    "gn:name":"Chingolo",
    "gn:population":0,
    "gn:timezone":"Africa/Lusaka",
    "iso:country":"ZM",
    "name:spa_x_preferred":[
        "Chingolo"
    ],
    "wof:name":"Chingolo",
    "wof:placetype":"locality"
},
  "geometry": {"coordinates":[32.21667,-12.83333],"type":"Point"}
}