{
  "type": "Feature",
  "properties": {
    "gn:admin1_code":"9.0",
    "gn:asciiname":"Chapindula",
    "gn:country_code":"ZM",
    "gn:dem":1006,
    "gn:feature_class":"P",
    "gn:feature_code":"PPL",
    "gn:name":"Chapindula",
    "gn:population":0,
    "gn:timezone":"Africa/Lusaka",
    "iso:country":"ZM",
    "wof:name":"Chapindula",
    "wof:placetype":"locality"
},
  "geometry": {"coordinates":[28.95456,-15.45132],"type":"Point"}
}