{
  "type": "Feature",
  "properties": {
    "gn:admin1_code":"2.0",
    "gn:asciiname":"Shamafumba",
    "gn:country_code":"ZM",
    "gn:dem":1079,
    "gn:feature_class":"P",
    "gn:feature_code":"PPL",
    "gn:name":"Shamafumba",
    "gn:population":0,
    "gn:timezone":"Africa/Lusaka",
    "iso:country":"ZM",
    "name:und_x_variant":[
        "Fumba",
        "Shamafumba"
    ],
    "wof:name":"Shamafumba",
    "wof:placetype":"locality"
},
  "geometry": {"coordinates":[27.35,-15.11667],"type":"Point"}
}