{
  "type": "Feature",
  "properties": {
    "gn:admin1_code":"7.0",
    "gn:asciiname":"Tara",
    "gn:country_code":"ZM",
    "gn:dem":1333,
    "gn:feature_class":"P",
    "gn:feature_code":"PPL",
    "gn:name":"Tara",
    "gn:population":0,
    "gn:timezone":"Africa/Lusaka",
    "iso:country":"ZM",
    "wof:name":"Tara",
    "wof:placetype":"locality"
},
  "geometry": {"coordinates":[26.77736,-16.93403],"type":"Point"}
}