{
  "type": "Feature",
  "properties": {
    "gn:admin1_code":"7.0",
    "gn:asciiname":"Koma",
    "gn:country_code":"ZM",
    "gn:dem":967,
    "gn:feature_class":"P",
    "gn:feature_code":"PPL",
    "gn:name":"Koma",
    "gn:population":0,
    "gn:timezone":"Africa/Lusaka",
    "iso:country":"ZM",
    "wof:name":"Koma",
    "wof:placetype":"locality"
},
  "geometry": {"coordinates":[25.55,-17.71667],"type":"Point"}
}