{
  "type": "Feature",
  "properties": {
    "gn:admin1_code":"5.0",
    "gn:asciiname":"Kampinda",
    "gn:country_code":"ZM",
    "gn:dem":978,
    "gn:feature_class":"P",
    "gn:feature_code":"PPL",
    "gn:name":"Kampinda",
    "gn:population":0,
    "gn:timezone":"Africa/Lusaka",
    "iso:country":"ZM",
    "wof:name":"Kampinda",
    "wof:placetype":"locality"
},
  "geometry": {"coordinates":[29.76388,-8.78417],"type":"Point"}
}