{
  "type": "Feature",
  "properties": {
    "gn:admin1_code":"2.0",
    "gn:asciiname":"Nambala",
    "gn:country_code":"ZM",
    "gn:dem":1104,
    "gn:feature_class":"P",
    "gn:feature_code":"PPL",
    "gn:name":"Nambala",
    "gn:population":0,
    "gn:timezone":"Africa/Lusaka",
    "iso:country":"ZM",
    "wof:name":"Nambala",
    "wof:placetype":"locality"
},
  "geometry": {"coordinates":[27.03333,-15.11667],"type":"Point"}
}