{
  "type": "Feature",
  "properties": {
    "gn:admin1_code":"6.0",
    "gn:asciiname":"Sacheka",
    "gn:country_code":"ZM",
    "gn:dem":1126,
    "gn:feature_class":"P",
    "gn:feature_code":"PPL",
    "gn:name":"Sacheka",
    "gn:population":0,
    "gn:timezone":"Africa/Lusaka",
    "iso:country":"ZM",
    "wof:name":"Sacheka",
    "wof:placetype":"locality"
},
  "geometry": {"coordinates":[23.88555,-13.41618],"type":"Point"}
}