{
  "type": "Feature",
  "properties": {
    "gn:admin1_code":"5.0",
    "gn:asciiname":"Mangata",
    "gn:country_code":"ZM",
    "gn:dem":1542,
    "gn:feature_class":"P",
    "gn:feature_code":"PPL",
    "gn:name":"Mangata",
    "gn:population":0,
    "gn:timezone":"Africa/Lusaka",
    "iso:country":"ZM",
    "wof:name":"Mangata",
    "wof:placetype":"locality"
},
  "geometry": {"coordinates":[30.66667,-9.75],"type":"Point"}
}