{
  "type": "Feature",
  "properties": {
    "gn:admin1_code":"10.0",
    "gn:asciiname":"Pondamele",
    "gn:country_code":"ZM",
    "gn:dem":1304,
    "gn:feature_class":"P",
    "gn:feature_code":"PPL",
    "gn:name":"Pondamele",
    "gn:population":0,
    "gn:timezone":"Africa/Lusaka",
    "iso:country":"ZM",
    "wof:name":"Pondamele",
    "wof:placetype":"locality"
},
  "geometry": {"coordinates":[33.23333,-10.08333],"type":"Point"}
}