{
  "type": "Feature",
  "properties": {
    "gn:admin1_code":"6.0",
    "gn:asciiname":"Samahina",
    "gn:country_code":"ZM",
    "gn:dem":1402,
    "gn:feature_class":"P",
    "gn:feature_code":"PPL",
    "gn:name":"Samahina",
    "gn:population":0,
    "gn:timezone":"Africa/Lusaka",
    "iso:country":"ZM",
    "wof:name":"Samahina",
    "wof:placetype":"locality"
},
  "geometry": {"coordinates":[24.33073,-11.18912],"type":"Point"}
}