{
  "type": "Feature",
  "properties": {
    "gn:admin1_code":"6.0",
    "gn:asciiname":"Chivinda",
    "gn:country_code":"ZM",
    "gn:dem":1085,
    "gn:feature_class":"P",
    "gn:feature_code":"PPL",
    "gn:name":"Chivinda",
    "gn:population":0,
    "gn:timezone":"Africa/Lusaka",
    "iso:country":"ZM",
    "wof:name":"Chivinda",
    "wof:placetype":"locality"
},
  "geometry": {"coordinates":[22.05,-13.45],"type":"Point"}
}