{
  "type": "Feature",
  "properties": {
    "gn:admin1_code":"5.0",
    "gn:asciiname":"Mukanda",
    "gn:country_code":"ZM",
    "gn:dem":1525,
    "gn:feature_class":"P",
    "gn:feature_code":"PPL",
    "gn:name":"Mukanda",
    "gn:population":0,
    "gn:timezone":"Africa/Lusaka",
    "iso:country":"ZM",
    "wof:name":"Mukanda",
    "wof:placetype":"locality"
},
  "geometry": {"coordinates":[31.26887,-9.29615],"type":"Point"}
}