{
  "type": "Feature",
  "properties": {
    "gn:admin1_code":"3.0",
    "gn:asciiname":"Filimoni",
    "gn:country_code":"ZM",
    "gn:dem":984,
    "gn:feature_class":"P",
    "gn:feature_code":"PPL",
    "gn:name":"Filimoni",
    "gn:population":0,
    "gn:timezone":"Africa/Lusaka",
    "iso:country":"ZM",
    "wof:name":"Filimoni",
    "wof:placetype":"locality"
},
  "geometry": {"coordinates":[31.11297,-14.61674],"type":"Point"}
}