{
  "type": "Feature",
  "properties": {
    "gn:admin1_code":"2.0",
    "gn:asciiname":"Mande",
    "gn:country_code":"ZM",
    "gn:dem":1165,
    "gn:feature_class":"P",
    "gn:feature_code":"PPL",
    "gn:name":"Mande",
    "gn:population":0,
    "gn:timezone":"Africa/Lusaka",
    "iso:country":"ZM",
    "name:und_x_variant":[
        "Mandi",
        "Mande"
    ],
    "wof:name":"Mande",
    "wof:placetype":"locality"
},
  "geometry": {"coordinates":[27.64451,-14.95825],"type":"Point"}
}