{
  "type": "Feature",
  "properties": {
    "gn:admin1_code":"1.0",
    "gn:asciiname":"Nanyenzo",
    "gn:country_code":"ZM",
    "gn:dem":1117,
    "gn:feature_class":"P",
    "gn:feature_code":"PPL",
    "gn:name":"Nanyenzo",
    "gn:population":0,
    "gn:timezone":"Africa/Lusaka",
    "iso:country":"ZM",
    "wof:name":"Nanyenzo",
    "wof:placetype":"locality"
},
  "geometry": {"coordinates":[24.15,-15.56667],"type":"Point"}
}