{
  "type": "Feature",
  "properties": {
    "gn:admin1_code":"3.0",
    "gn:asciiname":"Chimoto",
    "gn:country_code":"ZM",
    "gn:dem":997,
    "gn:feature_class":"P",
    "gn:feature_code":"PPL",
    "gn:name":"Chimoto",
    "gn:population":0,
    "gn:timezone":"Africa/Lusaka",
    "iso:country":"ZM",
    "wof:name":"Chimoto",
    "wof:placetype":"locality"
},
  "geometry": {"coordinates":[31.16529,-14.591],"type":"Point"}
}