{
  "type": "Feature",
  "properties": {
    "gn:admin1_code":"5.0",
    "gn:asciiname":"Yamutenga",
    "gn:country_code":"ZM",
    "gn:dem":1192,
    "gn:feature_class":"P",
    "gn:feature_code":"PPL",
    "gn:name":"Yamutenga",
    "gn:population":0,
    "gn:timezone":"Africa/Lusaka",
    "iso:country":"ZM",
    "wof:name":"Yamutenga",
    "wof:placetype":"locality"
},
  "geometry": {"coordinates":[30.77044,-9.09127],"type":"Point"}
}