{
  "type": "Feature",
  "properties": {
    "gn:admin1_code":"6.0",
    "gn:asciiname":"Mukandakunda",
    "gn:country_code":"ZM",
    "gn:dem":1079,
    "gn:feature_class":"P",
    "gn:feature_code":"PPL",
    "gn:name":"Mukandakunda",
    "gn:population":0,
    "gn:timezone":"Africa/Lusaka",
    "iso:country":"ZM",
    "name:und_x_variant":[
        "Mukandakundu",
        "Mukandakunda"
    ],
    "wof:name":"Mukandakunda",
    "wof:placetype":"locality"
},
  "geometry": {"coordinates":[23.07284,-13.38358],"type":"Point"}
}