{
  "type": "Feature",
  "properties": {
    "gn:admin1_code":"1.0",
    "gn:asciiname":"Marumo",
    "gn:country_code":"ZM",
    "gn:dem":1023,
    "gn:feature_class":"P",
    "gn:feature_code":"PPL",
    "gn:name":"Marumo",
    "gn:population":0,
    "gn:timezone":"Africa/Lusaka",
    "iso:country":"ZM",
    "wof:name":"Marumo",
    "wof:placetype":"locality"
},
  "geometry": {"coordinates":[22.75,-15.16667],"type":"Point"}
}