{
  "type": "Feature",
  "properties": {
    "gn:admin1_code":"6.0",
    "gn:asciiname":"Nyampasa",
    "gn:country_code":"ZM",
    "gn:dem":1081,
    "gn:feature_class":"P",
    "gn:feature_code":"PPL",
    "gn:name":"Nyampasa",
    "gn:population":0,
    "gn:timezone":"Africa/Lusaka",
    "iso:country":"ZM",
    "name:und_x_variant":[
        "Nyampaso",
        "Nyampasa"
    ],
    "wof:name":"Nyampasa",
    "wof:placetype":"locality"
},
  "geometry": {"coordinates":[23.31667,-13.36667],"type":"Point"}
}