{
  "type": "Feature",
  "properties": {
    "gn:admin1_code":"1.0",
    "gn:asciiname":"Namabunga",
    "gn:country_code":"ZM",
    "gn:dem":1067,
    "gn:feature_class":"P",
    "gn:feature_code":"PPL",
    "gn:name":"Namabunga",
    "gn:population":0,
    "gn:timezone":"Africa/Lusaka",
    "iso:country":"ZM",
    "wof:name":"Namabunga",
    "wof:placetype":"locality"
},
  "geometry": {"coordinates":[23.46667,-16.03333],"type":"Point"}
}