{
  "type": "Feature",
  "properties": {
    "gn:admin1_code":"3.0",
    "gn:asciiname":"Vinchetu",
    "gn:country_code":"ZM",
    "gn:dem":892,
    "gn:feature_class":"P",
    "gn:feature_code":"PPL",
    "gn:name":"Vinchetu",
    "gn:population":0,
    "gn:timezone":"Africa/Lusaka",
    "iso:country":"ZM",
    "name:und_x_variant":[
        "Vincheto",
        "Vinchetu"
    ],
    "wof:name":"Vinchetu",
    "wof:placetype":"locality"
},
  "geometry": {"coordinates":[32.58048,-13.17815],"type":"Point"}
}