{
  "type": "Feature",
  "properties": {
    "gn:admin1_code":"10.0",
    "gn:asciiname":"Alon",
    "gn:country_code":"ZM",
    "gn:dem":1359,
    "gn:feature_class":"P",
    "gn:feature_code":"PPL",
    "gn:name":"Alon",
    "gn:population":0,
    "gn:timezone":"Africa/Lusaka",
    "iso:country":"ZM",
    "name:ceb_x_preferred":[
        "Alon"
    ],
    "name:ces_x_preferred":[
        "Alon"
    ],
    "name:deu_x_preferred":[
        "Alon"
    ],
    "name:fra_x_preferred":[
        "Alon"
    ],
    "name:heb_x_preferred":[
        "\u05d0\u05dc\u05d5\u05df"
    ],
    "name:slv_x_preferred":[
        "Alon"
    ],
    "name:swe_x_preferred":[
        "Alon"
    ],
    "wof:name":"Alon",
    "wof:placetype":"locality"
},
  "geometry": {"coordinates":[33.48333,-10.38333],"type":"Point"}
}