{
  "type": "Feature",
  "properties": {
    "gn:admin1_code":"1.0",
    "gn:asciiname":"Malamo",
    "gn:country_code":"ZM",
    "gn:dem":1042,
    "gn:feature_class":"P",
    "gn:feature_code":"PPL",
    "gn:name":"Malamo",
    "gn:population":0,
    "gn:timezone":"Africa/Lusaka",
    "iso:country":"ZM",
    "wof:name":"Malamo",
    "wof:placetype":"locality"
},
  "geometry": {"coordinates":[23.63333,-15.66667],"type":"Point"}
}