{
  "type": "Feature",
  "properties": {
    "gn:admin1_code":"2.0",
    "gn:asciiname":"Samwell Kampeshi",
    "gn:country_code":"ZM",
    "gn:dem":1278,
    "gn:feature_class":"P",
    "gn:feature_code":"PPL",
    "gn:name":"Samwell Kampeshi",
    "gn:population":0,
    "gn:timezone":"Africa/Lusaka",
    "iso:country":"ZM",
    "wof:name":"Samwell Kampeshi",
    "wof:placetype":"locality"
},
  "geometry": {"coordinates":[30.28835,-12.8856],"type":"Point"}
}