{
  "type": "Feature",
  "properties": {
    "gn:admin1_code":"3.0",
    "gn:asciiname":"Kampangore",
    "gn:country_code":"ZM",
    "gn:dem":992,
    "gn:feature_class":"P",
    "gn:feature_code":"PPL",
    "gn:name":"Kampangore",
    "gn:population":0,
    "gn:timezone":"Africa/Lusaka",
    "iso:country":"ZM",
    "wof:name":"Kampangore",
    "wof:placetype":"locality"
},
  "geometry": {"coordinates":[31.52894,-14.15895],"type":"Point"}
}