{
  "type": "Feature",
  "properties": {
    "gn:admin1_code":"5.0",
    "gn:asciiname":"Chaba",
    "gn:country_code":"ZM",
    "gn:dem":1180,
    "gn:feature_class":"P",
    "gn:feature_code":"PPL",
    "gn:name":"Chaba",
    "gn:population":0,
    "gn:timezone":"Africa/Lusaka",
    "iso:country":"ZM",
    "name:ceb_x_preferred":[
        "Chaba"
    ],
    "name:deu_x_preferred":[
        "Chaba"
    ],
    "name:fra_x_preferred":[
        "Chaba"
    ],
    "name:jpn_x_preferred":[
        "\u30c1\u30e3\u30d0"
    ],
    "name:und_x_variant":[
        "Chyawa",
        "Chaba"
    ],
    "wof:name":"Chaba",
    "wof:placetype":"locality"
},
  "geometry": {"coordinates":[30.08604,-10.97826],"type":"Point"}
}