{
  "type": "Feature",
  "properties": {
    "gn:admin1_code":"6.0",
    "gn:asciiname":"Samujimu",
    "gn:country_code":"ZM",
    "gn:dem":1051,
    "gn:feature_class":"P",
    "gn:feature_code":"PPL",
    "gn:name":"Samujimu",
    "gn:population":0,
    "gn:timezone":"Africa/Lusaka",
    "iso:country":"ZM",
    "name:und_x_variant":[
        "Samuzimo",
        "Samujimu"
    ],
    "wof:name":"Samujimu",
    "wof:placetype":"locality"
},
  "geometry": {"coordinates":[22.96667,-13.16667],"type":"Point"}
}