{
  "type": "Feature",
  "properties": {
    "gn:admin1_code":"3.0",
    "gn:asciiname":"Kavala",
    "gn:country_code":"ZM",
    "gn:dem":777,
    "gn:feature_class":"P",
    "gn:feature_code":"PPL",
    "gn:name":"Kavala",
    "gn:population":0,
    "gn:timezone":"Africa/Lusaka",
    "iso:country":"ZM",
    "name:ara_x_preferred":[
        "\u0643\u0627\u0641\u0627\u0644\u0627"
    ],
    "name:arz_x_preferred":[
        "\u0642\u0648\u0644\u0647"
    ],
    "name:bul_x_preferred":[
        "\u041a\u0430\u0432\u0430\u043b\u0430"
    ],
    "name:cat_x_preferred":[
        "Kavala"
    ],
    "name:ceb_x_preferred":[
        "Kav\u00e1la"
    ],
    "name:ces_x_preferred":[
        "Kavala"
    ],
    "name:chu_x_preferred":[
        "\u041a\u0430\u0432\u0430\u043b\u0430"
    ],
    "name:deu_x_preferred":[
        "Kavala"
    ],
    "name:ell_x_preferred":[
        "\u039a\u03b1\u03b2\u03ac\u03bb\u03b1"
    ],
    "name:est_x_preferred":[
        "Kav\u00e1la"
    ],
    "name:eus_x_preferred":[
        "Kavala"
    ],
    "name:fas_x_preferred":[
        "\u06a9\u0627\u0648\u0627\u0644\u0627"
    ],
    "name:fin_x_preferred":[
        "Kav\u00e1la"
    ],
    "name:fra_x_preferred":[
        "Kavala"
    ],
    "name:heb_x_preferred":[
        "\u05e7\u05d5\u05d5\u05d0\u05dc\u05d4"
    ],
    "name:hrv_x_preferred":[
        "Kavala"
    ],
    "name:hun_x_preferred":[
        "Kav\u00e1la"
    ],
    "name:hye_x_preferred":[
        "\u053f\u0561\u057e\u0561\u056c\u0561"
    ],
    "name:ind_x_preferred":[
        "Kavala"
    ],
    "name:ita_x_preferred":[
        "Kavala"
    ],
    "name:jpn_x_preferred":[
        "\u30ab\u30f4\u30a1\u30e9"
    ],
    "name:kat_x_preferred":[
        "\u10d9\u10d0\u10d5\u10d0\u10da\u10d0"
    ],
    "name:kor_x_preferred":[
        "\uce74\ubc1c\ub77c"
    ],
    "name:lat_x_preferred":[
        "Cabala"
    ],
    "name:lit_x_preferred":[
        "Kavala"
    ],
    "name:mkd_x_preferred":[
        "\u041a\u0430\u0432\u0430\u043b\u0430"
    ],
    "name:nld_x_preferred":[
        "Kavala"
    ],
    "name:nno_x_preferred":[
        "Kav\u00e1la"
    ],
    "name:nor_x_preferred":[
        "Kavala"
    ],
    "name:pnt_x_preferred":[
        "\u039a\u03b1\u03b2\u03ac\u03bb\u03b1"
    ],
    "name:pol_x_preferred":[
        "Kawala"
    ],
    "name:por_x_preferred":[
        "Cavala"
    ],
    "name:ron_x_preferred":[
        "Kavala"
    ],
    "name:rus_x_preferred":[
        "\u041a\u0430\u0432\u0430\u043b\u0430"
    ],
    "name:sco_x_preferred":[
        "Kavala"
    ],
    "name:slk_x_preferred":[
        "Kavala"
    ],
    "name:spa_x_preferred":[
        "Kavala"
    ],
    "name:srp_x_preferred":[
        "\u041a\u0430\u0432\u0430\u043b\u0430"
    ],
    "name:tur_x_preferred":[
        "Kavala"
    ],
    "name:ukr_x_preferred":[
        "\u041a\u0430\u0432\u0430\u043b\u0430"
    ],
    "name:und_x_variant":[
        "Kalala"
    ],
    "name:urd_x_preferred":[
        "\u06a9\u0627\u0648\u0627\u0644\u0627"
    ],
    "name:vie_x_preferred":[
        "Kav\u00e1la"
    ],
    "name:war_x_preferred":[
        "Kavala"
    ],
    "name:zho_x_preferred":[
        "\u5361\u74e6\u62c9"
    ],
    "wof:name":"Kavala",
    "wof:placetype":"locality"
},
  "geometry": {"coordinates":[32.6039,-14.18828],"type":"Point"}
}