{
  "type": "Feature",
  "properties": {
    "gn:admin1_code":"3.0",
    "gn:asciiname":"Kavala",
    "gn:country_code":"ZM",
    "gn:dem":777,
    "gn:feature_class":"P",
    "gn:feature_code":"PPL",
    "gn:name":"Kavala",
    "gn:population":0,
    "gn:timezone":"Africa/Lusaka",
    "iso:country":"ZM",
    "name:und_x_variant":[
        "Kalala",
        "Kavala"
    ],
    "wof:name":"Kavala",
    "wof:placetype":"locality"
},
  "geometry": {"coordinates":[32.6039,-14.18828],"type":"Point"}
}