{
  "type": "Feature",
  "properties": {
    "gn:admin1_code":"5.0",
    "gn:asciiname":"Aron",
    "gn:country_code":"ZM",
    "gn:dem":1587,
    "gn:feature_class":"P",
    "gn:feature_code":"PPL",
    "gn:name":"Aron",
    "gn:population":0,
    "gn:timezone":"Africa/Lusaka",
    "iso:country":"ZM",
    "name:ben_x_preferred":[
        "\u0986\u09b0\u09cb\u09a8"
    ],
    "name:bre_x_preferred":[
        "Aron"
    ],
    "name:ceb_x_preferred":[
        "Aron"
    ],
    "name:ces_x_preferred":[
        "\u00c1r\u00f3n"
    ],
    "name:dan_x_preferred":[
        "Aron"
    ],
    "name:deu_x_preferred":[
        "Aron"
    ],
    "name:est_x_preferred":[
        "Aron"
    ],
    "name:fra_x_preferred":[
        "Aron"
    ],
    "name:heb_x_preferred":[
        "\u05d0\u05e8\u05d5\u05df"
    ],
    "name:hun_x_preferred":[
        "\u00c1ron"
    ],
    "name:ita_x_preferred":[
        "Aron"
    ],
    "name:jpn_x_preferred":[
        "\u30a2\u30ed\u30f3"
    ],
    "name:msa_x_preferred":[
        "Aron"
    ],
    "name:new_x_preferred":[
        "\u0905\u0930\u094b\u0928"
    ],
    "name:nld_x_preferred":[
        "Aron"
    ],
    "name:pol_x_preferred":[
        "Aron"
    ],
    "name:rus_x_preferred":[
        "\u0410\u0440\u043e\u043d"
    ],
    "name:slk_x_preferred":[
        "\u00c1ron"
    ],
    "name:spa_x_preferred":[
        "Aron"
    ],
    "name:srp_x_preferred":[
        "\u0410\u0440\u043e\u043d"
    ],
    "name:swe_x_preferred":[
        "Aron"
    ],
    "name:ukr_x_preferred":[
        "\u0410\u0440\u043e\u043d"
    ],
    "wof:name":"Aron",
    "wof:placetype":"locality"
},
  "geometry": {"coordinates":[31.67208,-8.94918],"type":"Point"}
}