{
  "type": "Feature",
  "properties": {
    "gn:admin1_code":"5.0",
    "gn:asciiname":"Aron",
    "gn:country_code":"ZM",
    "gn:dem":1587,
    "gn:feature_class":"P",
    "gn:feature_code":"PPL",
    "gn:name":"Aron",
    "gn:population":0,
    "gn:timezone":"Africa/Lusaka",
    "iso:country":"ZM",
    "wof:name":"Aron",
    "wof:placetype":"locality"
},
  "geometry": {"coordinates":[31.67208,-8.94918],"type":"Point"}
}