{
  "type": "Feature",
  "properties": {
    "gn:admin1_code":"6.0",
    "gn:asciiname":"Chilingo",
    "gn:country_code":"ZM",
    "gn:dem":1059,
    "gn:feature_class":"P",
    "gn:feature_code":"PPL",
    "gn:name":"Chilingo",
    "gn:population":0,
    "gn:timezone":"Africa/Lusaka",
    "iso:country":"ZM",
    "wof:name":"Chilingo",
    "wof:placetype":"locality"
},
  "geometry": {"coordinates":[23.08333,-13.63333],"type":"Point"}
}