{
  "type": "Feature",
  "properties": {
    "gn:admin1_code":"5.0",
    "gn:asciiname":"Jeremia",
    "gn:country_code":"ZM",
    "gn:dem":1535,
    "gn:feature_class":"P",
    "gn:feature_code":"PPL",
    "gn:name":"Jeremia",
    "gn:population":0,
    "gn:timezone":"Africa/Lusaka",
    "iso:country":"ZM",
    "wof:name":"Jeremia",
    "wof:placetype":"locality"
},
  "geometry": {"coordinates":[31.65,-8.98333],"type":"Point"}
}