{
  "type": "Feature",
  "properties": {
    "gn:admin1_code":"3.0",
    "gn:asciiname":"Mutalimanja",
    "gn:country_code":"ZM",
    "gn:dem":546,
    "gn:feature_class":"P",
    "gn:feature_code":"PPL",
    "gn:name":"Mutalimanja",
    "gn:population":0,
    "gn:timezone":"Africa/Lusaka",
    "iso:country":"ZM",
    "wof:name":"Mutalimanja",
    "wof:placetype":"locality"
},
  "geometry": {"coordinates":[31.83333,-13.18333],"type":"Point"}
}