{
  "type": "Feature",
  "properties": {
    "gn:admin1_code":"6.0",
    "gn:asciiname":"Mukonshi",
    "gn:country_code":"ZM",
    "gn:dem":1276,
    "gn:feature_class":"P",
    "gn:feature_code":"PPL",
    "gn:name":"Mukonshi",
    "gn:population":0,
    "gn:timezone":"Africa/Lusaka",
    "iso:country":"ZM",
    "wof:name":"Mukonshi",
    "wof:placetype":"locality"
},
  "geometry": {"coordinates":[25.68333,-12.13333],"type":"Point"}
}