{
  "type": "Feature",
  "properties": {
    "gn:admin1_code":"4.0",
    "gn:asciiname":"Chaba",
    "gn:country_code":"ZM",
    "gn:dem":1233,
    "gn:feature_class":"P",
    "gn:feature_code":"PPL",
    "gn:name":"Chaba",
    "gn:population":0,
    "gn:timezone":"Africa/Lusaka",
    "iso:country":"ZM",
    "name:ceb_x_preferred":[
        "Chaba"
    ],
    "name:deu_x_preferred":[
        "Chaba"
    ],
    "name:fra_x_preferred":[
        "Chaba"
    ],
    "name:jpn_x_preferred":[
        "\u30c1\u30e3\u30d0"
    ],
    "wof:name":"Chaba",
    "wof:placetype":"locality"
},
  "geometry": {"coordinates":[29.35786,-11.26445],"type":"Point"}
}