{
  "type": "Feature",
  "properties": {
    "gn:admin1_code":"10.0",
    "gn:asciiname":"Mzangwa",
    "gn:country_code":"ZM",
    "gn:dem":1327,
    "gn:feature_class":"P",
    "gn:feature_code":"PPL",
    "gn:name":"Mzangwa",
    "gn:population":0,
    "gn:timezone":"Africa/Lusaka",
    "iso:country":"ZM",
    "wof:name":"Mzangwa",
    "wof:placetype":"locality"
},
  "geometry": {"coordinates":[32.83333,-9.73333],"type":"Point"}
}