{
  "type": "Feature",
  "properties": {
    "gn:admin1_code":"3.0",
    "gn:asciiname":"Kasenga",
    "gn:country_code":"ZM",
    "gn:dem":859,
    "gn:feature_class":"P",
    "gn:feature_code":"PPL",
    "gn:name":"Kasenga",
    "gn:population":0,
    "gn:timezone":"Africa/Lusaka",
    "iso:country":"ZM",
    "name:fra_x_preferred":[
        "Kasenga"
    ],
    "name:ron_x_preferred":[
        "Kasenga"
    ],
    "wof:name":"Kasenga",
    "wof:placetype":"locality"
},
  "geometry": {"coordinates":[30.96667,-14.66667],"type":"Point"}
}