{
  "type": "Feature",
  "properties": {
    "gn:admin1_code":"10.0",
    "gn:asciiname":"Mulopwe",
    "gn:country_code":"ZM",
    "gn:dem":665,
    "gn:feature_class":"P",
    "gn:feature_code":"PPL",
    "gn:name":"Mulopwe",
    "gn:population":0,
    "gn:timezone":"Africa/Lusaka",
    "iso:country":"ZM",
    "wof:name":"Mulopwe",
    "wof:placetype":"locality"
},
  "geometry": {"coordinates":[32.84745,-11.18996],"type":"Point"}
}