{
  "type": "Feature",
  "properties": {
    "gn:admin1_code":"1.0",
    "gn:asciiname":"Malafu",
    "gn:country_code":"ZM",
    "gn:dem":979,
    "gn:feature_class":"P",
    "gn:feature_code":"PPL",
    "gn:name":"Malafu",
    "gn:population":0,
    "gn:timezone":"Africa/Lusaka",
    "iso:country":"ZM",
    "wof:name":"Malafu",
    "wof:placetype":"locality"
},
  "geometry": {"coordinates":[25.13333,-16.88332999999999],"type":"Point"}
}