{
  "type": "Feature",
  "properties": {
    "gn:admin1_code":"4.0",
    "gn:asciiname":"Bwalya Mponda",
    "gn:country_code":"ZM",
    "gn:dem":1170,
    "gn:feature_class":"P",
    "gn:feature_code":"PPL",
    "gn:name":"Bwalya Mponda",
    "gn:population":0,
    "gn:timezone":"Africa/Lusaka",
    "iso:country":"ZM",
    "name:und_x_variant":[
        "Piana Walya",
        "Bwalya Mponde",
        "Bwalya Mponda"
    ],
    "wof:name":"Bwalya Mponda",
    "wof:placetype":"locality"
},
  "geometry": {"coordinates":[30.07445,-11.66678],"type":"Point"}
}