{
  "type": "Feature",
  "properties": {
    "gn:admin1_code":"6.0",
    "gn:asciiname":"Ntemwa",
    "gn:country_code":"ZM",
    "gn:dem":1145,
    "gn:feature_class":"P",
    "gn:feature_code":"PPL",
    "gn:name":"Ntemwa",
    "gn:population":0,
    "gn:timezone":"Africa/Lusaka",
    "iso:country":"ZM",
    "wof:name":"Ntemwa",
    "wof:placetype":"locality"
},
  "geometry": {"coordinates":[26.13333,-14.03333],"type":"Point"}
}