{
  "type": "Feature",
  "properties": {
    "gn:admin1_code":"8.0",
    "gn:asciiname":"Chikumbi",
    "gn:country_code":"ZM",
    "gn:dem":1250,
    "gn:feature_class":"P",
    "gn:feature_code":"PPL",
    "gn:name":"Chikumbi",
    "gn:population":0,
    "gn:timezone":"Africa/Lusaka",
    "iso:country":"ZM",
    "name:und_x_variant":[
        "Chikombi",
        "Chikumbi"
    ],
    "wof:name":"Chikumbi",
    "wof:placetype":"locality"
},
  "geometry": {"coordinates":[28.67148,-12.88683],"type":"Point"}
}