{
  "type": "Feature",
  "properties": {
    "gn:admin1_code":"1.0",
    "gn:asciiname":"Natamoyo",
    "gn:country_code":"ZM",
    "gn:dem":1008,
    "gn:feature_class":"P",
    "gn:feature_code":"PPL",
    "gn:name":"Natamoyo",
    "gn:population":0,
    "gn:timezone":"Africa/Lusaka",
    "iso:country":"ZM",
    "wof:name":"Natamoyo",
    "wof:placetype":"locality"
},
  "geometry": {"coordinates":[23.21667,-15.63333],"type":"Point"}
}