{
  "type": "Feature",
  "properties": {
    "gn:admin1_code":"1.0",
    "gn:asciiname":"Muleka",
    "gn:country_code":"ZM",
    "gn:dem":1152,
    "gn:feature_class":"P",
    "gn:feature_code":"PPL",
    "gn:name":"Muleka",
    "gn:population":0,
    "gn:timezone":"Africa/Lusaka",
    "iso:country":"ZM",
    "wof:name":"Muleka",
    "wof:placetype":"locality"
},
  "geometry": {"coordinates":[25.18333,-14.86667],"type":"Point"}
}