{
  "type": "Feature",
  "properties": {
    "gn:admin1_code":"1.0",
    "gn:asciiname":"Situla",
    "gn:country_code":"ZM",
    "gn:dem":1033,
    "gn:feature_class":"P",
    "gn:feature_code":"PPL",
    "gn:name":"Situla",
    "gn:population":0,
    "gn:timezone":"Africa/Lusaka",
    "iso:country":"ZM",
    "name:bul_x_preferred":[
        "\u0421\u0438\u0442\u0443\u043b\u0430"
    ],
    "name:cat_x_preferred":[
        "Sitra"
    ],
    "name:deu_x_preferred":[
        "Situla"
    ],
    "name:eus_x_preferred":[
        "Antoxin"
    ],
    "name:fra_x_preferred":[
        "Situle"
    ],
    "name:ind_x_preferred":[
        "Situla"
    ],
    "name:ita_x_preferred":[
        "Situla"
    ],
    "name:kat_x_preferred":[
        "\u10e1\u10d8\u10e2\u10e3\u10da\u10d0"
    ],
    "name:pol_x_preferred":[
        "Situla"
    ],
    "name:rus_x_preferred":[
        "\u0421\u0438\u0442\u0443\u043b\u0430"
    ],
    "name:slv_x_preferred":[
        "Situla"
    ],
    "name:spa_x_preferred":[
        "Acetre"
    ],
    "wof:name":"Situla",
    "wof:placetype":"locality"
},
  "geometry": {"coordinates":[22.61667000000001,-16.08333],"type":"Point"}
}