{
  "type": "Feature",
  "properties": {
    "gn:admin1_code":"1.0",
    "gn:asciiname":"Malamani",
    "gn:country_code":"ZM",
    "gn:dem":1013,
    "gn:feature_class":"P",
    "gn:feature_code":"PPL",
    "gn:name":"Malamani",
    "gn:population":0,
    "gn:timezone":"Africa/Lusaka",
    "iso:country":"ZM",
    "wof:name":"Malamani",
    "wof:placetype":"locality"
},
  "geometry": {"coordinates":[25.25,-16.71667],"type":"Point"}
}