{
  "type": "Feature",
  "properties": {
    "gn:admin1_code":"2.0",
    "gn:asciiname":"Lailo Musoshya",
    "gn:country_code":"ZM",
    "gn:dem":1562,
    "gn:feature_class":"P",
    "gn:feature_code":"PPL",
    "gn:name":"Lailo Musoshya",
    "gn:population":0,
    "gn:timezone":"Africa/Lusaka",
    "iso:country":"ZM",
    "wof:name":"Lailo Musoshya",
    "wof:placetype":"locality"
},
  "geometry": {"coordinates":[30.91637,-13.10778],"type":"Point"}
}