{
  "type": "Feature",
  "properties": {
    "gn:admin1_code":"3.0",
    "gn:asciiname":"Chingaliwa",
    "gn:country_code":"ZM",
    "gn:dem":1022,
    "gn:feature_class":"P",
    "gn:feature_code":"PPL",
    "gn:name":"Chingaliwa",
    "gn:population":0,
    "gn:timezone":"Africa/Lusaka",
    "iso:country":"ZM",
    "wof:name":"Chingaliwa",
    "wof:placetype":"locality"
},
  "geometry": {"coordinates":[32.33333,-13.83333],"type":"Point"}
}