{
  "type": "Feature",
  "properties": {
    "gn:admin1_code":"6.0",
    "gn:asciiname":"Mulonga",
    "gn:country_code":"ZM",
    "gn:dem":1346,
    "gn:feature_class":"P",
    "gn:feature_code":"PPL",
    "gn:name":"Mulonga",
    "gn:population":0,
    "gn:timezone":"Africa/Lusaka",
    "iso:country":"ZM",
    "wof:name":"Mulonga",
    "wof:placetype":"locality"
},
  "geometry": {"coordinates":[26.88333,-12.15],"type":"Point"}
}