{
  "type": "Feature",
  "properties": {
    "gn:admin1_code":"3.0",
    "gn:asciiname":"Chilembwe",
    "gn:country_code":"ZM",
    "gn:dem":874,
    "gn:feature_class":"P",
    "gn:feature_code":"PPL",
    "gn:name":"Chilembwe",
    "gn:population":0,
    "gn:timezone":"Africa/Lusaka",
    "iso:country":"ZM",
    "name:und_x_variant":[
        "Chilembwi",
        "Chilembwe"
    ],
    "wof:name":"Chilembwe",
    "wof:placetype":"locality"
},
  "geometry": {"coordinates":[31.78333,-13.98333],"type":"Point"}
}