{
  "type": "Feature",
  "properties": {
    "gn:admin1_code":"3.0",
    "gn:asciiname":"Chinkuni",
    "gn:country_code":"ZM",
    "gn:dem":726,
    "gn:feature_class":"P",
    "gn:feature_code":"PPL",
    "gn:name":"Chinkuni",
    "gn:population":0,
    "gn:timezone":"Africa/Lusaka",
    "iso:country":"ZM",
    "wof:name":"Chinkuni",
    "wof:placetype":"locality"
},
  "geometry": {"coordinates":[31.5631,-13.88075],"type":"Point"}
}