{
  "type": "Feature",
  "properties": {
    "gn:admin1_code":"6.0",
    "gn:asciiname":"Salikishi",
    "gn:country_code":"ZM",
    "gn:dem":1081,
    "gn:feature_class":"P",
    "gn:feature_code":"PPL",
    "gn:name":"Salikishi",
    "gn:population":0,
    "gn:timezone":"Africa/Lusaka",
    "iso:country":"ZM",
    "wof:name":"Salikishi",
    "wof:placetype":"locality"
},
  "geometry": {"coordinates":[22.35,-13.06667],"type":"Point"}
}