{
  "type": "Feature",
  "properties": {
    "gn:admin1_code":"1.0",
    "gn:asciiname":"Siboleka",
    "gn:country_code":"ZM",
    "gn:dem":943,
    "gn:feature_class":"P",
    "gn:feature_code":"PPL",
    "gn:name":"Siboleka",
    "gn:population":0,
    "gn:timezone":"Africa/Lusaka",
    "iso:country":"ZM",
    "wof:name":"Siboleka",
    "wof:placetype":"locality"
},
  "geometry": {"coordinates":[24.53333,-17.43333],"type":"Point"}
}