{
  "type": "Feature",
  "properties": {
    "gn:admin1_code":"2.0",
    "gn:asciiname":"Kasuko",
    "gn:country_code":"ZM",
    "gn:dem":1298,
    "gn:feature_class":"P",
    "gn:feature_code":"PPL",
    "gn:name":"Kasuko",
    "gn:population":0,
    "gn:timezone":"Africa/Lusaka",
    "iso:country":"ZM",
    "wof:name":"Kasuko",
    "wof:placetype":"locality"
},
  "geometry": {"coordinates":[30.56301,-12.7384],"type":"Point"}
}