{
  "type": "Feature",
  "properties": {
    "gn:admin1_code":"3.0",
    "gn:asciiname":"Kavulasiya",
    "gn:country_code":"ZM",
    "gn:dem":1092,
    "gn:feature_class":"P",
    "gn:feature_code":"PPL",
    "gn:name":"Kavulasiya",
    "gn:population":0,
    "gn:timezone":"Africa/Lusaka",
    "iso:country":"ZM",
    "wof:name":"Kavulasiya",
    "wof:placetype":"locality"
},
  "geometry": {"coordinates":[31.53333,-14.38333],"type":"Point"}
}