{
  "type": "Feature",
  "properties": {
    "gn:admin1_code":"1.0",
    "gn:asciiname":"Simbundu",
    "gn:country_code":"ZM",
    "gn:dem":950,
    "gn:feature_class":"P",
    "gn:feature_code":"PPL",
    "gn:name":"Simbundu",
    "gn:population":0,
    "gn:timezone":"Africa/Lusaka",
    "iso:country":"ZM",
    "wof:name":"Simbundu",
    "wof:placetype":"locality"
},
  "geometry": {"coordinates":[24.81667,-17.43333],"type":"Point"}
}