{
  "type": "Feature",
  "properties": {
    "gn:admin1_code":"5.0",
    "gn:asciiname":"Kameme",
    "gn:country_code":"ZM",
    "gn:dem":1338,
    "gn:feature_class":"P",
    "gn:feature_code":"PPL",
    "gn:name":"Kameme",
    "gn:population":0,
    "gn:timezone":"Africa/Lusaka",
    "iso:country":"ZM",
    "wof:name":"Kameme",
    "wof:placetype":"locality"
},
  "geometry": {"coordinates":[30.08333,-10.15],"type":"Point"}
}