{
  "type": "Feature",
  "properties": {
    "gn:admin1_code":"7.0",
    "gn:asciiname":"Mulambwa",
    "gn:country_code":"ZM",
    "gn:dem":1112,
    "gn:feature_class":"P",
    "gn:feature_code":"PPL",
    "gn:name":"Mulambwa",
    "gn:population":0,
    "gn:timezone":"Africa/Lusaka",
    "iso:country":"ZM",
    "wof:name":"Mulambwa",
    "wof:placetype":"locality"
},
  "geometry": {"coordinates":[27.46667,-16.28333],"type":"Point"}
}