{
  "type": "Feature",
  "properties": {
    "gn:admin1_code":"3.0",
    "gn:asciiname":"Mnukwa",
    "gn:country_code":"ZM",
    "gn:dem":923,
    "gn:feature_class":"P",
    "gn:feature_code":"PPL",
    "gn:name":"Mnukwa",
    "gn:population":0,
    "gn:timezone":"Africa/Lusaka",
    "iso:country":"ZM",
    "name:und_x_variant":[
        "Mnukwa-Mgazini",
        "Mnukwa"
    ],
    "wof:name":"Mnukwa",
    "wof:placetype":"locality"
},
  "geometry": {"coordinates":[32.57455,-13.45698],"type":"Point"}
}