{
  "type": "Feature",
  "properties": {
    "gn:admin1_code":"5.0",
    "gn:asciiname":"Munyama",
    "gn:country_code":"ZM",
    "gn:dem":1674,
    "gn:feature_class":"P",
    "gn:feature_code":"PPL",
    "gn:name":"Munyama",
    "gn:population":0,
    "gn:timezone":"Africa/Lusaka",
    "iso:country":"ZM",
    "wof:name":"Munyama",
    "wof:placetype":"locality"
},
  "geometry": {"coordinates":[31.13333,-9.03333],"type":"Point"}
}