{
  "type": "Feature",
  "properties": {
    "gn:admin1_code":"7.0",
    "gn:asciiname":"Nyanga",
    "gn:country_code":"ZM",
    "gn:dem":541,
    "gn:feature_class":"P",
    "gn:feature_code":"PPL",
    "gn:name":"Nyanga",
    "gn:population":0,
    "gn:timezone":"Africa/Lusaka",
    "iso:country":"ZM",
    "name:bar_x_preferred":[
        "Nyanga"
    ],
    "name:ceb_x_preferred":[
        "Nyanga"
    ],
    "name:deu_x_preferred":[
        "Nyanga"
    ],
    "name:eng_x_preferred":[
        "Nyanga"
    ],
    "name:fin_x_preferred":[
        "Nyanga"
    ],
    "name:fra_x_preferred":[
        "Nyanga"
    ],
    "name:hrv_x_preferred":[
        "Nyanga"
    ],
    "name:ita_x_preferred":[
        "Nyanga"
    ],
    "name:nld_x_preferred":[
        "Nyanga"
    ],
    "name:spa_x_preferred":[
        "Nyanga"
    ],
    "name:srp_x_preferred":[
        "\u040a\u0430\u043d\u0433\u0430"
    ],
    "name:swe_x_preferred":[
        "Nyanga"
    ],
    "name:tur_x_preferred":[
        "Nyanga"
    ],
    "wof:name":"Nyanga",
    "wof:placetype":"locality"
},
  "geometry": {"coordinates":[27.08333,-17.66667],"type":"Point"}
}