{
  "type": "Feature",
  "properties": {
    "gn:admin1_code":"7.0",
    "gn:asciiname":"Nyanga",
    "gn:country_code":"ZM",
    "gn:dem":541,
    "gn:feature_class":"P",
    "gn:feature_code":"PPL",
    "gn:name":"Nyanga",
    "gn:population":0,
    "gn:timezone":"Africa/Lusaka",
    "iso:country":"ZM",
    "name:eng_x_preferred":[
        "Nyanga"
    ],
    "wof:name":"Nyanga",
    "wof:placetype":"locality"
},
  "geometry": {"coordinates":[27.08333,-17.66667],"type":"Point"}
}