{
  "type": "Feature",
  "properties": {
    "gn:admin1_code":"1.0",
    "gn:asciiname":"Kanjengo",
    "gn:country_code":"ZM",
    "gn:dem":1062,
    "gn:feature_class":"P",
    "gn:feature_code":"PPL",
    "gn:name":"Kanjengo",
    "gn:population":0,
    "gn:timezone":"Africa/Lusaka",
    "iso:country":"ZM",
    "wof:name":"Kanjengo",
    "wof:placetype":"locality"
},
  "geometry": {"coordinates":[22.85,-15.53333],"type":"Point"}
}