{
  "type": "Feature",
  "properties": {
    "gn:admin1_code":"6.0",
    "gn:asciiname":"Jutila",
    "gn:country_code":"ZM",
    "gn:dem":1304,
    "gn:feature_class":"P",
    "gn:feature_code":"PPL",
    "gn:name":"Jutila",
    "gn:population":0,
    "gn:timezone":"Africa/Lusaka",
    "iso:country":"ZM",
    "name:und_x_variant":[
        "Jitula",
        "Jutila"
    ],
    "wof:name":"Jutila",
    "wof:placetype":"locality"
},
  "geometry": {"coordinates":[26.15,-12.53333],"type":"Point"}
}