{
  "type": "Feature",
  "properties": {
    "gn:admin1_code":"10.0",
    "gn:asciiname":"Kapandashila",
    "gn:country_code":"ZM",
    "gn:dem":1573,
    "gn:feature_class":"P",
    "gn:feature_code":"PPL",
    "gn:name":"Kapandashila",
    "gn:population":0,
    "gn:timezone":"Africa/Lusaka",
    "iso:country":"ZM",
    "wof:name":"Kapandashila",
    "wof:placetype":"locality"
},
  "geometry": {"coordinates":[31.01667,-12.68333],"type":"Point"}
}