{
  "type": "Feature",
  "properties": {
    "gn:admin1_code":"1.0",
    "gn:asciiname":"Kwibisa",
    "gn:country_code":"ZM",
    "gn:dem":1036,
    "gn:feature_class":"P",
    "gn:feature_code":"PPL",
    "gn:name":"Kwibisa",
    "gn:population":0,
    "gn:timezone":"Africa/Lusaka",
    "iso:country":"ZM",
    "wof:name":"Kwibisa",
    "wof:placetype":"locality"
},
  "geometry": {"coordinates":[23.35,-16.16667],"type":"Point"}
}