{
  "type": "Feature",
  "properties": {
    "gn:admin1_code":"7.0",
    "gn:asciiname":"Siamaiba",
    "gn:country_code":"ZM",
    "gn:dem":1078,
    "gn:feature_class":"P",
    "gn:feature_code":"PPL",
    "gn:name":"Siamaiba",
    "gn:population":0,
    "gn:timezone":"Africa/Lusaka",
    "iso:country":"ZM",
    "wof:name":"Siamaiba",
    "wof:placetype":"locality"
},
  "geometry": {"coordinates":[25.91667,-17.43333],"type":"Point"}
}