{
  "type": "Feature",
  "properties": {
    "gn:admin1_code":"2.0",
    "gn:asciiname":"Nchimishi",
    "gn:country_code":"ZM",
    "gn:dem":1416,
    "gn:feature_class":"P",
    "gn:feature_code":"PPL",
    "gn:name":"Nchimishi",
    "gn:population":0,
    "gn:timezone":"Africa/Lusaka",
    "iso:country":"ZM",
    "name:und_x_variant":[
        "Chimisi",
        "Nchimishi"
    ],
    "wof:name":"Nchimishi",
    "wof:placetype":"locality"
},
  "geometry": {"coordinates":[30.03333,-13.55],"type":"Point"}
}