{
  "type": "Feature",
  "properties": {
    "gn:admin1_code":"1.0",
    "gn:asciiname":"Mwene Mutondo",
    "gn:country_code":"ZM",
    "gn:dem":1133,
    "gn:feature_class":"P",
    "gn:feature_code":"PPL",
    "gn:name":"Mwene Mutondo",
    "gn:population":0,
    "gn:timezone":"Africa/Lusaka",
    "iso:country":"ZM",
    "name:und_x_variant":[
        "Mutondo",
        "Mwene-Mutonde",
        "Mwene Mutondo"
    ],
    "wof:name":"Mwene Mutondo",
    "wof:placetype":"locality"
},
  "geometry": {"coordinates":[24.61514,-14.71912],"type":"Point"}
}