{
  "type": "Feature",
  "properties": {
    "gn:admin1_code":"6.0",
    "gn:asciiname":"Vunda",
    "gn:country_code":"ZM",
    "gn:dem":1047,
    "gn:feature_class":"P",
    "gn:feature_code":"PPL",
    "gn:name":"Vunda",
    "gn:population":0,
    "gn:timezone":"Africa/Lusaka",
    "iso:country":"ZM",
    "wof:name":"Vunda",
    "wof:placetype":"locality"
},
  "geometry": {"coordinates":[22.88333,-13.23333],"type":"Point"}
}