{
  "type": "Feature",
  "properties": {
    "gn:admin1_code":"9.0",
    "gn:asciiname":"Shikaweta",
    "gn:country_code":"ZM",
    "gn:dem":530,
    "gn:feature_class":"P",
    "gn:feature_code":"PPL",
    "gn:name":"Shikaweta",
    "gn:population":0,
    "gn:timezone":"Africa/Lusaka",
    "iso:country":"ZM",
    "wof:name":"Shikaweta",
    "wof:placetype":"locality"
},
  "geometry": {"coordinates":[29.68388,-14.87064],"type":"Point"}
}