{
  "type": "Feature",
  "properties": {
    "gn:admin1_code":"3.0",
    "gn:asciiname":"Mpesi",
    "gn:country_code":"ZM",
    "gn:dem":619,
    "gn:feature_class":"P",
    "gn:feature_code":"PPL",
    "gn:name":"Mpesi",
    "gn:population":0,
    "gn:timezone":"Africa/Lusaka",
    "iso:country":"ZM",
    "wof:name":"Mpesi",
    "wof:placetype":"locality"
},
  "geometry": {"coordinates":[32.07718,-13.4025],"type":"Point"}
}