{
  "type": "Feature",
  "properties": {
    "gn:admin1_code":"3.0",
    "gn:asciiname":"Chimumba",
    "gn:country_code":"ZM",
    "gn:dem":686,
    "gn:feature_class":"P",
    "gn:feature_code":"PPL",
    "gn:name":"Chimumba",
    "gn:population":0,
    "gn:timezone":"Africa/Lusaka",
    "iso:country":"ZM",
    "wof:name":"Chimumba",
    "wof:placetype":"locality"
},
  "geometry": {"coordinates":[32.61667,-12.16667],"type":"Point"}
}