{
  "type": "Feature",
  "properties": {
    "gn:admin1_code":"10.0",
    "gn:asciiname":"Sepa",
    "gn:country_code":"ZM",
    "gn:dem":1109,
    "gn:feature_class":"P",
    "gn:feature_code":"PPL",
    "gn:name":"Sepa",
    "gn:population":0,
    "gn:timezone":"Africa/Lusaka",
    "iso:country":"ZM",
    "wof:name":"Sepa",
    "wof:placetype":"locality"
},
  "geometry": {"coordinates":[33.16667,-11.71667],"type":"Point"}
}