{
  "type": "Feature",
  "properties": {
    "gn:admin1_code":"7.0",
    "gn:asciiname":"Chilumbi",
    "gn:country_code":"ZM",
    "gn:dem":1245,
    "gn:feature_class":"P",
    "gn:feature_code":"PPL",
    "gn:name":"Chilumbi",
    "gn:population":0,
    "gn:timezone":"Africa/Lusaka",
    "iso:country":"ZM",
    "wof:name":"Chilumbi",
    "wof:placetype":"locality"
},
  "geometry": {"coordinates":[26.83333,-16.55],"type":"Point"}
}