{
  "type": "Feature",
  "properties": {
    "gn:admin1_code":"6.0",
    "gn:asciiname":"Chitau",
    "gn:country_code":"ZM",
    "gn:dem":1072,
    "gn:feature_class":"P",
    "gn:feature_code":"PPL",
    "gn:name":"Chitau",
    "gn:population":0,
    "gn:timezone":"Africa/Lusaka",
    "iso:country":"ZM",
    "wof:name":"Chitau",
    "wof:placetype":"locality"
},
  "geometry": {"coordinates":[22.71667,-13.08333],"type":"Point"}
}