{
  "type": "Feature",
  "properties": {
    "gn:admin1_code":"3.0",
    "gn:asciiname":"Kumbuyu",
    "gn:country_code":"ZM",
    "gn:dem":986,
    "gn:feature_class":"P",
    "gn:feature_code":"PPL",
    "gn:name":"Kumbuyu",
    "gn:population":0,
    "gn:timezone":"Africa/Lusaka",
    "iso:country":"ZM",
    "name:und_x_variant":[
        "Kumbuyo",
        "Kumbuyu"
    ],
    "wof:name":"Kumbuyu",
    "wof:placetype":"locality"
},
  "geometry": {"coordinates":[31.4655,-14.15239],"type":"Point"}
}