{
  "type": "Feature",
  "properties": {
    "gn:admin1_code":"4.0",
    "gn:asciiname":"Kabeke",
    "gn:country_code":"ZM",
    "gn:dem":942,
    "gn:feature_class":"P",
    "gn:feature_code":"PPL",
    "gn:name":"Kabeke",
    "gn:population":0,
    "gn:timezone":"Africa/Lusaka",
    "iso:country":"ZM",
    "wof:name":"Kabeke",
    "wof:placetype":"locality"
},
  "geometry": {"coordinates":[28.49149,-9.27645],"type":"Point"}
}