{
  "type": "Feature",
  "properties": {
    "gn:admin1_code":"7.0",
    "gn:asciiname":"Chikonga",
    "gn:country_code":"ZM",
    "gn:dem":1149,
    "gn:feature_class":"P",
    "gn:feature_code":"PPL",
    "gn:name":"Chikonga",
    "gn:population":0,
    "gn:timezone":"Africa/Lusaka",
    "iso:country":"ZM",
    "name:und_x_variant":[
        "Chiganka",
        "Chikonga"
    ],
    "wof:name":"Chikonga",
    "wof:placetype":"locality"
},
  "geometry": {"coordinates":[27.58333,-16.36667000000001],"type":"Point"}
}