{
  "type": "Feature",
  "properties": {
    "gn:admin1_code":"6.0",
    "gn:asciiname":"Mwinyika",
    "gn:country_code":"ZM",
    "gn:dem":1166,
    "gn:feature_class":"P",
    "gn:feature_code":"PPL",
    "gn:name":"Mwinyika",
    "gn:population":0,
    "gn:timezone":"Africa/Lusaka",
    "iso:country":"ZM",
    "wof:name":"Mwinyika",
    "wof:placetype":"locality"
},
  "geometry": {"coordinates":[24.78333,-12.45],"type":"Point"}
}