{
  "type": "Feature",
  "properties": {
    "gn:admin1_code":"7.0",
    "gn:asciiname":"Gamela",
    "gn:country_code":"ZM",
    "gn:dem":625,
    "gn:feature_class":"P",
    "gn:feature_code":"PPL",
    "gn:name":"Gamela",
    "gn:population":0,
    "gn:timezone":"Africa/Lusaka",
    "iso:country":"ZM",
    "name:eng_x_preferred":[
        "Gamela"
    ],
    "name:eng_x_variant":[
        "Gamera"
    ],
    "name:und_x_variant":[
        "Gamera"
    ],
    "wof:name":"Gamela",
    "wof:placetype":"locality"
},
  "geometry": {"coordinates":[27.13537,-17.434],"type":"Point"}
}