{
  "type": "Feature",
  "properties": {
    "gn:admin1_code":"3.0",
    "gn:asciiname":"Hoya",
    "gn:country_code":"ZM",
    "gn:dem":1130,
    "gn:feature_class":"P",
    "gn:feature_code":"PPL",
    "gn:name":"Hoya",
    "gn:population":0,
    "gn:timezone":"Africa/Lusaka",
    "iso:country":"ZM",
    "name:afr_x_preferred":[
        "Hoya"
    ],
    "name:ben_x_preferred":[
        "\u09b9\u09af\u09bc\u09be"
    ],
    "name:bul_x_preferred":[
        "\u0425\u043e\u044f"
    ],
    "name:ceb_x_preferred":[
        "Hoya"
    ],
    "name:ces_x_preferred":[
        "Hoja"
    ],
    "name:deu_x_preferred":[
        "Wachsblumen"
    ],
    "name:est_x_preferred":[
        "Vahalill"
    ],
    "name:eus_x_preferred":[
        "Hoya"
    ],
    "name:fas_x_preferred":[
        "\u0634\u0645\u0639\u06cc"
    ],
    "name:fin_x_preferred":[
        "Posliinikukat"
    ],
    "name:fra_x_preferred":[
        "Hoya"
    ],
    "name:hrv_x_preferred":[
        "Vo\u0161tani cvijet"
    ],
    "name:hsb_x_preferred":[
        "W\u00f3skowka"
    ],
    "name:hun_x_preferred":[
        "Viaszvir\u00e1g"
    ],
    "name:hye_x_preferred":[
        "\u0544\u0578\u0574\u0561\u0562\u0561\u0572\u0565\u0572"
    ],
    "name:ita_x_preferred":[
        "Hoya"
    ],
    "name:lit_x_preferred":[
        "Va\u0161kuol\u0117"
    ],
    "name:mal_x_preferred":[
        "\u0d39\u0d4b\u0d2f"
    ],
    "name:nld_x_preferred":[
        "Hoya"
    ],
    "name:nor_x_preferred":[
        "Voksblomst"
    ],
    "name:pol_x_preferred":[
        "Hoja"
    ],
    "name:rus_x_preferred":[
        "\u0425\u043e\u0439\u044f"
    ],
    "name:slk_x_preferred":[
        "Hoja"
    ],
    "name:spa_x_preferred":[
        "Hoya"
    ],
    "name:srp_x_preferred":[
        "Hoya"
    ],
    "name:swe_x_preferred":[
        "Porslinsblomssl\u00e4ktet"
    ],
    "name:tha_x_preferred":[
        "\u0e2a\u0e01\u0e38\u0e25\u0e19\u0e21\u0e15\u0e33\u0e40\u0e25\u0e35\u0e22"
    ],
    "name:tur_x_preferred":[
        "Mum \u00e7i\u00e7e\u011fi"
    ],
    "name:ukr_x_preferred":[
        "\u0425\u043e\u0439\u044f"
    ],
    "name:war_x_preferred":[
        "Hoya"
    ],
    "name:zho_x_preferred":[
        "\u7403\u5170\u5c5e"
    ],
    "wof:name":"Hoya",
    "wof:placetype":"locality"
},
  "geometry": {"coordinates":[33.15,-12.15],"type":"Point"}
}