{
  "type": "Feature",
  "properties": {
    "gn:admin1_code":"3.0",
    "gn:asciiname":"Hoya",
    "gn:country_code":"ZM",
    "gn:dem":1130,
    "gn:feature_class":"P",
    "gn:feature_code":"PPL",
    "gn:name":"Hoya",
    "gn:population":0,
    "gn:timezone":"Africa/Lusaka",
    "iso:country":"ZM",
    "wof:name":"Hoya",
    "wof:placetype":"locality"
},
  "geometry": {"coordinates":[33.15,-12.15],"type":"Point"}
}