{
  "type": "Feature",
  "properties": {
    "gn:admin1_code":"1.0",
    "gn:asciiname":"Neywa",
    "gn:country_code":"ZM",
    "gn:dem":1018,
    "gn:feature_class":"P",
    "gn:feature_code":"PPL",
    "gn:name":"Neywa",
    "gn:population":0,
    "gn:timezone":"Africa/Lusaka",
    "iso:country":"ZM",
    "wof:name":"Neywa",
    "wof:placetype":"locality"
},
  "geometry": {"coordinates":[23.25,-15.56667],"type":"Point"}
}