{
  "type": "Feature",
  "properties": {
    "gn:admin1_code":"3.0",
    "gn:asciiname":"Kapenya",
    "gn:country_code":"ZM",
    "gn:dem":972,
    "gn:feature_class":"P",
    "gn:feature_code":"PPL",
    "gn:name":"Kapenya",
    "gn:population":0,
    "gn:timezone":"Africa/Lusaka",
    "iso:country":"ZM",
    "wof:name":"Kapenya",
    "wof:placetype":"locality"
},
  "geometry": {"coordinates":[32.35,-13.45],"type":"Point"}
}