{
  "type": "Feature",
  "properties": {
    "gn:admin1_code":"3.0",
    "gn:asciiname":"Asafu",
    "gn:country_code":"ZM",
    "gn:dem":896,
    "gn:feature_class":"P",
    "gn:feature_code":"PPL",
    "gn:name":"Asafu",
    "gn:population":0,
    "gn:timezone":"Africa/Lusaka",
    "iso:country":"ZM",
    "wof:name":"Asafu",
    "wof:placetype":"locality"
},
  "geometry": {"coordinates":[32.24941,-13.63518],"type":"Point"}
}