{
  "type": "Feature",
  "properties": {
    "gn:admin1_code":"4.0",
    "gn:asciiname":"Mukondola",
    "gn:country_code":"ZM",
    "gn:dem":1315,
    "gn:feature_class":"P",
    "gn:feature_code":"PPL",
    "gn:name":"Mukondola",
    "gn:population":0,
    "gn:timezone":"Africa/Lusaka",
    "iso:country":"ZM",
    "wof:name":"Mukondola",
    "wof:placetype":"locality"
},
  "geometry": {"coordinates":[28.96667,-10.81667],"type":"Point"}
}