{
  "type": "Feature",
  "properties": {
    "gn:admin1_code":"2.0",
    "gn:asciiname":"Yotam",
    "gn:country_code":"ZM",
    "gn:dem":1593,
    "gn:feature_class":"P",
    "gn:feature_code":"PPL",
    "gn:name":"Yotam",
    "gn:population":0,
    "gn:timezone":"Africa/Lusaka",
    "iso:country":"ZM",
    "wof:name":"Yotam",
    "wof:placetype":"locality"
},
  "geometry": {"coordinates":[30.70552,-13.08145],"type":"Point"}
}