{
  "type": "Feature",
  "properties": {
    "gn:admin1_code":"2.0",
    "gn:asciiname":"Lukakesha",
    "gn:country_code":"ZM",
    "gn:dem":520,
    "gn:feature_class":"P",
    "gn:feature_code":"PPL",
    "gn:name":"Lukakesha",
    "gn:population":0,
    "gn:timezone":"Africa/Lusaka",
    "iso:country":"ZM",
    "name:und_x_variant":[
        "Lukakeshya",
        "Lukakesha"
    ],
    "wof:name":"Lukakesha",
    "wof:placetype":"locality"
},
  "geometry": {"coordinates":[29.16667,-14.78333],"type":"Point"}
}