{
  "type": "Feature",
  "properties": {
    "gn:admin1_code":"3.0",
    "gn:asciiname":"Hofmeyer",
    "gn:country_code":"ZM",
    "gn:dem":811,
    "gn:feature_class":"P",
    "gn:feature_code":"PPL",
    "gn:name":"Hofmeyer",
    "gn:population":0,
    "gn:timezone":"Africa/Lusaka",
    "iso:country":"ZM",
    "name:und_x_variant":[
        "Hofmeyr",
        "Hofmeyer"
    ],
    "wof:name":"Hofmeyer",
    "wof:placetype":"locality"
},
  "geometry": {"coordinates":[30.84515,-14.66386],"type":"Point"}
}