{
  "type": "Feature",
  "properties": {
    "gn:admin1_code":"5.0",
    "gn:asciiname":"Suse",
    "gn:country_code":"ZM",
    "gn:dem":1506,
    "gn:feature_class":"P",
    "gn:feature_code":"PPL",
    "gn:name":"Suse",
    "gn:population":0,
    "gn:timezone":"Africa/Lusaka",
    "iso:country":"ZM",
    "name:deu_x_preferred":[
        "Suse"
    ],
    "name:fra_x_preferred":[
        "Suse"
    ],
    "name:nep_x_preferred":[
        "\u0938\u0941\u091c\u0947"
    ],
    "wof:name":"Suse",
    "wof:placetype":"locality"
},
  "geometry": {"coordinates":[31.08333,-9.56667],"type":"Point"}
}