{
  "type": "Feature",
  "properties": {
    "gn:admin1_code":"6.0",
    "gn:asciiname":"Lipesa",
    "gn:country_code":"ZM",
    "gn:dem":1065,
    "gn:feature_class":"P",
    "gn:feature_code":"PPL",
    "gn:name":"Lipesa",
    "gn:population":0,
    "gn:timezone":"Africa/Lusaka",
    "iso:country":"ZM",
    "wof:name":"Lipesa",
    "wof:placetype":"locality"
},
  "geometry": {"coordinates":[22.75497,-13.55171],"type":"Point"}
}