{
  "type": "Feature",
  "properties": {
    "gn:admin1_code":"6.0",
    "gn:asciiname":"James Benwa",
    "gn:country_code":"ZM",
    "gn:dem":1198,
    "gn:feature_class":"P",
    "gn:feature_code":"PPL",
    "gn:name":"James Benwa",
    "gn:population":0,
    "gn:timezone":"Africa/Lusaka",
    "iso:country":"ZM",
    "wof:name":"James Benwa",
    "wof:placetype":"locality"
},
  "geometry": {"coordinates":[24.03043,-11.11122],"type":"Point"}
}