{
  "type": "Feature",
  "properties": {
    "gn:admin1_code":"1.0",
    "gn:asciiname":"Dandaule",
    "gn:country_code":"ZM",
    "gn:dem":1052,
    "gn:feature_class":"P",
    "gn:feature_code":"PPL",
    "gn:name":"Dandaule",
    "gn:population":0,
    "gn:timezone":"Africa/Lusaka",
    "iso:country":"ZM",
    "wof:name":"Dandaule",
    "wof:placetype":"locality"
},
  "geometry": {"coordinates":[22.03333,-14.23333],"type":"Point"}
}