{
  "type": "Feature",
  "properties": {
    "gn:admin1_code":"10.0",
    "gn:asciiname":"Chibuye Kofi",
    "gn:country_code":"ZM",
    "gn:dem":1495,
    "gn:feature_class":"P",
    "gn:feature_code":"PPL",
    "gn:name":"Chibuye Kofi",
    "gn:population":0,
    "gn:timezone":"Africa/Lusaka",
    "iso:country":"ZM",
    "wof:name":"Chibuye Kofi",
    "wof:placetype":"locality"
},
  "geometry": {"coordinates":[30.74702000000001,-12.78596],"type":"Point"}
}