{
  "type": "Feature",
  "properties": {
    "gn:admin1_code":"10.0",
    "gn:asciiname":"Nabwalya",
    "gn:country_code":"ZM",
    "gn:dem":574,
    "gn:feature_class":"P",
    "gn:feature_code":"PPL",
    "gn:name":"Nabwalya",
    "gn:population":0,
    "gn:timezone":"Africa/Lusaka",
    "iso:country":"ZM",
    "wof:name":"Nabwalya",
    "wof:placetype":"locality"
},
  "geometry": {"coordinates":[32.00857,-12.41507],"type":"Point"}
}