{
  "type": "Feature",
  "properties": {
    "gn:admin1_code":"5.0",
    "gn:asciiname":"Tansuka",
    "gn:country_code":"ZM",
    "gn:dem":1456,
    "gn:feature_class":"P",
    "gn:feature_code":"PPL",
    "gn:name":"Tansuka",
    "gn:population":0,
    "gn:timezone":"Africa/Lusaka",
    "iso:country":"ZM",
    "name:und_x_variant":[
        "Tanzuka",
        "Tansuka"
    ],
    "wof:name":"Tansuka",
    "wof:placetype":"locality"
},
  "geometry": {"coordinates":[31.88513,-9.32999],"type":"Point"}
}