{
  "type": "Feature",
  "properties": {
    "gn:admin1_code":"8.0",
    "gn:asciiname":"Kahende",
    "gn:country_code":"ZM",
    "gn:dem":1249,
    "gn:feature_class":"P",
    "gn:feature_code":"PPL",
    "gn:name":"Kahende",
    "gn:population":0,
    "gn:timezone":"Africa/Lusaka",
    "iso:country":"ZM",
    "wof:name":"Kahende",
    "wof:placetype":"locality"
},
  "geometry": {"coordinates":[27.91667,-13.01667],"type":"Point"}
}