{
  "type": "Feature",
  "properties": {
    "gn:admin1_code":"3.0",
    "gn:asciiname":"Chikalawa",
    "gn:country_code":"ZM",
    "gn:dem":560,
    "gn:feature_class":"P",
    "gn:feature_code":"PPL",
    "gn:name":"Chikalawa",
    "gn:population":0,
    "gn:timezone":"Africa/Lusaka",
    "iso:country":"ZM",
    "name:und_x_variant":[
        "Chiwaula",
        "Chikalawa"
    ],
    "wof:name":"Chikalawa",
    "wof:placetype":"locality"
},
  "geometry": {"coordinates":[31.96667,-13.23333],"type":"Point"}
}