{
  "type": "Feature",
  "properties": {
    "gn:admin1_code":"2.0",
    "gn:asciiname":"Namwelwa Yotam",
    "gn:country_code":"ZM",
    "gn:dem":1270,
    "gn:feature_class":"P",
    "gn:feature_code":"PPL",
    "gn:name":"Namwelwa Yotam",
    "gn:population":0,
    "gn:timezone":"Africa/Lusaka",
    "iso:country":"ZM",
    "wof:name":"Namwelwa Yotam",
    "wof:placetype":"locality"
},
  "geometry": {"coordinates":[30.36918,-12.68829],"type":"Point"}
}