{
  "type": "Feature",
  "properties": {
    "gn:admin1_code":"6.0",
    "gn:asciiname":"Bwacha",
    "gn:country_code":"ZM",
    "gn:dem":1189,
    "gn:feature_class":"P",
    "gn:feature_code":"PPL",
    "gn:name":"Bwacha",
    "gn:population":0,
    "gn:timezone":"Africa/Lusaka",
    "iso:country":"ZM",
    "wof:name":"Bwacha",
    "wof:placetype":"locality"
},
  "geometry": {"coordinates":[25.78333,-13.83333],"type":"Point"}
}