{
  "type": "Feature",
  "properties": {
    "gn:admin1_code":"7.0",
    "gn:asciiname":"Sianzovo",
    "gn:country_code":"ZM",
    "gn:dem":666,
    "gn:feature_class":"P",
    "gn:feature_code":"PPL",
    "gn:name":"Sianzovo",
    "gn:population":0,
    "gn:timezone":"Africa/Lusaka",
    "iso:country":"ZM",
    "wof:name":"Sianzovo",
    "wof:placetype":"locality"
},
  "geometry": {"coordinates":[26.89526,-17.79002000000001],"type":"Point"}
}