{
  "type": "Feature",
  "properties": {
    "gn:admin1_code":"9.0",
    "gn:asciiname":"Chombela",
    "gn:country_code":"ZM",
    "gn:dem":1139,
    "gn:feature_class":"P",
    "gn:feature_code":"PPL",
    "gn:name":"Chombela",
    "gn:population":0,
    "gn:timezone":"Africa/Lusaka",
    "iso:country":"ZM",
    "wof:name":"Chombela",
    "wof:placetype":"locality"
},
  "geometry": {"coordinates":[28.35,-15.18333],"type":"Point"}
}