{
  "type": "Feature",
  "properties": {
    "gn:admin1_code":"3.0",
    "gn:asciiname":"Kazimbwe",
    "gn:country_code":"ZM",
    "gn:dem":1160,
    "gn:feature_class":"P",
    "gn:feature_code":"PPL",
    "gn:name":"Kazimbwe",
    "gn:population":0,
    "gn:timezone":"Africa/Lusaka",
    "iso:country":"ZM",
    "wof:name":"Kazimbwe",
    "wof:placetype":"locality"
},
  "geometry": {"coordinates":[33.28795,-11.71749],"type":"Point"}
}