{
  "type": "Feature",
  "properties": {
    "gn:admin1_code":"2.0",
    "gn:asciiname":"Enoch Kunda",
    "gn:country_code":"ZM",
    "gn:dem":1385,
    "gn:feature_class":"P",
    "gn:feature_code":"PPL",
    "gn:name":"Enoch Kunda",
    "gn:population":0,
    "gn:timezone":"Africa/Lusaka",
    "iso:country":"ZM",
    "wof:name":"Enoch Kunda",
    "wof:placetype":"locality"
},
  "geometry": {"coordinates":[30.38862,-12.86021],"type":"Point"}
}