{
  "type": "Feature",
  "properties": {
    "gn:admin1_code":"4.0",
    "gn:asciiname":"Nsemuchila",
    "gn:country_code":"ZM",
    "gn:dem":1180,
    "gn:feature_class":"P",
    "gn:feature_code":"PPL",
    "gn:name":"Nsemuchila",
    "gn:population":0,
    "gn:timezone":"Africa/Lusaka",
    "iso:country":"ZM",
    "name:und_x_variant":[
        "Semigena",
        "Nsemuchila"
    ],
    "wof:name":"Nsemuchila",
    "wof:placetype":"locality"
},
  "geometry": {"coordinates":[29.71667,-11.66667],"type":"Point"}
}