{
  "type": "Feature",
  "properties": {
    "gn:admin1_code":"3.0",
    "gn:asciiname":"Kanjala",
    "gn:country_code":"ZM",
    "gn:dem":1037,
    "gn:feature_class":"P",
    "gn:feature_code":"PPL",
    "gn:name":"Kanjala",
    "gn:population":0,
    "gn:timezone":"Africa/Lusaka",
    "iso:country":"ZM",
    "wof:name":"Kanjala",
    "wof:placetype":"locality"
},
  "geometry": {"coordinates":[31.86667000000001,-14.03333],"type":"Point"}
}