{
  "type": "Feature",
  "properties": {
    "gn:admin1_code":"1.0",
    "gn:asciiname":"Samakutu",
    "gn:country_code":"ZM",
    "gn:dem":1071,
    "gn:feature_class":"P",
    "gn:feature_code":"PPL",
    "gn:name":"Samakutu",
    "gn:population":0,
    "gn:timezone":"Africa/Lusaka",
    "iso:country":"ZM",
    "wof:name":"Samakutu",
    "wof:placetype":"locality"
},
  "geometry": {"coordinates":[24.51667,-16.48333],"type":"Point"}
}