{
  "type": "Feature",
  "properties": {
    "gn:admin1_code":"6.0",
    "gn:asciiname":"Nyakawanda",
    "gn:country_code":"ZM",
    "gn:dem":1075,
    "gn:feature_class":"P",
    "gn:feature_code":"PPL",
    "gn:name":"Nyakawanda",
    "gn:population":0,
    "gn:timezone":"Africa/Lusaka",
    "iso:country":"ZM",
    "wof:name":"Nyakawanda",
    "wof:placetype":"locality"
},
  "geometry": {"coordinates":[23.21703,-13.3327],"type":"Point"}
}