{
  "type": "Feature",
  "properties": {
    "gn:admin1_code":"3.0",
    "gn:asciiname":"Mwenje",
    "gn:country_code":"ZM",
    "gn:dem":806,
    "gn:feature_class":"P",
    "gn:feature_code":"PPL",
    "gn:name":"Mwenje",
    "gn:population":0,
    "gn:timezone":"Africa/Lusaka",
    "iso:country":"ZM",
    "wof:name":"Mwenje",
    "wof:placetype":"locality"
},
  "geometry": {"coordinates":[30.91667,-14.65],"type":"Point"}
}