{
  "type": "Feature",
  "properties": {
    "gn:admin1_code":"1.0",
    "gn:asciiname":"Momo",
    "gn:country_code":"ZM",
    "gn:dem":1083,
    "gn:feature_class":"P",
    "gn:feature_code":"PPL",
    "gn:name":"Momo",
    "gn:population":0,
    "gn:timezone":"Africa/Lusaka",
    "iso:country":"ZM",
    "wof:name":"Momo",
    "wof:placetype":"locality"
},
  "geometry": {"coordinates":[23.28333,-15.53333],"type":"Point"}
}