{
  "type": "Feature",
  "properties": {
    "gn:admin1_code":"2.0",
    "gn:asciiname":"Seti Manikunda",
    "gn:country_code":"ZM",
    "gn:dem":1592,
    "gn:feature_class":"P",
    "gn:feature_code":"PPL",
    "gn:name":"Seti Manikunda",
    "gn:population":0,
    "gn:timezone":"Africa/Lusaka",
    "iso:country":"ZM",
    "wof:name":"Seti Manikunda",
    "wof:placetype":"locality"
},
  "geometry": {"coordinates":[30.68502,-13.1395],"type":"Point"}
}