{
  "type": "Feature",
  "properties": {
    "gn:admin1_code":"3.0",
    "gn:asciiname":"Chonongela",
    "gn:country_code":"ZM",
    "gn:dem":1052,
    "gn:feature_class":"P",
    "gn:feature_code":"PPL",
    "gn:name":"Chonongela",
    "gn:population":0,
    "gn:timezone":"Africa/Lusaka",
    "iso:country":"ZM",
    "wof:name":"Chonongela",
    "wof:placetype":"locality"
},
  "geometry": {"coordinates":[32.04901,-14.14327],"type":"Point"}
}