{
  "type": "Feature",
  "properties": {
    "gn:admin1_code":"10.0",
    "gn:asciiname":"Chikalanga",
    "gn:country_code":"ZM",
    "gn:dem":715,
    "gn:feature_class":"P",
    "gn:feature_code":"PPL",
    "gn:name":"Chikalanga",
    "gn:population":0,
    "gn:timezone":"Africa/Lusaka",
    "iso:country":"ZM",
    "wof:name":"Chikalanga",
    "wof:placetype":"locality"
},
  "geometry": {"coordinates":[33.03333,-11.21667],"type":"Point"}
}