{
  "type": "Feature",
  "properties": {
    "gn:admin1_code":"3.0",
    "gn:asciiname":"Chiuukula",
    "gn:country_code":"ZM",
    "gn:dem":1070,
    "gn:feature_class":"P",
    "gn:feature_code":"PPL",
    "gn:name":"Chiuukula",
    "gn:population":0,
    "gn:timezone":"Africa/Lusaka",
    "iso:country":"ZM",
    "wof:name":"Chiuukula",
    "wof:placetype":"locality"
},
  "geometry": {"coordinates":[31.23333,-14.53333],"type":"Point"}
}