{
  "type": "Feature",
  "properties": {
    "gn:admin1_code":"2.0",
    "gn:asciiname":"Chambula",
    "gn:country_code":"ZM",
    "gn:dem":1311,
    "gn:feature_class":"P",
    "gn:feature_code":"PPL",
    "gn:name":"Chambula",
    "gn:population":0,
    "gn:timezone":"Africa/Lusaka",
    "iso:country":"ZM",
    "wof:name":"Chambula",
    "wof:placetype":"locality"
},
  "geometry": {"coordinates":[28.95185,-13.52066],"type":"Point"}
}