{
  "type": "Feature",
  "properties": {
    "gn:admin1_code":"2.0",
    "gn:asciiname":"Shaba",
    "gn:country_code":"ZM",
    "gn:dem":1132,
    "gn:feature_class":"P",
    "gn:feature_code":"PPL",
    "gn:name":"Shaba",
    "gn:population":0,
    "gn:timezone":"Africa/Lusaka",
    "iso:country":"ZM",
    "wof:name":"Shaba",
    "wof:placetype":"locality"
},
  "geometry": {"coordinates":[27.76577,-14.81929],"type":"Point"}
}