{
  "type": "Feature",
  "properties": {
    "gn:admin1_code":"1.0",
    "gn:asciiname":"Chippia",
    "gn:country_code":"ZM",
    "gn:dem":1042,
    "gn:feature_class":"P",
    "gn:feature_code":"PPL",
    "gn:name":"Chippia",
    "gn:population":0,
    "gn:timezone":"Africa/Lusaka",
    "iso:country":"ZM",
    "wof:name":"Chippia",
    "wof:placetype":"locality"
},
  "geometry": {"coordinates":[22.18333,-14.83333],"type":"Point"}
}