{
  "type": "Feature",
  "properties": {
    "gn:admin1_code":"8.0",
    "gn:asciiname":"Kamfwa",
    "gn:country_code":"ZM",
    "gn:dem":1184,
    "gn:feature_class":"P",
    "gn:feature_code":"PPL",
    "gn:name":"Kamfwa",
    "gn:population":0,
    "gn:timezone":"Africa/Lusaka",
    "iso:country":"ZM",
    "wof:name":"Kamfwa",
    "wof:placetype":"locality"
},
  "geometry": {"coordinates":[28.38333,-13.25],"type":"Point"}
}