{
  "type": "Feature",
  "properties": {
    "gn:admin1_code":"10.0",
    "gn:asciiname":"Masandiko",
    "gn:country_code":"ZM",
    "gn:dem":647,
    "gn:feature_class":"P",
    "gn:feature_code":"PPL",
    "gn:name":"Masandiko",
    "gn:population":0,
    "gn:timezone":"Africa/Lusaka",
    "iso:country":"ZM",
    "name:und_x_variant":[
        "Musandiko",
        "Masandika",
        "Masandiko"
    ],
    "wof:name":"Masandiko",
    "wof:placetype":"locality"
},
  "geometry": {"coordinates":[32.85689,-11.37259],"type":"Point"}
}