{
  "type": "Feature",
  "properties": {
    "gn:admin1_code":"3.0",
    "gn:asciiname":"Mshashu",
    "gn:country_code":"ZM",
    "gn:dem":1073,
    "gn:feature_class":"P",
    "gn:feature_code":"PPL",
    "gn:name":"Mshashu",
    "gn:population":0,
    "gn:timezone":"Africa/Lusaka",
    "iso:country":"ZM",
    "name:und_x_variant":[
        "Mshasho",
        "Mshashu"
    ],
    "wof:name":"Mshashu",
    "wof:placetype":"locality"
},
  "geometry": {"coordinates":[32.67452,-13.54054],"type":"Point"}
}