{
  "type": "Feature",
  "properties": {
    "gn:admin1_code":"3.0",
    "gn:asciiname":"Tepeka",
    "gn:country_code":"ZM",
    "gn:dem":1016,
    "gn:feature_class":"P",
    "gn:feature_code":"PPL",
    "gn:name":"Tepeka",
    "gn:population":0,
    "gn:timezone":"Africa/Lusaka",
    "iso:country":"ZM",
    "name:und_x_variant":[
        "Topeka",
        "Tepeka"
    ],
    "wof:name":"Tepeka",
    "wof:placetype":"locality"
},
  "geometry": {"coordinates":[32.76712,-13.35308],"type":"Point"}
}