{
  "type": "Feature",
  "properties": {
    "gn:admin1_code":"2.0",
    "gn:asciiname":"Mulilo",
    "gn:country_code":"ZM",
    "gn:dem":1443,
    "gn:feature_class":"P",
    "gn:feature_code":"PPL",
    "gn:name":"Mulilo",
    "gn:population":0,
    "gn:timezone":"Africa/Lusaka",
    "iso:country":"ZM",
    "wof:name":"Mulilo",
    "wof:placetype":"locality"
},
  "geometry": {"coordinates":[30.7245,-12.69821],"type":"Point"}
}