{
  "type": "Feature",
  "properties": {
    "gn:admin1_code":"3.0",
    "gn:asciiname":"Chatuluka",
    "gn:country_code":"ZM",
    "gn:dem":1024,
    "gn:feature_class":"P",
    "gn:feature_code":"PPL",
    "gn:name":"Chatuluka",
    "gn:population":0,
    "gn:timezone":"Africa/Lusaka",
    "iso:country":"ZM",
    "wof:name":"Chatuluka",
    "wof:placetype":"locality"
},
  "geometry": {"coordinates":[31.86453,-14.37459],"type":"Point"}
}