{
  "type": "Feature",
  "properties": {
    "gn:admin1_code":"1.0",
    "gn:asciiname":"Lisakwa",
    "gn:country_code":"ZM",
    "gn:dem":1026,
    "gn:feature_class":"P",
    "gn:feature_code":"PPL",
    "gn:name":"Lisakwa",
    "gn:population":0,
    "gn:timezone":"Africa/Lusaka",
    "iso:country":"ZM",
    "wof:name":"Lisakwa",
    "wof:placetype":"locality"
},
  "geometry": {"coordinates":[23.06667,-14.76667],"type":"Point"}
}