{
  "type": "Feature",
  "properties": {
    "gn:admin1_code":"6.0",
    "gn:asciiname":"Kangalesha",
    "gn:country_code":"ZM",
    "gn:dem":1255,
    "gn:feature_class":"P",
    "gn:feature_code":"PPL",
    "gn:name":"Kangalesha",
    "gn:population":0,
    "gn:timezone":"Africa/Lusaka",
    "iso:country":"ZM",
    "wof:name":"Kangalesha",
    "wof:placetype":"locality"
},
  "geometry": {"coordinates":[25.36305,-13.05959],"type":"Point"}
}