{
  "type": "Feature",
  "properties": {
    "gn:admin1_code":"2.0",
    "gn:asciiname":"Shanduma",
    "gn:country_code":"ZM",
    "gn:dem":1064,
    "gn:feature_class":"P",
    "gn:feature_code":"PPL",
    "gn:name":"Shanduma",
    "gn:population":0,
    "gn:timezone":"Africa/Lusaka",
    "iso:country":"ZM",
    "name:und_x_variant":[
        "Shaduma",
        "Shanduma"
    ],
    "wof:name":"Shanduma",
    "wof:placetype":"locality"
},
  "geometry": {"coordinates":[26.98333,-15.16667],"type":"Point"}
}